Workbook

Sheet 操作处罚记录
A1: 文本序 | B1: 股票代码 | C1: 股票名称 | D1: 开始日期 | E1: 结束日期 | F1: 操纵期间 | G1: 处罚宣告日 | H1: 备注
A2: 202423 | B2: =VLOOKUP(C2,'全部股票代码（手动检索）'!A:B,2,0) -> 002730.SZ | C2: 电光科技 | D2: 44180 | E2: 44517 | G2: 45352
A3: 202409 | B3: =VLOOKUP(C3,'全部股票代码（手动检索）'!A:B,2,0) -> F1007420.00 | C3: 美尚生态 | D3: 43263 | E3: 44015 | G3: 45307
A4: 202406 | C4: “维格娜丝”等11支股票 | G4: 45306
B5: =VLOOKUP(C5,补充空白与2019的股票代码!A:B,2,0) -> 603518.SH | C5: 维格娜丝 | D5: 42941 | E5: 42961 | F5: 2017年7月25日至8月14日 | H5: 1支股票在两段时期内被操纵
B6: =VLOOKUP(C6,补充空白与2019的股票代码!A:B,2,0) -> 603518.SH | C6: 维格娜丝 | D6: 42970 | E6: 42992 | F6: 2017年8月23日至9月14日
B7: =VLOOKUP(C7,补充空白与2019的股票代码!A:B,2,0) -> 603665.SH | C7: 康隆达 | D7: 42998 | E7: 43007 | F7: 2017年9月20日至9月29日
B8: =VLOOKUP(C8,补充空白与2019的股票代码!A:B,2,0) -> 603586.SH | C8: 金麒麟 | D8: 42969 | E8: 42978 | F8: 2017年8月22日至8月31日 | H8: 1支股票在两段时期内被操纵
B9: =VLOOKUP(C9,补充空白与2019的股票代码!A:B,2,0) -> 603586.SH | C9: 金麒麟 | D9: 42982 | E9: 43000 | F9: 2017年9月4日至9月22日
B10: =VLOOKUP(C10,补充空白与2019的股票代码!A:B,2,0) -> 603926.SH | C10: 铁流股份 | D10: 42962 | E10: 42972 | F10: 2017年8月15日至8月25日
B11: =VLOOKUP(C11,补充空白与2019的股票代码!A:B,2,0) -> 603116.SH | C11: 红蜻蜓 | D11: 42940 | E11: 42949 | F11: 2017年7月24日至8月2日 | H11: 1支股票在两段时期内被操纵
B12: =VLOOKUP(C12,补充空白与2019的股票代码!A:B,2,0) -> 603116.SH | C12: 红蜻蜓 | D12: 42978 | E12: 42986 | F12: 2017年8月31日至9月8日
B13: =VLOOKUP(C13,补充空白与2019的股票代码!A:B,2,0) -> 603218.SH | C13: 日月股份 | D13: 42936 | E13: 42942 | F13: 2017年7月20日至7月26日
B14: =VLOOKUP(C14,补充空白与2019的股票代码!A:B,2,0) -> 603877.SH | C14: 太平鸟 | D14: 42912 | E14: 42923 | F14: 2017年6月26日至7月7日 | H14: 1支股票在两段时期内被操纵
B15: =VLOOKUP(C15,补充空白与2019的股票代码!A:B,2,0) -> 603877.SH | C15: 太平鸟 | D15: 42936 | E15: 42944 | F15: 2017年7月20日至7月28日
B16: =VLOOKUP(C16,补充空白与2019的股票代码!A:B,2,0) -> 603758.SH | C16: 秦安股份 | D16: 43172 | E16: 43193 | F16: 2018年3月13日至4月3日
B17: =VLOOKUP(C17,补充空白与2019的股票代码!A:B,2,0) -> 603159.SH | C17: 上海亚虹 | D17: 43168 | E17: 43175 | F17: 2018年3月9日至3月16日
B18: =VLOOKUP(C18,补充空白与2019的股票代码!A:B,2,0) -> 603985.SH | C18: 恒润股份 | D18: 43192 | E18: 43215 | F18: 2018年4月2日至4月25日
B19: =VLOOKUP(C19,补充空白与2019的股票代码!A:B,2,0) -> 603767.SH | C19: 中马传动 | D19: 43165 | E19: 43201 | F19: 2018年3月6日至4月11日
A20: 202402 | B20: =VLOOKUP(C20,'全部股票代码（手动检索）'!A:B,2,0) -> 300289.SZ | C20: 利德曼 | D20: 42801 | E20: 42951 | G20: 45296
A21: 2023151 | B21: =VLOOKUP(C21,'全部股票代码（手动检索）'!A:B,2,0) -> 603638.SH | C21: 艾迪精密 | D21: 43228 | E21: 44761 | G21: 45279
A22: 202383 | C22: 劲拓股份 | D22: 43045 | E22: 43584 | F22: 2017年11月6日至2019年4月29日 | G22: 45260
A23: 202377 | B23: =VLOOKUP(C23,'全部股票代码（手动检索）'!A:B,2,0) -> 002358.SZ | C23: 森源电气 | D23: 43166 | E23: 43523 | G23: 45230 | H23: 操纵行为分成三个阶段，开始日期与结束日期分别为操作行为最早开始时间和最晚结束时间
A24: 202371 | B24: =VLOOKUP(C24,'全部股票代码（手动检索）'!A:B,2,0) -> 300503.SZ | C24: 昊志机电 | D24: 44554 | E24: 44558 | G24: 45224 | H24: 内幕交易
A25: 202370 | B25: =VLOOKUP(C25,'全部股票代码（手动检索）'!A:B,2,0) -> F1002802.00 | C25: 金一文化 | D25: 43076 | E25: 43248 | F25: 2017年12月7日至2018年5月28日 | G25: 45222
A26: 202368 | C26: “利民股份”等16只股票 | G26: 45191 | H26: 操纵多支股票
B27: =VLOOKUP(C27,'全部股票代码（手动检索）'!A:B,2,0) -> 002734.SZ | C27: 利民股份 | D27: 42345 | E27: 42489 | F27: 2015年12月7日至2016年4月29日
B28: =VLOOKUP(C28,'全部股票代码（手动检索）'!A:B,2,0) -> 600328.SH | C28: 兰太实业 | D28: 42314 | E28: 42479 | F28: 2015年11月6日至2016年4月19日
B29: =VLOOKUP(C29,'全部股票代码（手动检索）'!A:B,2,0) -> 603309.SH | C29: 维力医疗 | D29: 42341 | E29: 42489 | F29: 2015年12月3日至2016年4月29日
B30: =VLOOKUP(C30,'全部股票代码（手动检索）'!A:B,2,0) -> 600560.SH | C30: 金自天正 | D30: 42332 | E30: 42537 | F30: 2015年11月24日至2016年6月16日
B31: =VLOOKUP(C31,'全部股票代码（手动检索）'!A:B,2,0) -> 600310.SH | C31: 桂东电力 | D31: 42384 | E31: 42480 | F31: 2016年1月15日至4月20日
B32: =VLOOKUP(C32,'全部股票代码（手动检索）'!A:B,2,0) -> 300309.SZ | C32: 吉艾科技 | D32: 42318 | E32: 42522 | F32: 2015年11月10日至2016年6月1日
B33: =VLOOKUP(C33,'全部股票代码（手动检索）'!A:B,2,0) -> 000411.SZ | C33: 英特集团 | D33: 42396 | E33: 42544 | F33: 2016年1月27日至2016年6月23日
B34: =VLOOKUP(C34,'全部股票代码（手动检索）'!A:B,2,0) -> 000702.SZ | C34: 正虹科技 | D34: 42180 | E34: 42562 | F34: 2015年6月25日至2016年7月11日
B35: =VLOOKUP(C35,'全部股票代码（手动检索）'!A:B,2,0) -> 000691.SZ | C35: 亚太实业 | D35: 42236 | E35: 42325 | F35: 2015年8月20日至11月17日
B36: =VLOOKUP(C36,'全部股票代码（手动检索）'!A:B,2,0) -> 300478.SZ | C36: 杭州高新 | D36: 42212 | E36: 42332 | F36: 2015年7月27日至11月24日
B37: =VLOOKUP(C37,'全部股票代码（手动检索）'!A:B,2,0) -> 002072.SZ | C37: 凯瑞德 | D37: 42396 | E37: 42710 | F37: 2016年1月27日至12月6日
B38: =VLOOKUP(C38,'全部股票代码（手动检索）'!A:B,2,0) -> 002509.SZ | C38: 天广消防 | D38: 42227 | E38: 42440 | F38: 2015年8月11日至2016年3月11日
... B42: =VLOOKUP(C42,'全部股票代码（手动检索）'!A:B,2,0) -> 600165.SH | C42: 新日恒力 | D42: 42759 | E42: 42822 | F42: 2017年1月24日至3月28日
A43: 202364 | B43: =VLOOKUP(C43,'全部股票代码（手动检索）'!A:B,2,0) -> 832966.NQ | C43: 道尔智控 | D43: 42984 | E43: 43112 | F43: 2017年9月6日至2018年1月12日 | G43: 45170
A44: 202360 | B44: =VLOOKUP(C44,'全部股票代码（手动检索）'!A:B,2,0) -> 002858.SZ | C44: 力盛运动 | D44: 43833 | E44: 44189 | F44: 2020年1月3日至12月24日 | G44: 45154
A45: 202355 | B45: =VLOOKUP(C45,'全部股票代码（手动检索）'!A:B,2,0) -> 002760.SZ | C45: 凤形股份 | D45: 43017 | E45: 43159 | F45: 2017年10月9日至2018年2月28日 | G45: 45121
A46: 202354 | B46: =VLOOKUP(C46,'全部股票代码（手动检索）'!A:B,2,0) -> 000673.SZ | C46: 当代东方 | D46: 42970 | E46: 43327 | F46: 2017年8月23日至2018年8月15日 | G46: 45113
A47: 202352 | B47: =VLOOKUP(C47,'全部股票代码（手动检索）'!A:B,2,0) -> 603726.SH | C47: 朗迪集团 | D47: 43773 | E47: 43928 | F47: 2019年11月4日至2020年4月7日 | G47: 45107
A48: 202349 | B48: =VLOOKUP(C48,'全部股票代码（手动检索）'!A:B,2,0) -> 603937.SH | C48: 丽岛新材 | D48: 43914 | E48: 44021 | F48: 2020年3月24日至2020年7月9日 | G48: 45106
A49: 202344 | C49: “麦迪电气”等8支股票 | G49: 45094 | H49: 操纵多支股票
B50: =VLOOKUP(C50,'全部股票代码（手动检索）'!A:B,2,0) -> 300341.SZ | C50: 麦迪电气 | D50: 42926 | E50: 42947 | F50: 2017年7月10日至7月31日
B51: =VLOOKUP(C51,'全部股票代码（手动检索）'!A:B,2,0) -> 300250.SZ | C51: 初灵信息 | D51: 43382 | E51: 43398 | F51: 2018年10月9日至10月25日
B52: =VLOOKUP(C52,'全部股票代码（手动检索）'!A:B,2,0) -> 000032.SZ | C52: 深桑达A | D52: 43252 | E52: 43273 | F52: 2018年6月1日至22日
B53: =VLOOKUP(C53,'全部股票代码（手动检索）'!A:B,2,0) -> 300605.SZ | C53: 恒锋信息 | D53: 43433 | E53: 43451 | F53: 2018年11月29日至12月17日
B54: =VLOOKUP(C54,'全部股票代码（手动检索）'!A:B,2,0) -> 603721.SH | C54: 中广天择 | D54: 43171 | E54: 43199 | F54: 2018年3月12日至4月9日
B55: =VLOOKUP(C55,'全部股票代码（手动检索）'!A:B,2,0) -> 600488.SH | C55: 天药股份 | D55: 43179 | E55: 43188 | F55: 2018年3月20日至29日
B56: =VLOOKUP(C56,'全部股票代码（手动检索）'!A:B,2,0) -> 601226.SH | C56: 华电重工 | D56: 43045 | E56: 43070 | F56: 2017年11月6日至12月1日
B57: =VLOOKUP(C57,'全部股票代码（手动检索）'!A:B,2,0) -> 600853.SH | C57: 龙建股份 | D57: 42968 | E57: 42984 | F57: 2017年8月21日至9月6日
A58: 202340 | C58: “浙数文化”等3支股票 | G58: 45065
B59: =VLOOKUP(C59,补充空白与2019的股票代码!A:B,2,0) -> 600633.SH | C59: 浙数文化 | D59: 42674 | E59: 42944 | F59: 2016年10月31日至2017年7月28日
B60: =VLOOKUP(C60,补充空白与2019的股票代码!A:B,2,0) -> 002061.SZ | C60: 浙江交科 | D60: 42972 | E60: 43238 | F60: 2017年8月25日至2018年5月18日 | H60: 1支股票在两段时期内被操纵
B61: =VLOOKUP(C61,补充空白与2019的股票代码!A:B,2,0) -> 002061.SZ | C61: 浙江交科 | D61: 43241 | E61: 43476 | F61: 2018年5月21日至2019年1月11日
B62: =VLOOKUP(C62,补充空白与2019的股票代码!A:B,2,0) -> 600797.SH | C62: 浙大网新 | D62: 42450 | E62: 42800 | F62: 2016年3月21日至2017年3月6日 | H62: 超比例持有，并非操纵
A63: 202337 | B63: =VLOOKUP(C63,'全部股票代码（手动检索）'!A:B,2,0) -> 002776.SZ | C63: 柏堡龙 | D63: 43287 | E63: 43616 | F63: 2018年7月6日至2019年5月31日 | G63: 45064
A64: 202336 | C64: “酒钢宏兴”等16支股票 | G64: 45065
B65: =VLOOKUP(C65,补充空白与2019的股票代码!A:B,2,0) -> 600307.SH | C65: 酒钢宏兴 | D65: 42107 | E65: 42138 | F65: 2015年4月13日至2015年5月14日
B66: =VLOOKUP(C66,补充空白与2019的股票代码!A:B,2,0) -> F1006086.00 | C66: 贵人鸟 | D66: 42157 | E66: 42219 | F66: 2015年6月2日至2015年8月3日
B67: =VLOOKUP(C67,补充空白与2019的股票代码!A:B,2,0) -> 000723.SZ | C67: 美锦能源 | D67: 42166 | E67: 42234 | F67: 2015年6月11日至2015年8月18日 | H67: 1支股票在两段时期内被操纵
B68: =VLOOKUP(C68,补充空白与2019的股票代码!A:B,2,0) -> 000723.SZ | C68: 美锦能源 | D68: 42247 | E68: 42257 | F68: 2015年8月31日至2015年9月10日
B69: =VLOOKUP(C69,补充空白与2019的股票代码!A:B,2,0) -> 600281.SH | C69: 太化股份 | D69: 42180 | E69: 42207 | F69: 2015年6月25日至2015年7月22日 | H69: 1支股票在两段时期内被操纵
B70: =VLOOKUP(C70,补充空白与2019的股票代码!A:B,2,0) -> 600281.SH | C70: 太化股份 | D70: 42215 | E70: 42226 | F70: 2015年7月30日至2015年8月10日
B71: =VLOOKUP(C71,补充空白与2019的股票代码!A:B,2,0) -> 000753.SZ | C71: 漳州发展 | D71: 42205 | E71: 42264 | F71: 2015年7月20日至2015年9月17日 | H71: 1支股票在两段时期内被操纵
B72: =VLOOKUP(C72,补充空白与2019的股票代码!A:B,2,0) -> 000753.SZ | C72: 漳州发展 | D72: 42292 | E72: 42296 | F72: 2015年10月15日至2015年10月19日
B73: =VLOOKUP(C73,补充空白与2019的股票代码!A:B,2,0) -> 002093.SZ | C73: 国脉科技 | D73: 42205 | E73: 42226 | F73: 2015年7月20日至2015年8月10日 | H73: 1支股票在两段时期内被操纵
B74: =VLOOKUP(C74,补充空白与2019的股票代码!A:B,2,0) -> 002093.SZ | C74: 国脉科技 | D74: 42244 | E74: 42254 | F74: 2015年8月28日至2015年9月7日
B75: =VLOOKUP(C75,补充空白与2019的股票代码!A:B,2,0) -> 000537.SZ | C75: 广宇发展 | D75: 42208 | E75: 42255 | F75: 2015年7月23日至2015年9月8日 | H75: 1支股票在三段时期内被操纵
B76: =VLOOKUP(C76,补充空白与2019的股票代码!A:B,2,0) -> 000537.SZ | C76: 广宇发展 | D76: 42272 | E76: 42321 | F76: 2015年9月25日至2015年11月13日
B77: =VLOOKUP(C77,补充空白与2019的股票代码!A:B,2,0) -> 000537.SZ | C77: 广宇发展 | D77: 42334 | E77: 42352 | F77: 2015年11月26日至2015年12月14日
B78: =VLOOKUP(C78,补充空白与2019的股票代码!A:B,2,0) -> 600303.SH | C78: 曙光股份 | D78: 42229 | E78: 42249 | F78: 2015年8月13日至2015年9月2日
B79: =VLOOKUP(C79,补充空白与2019的股票代码!A:B,2,0) -> 600796.SH | C79: 钱江生化 | D79: 42229 | E79: 42255 | F79: 2015年8月13日至2015年9月8日
B80: =VLOOKUP(C80,补充空白与2019的股票代码!A:B,2,0) -> 002133.SZ | C80: 广宇集团 | D80: 42229 | E80: 42254 | F80: 2015年8月13日至2015年9月7日
B81: =VLOOKUP(C81,补充空白与2019的股票代码!A:B,2,0) -> 600218.SH | C81: 全柴动力 | D81: 42268 | E81: 42277 | F81: 2015年9月21日至2015年9月30日 | H81: 1支股票在两段时期内被操纵
B82: =VLOOKUP(C82,补充空白与2019的股票代码!A:B,2,0) -> 600218.SH | C82: 全柴动力 | D82: 42333 | E82: 42355 | F82: 2015年11月25日至2015年12月17日
B83: =VLOOKUP(C83,补充空白与2019的股票代码!A:B,2,0) -> 002220.SZ | C83: 天宝股份 | D83: 42293 | E83: 42310 | F83: 2015年10月16日至2015年11月2日
B84: =VLOOKUP(C84,补充空白与2019的股票代码!A:B,2,0) -> 000683.SZ | C84: 远兴能源 | D84: 42601 | E84: 42681 | F84: 2016年8月19日至2016年11月7日 | H84: 1支股票在两段时期内被操纵
B85: =VLOOKUP(C85,补充空白与2019的股票代码!A:B,2,0) -> 000683.SZ | C85: 远兴能源 | D85: 42920 | E85: 42999 | F85: 2017年7月4日至2017年9月21日
B86: =VLOOKUP(C86,补充空白与2019的股票代码!A:B,2,0) -> 300263.SZ | C86: 隆华节能 | D86: 42872 | E86: 43003 | F86: 2017年5月17日至2017年9月25日
B87: =VLOOKUP(C87,补充空白与2019的股票代码!A:B,2,0) -> 600251.SH | C87: 冠农股份 | D87: 42895 | E87: 42934 | F87: 2017年6月9日至2017年7月18日
B88: =VLOOKUP(C88,补充空白与2019的股票代码!A:B,2,0) -> 600300.SH | C88: 维维股份 | D88: 42892 | E88: 42902 | F88: 2017年6月6日至2017年6月16日 | H88: 1支股票在三段时期内被操纵
B89: =VLOOKUP(C89,补充空白与2019的股票代码!A:B,2,0) -> 600300.SH | C89: 维维股份 | D89: 42929 | E89: 42943 | F89: 2017年7月13日至2017年7月27日
B90: =VLOOKUP(C90,补充空白与2019的股票代码!A:B,2,0) -> 600300.SH | C90: 维维股份 | D90: 43019 | E90: 43032 | F90: 2017年10月11日至2017年10月24日
A91: 202333 | B91: =VLOOKUP(C91,'全部股票代码（手动检索）'!A:B,2,0) -> 600333.SH | C91: 长春燃气 | D91: 42774 | E91: 42782 | F91: 2017年2月8日至2017年2月16日 | G91: 45043
A92: 202327 | B92: =VLOOKUP(C92,'全部股票代码（手动检索）'!A:B,2,0) -> 300509.SZ | C92: 新美星 | D92: 43369 | E92: 43642 | F92: 2018年9月26日至2019年6月26日 | G92: 45027
A93: 202325 | C93: “天龙股份”等4支股票 | G93: 45023 | H93: 操纵多支股票
B94: =VLOOKUP(C94,'全部股票代码（手动检索）'!A:B,2,0) -> 603266.SH | C94: 天龙股份 | D94: 43509 | E94: 43595 | F94: 2019年2月13日至5月10日
B95: =VLOOKUP(C95,'全部股票代码（手动检索）'!A:B,2,0) -> 603365.SH | C95: 水星家纺 | D95: 43451 | E95: 43529 | F95: 2018年12月17日至2019年3月5日
B96: =VLOOKUP(C96,'全部股票代码（手动检索）'!A:B,2,0) -> 300539.SZ | C96: 横河模具 | D96: 43493 | E96: 43537 | F96: 2019年1月28日至3月13日
B97: =VLOOKUP(C97,'全部股票代码（手动检索）'!A:B,2,0) -> 300658.SZ | C97: 延江股份 | D97: 43509 | E97: 43595
A98: 202317 | B98: =VLOOKUP(C98,'全部股票代码（手动检索）'!A:B,2,0) -> 603222.SH | C98: 济民医疗 | D98: 42823 | E98: 43136 | F98: 2017年3月29日至2018年2月5日 | G98: 44992
B99: =VLOOKUP(C99,'全部股票代码（手动检索）'!A:B,2,0) -> 002178.SZ | C99: 延华智能 | D99: 43090 | E99: 43136 | F99: 2017年12月21日至2018年2月5日 | H99: 超比例持有，并非操纵
A100: 202305 | B100: =VLOOKUP(C100,'全部股票代码（手动检索）'!A:B,2,0) -> 002780.SZ | C100: 三夫户外 | D100: 43405 | E100: 44001 | F100: 2018年11月1日至2020年6月19日 | G100: 44958
A101: 202301 | G101: 44931 | H101: 信息披露违规，并非操纵
A102: 202273 | C102: “牧高笛”等13支股票
B103: =VLOOKUP(C103,补充空白与2019的股票代码!A:B,2,0) -> 603908.SH | C103: 牧高笛 | D103: 43570 | E103: 43580 | F103: 2019年4月15日至4月25日
...

Sheet 全部股票代码（手动检索）
A1: 股票名称
A2: 电光科技 | B2: =VLOOKUP(A2,部分股票代码!A:B,2,0) -> 002730.SZ
A3: 美尚生态 | B3: F1007420.00
A4: 利德曼 | B4: =VLOOKUP(A4,部分股票代码!A:B,2,0) -> 300289.SZ
A5: 艾迪精密 | B5: =VLOOKUP(A5,部分股票代码!A:B,2,0) -> 603638.SH
A6: 森源电气 | B6: =VLOOKUP(A6,部分股票代码!A:B,2,0) -> 002358.SZ
A7: 昊志机电 | B7: =VLOOKUP(A7,部分股票代码!A:B,2,0) -> 300503.SZ
A8: 金一文化 | B8: F1002802.00
A9: 利民股份 | B9: =VLOOKUP(A9,部分股票代码!A:B,2,0) -> 002734.SZ
A10: 兰太实业 | B10: 600328.SH
A11: 维力医疗 | B11: =VLOOKUP(A11,部分股票代码!A:B,2,0) -> 603309.SH
A12: 金自天正 | B12: =VLOOKUP(A12,部分股票代码!A:B,2,0) -> 600560.SH
A13: 桂东电力 | B13: 600310.SH
A14: 吉艾科技 | B14: 300309.SZ
A15: 英特集团 | B15: =VLOOKUP(A15,部分股票代码!A:B,2,0) -> 000411.SZ
A16: 正虹科技 | B16: =VLOOKUP(A16,部分股票代码!A:B,2,0) -> 000702.SZ
A17: 亚太实业 | B17: =VLOOKUP(A17,部分股票代码!A:B,2,0) -> 000691.SZ
A18: 杭州高新 | B18: =VLOOKUP(A18,部分股票代码!A:B,2,0) -> 300478.SZ
A19: 凯瑞德 | B19: =VLOOKUP(A19,部分股票代码!A:B,2,0) -> 002072.SZ
A20: 天广消防 | B20: 002509.SZ
A21: 天马精化 | B21: 002453.SZ
A22: 嘉应制药 | B22: =VLOOKUP(A22,部分股票代码!A:B,2,0) -> 002198.SZ
A23: 凤形股份 | B23: =VLOOKUP(A23,部分股票代码!A:B,2,0) -> 002760.SZ
A24: 新日恒力 | B24: 600165.SH
A25: 道尔智控 | B25: =VLOOKUP(A25,部分股票代码!A:B,2,0) -> 832966.NQ
A26: 力盛运动 | B26: 002858.SZ
A27: 凤形股份 | B27: =VLOOKUP(A27,部分股票代码!A:B,2,0) -> 002760.SZ
A28: 当代东方 | B28: 000673.SZ
A29: 朗迪集团 | B29: =VLOOKUP(A29,部分股票代码!A:B,2,0) -> 603726.SH
A30: 丽岛新材 | B30: =VLOOKUP(A30,部分股票代码!A:B,2,0) -> 603937.SH
A31: 麦迪电气 | B31: 300341.SZ
A32: 初灵信息 | B32: =VLOOKUP(A32,部分股票代码!A:B,2,0) -> 300250.SZ
A33: 深桑达A | B33: =VLOOKUP(A33,部分股票代码!A:B,2,0) -> 000032.SZ
A34: 恒锋信息 | B34: =VLOOKUP(A34,部分股票代码!A:B,2,0) -> 300605.SZ
A35: 中广天择 | B35: =VLOOKUP(A35,部分股票代码!A:B,2,0) -> 603721.SH
A36: 天药股份 | B36: 600488.SH
A37: 华电重工 | B37: =VLOOKUP(A37,部分股票代码!A:B,2,0) -> 601226.SH
A38: 龙建股份 | B38: =VLOOKUP(A38,部分股票代码!A:B,2,0) -> 600853.SH
A39: 柏堡龙 | B39: 002776.SZ
A40: 长春燃气 | B40: =VLOOKUP(A40,部分股票代码!A:B,2,0) -> 600333.SH
A41: 新美星 | B41: =VLOOKUP(A41,部分股票代码!A:B,2,0) -> 300509.SZ
A42: 天龙股份 | B42: =VLOOKUP(A42,部分股票代码!A:B,2,0) -> 603266.SH
A43: 水星家纺 | B43: =VLOOKUP(A43,部分股票代码!A:B,2,0) -> 603365.SH
A44: 横河模具 | B44: 300539.SZ
A45: 延江股份 | B45: =VLOOKUP(A45,部分股票代码!A:B,2,0) -> 300658.SZ
A46: 济民医疗 | B46: =VLOOKUP(A46,部分股票代码!A:B,2,0) -> 603222.SH
A47: 延华智能 | B47: =VLOOKUP(A47,部分股票代码!A:B,2,0) -> 002178.SZ
A48: 三夫户外 | B48: =VLOOKUP(A48,部分股票代码!A:B,2,0) -> 002780.SZ
A49: 汇金通 | B49: =VLOOKUP(A49,部分股票代码!A:B,2,0) -> 603577.SH
A50: 得邦照明 | B50: =VLOOKUP(A50,部分股票代码!A:B,2,0) -> 603303.SH
A51: 吉林高速 | B51: =VLOOKUP(A51,部分股票代码!A:B,2,0) -> 601518.SH
A52: 大连热电 | B52: =VLOOKUP(A52,部分股票代码!A:B,2,0) -> 600719.SH
A53: 宜宾纸业 | B53: =VLOOKUP(A53,部分股票代码!A:B,2,0) -> 600793.SH
A54: 绿城水务 | B54: =VLOOKUP(A54,部分股票代码!A:B,2,0) -> 601368.SH
A55: 宁波热电 | B55: 600982.SH
A56: 哈森股份 | B56: =VLOOKUP(A56,部分股票代码!A:B,2,0) -> 603958.SH
A57: 友邦吊顶 | B57: =VLOOKUP(A57,部分股票代码!A:B,2,0) -> 002718.SZ
A58: 大庆华科 | B58: =VLOOKUP(A58,部分股票代码!A:B,2,0) -> 000985.SZ
A59: 昇兴股份 | B59: =VLOOKUP(A59,部分股票代码!A:B,2,0) -> 002752.SZ
A60: ST天业 | B60: 600807.SH
A61: 宜华健康 | B61: 000150.SZ
A62: 上柴股份 | B62: 600841.SH
A63: 新莱应材 | B63: =VLOOKUP(A63,部分股票代码!A:B,2,0) -> 300260.SZ
A64: 三星新材 | B64: =VLOOKUP(A64,部分股票代码!A:B,2,0) -> 603578.SH
A65: 安德利 | B65: =VLOOKUP(A65,部分股票代码!A:B,2,0) -> 605198.SH
A66: 君禾股份 | B66: =VLOOKUP(A66,部分股票代码!A:B,2,0) -> 603617.SH
A67: 第一医药 | B67: =VLOOKUP(A67,部分股票代码!A:B,2,0) -> 600833.SH
A68: 梅轮电梯 | B68: =VLOOKUP(A68,部分股票代码!A:B,2,0) -> 603321.SH
A69: 康惠制药 | B69: =VLOOKUP(A69,部分股票代码!A:B,2,0) -> 603139.SH
A70: 亚振家居 | B70: =VLOOKUP(A70,部分股票代码!A:B,2,0) -> 603389.SH
A71: 诺邦股份 | B71: =VLOOKUP(A71,部分股票代码!A:B,2,0) -> 603238.SH
A72: 圣龙股份 | B72: =VLOOKUP(A72,部分股票代码!A:B,2,0) -> 603178.SH
A73: 金新农 | B73: =VLOOKUP(A73,部分股票代码!A:B,2,0) -> 002548.SZ
A74: 天铁股份 | B74: =VLOOKUP(A74,部分股票代码!A:B,2,0) -> 300587.SZ
... A77: 瑞普生物 | B77: =VLOOKUP(A77,部分股票代码!A:B,2,0) -> 300119.SZ
A78: 新光圆成 | B78: 002147.SZ
A79: 仁东控股 | B79: =VLOOKUP(A79,部分股票代码!A:B,2,0) -> 002647.SZ
A80: 天山生物 | B80: 300313.SZ
A81: 百合花 | B81: =VLOOKUP(A81,部分股票代码!A:B,2,0) -> 603823.SH
A82: 福建金森 | B82: =VLOOKUP(A82,部分股票代码!A:B,2,0) -> 002679.SZ
A83: 华鼎股份 | B83: =VLOOKUP(A83,部分股票代码!A:B,2,0) -> 601113.SH
A84: 新华医疗 | B84: =VLOOKUP(A84,部分股票代码!A:B,2,0) -> 600587.SH
A85: 弘宇股份 | B85: =VLOOKUP(A85,部分股票代码!A:B,2,0) -> 002890.SZ
A86: 吉林森工 | B86: 600189.SH
A87: 中昌数据 | B87: 600242.SH
A88: 华仁药业 | B88: =VLOOKUP(A88,部分股票代码!A:B,2,0) -> 300110.SZ
A89: 科菲特 | B89: 837367.NQ
A90: 华平股份 | B90: =VLOOKUP(A90,部分股票代码!A:B,2,0) -> 300074.SZ
A91: 公准股份 | B91: 830916.NQ
A92: 德美化工 | B92: =VLOOKUP(A92,部分股票代码!A:B,2,0) -> 002054.SZ
A93: 梅花生物 | B93: =VLOOKUP(A93,部分股票代码!A:B,2,0) -> 600873.SH
A94: 聚隆科技 | B94: 300475.SZ
A95: ST北讯 | B95: 400154.NQ
A96: 正平股份 | B96: =VLOOKUP(A96,部分股票代码!A:B,2,0) -> 603843.SH
A97: 阿波罗 | B97: =VLOOKUP(A97,部分股票代码!A:B,2,0) -> 832568.NQ
A98: 凯瑞德 | B98: =VLOOKUP(A98,部分股票代码!A:B,2,0) -> 002072.SZ
A99: 粤泰股份 | B99: 600393.SH

Sheet 部分股票代码
A1: 证券简称 | B1: 证券代码
A2: 电光科技 | B2: 002730.SZ
A3: 美尚生态景观股份有限公司 | B3: F1007420.00
A4: 利德曼 | B4: 300289.SZ
A5: 艾迪精密 | B5: 603638.SH
A6: 森源电气 | B6: 002358.SZ
A7: 昊志机电 | B7: 300503.SZ
A8: 北京金一文化发展股份有限公司 | B8: F1002802.00
A9: 利民股份 | B9: 002734.SZ
A10: 维力医疗 | B10: 603309.SH
A11: 金自天正 | B11: 600560.SH
A12: 广西能源股份有限公司 | B12: F1001132.00
... A76: 广州粤泰集团股份有限公司 | B76: F1001162.00

Sheet 补充空白与2019
A1: 是 | B1: 是 | C1: 〔2024〕6号当事人:张顺平,男,1977年9月出生,住址:山东省潍坊市高新技术开发区。依据2005年修订、2014年修正的《中华人民共和国证券法》(以下简称2005年《证券法》)的有关规定,我会对张顺平操纵证券市场行为进行了立案调查、审理,并依法向当事人告知了作出行政处罚的事实、理由、依据及当事人依法享有的权利,当事人未提出陈述、申辩意见,也未要求听证。本案现已调查、审理终结。经查明,张顺平存在以下违法事实:一、控制使用证券账户的情况根据账户名义持有人指认、其他涉案人员陈述、账户开户资料及情况说明、借款协议、账户资金往来记录、账户交易流水、手机取证信息、账户交易终端信息(IP、MAC、硬盘序列号、下单手机号)等证据,2017年6月26日至9月29日期间,张顺平控制使用“韩某萍”财通证券账户等27个证券账户(以下称“账户组1”),交易“维格娜丝”等7只股票;2018年3月6日至4月27日期间,张顺平控制使用“庞某”财达证券账户等39个证券账户(以下称“账户组2”),交易“秦安股份”等4只股票。张顺平实际控制使用账户组所从事的涉案交易,由张顺平决策,由其实际操作下单或指派他人下单。二、张顺平操纵“维格娜丝”等11只股票的情况2017年6月26日至9月29日期间,张顺平控制使用“账户组1”,通过集中资金优势、持股优势连续买卖,虚假申报等手段,影响“维格娜丝”“金麒麟”“康隆达”“铁流股份”“红蜻蜓”“日月股份”“太平鸟”等7只股票交易价格和交易量;2018年3月6日至4月27日期间,张顺平控制使用“账户组2”,通过集中资金优势、持股优势连续买卖,在自己实际控制的账户之间进行证券交易(以下简称对倒交易),虚假申报等手段,影响“秦安股份”“上海亚虹”“恒润股份”“中马传动”等4只股票交易价格和交易量。具体情况如下:(一)操纵“维格娜丝”的情况1.2017年7月25日至8月14日操纵情况2017年7月25日至8月14日期间,张顺平控制使用“账户组1”,通过集中资金优势连续买卖、虚假申报等手段,影响“维格娜丝”交易价格和交易量,操纵市场。期间累计买入3,366,130股,累计买入金额81,148,242.15元;累计卖出3,366,130股,累计卖出金额81,254,769.32元。“账户组1”期初持有“维格娜丝”0股,期间期末持有0股。(1)集中资金优势连续买卖2017年7月25日至8月14日期间,“维格娜丝”共有15个交易日,“账户组1”共有15个交易日参与交易,占期间该股交易日总数的100%。“账户组1”申买量排名第一的有10个交易日,买成交量排名第一的有10个交易日,均占期间该股交易日总数的66.67%。“账户组1”买成交量占当日市场成交量比例的日均值为18.33%,超过20%有7个交易日,2017年8月7日占比最高,达48.68%。“账户组1”申卖量排名第一的有6个交易日,卖成交量排名第一的有5个交易日,分别占期间该股交易日总数的40%和33.33%。“账户组1”卖成交量占当日市场成交量比例的日均值为13.27%,超过20%有3个交易日,2017年8月8日占比最高,达71.28%。2017年7月25日至8月14日期间,“账户组1”以不低于市场卖一价或市价申买3,460,500股,占同期该账户组同向总申报量比例的日均值为88.24%,日最高占比值为100%;该类申买成交3,132,942股,占同期市场成交量比例的日均值为23.47%,日最高占比值为42.31%。在上述期间,“账户组1”有3个交易日存在盘中时段内股价涨幅2%以上且时段内买成交占比20%以上的情形。(2)虚假申报2017年7月25日至8月14日期间,张顺平控制使用“账户组1”,不以成交为目的,频繁申报、撤单,并进行与申报相反的交易。“账户组1”申买撤单量占该账户组申买量比例的日均值为11.82%,其中,2017年8月9日13:29:57至13:32:19期间,“账户组1”申买26笔,申买量为253,900股,“账户组1”申买量占市场申买量的78.68%,对应撤单量占“账户组1”申买量的55.03%,自申买开始后反向申报卖出且成交838,581股,成交金额20,202,817.53元。2017年7月25日至8月14日期间,“维格娜丝”股价走势较上证综指明显异常。该股2017年7月25日前一交易日收盘价23.25元,上述期间最高收盘价24.82元(2017年8月3日),较期初上涨6.75%,而同期上证综指涨幅0.69%,股价偏离上证综指6.06个百分点;期末(2017年8月14日)收盘价23.10元,较期初下跌0.65%,同期上证综指跌幅0.41%,股价偏离上证综指0.24个百分点。2.2017年8月23日至9月14日操纵情况2017年8月23日至9月14日期间,张顺平控制使用“账户组1”,通过集中资金优势、持股优势连续买卖的手段,影响“维格娜丝”交易价格和交易量,操纵市场。期间累计买入14,797,508股,累计买入金额386,760,816.44元;累计卖出14,797,508股,累计卖出金额388,322,464.48元。“账户组1”期初持有“维格娜丝”0股,期间期末持有0股。2017年8月23日至9月14日期间,“维格娜丝”共有17个交易日,“账户组1”共有17个交易日参与交易,占期间该股交易日总数的100%。“账户组1”申买量排名第一的有14个交易日,买成交量排名第一的有15个交易日,分别占期间该股交易日总数的82.35%和88.24%。“账户组1”买成交量占当日市场成交量比例的日均值为26.85%,超过20%有12个交易日,2017年8月28日占比最高,达59.04%。“账户组1”期初持股为0,从2017年8月23日开始买入,所持“维格娜丝”股票数量不断增加,在上述期间有3个交易日持股量占该股流通股本比例大于5%,2017年9月4日持股量最多,达3,614,480股,占该股流通股本的6.50%。“账户组1”申卖量排名第一的有12个交易日,卖成交量排名第一的有12个交易日,均占期间该股交易日总数的70.59%。“账户组1”卖成交量占当日市场成交量比例的日均值为22.17%,超过20%有9个交易日,2017年9月8日占比最高,达51.16%。2017年8月23日至9月14日期间,“账户组1”以不低于市场卖一价或市价申买18,656,500股,占同期“账户组1”同向总申报量的平均值为75.72%,日最高占比值为99.59%;该类申买成交13,589,408股,占同期市场成交量比例的日均值为28.35%,日最高占比值为59.02%。“账户组1”共有8个交易日存在盘中时段内股价涨幅2%以上且时段内买成交占比20%以上的情形。2017年8月23日至9月14日期间,“维格娜丝”股价走势较上证综指明显异常。该股2017年8月23日前一交易日收盘价23.85元,上述期间最高收盘价26.87元(2017年9月1日),较期初上涨12.66%,而同期上证综指涨幅2.34%,股价偏离上证综指10.32个百分点;期末(2017年9月14日)收盘价25.62元,较期初上涨7.42%,同期上证综指涨幅2.47%,股价偏离上证综指4.95个百分点。经统计,张顺平通过“账户组1”交易“维格娜丝”盈利900,505.92元。(二)操纵“康隆达”的情况2017年9月20日至9月29日期间,张顺平控制使用“账户组1”,通过集中资金优势、持股优势连续买卖的手段,影响“康隆达”交易价格和交易量,操纵市场。期间“账户组1”累计买入2,357,198股,买入金额92,089,376.68元;累计卖出2,357,198股,卖出金额92,752,209.95元。“账户组1”期初持有“康隆达”0股,期间期末持有0股。2017年9月20日至9月29日期间,“康隆达”共有8个交易日,“账户组1”共有8个交易日参与交易,占期间该股交易日总数的100%。“账户组1”申买量排名第一的有7个交易日,买成交量排名第一的有4个交易日,分别占期间该股交易日总数的87.50%和50%。“账户组1”买成交量占当日市场成交量比例的日均值为15.60%,超过20%有2个交易日,2017年9月20日占比最高,达40.87%。“账户组1”期初持股为0,从2017年9月20日开始买入,所持“康隆达”股票数量不断增加,2017年9月22日持股量达1,361,020股,占该股流通股本的5.44%。“账户组1”申卖量排名第一的有2个交易日,卖成交量排名第一的有2个交易日,均占期间该股交易日总数的25%。“账户组1”卖成交量占当日市场成交量比例的日均值为11.70%,超过20%有2个交易日,2017年9月27日占比最高,达38.47%。2017年9月20日至9月29日期间,“账户组1”以不低于市场卖一价或市价申买2,779,200股,占同期“账户组1”同向总申报量比例的日均值为70.79%,日最高占比值为99.38%;该类申买成交1,987,113股,占同期市场成交量比例的日均值为17.84%,日最高占比值为35.65%。“账户组1”共有3个交易日存在盘中时段内股价涨幅2%以上且时段内买成交占比20%以上的情形。2017年9月20日至9月29日期间,“康隆达”股价走势较上证综指明显异常。该股2017年9月20日前一交易日收盘价37.12元,期间最高收盘价39.82元(2017年9月22日),较期初上涨7.27%,同期上证指数跌幅为0.13%,股价偏离上证综指7.40个百分点。期末(2017年9月29日)收盘价36.46元,较期初下跌1.78%,同期上证综指跌幅0.24%,股价偏离上证综指1.54个百分点。经统计,张顺平通过“账户组1”交易“康隆达”盈利512,617.73元。(三)操纵“金麒麟”的情况1.2017年8月22日至8月31日操纵情况2017年8月22日至8月31日期间,张顺平控制使用“账户组1”,通过集中资金优势连续买卖、虚假申报等手段,影响“金麒麟”交易价格和交易量,操纵市场。期间累计买入2,594,495股,累计买入金额79,808,907.69元;累计卖出2,594,495股,累计卖出金额81,081,823.44元。“账户组1”期初持有“金麒麟”0股,期间期末持有0股。2017年8月22日至8月31日期间,“金麒麟”共有8个交易日,“账户组1”共有8个交易日参与交易,占期间该股交易日总数的100%。“账户组1”申买量排名第一的有6个交易日,买成交量排名第一的有6个交易日,均占期间该股交易日总数的75%。“账户组1”买成交量占当日市场成交量比例的日均值为7.61%,超过20%有1个交易日,2017年8月25日占比达23.05%。“账户组1”申卖量排名第一的有4个交易日,卖成交量排名第一的有4个交易日,均占期间该股交易日总数的50%。“账户组1”卖成交量占当日市场成交量比例的日均值为6.66%,超过20%有1个交易日,2017年8月29日占比达21.77%。2017年8月22日至8月31日期间,“账户组1”以不低于市场卖一价或市价申买2,928,500股,占同期“账户组1”同向总申报量比例的日均值为89.57%,日最高占比值为100%;该类申买成交2,495,595股,占同期市场成交量比例的日均值为9.90%,日最高占比值为22.96%。2017年8月22日至8月31日期间,“金麒麟”股价走势较上证综指明显异常。该股2017年8月22日前一交易日收盘价30.11元,期间最高收盘价31.59元(2017年8月29日),较期初上涨4.92%,而同期上证综指涨幅2.38%,与同期上证综指偏离2.54个百分点。期末(2017年8月31日)收盘价31.55元,较期初上涨4.78%,同期上证综指涨幅2.25%,股价偏离上证综指2.53个百分点。2.2017年9月4日至9月22日操纵情况2017年9月4日至9月22日期间,张顺平控制使用“账户组1”,通过集中资金优势、持股优势连续买卖,虚假申报的手段,影响“金麒麟”交易价格和交易量,操纵市场。期间累计买入6,760,666股,累计买入金额221,119,994.94元;累计卖出6,760,666股,累计卖出金额223,864,885.75元。“账户组1”期初持有“金麒麟”0股,期间期末持有0股。(1)集中资金优势、持股优势连续买卖2017年9月4日至9月22日期间,“金麒麟”共有15个交易日,“账户组1”共有15个交易日参与交易,占期间该股交易日总数的100%。“账户组1”申买量排名第一的有12个交易日,买成交量排名第一的有11个交易日,分别占期间该股交易日总数的80%和73.33%。“账户组1”买成交量占当日市场成交量比例的日均值为10.78%,超过20%有1个交易日,2017年9月7日占比达29.11%。账户组1”期初持股为0,从2017年9月4日开始买入,所持“金麒麟”股票数量不断增加,上述期间有4个交易日持股量占该股流通股本比例大于5%,2017年9月18日持股量达3,290,743股,占该股流通股本的6.27%。“账户组1”申卖量排名第一的有7个交易日,卖成交量排名第一的有8个交易日,分别占期间该股交易日总数的46.67%和53.33%。“账户组1”卖成交量占当日市场成交量比例的日均值为8.24%,超过20%有2个交易日,2017年9月19日占比最高,达39.93%。2017年9月4日至9月22日期间,“账户组1”以不低于市场卖一价或市价申买8,383,900股,占同期“账户组1”同向总申报量比例的日均值为71.95%,日最高占比值为100%;该类申买成交6,086,705股,占同期市场成交量比例的日均值为11.47%,日最高占比值为29.18%。“账户组1”共有6个交易日存在盘中时段内股价涨幅2%以上且时段内买成交占比20%以上的情形。(2)虚假申报2017年9月4日至9月22日期间,张顺平控制使用“账户组1”,不以成交为目的,频繁申报、撤单,并进行与申报相反的交易。“账户组1”买入撤单量占“账户组1”申买量的日均比例为28.75%。其中,2017年9月13日9:15:03至14:58:07期间,“账户组1”申买506笔,申买量为2,551,100股,“账户组1”申买量占市场申买量的33.19%,对应撤单量占“账户组1”申买量的55.84%,自申买开始后反向申报卖出且成交643,900股,成交金额21,291,622.10元。2017年9月20日9:15:02至9:54:10期间,“账户组1”申买123笔,申买量为906,200股,“账户组1”申买量占市场申买量的43.72%,撤单量占“账户组1”申买量的76.70%,自申买开始后反向申报卖出且成交1,278,733股,成交金额42,662,057.88元。2017年9月4日至9月22日期间,“金麒麟”股价走势较上证综指明显异常。该股2017年9月4日前一交易日收盘价31.30元,期间最高收盘价34.06元(2017年9月18日),较期初上涨8.82%,而同期上证综指下跌0.13%,股价偏离上证综指8.95个百分点。期末(2017年9月22日)收盘价31.53元,较期初上涨0.73%,同期上证综指跌幅0.43%,股价偏离上证综指1.16个百分点。经统计,张顺平通过“账户组1”交易“金麒麟”盈利3,538,398.15元。(四)操纵“铁流股份”的情况2017年8月15日至8月25日期间,张顺平控制使用“账户组1”,通过集中资金优势、持股优势连续买卖,虚假申报等手段,影响“铁流股份”交易价格和交易量,操纵市场。期间“账户组1”累计买入6,819,267股,买入金额211,254,876.64元;累计卖出6,819,267股,卖出金额213,865,254.66元。“账户组1”期初持有“铁流股份”0股,期间期末持有0股。1.集中资金优势、持股优势连续买卖2017年8月15日至8月25日期间,“铁流股份”共有9个交易日,“账户组1”共有9个交易日参与交易,占期间该股交易日总数的100%。“账户组1”申买量排名第一的有8个交易日,买成交量排名第一的有8个交易日,占期间该股交易日总数的88.89%。“账户组1”买成交量占当日市场成交量比例的日均值为20.83%,超过20%有4个交易日,2017年8月17日占比最高,达44.03%。“账户组1”期初持股为0,从2017年8月15日开始买入,所持“铁流股份”股票数量不断增加,上述期间有3个交易日持股量占该股流通股本比例大于5%,2017年8月21日持股量达3,094,731股,占该股流通股本的10.32%。“账户组1”申卖量排名第一的有6个交易日,卖成交量排名第一的有6个交易日,均占期间该股交易日总数的66.67%。“账户组1”卖成交量占当日市场成交量比例的日均值为18.50%,超过20%有5个交易日,2017年8月22日占比最高,达50.89%。2017年8月15日至8月25日期间,“账户组1”以不低于市场卖一价或市价申买7,094,200股,占同期“账户组1”同向总申报量比例的日均值为71.52%,日最高占比值为93.31%;该类申买成交6,238,185股,占同期市场成交量比例的日均值为21.20%,日最高占比值为39.94%。“账户组1”共有5个交易日存在盘中时段内股价涨幅2%以上且时段内买成交占比20%以上的情形。2.虚假申报2017年8月15日至8月25日期间,张顺平控制使用“账户组1”,不以成交为目的,频繁申报、撤单,并进行与申报相反的交易。“账户组1”买入撤单量占“账户组1”申买量的日均比例为28.75%。其中,2017年8月24日9:15:02至9:30:02期间,“账户组1”申买3笔,申买量为221,900股,“账户组1”申买量占市场申买量的75.79%,对应撤单量占“账户组1”申买量的100%,自申买开始后反向申报卖出且成交539,869股,成交金额16,206,354.79元。2017年8月15日至8月25日,“铁流股份”股价走势较上证综指明显异常。该股2017年8月15日前一交易日收盘价28.31元,期间最高收盘价32.62元(2017年8月21日),较期初上涨15.22%,而同期上证综指涨幅1.53%,股价偏离上证综指13.69个百分点。期末(2017年8月25日)收盘价29.96元,较期初上涨5.83%,同期上证综指涨幅2.91%,股价偏离上证综指2.92个百分点。经统计,张顺平通过“账户组1”交易“铁流股份”盈利2,128,721.93元。(五)操纵“红蜻蜓”的情况1.2017年7月24日至8月2日操纵情况2017年7月24日至8月2日期间,张顺平控制使用“账户组1”,通过集中资金优势连续买卖、虚假申报等手段,影响“红蜻蜓”交易价格和交易量,操纵市场。期间“账户组1”累计买入7,891,653股,累计买入金额140,684,332.36元;累计卖出7,891,653股,累计卖出金额141,270,129.78元。“账户组1”期初持有“红蜻蜓”0股,期间期末持有0股。(1)集中资金优势连续买卖2017年7月24日至8月2日期间,“红蜻蜓”共有8个交易日,“账户组1”共有8个交易日参与交易,占期间该股交易日总数的100%。“账户组1”申买量排名第一的有6个交易日,买成交量排名第一的有6个交易日,均占期间该股交易日总数的75%。“账户组1”买成交量占当日市场成交量比例的日均值为22.19%,超过20%有5个交易日,2017年7月24日占比最高,达43.07%。“账户组1”申卖量排名第一的有6个交易日,卖成交量排名第一的有6个交易日,均占期间该股交易日总数的75%。2017年7月24日至8月2日期间,“账户组1”以不低于市场卖一价或市价申买8,978,100股,占同期“账户组1”同向总申报量比例的日均值为67.54%,日最高占比值为91.33%;该类申买成交7,466,852股,占同期市场成交量比例的日均值为24.06%,日最高占比值为41.82%。“账户组1”共有4个交易日存在盘中时段内股价涨幅2%以上且时段内买成交占比20%以上的情形。(2)虚假申报2017年7月24日至8月2日期间,张顺平控制使用“账户组1”,不以成交为目的,频繁申报、撤单,并进行与申报相反的交易。“账户组1”买入撤单量占“账户组1”申买量的日均比例为34.24%。其中,2017年7月28日9:23:26至13:02:51期间,“账户组1”申买118笔,申买量为1,233,800股,“账户组1”申买量占市场申买量的35.02%,对应撤单量占“账户组1”申买量的57.57%,自申买开始后反向申报卖出且成交2,299,500股,成交金额41,448,113.00元。2017年8月1日13:27:56至13:28:08期间,“账户组1”申买2笔,申买量为55,100股,“账户组1”申买量占市场申买量的98.39%,对应撤单量达到“账户组1”申买量的100%,自申买开始后反向申报卖出且成交147,074股,成交金额2,602,400.36元。2017年7月24日至8月2日期间,“红蜻蜓”股价走势较上证综指明显异常。该股2017年7月24日前一交易日收盘价17.07元,期间最高收盘价18.14元(2017年7月27日),较期初上涨6.27%,而同期上证综指涨幅0.36%,股价偏离上证综指偏离5.91个百分点。期末(2017年8月2日)收盘价17.34元,较期初上涨1.58%,同期上证综指涨幅1.45%,股价偏离上证综指0.13个百分点。2.2017年8月31日至9月8日操纵情况2017年8月31日至9月8日期间,张顺平控制使用“账户组1”,通过集中资金优势连续买卖的手段,影响“红蜻蜓”交易价格和交易量,操纵市场。期间“账户组1”累计买入2,925,600股,累计买入金额52,563,947.74元;累计卖出2,925,600股,累计卖出金额52,493,007.00元。“账户组1”期初持有“红蜻蜓”0股,期间期末持有0股。2017年8月31日至9月8日期间,“红蜻蜓”共有7个交易日,“账户组1”共有7个交易日参与交易,占期间该股交易日总数的100%。“账户组1”申买量排名第一的有3个交易日,买成交量排名第一的有3个交易日,均占期间该股交易日总数的42.86%。“账户组1”买成交量占当日市场成交量比例的日均值为9.68%,超过20%有2个交易日,2017年9月1日占比最高,达28.64%。“账户组1”申卖量排名第一的有2个交易日,卖成交量排名第一的有2个交易日,均占期间该股交易日总数的28.57%。“账户组1”卖成交量占当日市场成交量比例的日均值为11.27%,超过20%有2个交易日,2017年9月4日占比最高,达46.41%。2017年8月31日至9月8日期间,“账户组1”以不低于市场卖一价或市价申买2,955,300股,占同期“账户组1”同向总申报量比例的日均值为98.55%,日最高占比值为99.22%;该类申买成交2915500股,占同期市场成交量比例的日均值为22.53%,日最高占比值为28.63%。该股2017年8月31日前一交易日收盘价17.70元,期间最高收盘价18.13元(2017年9月1日),较期初上涨2.43%,而同期上证综指涨幅0.10%,股价偏离上证综指2.33个百分点。期末(2017年9月8日)收盘价17.88元,较期初上涨1.02%,同期上证综指涨幅0.05%,股价偏离上证综指0.97个百分点。经统计,张顺平通过“账户组1”交易“红蜻蜓”盈利127,659.28元。(六)操纵“日月股份”的情况2017年7月20日至7月26日期间,张顺平控制使用“账户组1”,通过集中资金优势连续买卖、虚假申报的手段,影响“日月股份”交易价格和交易量,操纵市场。期间“账户组1”累计买入2,685,999股,累计买入金额86,377,979.88元;累计卖出2,685,999股,累计卖出金额88,682,811.24元。“账户组1”期初持有“日月股份”0股,期间期末持有0股。1.集中资金优势连续买卖2017年7月20日至7月26日期间,“日月股份”共有5个交易日,“账户组1”共有5个交易日参与交易,占期间该股交易日总数的100%。“账户组1”申买量排名第一的有4个交易日,买成交量排名第一的有4个交易日,均占期间该股交易日总数的80%。“账户组1”买成交量占当日市场成交量比例的日均值为18.03%,超过20%有3个交易日,2017年7月24日占比最高,达35.22%。“账户组1”申卖量排名第一的有3个交易日,卖成交量排名第一的有4个交易日,分别占期间该股交易日总数的60%和80%。“账户组1”卖成交量占当日市场成交量比例的日均值为13.46%,超过20%有1个交易日,2017年7月25日占比达42.16%。2017年7月20日至7月26日期间,“账户组1”以不低于市场卖一价或市价申买4,012,500股,占同期“账户组1”同向总申报量比例的日均值为79.38%,日最高占比值为92.40%;该类申买成交2,574,099股,占同期市场成交量比例的日均值为21.62%,日最高占比值为33.78%。“账户组1”共有4个交易日存在盘中时段内股价涨幅2%以上且时段内买成交占比20%以上的情形。2.虚假申报2017年7月20日至7月26日期间,张顺平控制使用“账户组1”,不以成交为目的,频繁申报、撤单,并进行与申报相反的交易。“账户组1”申买撤单量占“账户组1”申买量的日均比例为35.73%。其中,2017年7月21日9:15:02至14:57:51期间,“账户组1”申买403笔,申买量为1,740,200股,“账户组1”申买量占市场申买量的33.86%,对应撤单量占“账户组1”申买量的55.20%,自申买开始后反向申报卖出且成交267,252股,成交金额8,555,173.29元。2017年7月24日9:19:14至14:59:04期间,“账户组1”申买362笔,申买量为2,213,400股,“账户组1”申买量占市场申买量的43.51%,对应撤单量占“账户组1”申买量的56.54%,自申买开始后反向申报卖出且成交202,200股,成交金额6,676,962.00元。2017年7月25日9:15:03至9:33:04期间,“账户组1”申买10笔,申买量为149,800股,“账户组1”申买量占市场申买量的55.85%,对应撤单量占“账户组1”申买量的96.06%,自申买开始后反向申报卖出且成交1,975,347股,成交金额65,650,923.67元。2017年7月20日至7月26日期间,“日月股份”股价走势较上证综指明显异常。该股2017年7月20日前一交易日收盘价30.48元,期间最高收盘价33.26元(2017年7月25日),较期初上涨9.12%,而同期上证综指涨幅0.39%,股价偏离上证综指8.73个百分点。期末(2017年7月26日)收盘价31.68元,较期初上涨3.94%,同期上证综指涨幅0.52%,股价偏离上证综指3.42个百分点。经统计,张顺平通过“账户组1”交易“日月股份”盈利2,160,131.60元。(七)操纵“太平鸟”的情况1.2017年6月26日至7月7日操纵情况2017年6月26日至7月7日期间,张顺平控制使用“账户组1”,通过集中资金优势连续买卖的手段,影响“太平鸟”交易价格和交易量,操纵市场。期间“账户组1”累计买入1,341,057股,累计买入金额36,652,408.66元;累计卖出1,341,057股,累计卖出金额38,269,837.44元。“账户组1”期初持有“太平鸟”0股,期间期末持有0股。2017年6月26日至7月7日期间,“太平鸟”共有10个交易日,“账户组1”共有8个交易日参与交易,占期间该股交易日总数的80%。“账户组1”申买量排名第一的有4个交易日,买成交量排名第一的有4个交易日,均占期间该股交易日总数的40%。“账户组1”买成交量占当日市场成交量比例的日均值为6.46%,2017年6月28日占比最高,达17.64%。“账户组1”申卖量排名第一的有3个交易日,卖成交量排名第一的有4个交易日,分别占期间该股交易日总数的30%和40%。“账户组1”卖成交量占当日市场成交量比例的日均值为3.55%,2017年7月5日占比最高,达11.77%。2017年6月26日至7月7日期间,“账户组1”以不低于市场卖一价或市价申买1,118,200股,占同期“账户组1”同向总申报量比例的日均值为49.51%,日最高占比值为74.27%;该类申买成交1,097,222股,占同期市场成交量比例的日均值为6.77%,日最高占比值为12.35%。2017年6月26日至7月7日期间,“太平鸟”股价走势较上证综指明显异常。该股2017年6月26日前一交易日收盘价26.78元,期间最高收盘价28.71元(2017年7月5日),较期初上涨7.21%,而同期上证综指涨幅1.56%,股价偏离上证综指5.65个百分点。期末(2017年7月7日)收盘价28.10元,较期初上涨4.93%,同期上证综指涨幅1.90%,股价偏离上证综指3.03个百分点。2.2017年7月20日至7月28日操纵情况2017年7月20日至7月28日期间,张顺平控制使用“账户组1”,通过集中资金优势连续买卖的手段,影响“太平鸟”交易价格和交易量,操纵市场。期间“账户组1”累计买入1,511,013股,累计买入金额38,387,728.69元;累计卖出1,511,013股,累计卖出金额39,089,971.45元。“账户组1”期初持有“太平鸟”0股,期间期末持有0股。2017年7月20日至7月28日期间,“太平鸟”共有7个交易日,“账户组1”共有7个交易日参与交易,占期间该股交易日总数的100%。“账户组1”申买量排名第一的有2个交易日,买成交量排名第一的有4个交易日,分别占期间该股交易日总数的28.57%和57.14%。“账户组1”买成交量占当日市场成交量比例的日均值为8.96%,超过20%有1个交易日,2017年7月26日占比最高,达28.94%。“账户组1”申卖量排名第一的有2个交易日,卖成交量排名第一的有3个交易日,分别占期间该股交易日总数的28.57%和42.86%。2017年7月20日至7月28日期间,“账户组1”以不低于市场卖一价或市价申买1,706,200股,占同期“账户组1”同向总申报量比例的日均值为93.46%,日最高占比值为99.32%;该类申买成交1,442,113股,占同期市场成交量比例的日均值为12.08%,日最高占比值为28.17%。“账户组1”共有2个交易日存在盘中时段内股价涨幅2%以上且时段内买成交占比20%以上的情形。2017年7月20日至7月28日期间,“太平鸟”股价走势较上证综指明显异常。该股2017年7月20日前一交易日收盘价25.08元,期间最高收盘价26.24元(2017年7月26日),较期初上涨4.63%,而同期上证综指涨幅0.52%,股价偏离上证综指4.11个百分点。期末(2017年7月28日)收盘价25.26元,较期初上涨0.72%,同期上证综指涨幅0.69%,股价偏离上证综指0.03个百分点。经统计,张顺平通过“账户组1”交易“太平鸟”盈利2,192,927.56元。(八)操纵“秦安股份”的情况2018年3月13日至4月3日,张顺平控制使用“账户组2”,通过集中资金优势、持股优势连续买卖,对倒交易,虚假申报等手段,影响“秦安股份”交易价格和交易量,操纵市场。期间累计买入18,228,186股,累计买入金额247,520,492.27元;累计卖出18,228,186股,累计卖出金额249,653,622.86元。“账户组2”期初持有“秦安股份”0股,期间期末持有0股。1.集中资金优势、持股优势连续买卖2018年3月13日至4月3日期间,“秦安股份”共有16个交易日,“账户组2”共有16个交易日参与交易,占期间该股交易日总数的100%。“账户组2”累计竞价买入成交15,150,590股(扣除对倒成交量),累计竞价卖出成交15,150,590股(扣除对倒成交量)。“账户组2”申买量排名第一的有15个交易日,买成交量排名第一的有13个交易日,分别占期间该股交易日总数的93.75%和81.25%。“账户组2”买成交量占当日市场成交量的日均值为22.50%,超过20%的有10个交易日,2018年3月19日占比最高,达48.65%。“账户组2”期初持股为0,从2018年3月13日开始买入,所持“秦安股份”股票数量不断增加,期间有7个交易日持股量占该股流通股本比例大于5%,有3个交易日持股量占该股流通股本比例大于10%,2018年3月23日持股量最多,达7,203,281股,占该股流通股本的12.01%。“账户组2”申卖量排名第一的有11个交易日,卖成交量排名第一的有11个交易日,均占期间该股交易日总数的68.75%。“账户组2”卖成交量占当日市场成交量比例的日均值为18.65%,超过20%的有6个交易日,2018年3月27日占比最高,达61.34%。2018年3月13日至4月3日期间,“账户组2”以不低于市场卖一价或市价申买20,304,100股,占同期账户组同向总申报量比例的日均值为60.30%,日最高占比值为98.26%;该类申买成交15,052,786股,占同期市场成交量比例的日均值为19.95%,日最高占比值为42.41%。在上述期间,“账户组2”共有9个交易日存在盘中时段内股价涨幅2%以上且时段内买成交占比20%以上的情形。2.对倒交易2018年3月13日至4月3日期间,当事人共有13个交易日在自己实际控制的账户之间交易“秦安股份”,成交量3,077,596股;其中,有1个交易日在自己实际控制的账户之间交易的成交量占当日市场成交量的比例大于10%,2018年3月22日占比达21.34%。3.虚假申报2018年3月13日至4月3日期间,张顺平控制使用“账户组2”,不以成交为目的,频繁申报、撤单,并进行与申报相反的交易。“账户组2”申买撤单量占“账户组2”申买量比例的日均值为31.54%。其中,2018年3月29日9:15:01至13:59:02期间,“账户组2”申买2,423笔,申买量为4,416,800股,“账户组2”申买量占市场申买量的42.15%,对应撤单量占“账户组2”申买量的53.50%,自申买开始后反向申报卖出且成交3,330,063股,成交金额45,674,621.14元;2018年3月30日9:15:01至10:31:37期间,“账户组2”申买790笔,申买量为1,973,900股,“账户组2”申买量占市场申买量的34.36%,对应撤单量占“账户组2”申买量的85.91%,自申买开始后反向申报卖出且成交1,605,720股,成交金额21,784,014.43元;2018年4月2日9:22:36至9:30:57期间,“账户组2”申买38笔,申买量为696,300股,“账户组2”申买量占市场申买量的73.54%,对应撤单量占“账户组2”申买量的99.87%,自申买开始后反向申报卖出且成交188,200股,成交金额2,522,185.95元。2018年3月13日至4月3日期间,“秦安股份”股价走势较上证综指明显异常,该股2018年3月13日前一交易日收盘价12.52元,上述期间最高收盘价14.33元(2018年3月20日),较期初上涨14.46%,而同期上证综指跌幅1.08%,股价偏离上证综15.54个百分点;期末(2018年4月3日)收盘价12.36元,较期初上涨1.92%,同期上证指数跌幅5.71%,股价偏离上证综指7.63个百分点。经统计,张顺平通过“账户组2”交易“秦安股份”盈利1,741,415.47元。(九)操纵“上海亚虹”的情况2018年3月9日至3月16日期间,张顺平控制使用“账户组2”,通过集中资金优势、持股优势连续买卖手段,影响“上海亚虹”交易价格和交易量,操纵市场。期间累计买入1,980,778股,累计买入金额47,122,545.36元;累计卖出1,980,778股,累计卖出金额49,174,430.06元。“账户组2”期初持有“上海亚虹”0股,期间期末持有0股。2018年3月9日至3月16日期间,“上海亚虹”共有6个交易日,“账户组2”共有6个交易日参与交易,占期间该股交易日总数的100%。“账户组2”申买量排名第一的有4个交易日,买成交量排名第一的有3个交易日,分别占期间该股交易日总数的66.67%和50%。“账户组2”买成交量占当日市场成交量比例的日均值为15.04%,超过20%的有2个交易日,2018年3月9日占比最高,达29.12%。“账户组2”期初持股为0,从2018年3月9日开始买入,所持“上海亚虹”股票数量不断增加,操纵期间有1个交易日持股量占该股流通股本比例大于5%,2018年3月12日持股量最多,达1,362,378股,占该股流通股本的5.45%。“账户组2”申卖量排名第一的有2个交易日,卖成交量排名第一的有2个交易日,均占期间该股交易日总数的33.33%。“账户组2”卖成交量占当日市场成交量比例的日均值为14.59%,超过20%的有2个交易日,2018年3月13日占比最高,达38.78%。2018年3月9日至3月16日期间,“账户组2”以不低于市场卖一价或市价申买1,954,500股,占同期账户组同向总申报量比例的日均值为53.89%,日最高占比值为100%;该类申买成交1,630,378股,占同期市场成交量比例的日均值为12.53%,日最高占比值为28.73%。在上述期间,“账户组2”共有3个交易日存在盘中时段内股价涨幅2%以上且时段内买成交占比20%以上的情形。2018年3月9日至3月16日期间,“上海亚虹”股价走势较上证综指明显异常,该股2018年3月9日前一交易日收盘价21.53元,上述期间最高收盘价25.27元(2018年3月12日),较期初上涨17.37%,而同期上证综指涨幅1.16%,股价偏离上证综指16.21个百分点;期末(2018年3月16日)收盘价22.38元,较期初上涨3.95%,同期上证指数跌幅0.56%,股价偏离上证综指4.51个百分点。经统计,张顺平通过“账户组2”交易“上海亚虹”盈利1,977,487.20元。(十)操纵“恒润股份”的情况2018年4月2日至4月25日期间,张顺平控制使用“账户组2”,通过集中资金优势、持股优势连续买卖,对倒交易,虚假申报等手段,影响“恒润股份”交易价格和交易量,操纵市场。期间累计买入12,523,172股,累计买入金额479,615,116.96元;累计卖出12,312,172股,累计卖出金额467,356,984.35元。账户组期初持有“恒润股份”0股,期末持有211,000股。1.集中资金优势、持股优势连续买卖2018年4月2日至4月25日期间,“恒润股份”共有16个交易日,“账户组2”共有16个交易日参与交易,占期间该股交易日总数的100%。“账户组2”累计竞价买入成交10,328,629股(扣除对倒成交量);累计竞价卖出成交10,117,629股(扣除对倒成交量)。“账户组2”申买量排名第一的有15个交易日,买成交量排名第一的有14个交易日,分别占期间该股交易日总数的93.75%和87.5%。“账户组2”买成交量占当日市场成交量比例的日均值为32.02%,超过20%的有13个交易日,2018年4月10日占比最高,达49.05%。“账户组2”期初持股为0,从2018年4月2日开始买入,所持“恒润股份”股票数量不断增加,期间有10个交易日持股量占该股流通股本比例大于5%,有7个交易日持股量占该股流通股本比例大于10%,2018年4月10日持股量最多,达3,419,043股,占该股流通股本的17.1%。“账户组2”申卖量排名第一的有14个交易日,卖成交量排名第一的有15个交易日,分别占期间该股交易日总数的87.5%和93.75%。“账户组2”卖成交量占当日市场成交量比例的日均值为29.67%,超过20%的有8个交易日,2018年4月17日占比最高,达62.66%。2018年4月2日至4月25日期间,“账户组2”以不低于市场卖一价或市价申买14,248,200股,占同期账户组同向总申报量比例的日均值为57.36%,日最高占比值为98.00%;该类申买成交10,518,272股,占同期市场成交量比例的日均值为27.10%,日最高占比值为42.46%。在上述期间,“账户组2”共有11个交易日存在盘中时段内股价涨幅2%以上且时段内买成交占比20%以上的情形。2.对倒交易2018年4月2日至4月25日期间,当事人共有14个交易日在自己实际控制的账户之间交易“恒润股份”,成交量2,194,543股;其中,有2个交易日在自己实际控制的账户之间交易的成交量占当日市场成交量的比例大于10%,2018年4月13日占比最高,达14.4%。3.虚假申报2018年4月2日至4月25日期间,张顺平控制使用“账户组2”,不以成交为目的,频繁申报、撤单,并进行与申报相反的交易。“账户组2”申买撤单量占“账户组2”申买量比例的日均值为25.72%。其中,2018年4月24日9:15:00至10:24:22期间,“账户组2”申买306笔,申买量为858,300股,“账户组2”申买量占市场申买量的54.83%,对应撤单量占“账户组2”申买量的95.36%,自申买开始后反向申报卖出且成交242,200股,成交金额8,198,625.00元。2018年4月2日至4月25日期间,“恒润股份”股价走势较上证综指明显异常,该股2018年4月2日前一交易日收盘价32.54元,上述期间最高收盘价40.52元(2018年4月11日),较期初上涨24.52%,而同期上证综指涨幅1.24%,股价偏离上证综指23.28个百分点;期末(2018年4月25日)收盘价34.1元,较期初上涨4.79%,同期上证指数跌幅1.61%,股价偏离上证综指6.40个百分点。经统计,张顺平通过“账户组2”交易“恒润股份”亏损6,302,121.55元。(十一)操纵“中马传动”的情况2018年3月6日至4月11日期间,张顺平控制使用“账户组2”,通过集中资金优势、持股优势连续买卖,对倒交易,虚假申报等手段,影响“中马传动”交易价格和交易量,操纵市场。期间累计买入17,605,196股,累计买入金额254,263,943.10元;累计卖出17,605,196股,累计卖出金额260,247,279.70元。“账户组2”期初持有“中马传动”0股,期间期末持有0股。1.集中资金优势、持股优势连续买卖2018年3月6日至4月11日期间,“中马传动”共有25个交易日,“账户组2”共有25个交易日参与交易,占期间该股交易日总数的100%。“账户组2”累计竞价买入成交15,237,582股(扣除对倒成交量);累计竞价卖出成交15,237,582股(扣除对倒成交量)。“账户组2”申买量排名第一的有20个交易日,买成交量排名第一的有21个交易日,分别占期间该股交易日总数的80%和84%。“账户组2”买成交量占当日市场成交量比例的日均值为17.41%,超过20%的有10个交易日,2018年3月20日占比最高,达39.60%。“账户组2”期初持股为0,从2018年3月6日开始买入,所持“中马传动”股票数量不断增加,期间有2个交易日持股量占该股流通股本比例大于5%,有1个交易日持股量占该股流通股本比例大于10%,2018年4月2日持股量最多,达5,861,833股,占该股流通股本的10.99%。“账户组2”申卖量排名第一的有17个交易日,卖成交量排名第一的有16个交易日,分别占期间该股交易日总数的68%和64%。“账户组2”卖成交量占当日市场成交量比例的日均值为13.58%,超过20%的有6个交易日,2018年4月3日占比最高,达45.82%。2018年3月6日至4月11日期间,“账户组2”以不低于市场卖一价或市价申买18,339,800股,占同期账户组同向总申报量比例的日均值为68.81%,日最高占比值为100%;该类申买成交15,194,149股,占同期市场成交量比例的日均值为14.34%,日最高占比值为33.75%。在上述期间,账户组共有10个交易日存在盘中时段内股价涨幅2%以上且时段内买成交占比20%以上的情形。2.对倒交易2018年3月6日至4月11日期间,当事人共有17个交易日在自己实际控制的账户之间交易“中马传动”,成交量2,367,614股;其中,有3个交易日在自己实际控制的账户之间交易的成交量占当日市场成交量的比例大于10%,2018年3月20日占比最高,达31.61%。3.虚假申报2018年3月6日至4月11日期间,张顺平控制使用“账户组2”,不以成交为目的,频繁申报、撤单,并进行与申报相反的交易。“账户组2”申买撤单量占“账户组2”申买量比例的日均值为23.74%。其中,2018年3月8日11:21:50至13:19:49期间,“账户组2”申买7笔,申买量为100,300股,“账户组2”申买量占市场申买量的31.89%,对应撤单量占“账户组2”申买量的83.13%,自申买开始后反向申报卖出且成交213,300股,金额2,840,885.00元。2018年3月12日13:03:47至13:07:28期间,“账户组2”申买3笔,申买量为17,400股,“账户组2”申买量占市场申买量的38.33%,对应撤单量占“账户组2”申买量的69.54%,自申买开始后反向申报卖出且成交1,089,124股,金额15,504,154.88元。2018年3月22日9:15:03至13:15:12期间,“账户组2”申买947笔,申买量为2,456,500股,“账户组2”申买量占市场申买量的35.94%,对应撤单量占“账户组2”申买量的54.43%,自申买开始后反向申报卖出且成交2,051,647股,金额28,894,229.47元。2018年3月23日9:15:02至10:32:54期间,“账户组2”申买731笔,申买量为1,466,200股,“账户组2”申买量占市场申买量的36.98%,对应撤单量占“账户组2”申买量的77.24%,自申买开始后反向申报卖出且成交748,147股,金额10,478,398.65元。2018年4月4日9:15:03至14:10:59期间,“账户组2”申买1,659笔,申买量为3,956,700股,“账户组2”申买量占市场申买量的34.60%,对应撤单量占“账户组2”申买量的60.32%,自申买开始后反向申报卖出且成交2,107,215股,金额32,098,118.17元。2018年3月6日至4月11日期间,“中马传动”股价走势较上证综指明显异常,该股2018年3月6日前一交易日收盘价13.16元,上述期间最高收盘价16.04元(2018年4月11日),较期初上涨21.88%,而同期上证综指跌幅1.50%,股价偏离上证综指23.38个百分点;期末(2018年4月11日)收盘价16.04元,较期初上涨21.88%,同期上证指数跌幅1.50%,股价偏离上证综指23.38个百分点。经统计,张顺平通过“账户组2”交易“中马传动”盈利5,570,203.06元。综上,2017年6月26日至2018年4月27日期间,张顺平控制使用“账户组1”和“账户组2”操纵“维格娜丝”等11只股票,合计盈利20,850,067.90元。上述违法事实,有相关人员询问笔录、证券账户资料及情况说明、交易流水、证券账户交易终端信息、银行账户资料、证券交易所统计数据等证据证明,足以认定。张顺平的上述行为违反了2005年《证券法》第七十七条第一款第一项、第三项和第四项的规定,构成2005年《证券法》第二百零三条所述的操纵证券市场行为。根据当事人违法行为的事实、性质、情节与社会危害程度,依据2005年《证券法》第二百零三条的规定,我会决定:责令张顺平依法处理非法持有的证券,没收违法所得20,850,067.90元,并处以62,550,203.70元罚款。上述当事人应自收到本处罚决定书之日起15日内,将罚没款汇交中国证券监督管理委员会开户银行:中信银行北京分行营业部,账号:7111010189800000162,由该行直接上缴国库,并将注有当事人名称的付款凭证复印件送中国证券监督管理委员会行政处罚委员会办公室备案。当事人如果对本处罚决定不服,可在收到本处罚决定书之日起60日内向中国证券监督管理委员会申请行政复议,也可在收到本处罚决定书之日起6个月内直接向有管辖权的人民法院提起行政诉讼。复议和诉讼期间,上述决定不停止执行。中国证监会2024年1月15日 | D1: 45306
A2: 是 | B2: 是 | C2: 〔2023〕83号当事人:陈磊,男,1970年3月出生,深圳市君如资产管理顾问有限公司(以下简称君如资产)董事长,住址:广东省深圳市罗湖区。吴限,男,1968年5月出生,深圳市劲拓自动化设备股份有限公司(以下简称劲拓股份)实际控制人,时任劲拓股份董事长。住址:广东省深圳市南山区。林建武,男,1974年9月出生,深圳市汇海宏融投资发展有限公司(以下简称汇海宏融)董事长,住址:广东省深圳市宝安区。依据2005年修订的《中华人民共和国证券法》(以下简称2005年《证券法》)有关规定,我会依法对陈磊、吴限、林建武等操纵劲拓股份股票价格进行了立案调查、审理,并依法向当事人告知了做出行政处罚的事实、理由、依据以及当事人依法享有的权利。根据当事人陈磊、林建武、吴限的要求,我会举行了听证,听取了当事人的陈述和申辩。本案现已调查、审理终结。经查明,陈磊、吴限、林建武存在以下违法事实:一、陈磊、林建武、吴限筹划、商议劲拓股份市值管理2017年6月,君如资产执行董事陈磊要求君如资产员工制作劲拓股份市值管理方案,拟联系劲拓股份大股东合作进行市值管理。汇海宏融董事长林建武与劲拓股份董事长及实际控制人吴限为朋友关系,两人均为长江商学院校友。2017年7月下旬至8月初,陈磊与林建武就劲拓股份市值管理及双方合作事宜多次沟通,并签订协议,约定由林建武帮助君如资产与吴限达成劲拓股份市值管理合作,陈磊则承诺将相关收益分配给林建武作为回报。在此期间,经由林建武居间,陈磊顺利接洽劲拓股份大股东及实际控制人吴限,三方合作开展劲拓股份市值管理项目。2017年8月7日,君如资产员工将劲拓股份市值管理项目进展状态更新为“完成签约,募集资金中”。之后,劲拓股份市值管理合作项目进入实质性操作阶段。二、当事人控制使用账户情况陈磊、林建武和吴限三方紧密合作,为实施市值管理筹集资金、准备账户。其中,吴限筹资以他人名义认购华宝信托有限责任公司-“辉煌”184号单一资金信托(以下简称“辉煌184号”)、陕西国际信托股份有限公司-陕国投·金元宝31号证券投资集合资金信托计划(以下简称“金元宝31号”)B类份额,通过1比2配资成立信托计划,将产品账户交由投资顾问君如资产具体操作。陈磊通过君如资产、深圳市前海小龙资产管理有限公司(以下简称前海小龙)、玖盈资本管理(深圳)有限责任公司(以下简称玖盈资本)等平台,发起设立数只私募基金产品,筹集大量资金,主要用于交易“劲拓股份”等由君如资产负责市值管理的股票。林建武亦参与了相关资金与账户的筹集活动。同时,陈磊、林建武、吴限等还使用多个自然人证券账户交易“劲拓股份”。陈磊、林建武、吴限控制账户(以下简称账户组)具体如下:1.陈磊控制使用23个账户根据账户资金来源、相关当事人之间关于账户设立和使用的信息交流、PB系统具体使用情况、交易终端关联及相关当事人询问笔录等证据,陈磊实际控制使用“辉煌184号”等23个账户,涉及28个证券账号:“辉煌184号”账户,2017年10月18日于华林证券深圳龙华证券营业部开立资金账户,下挂深圳证券账户089****074。“金元宝31号”账户,2017年12月5日于中信证券广东分公司开立资金账户,下挂深圳证券账户089****568。“兴业期货-进取1号集合资产管理计划”(以下简称“兴业进取1号”)账户,2017年12月26日于中信证券上海东方路证券营业部开立资金账户,下挂深圳证券账户089****307。“深圳市君如资产管理顾问有限公司-君如价值1号私募证券投资基金”(以下简称“君如价值1号”)账户,2018年3月12日于江海证券深圳民田路证券营业部开立信用资金账户,下挂深圳信用证券账户068***981。“深圳市君如资产管理顾问有限公司-君如价值2号私募证券投资基金”(以下简称“君如价值2号”)账户,2018年3月12日于江海证券深圳民田路营业部开立信用资金账户,下挂深圳信用证券账户068****982。“深圳市君如资产管理顾问有限公司-君如精选5号私募证券投资基金”(以下简称“君如精选5号”)账户,2018年6月6日于光大证券深圳新园路证券营业部开立资金账户,下挂深圳证券账户089***874。“深圳市君如资产管理顾问有限公司-君如精选6号私募证券投资基金”(以下简称“君如精选6号”)账户,2019年1月23日于华创证券凯里文化北路证券营业部开立信用资金账户,下挂深圳信用证券账户068***907。“深圳市君如资产管理顾问有限公司-赢丰成长1号私募基金”(以下简称“君如赢丰1号”)账户,2017年12月6日于华林证券深圳龙华证券营业部开立信用资金账户,下挂深圳信用证券账户068***449。“深圳市君如资产管理顾问有限公司-创智1号私募基金”(以下简称“君如创智1号”)账户,2018年1月24日于华林证券深圳龙华证券营业部开立信用资金账户,下挂深圳信用证券账户068***324。“深圳市前海小龙资产管理有限公司-小龙趋势1号私募证券投资基金”(以下简称“小龙趋势1号”)账户,2018年8月30日于光大证券深圳新园路营业部开立普通资金账户,下挂深圳证券账户089***458,2018年8月31日开立信用资金账户,下挂深圳信用证券账户068***005。“玖盈资本管理(深圳)有限责任公司-玖盈一号私募证券投资基金”(以下简称“玖盈一号”)账户,2018年12月18日于国泰君安证券深圳益田路营业部开立资金账户,下挂深圳证券账户089***207,2018年12月25日开立信用资金账户,下挂深圳信用证券账户068***579。“玖盈资本管理(深圳)有限责任公司-玖盈二号私募证券投资基金”(以下简称“玖盈二号”)账户,2019年1月24日于东兴证券福州五四路证券营业部开立资金账户,下挂深圳证券账户089****317,2019年1月29日开立信用资金账户,下挂深圳信用证券账户068***977。“玖盈资本管理(深圳)有限责任公司-玖盈三号私募证券投资基金”(以下简称“玖盈三号”)账户,2019年1月8日于国泰君安证券深圳益田路营业部开立资金账户,下挂深圳证券账户089****418、深圳信用证券账户068****764。“孙某梅”账户,2017年12月12日于中泰证券济南英雄山路证券营业部开立信用资金账户,下挂深圳信用证券账户060****198。“孙某瑞”账户,2017年8月21日于中泰证券济南英雄山路证券营业部开立信用资金账户,下挂深圳信用证券账户060****066。“张某波”账户,2018年1月19日中泰证券济南英雄山路证券营业部开立信用资金账户,下挂深圳信用证券账户060****204。“姚某刚”账户,2015年2月17日于中泰证券济南英雄山路证券营业部开立信用资金账户,下挂深圳信用证券账户060****231。“刘某香”账户,2018年3月21日于中泰证券济南英雄山路证券营业部开立信用资金账户,下挂深圳信用证券账户060****888。“郭某增”账户,2018年8月27日于中泰证券股份有限公司济南英雄山路证券营业部开立资金账户,下挂深圳证券账户025****652,2018年8月30日开立信用资金账户,下挂深圳信用证券账户060****160。“孙某民”账户,2018年4月20日于银河证券深圳深业上城证券营业部开立信用资金账户,下挂深圳信用证券账户060****854。“姬某华”账户,2018年5月15日于新时代证券深圳科苑路证券营业部开立信用资金账户,下挂深圳信用证券账户060****093。“罗某1”账户,2018年1月19日于华林证券深圳龙华营业部开立信用资金账户,下挂深圳信用证券账户060****792。该账户资金来源于吴限,由林建武提供给陈磊使用。“傅某斌”账户,2015年12月7日在西部证券深圳分公司营销业务部开立资金账户,下挂深圳证券账户005****110。2018年10月18日至2018年12月25日,吴限向其同学借用“傅某斌”账户,交由陈磊操作。2.林建武控制使用6个账户根据账户资金来源、相关当事人之间关于账户设立和使用的信息交流、交易终端关联及相关当事人询问笔录等证据,林建武控制使用“林某芬”等6个账户,涉及10个证券账号。具体如下:“林某芬”账户,2015年7月15日于平安证券芜湖营业部开立资金账户,下挂深圳证券账户018****213;2018年4月9日于平安证券芜湖营业部开立信用账户,下挂深圳信用证券账户060****493;2018年7月9日于华林证券深圳龙华营业部开立资金账户,下挂深圳证券账户018****213。“罗某2”账户,2018年1月23日于华林证券深圳龙华营业部开立信用资金账户,下挂深圳信用证券账户0604857521;2018年9月20日于平安证券深圳蛇口营业部开立资金账户,下挂深圳证券账户019****853。“黄某合”账户,2018年9月25日于平安证券深圳蛇口营业部开立信用资金账户,下挂深圳信用证券账户060****506。“刘某婷”账户,2016年11月2日于华林证券深圳龙华营业部开立资金账户,下挂深圳证券账户021****091;2017年6月12日开立信用资金账户,下挂深圳信用证券账户060****790。2019年1月11日、1月21日在平安证券深圳金田路证券营业部开立资金账户、信用资金账户,下挂深圳证券账户021****091、深圳信用证券账户060****790。“陈某如”账户,2018年1月23日于华林证券深圳龙华营业部开立资金账户,下挂深圳证券账户024****588,2018年1月25日开立信用资金账户,下挂深圳信用证券账户060****905。“林某森”账户,2018年7月26日于平安证券深圳金田路证券营业部开立信用资金账户,下挂深圳信用证券账户060****414。3.吴限控制使用7个账户根据账户资金来源、交易终端关联、相关当事人手机数据、询问笔录、书面协议等证据,吴限控制使用“吴限”等7个账户,具体如下:“吴限”账户,2018年6月27日于招商证券厦门湖滨东路营业部开立资金账户,下挂深圳证券账户010****477。“邓某”账户,2018年12月18日于财通证券成都天泰路营业部开立资金账户,下挂深圳证券账户025****223。“涂某娜”账户,2010年4月23日于光大证券深圳深南大道营业部开立资金账户,下挂深圳证券账户013****171。“孙某聚”账户,2014年10月13日于兴业证券深圳侨香路证券营业部开立资金账户,下挂深圳证券账户015****659。“朱某陵”账户,2016年11月14日于招商证券福清江滨路营业部开立资金账户,下挂深圳证券账户005****202。“余某盛”账户,2019年3月6日于国信证券深圳福中分公司开立资金账户,下挂深圳证券账户026****876。“劲通电子”账户,2015年11月24日于招商证券深圳蛇口工业三路营业部开立资金账户,下挂深圳证券账户080****428。三、陈磊、吴限、林建武利用资金、持股优势和信息优势操纵“劲拓股份”2017年11月6日至2019年4月29日(以下简称操纵期间),陈磊、吴限、林建武控制使用涉案账户组,通过集中资金优势、持股优势连续买卖,在实际控制的账户之间交易,以及利用信息优势影响股价等方式,操纵“劲拓股份”交易价格。期间,“劲拓股份”股价上涨19.93%,同期创业板综指下跌18.55%,偏离38.48个百分点。经计算,陈磊、吴限、林建武操纵行为获利165,262,585.59元。1.集中资金优势、持股优势连续买卖操纵期间的361个交易日中,账户组持有“劲拓股份”流通股占公司流通股比例的日均值为23.41%,其中账户组持股占流通股比例在10%以上的有344天,在20%以上的有174天,在30%以上的有137天。期间,账户组当日申买“劲拓股份”笔数在2笔以上的交易天数为260天,其中申买排名第一的天数为179天。账户组申买量占市场申买量比例在10%以上的有152天,在20%以上的有78天。操纵期间,账户组竞价成交量(不含账户组内彼此成交的数量)占市场竞价成交量的比例在10%以上的有166天,在20%以上的有42天,最高占比达33.82%。其中,账户组竞价买入成交量(不含账户组内彼此成交的数量)占市场竞价买成交量比例在10%以上的天数为160天,占比在20%以上的天数为93天,最高占比达67.25%。2.在自己实际控制的账户之间进行证券交易操纵期间,陈磊、林建武等人共计有137个交易日在实际控制的账户之间交易“劲拓股份”,交易量合计2402万余股,占账户组竞价买/卖成交量比例约为20%。期间,其在实际控制的账户之间的交易量占市场竞价成交量超过10%的有27天,最高占比达35.83%。3.利用信息优势影响股价陈磊、吴限等人利用信息优势地位,通过密集发布利好公告,联系证券分析师配合发布研究报告,以及组织员工在股吧发贴等方式,拉抬“劲拓股份”股价。2019年1月10日至2019年4月29日的72个交易日内,劲拓股份密集发布利好公告,其中涉及股份回购公告7份,5%以上股东君如资产旗下基金增持公告1份,2018年度业绩预增公告2份,中标及销售合同公告各1份,以及接受机构调研11次。同时,吴限授意公司人员联系兴业证券等机构的分析师,配合上市公司的利好公告频繁发布关键事项点评、深度报告等,吸引投资者买入“劲拓股份”。陈磊则指使属下员工在东方财富网的“劲拓股份”股吧发帖、评论,诱导投资者买入。2019年1月10日至2019年4月29日,“劲拓股份”股价从14.85元/股涨到19.92元/股,上涨34.14%。期间,“劲拓股份”在2019年4月4日收盘价达25.19元/股,相比期初上涨69.63%。以上事实,有相关证券账户资料、银行账户资料、相关人员询问笔录、电子设备取证信息、交易所相关数据等证据证明,足以认定。我会认为,陈磊、林建武、吴限的上述行为,违反了2005年《证券法》第七十七条第一款第一项、第三项、第四项的规定,构成第二百零三条所述的操纵证券市场行为。听证过程中,当事人陈磊、林建武、吴限提出了以下申辩意见:陈磊在申辩意见中提出:第一,陈磊从未主动牵头劲拓股份市值管理,并未与吴限签署过市值管理协议或相关文件,也没有其他证据证明吴陈二人合谋操纵劲拓股份股票。陈磊是在接触林建武、吴限后,再让员工从网上摘抄所谓的市值管理投资协议,微信记录上最早出现的“JTGF”市值管理方案计划书的时间是在陈磊与另两名当事人见面之后。再者,告知书中的“谋划由君如资产牵头,联合券商、基金、信托、私募、牛散等合作单位一起协力,对劲拓股份进行市值管理”的表述并未在陈磊发出的市值管理方案中出现过。调查人员称包含该内容的方案来源于君如资产员工王某发送给陈磊的文件,但陈磊并未向他人发送过该方案。第二,除君如资产管理的产品外,陈磊未控制其他账户。一是陈磊未控制玖盈资本、前海小龙公司,亦未控制玖盈系列账户和小龙趋势1号账户。二是陈磊未控制“罗某1”“傅某斌”“兴业进取1号”账户。三是陈磊虽与“姚某刚”“刘某香”“张某波”“孙某梅”“孙某瑞”账户签订过投资合作协议,但仅是给予投资建议,未实际控制、操作上述账户。四是陈磊未控制“郭某增”“姬某华”“孙某民”账户。第三,陈磊未实施操纵证券市场行为。一是其管理的君如系列产品账户交易“劲拓股份”合法合规,在举牌成为劲拓股份的正式股东后,及时按规定披露基金资金持股情况,不存在利用资金优势和持股优势操纵的行为。陈磊还积极和劲拓股份管理层沟通,为公司管理层出谋划策如建议利用国务院新规积极回购公司股票等,并积极介绍对接各种业务,尽一个股东的责任和义务。二是“劲拓股份”上涨集中于2019年2月至4月,期间股价从13.56元上涨至最高25.7元,陈磊管理的产品账户没有参与“劲拓股份”的拉抬和出货行为。三是东方财富网“股吧”是公众讨论平台,可以自由发表言论,在“股吧”发帖不足以影响股价。第四,本案责任划分偏颇、违法所得认定错误。一是陈磊不是市值管理的发起人,也不具有决定权。只有吴限作为上市公司实际控制人,才对此有拍板决定的权利。二是陈磊及君如资产没有向告知书所列账户出过资,而吴限及林建武有大量出资,其中“辉煌184号”由吴限通过傅某斌出资5000万并配资1亿,账户获利1700余万全部返还至傅某斌;“金元宝31号”由吴限通过王熙光出资2500万并配资5000万;“君如赢丰1号”由林建武通过徐某雄出资5000万并配资5000万;“君如创智1号”由林建武通过李某中出资5000万并配资5000万。三是陈磊不是最大受益人。陈磊的获利最多是收益分成、通道费用、返佣等,而吴限及林建武的配偶在案涉期间有大规模卖出。四是即使认定存在操纵市场,也应当扣除非陈磊控制的相关账户,并依照陈磊实际获利而非账户获利金额计算违法所得。第五,本案中,吴限、林建武作为上市公司大股东、实际控制人,具有信息优势,众多涉案的私募产品也由其安排、出资,相比之下陈磊作为一个私募管理人根本无法起到关键作用。因此,即便本案构成操纵证券市场,陈磊的涉案行为也属于显著轻微,不应给予市场禁入。吴限在申辩意见中提出:第一,吴限不存在与陈磊、林建武合谋操纵的主观意图。一是劲拓股份经营良好,吴限本人没有债务压力,吴限不存在与陈磊等人合谋操纵股价的动机。在告知书认定的操纵期间特别是“劲拓股份”价格上涨时期,吴限并未卖出其持有的股票获利。本案违法所得也没有一分钱流向吴限控制的账户。二是陈磊与林建武合谋以“市值管理”为名欺骗吴限,吴限对陈磊与林建武签订的居间协议不知情,也未与二人达成操纵“劲拓股份”合意。本案中,陈磊打着“市值管理”的幌子通过林建武认识了吴限并向其介绍市值管理,林建武为了促成所谓的市值管理,不惜亲自指导陈磊如何修改协议,并最终说服申辩人吴限参与市值管理。而吴限自始至终处在被蒙蔽的状态,只是按照陈磊和林建武的要求出资,并找他人帮忙,但这些都是基于吴限对合作市值管理的理解,而绝非合谋操纵劲拓股份股价。三是吴限拟引入陈磊控制的君如资产为战略投资者,但未向其泄露公司内部信息,更没有与其合谋操纵自己公司的股票。2019年1月左右,吴限了解到公司员工还在向君如资产提供股东名册后,就明令禁止再向君如资产提供股东名册。第二,吴限不存在利用资金优势、持股优势连续买卖的行为。一是吴限未安排以他人名义认购“辉煌184号”“金元宝31号”产品,前述产品的实际出资人分别应为徐某、王某光。二是“朱某陵”“劲通电子”账户并非由吴限控制。三是吴限对“邓某”“涂某娜”“孙某聚”“余某盛”账户的控制并非为了操纵证券市场,而是发现被骗后的自保、自救行为。2018年11月吴限与林建武、陈磊的关系破裂,因此在2018年12月至2019年3月期间采取以票还钱的方式进行了切割,将吴限先期投入资金所买入的股票,以及委托林建武的亲戚林某芬代持的股票平移到“邓某”“涂某娜”“孙某聚”“余某盛”等账户。第三,吴限不存在利用信息优势影响股价的行为。劲拓股份在2019年1月10日至4月29日发布的证监会认定的21份利好公告均是按照证监会、深圳证券交易所的规定,按期发布,吴限不存在控制公告发布节奏影响股价的情形。一是启动股份回购的原因是,2018年底韩国政府封锁柔性屏的相关设备,国内相应的生产厂商都以较高的薪资挖走劲拓股份的核心骨干人员,公司正努力突破柔性屏的关键技术,为此不得不通过股权激励稳定技术人才。将回购金额下限由5000万元调高至1亿元,是经过公司管理层内部讨论的结果,目的是为了更大规模地施行股权激励计划。且公司在2018年底的货币资金余额为5885.01万元,银行理财资金余额16,703万元,银行授信额度24500万元,公司合计可支配资金约为41179.18万元。此外2018年公司经营活动现金流净额12210.47万元。劲拓股份在12个月内的时间内有足够的能力和资金进行股份回购。至于劲拓股份公司董秘及相关人员与君如资产员工余某宏建立微信聊天群,并在国泰君安开立回购账户以及君如资产员工向公司证券事务代表建议回购时间安排、打听回购进度等,吴限并不知情,也不可能管理到如此细节的工作内容。二是2019年2月14日发布的君发资产增持公告属于按照监管规定及时发布的公告。君如资产作为市场上并不知名的私募机构,增持1%的消息也不属于重大利好,且公告后股价有大幅下跌。三是从2019年1月10日至4月29日,劲拓股份除了发布2份2018年度业绩预增公告,还在3月8日发布了2019年一季度业绩预亏公告。由于劲拓股份股价主要在3月至4月上涨,此时公告扭盈为亏,反而会打压市场。四是关于机构调研公告,是因为机构投资者对于劲拓股份是否生产3D贴合设备以及进展比较关注,在2019年2月19日起密集地来劲拓股份进行调研。劲拓股份公告机构调研符合规定,且吴限也无法控制机构来劲拓股份调研的时间。五是2019年4月11日中标公告是根据《中标通知书》及时发布,其公告的中标金额8120万元与4月26日公告的合同金额5424万元存在差异,是采购方根据生产需要自主决定的,为了维护和大客户的关系,劲拓股份及吴限只能配合采购方调整合同总价。六是吴限不存在授意相关人员联系分析师的情形,告知书事实认定错误,缺乏证据支持。第四,违法所得计算错误。一是吴限在2018年11月起即不再相信陈磊和君如资产作为战略投资者身份,并且已经不再向君如资产、陈磊提供股东名册,以2019年4月29日为共同操纵期间截止日明显缺乏事实和法律依据。二是告知书认定的账户组之间相互转让劲拓股份股票的获利不应当计算成违法所得。三是计算方式中卖出金额按照给交易所的发函日2020年9月10日计算,余股市值按照操纵截止日2019年4月29日的收盘价计算,导致获利的重复计算。四是“邓某”证券账户、“孙某聚”证券账户系吴限平移股票使用的账户,且主要是通过大宗交易的方式进行股票交易,其盈利不应当作为非法所得。第五,责任划分错误,违反罪行相当原则。吴限并不知晓,也不可能知晓陈磊、林建武还涉嫌控制其他个人账户交易劲拓股份的股票。陈磊、林建武涉嫌控制的个人账户的“获利”让吴限来承担明显缺乏法律依据。吴限的行为与本案陈磊的主导性和林建武的居间及私下参与完全不同,让其承担40%的罚没严重违法了罪行相当的原则。林建武在申辩意见中提出:第一,林建武仅系市值管理居间人,所接触、了解的案涉市值管理不涉及任何操纵手段内容,不应基于申辩人参与居间,认定存在操纵市场的共同故意与共同行为。第二,告知书关于陈磊、林建武、吴限筹划、商议劲拓股份市值管理的事实认定无证据支持。一是2017年7月陈磊向林建武发送的《市值管理投资合作协议草案(劲拓股份)》并无“联合券商、基金、信托、私募、牛散等合作单位一起协力,对劲拓股份进行市值管理”的表述,也完全不涉及以非法手段、异常交易方式拉抬股价。二是林建武与陈磊、吴限各自对“市值管理项目”的理解、意图以及对自身角色的认识不同,根本没有形成“合作关系”,更谈不上“合作进行市值管理”。林建武直至听证会才知悉,陈磊所谓市值管理仅是他的“营销手段”。吴限前期也完全不知悉林建武是“市值管理居间人”。三是陈磊与吴限没有签署市值管理协议,君如资产员工的聊天记录及询问笔录只能证明陈磊与吴限见过面,但无法证明二人达成了“合作进行市值管理”的合意。第三,“刘某婷”“林某芬”等6个账户均由户主本人控制使用,账户盈亏与林建武无关,告知书关于林建武控制相关账户、为方案实施筹集资金、准备账户等事实认定错误,无证据支持。一是资金往来方面,林某森、罗某2、黄某合与林建武没有资金往来,其他账户虽有资金往来,但与交易劲拓股份股票无关。二是涉案账户交易决策都是户主使用自己的设备下单操作,终端符合其工作生活地点。第四,无证据证明“刘某婷”等6个账户存在连续交易及账户间交易等操纵行为。一是6个账户买卖“劲拓股份”的交易时点、策略、风格不一致,不存在“集中资金优势和持股优势连续交易股票”,交易劲拓股份股票也不异常。二是6个账户自身之间没有交易行为,其与陈磊、吴限相关账户可能存在被动成交,但不构成操纵情形。三是6个账户在劲拓股份股价大幅上涨之前,已经开始在不同时间点大量卖出,不符合股价高位精准卖出的特点。第五,对林建武违法所得的认定没有事实依据,适用法律错误,不能成立。一是在林建武完成居间工作后,陈磊为推诿支付居间费用,从未向林建武说明其控制账户组的设立及交易情况,在2018年10月左右,林建武与陈磊彻底决裂、断绝往来后,更不可能知悉、了解陈磊、吴限的账户组交易情况,因此林建武对于陈磊和吴限相关账户的交易情况完全不知情,更未从中获益。二是案涉6账户不是林建武的账户,也没有实施操纵行为,不应计算违法所得。三是“林某芬”账户的两笔大宗交易,是替林建武的配偶孔某和吴限代持,与涉案操纵行为无关,该部分大宗交易不应纳入违法所得计算。四是2019年1月10日至4月29日期间的“操纵”行为与林建武完全无关,6账户在此期间的卖出获利不属于违法所得。经复核,我会认为:首先,在案证据显示,陈磊、吴限、林建武具有操纵“劲拓股份”股价的故意。根据林建武、华林证券李某、吴限同学徐某等人询问笔录及相关微信聊天记录等证据,2017年7月至8月期间陈磊与林建武、吴限沟通的市值管理合作模式主要为,大股东与君如资产共同出资并通过配资成立信托计划,由君如资产通过二级市场操作拉升股价,并在上市公司业绩配合下实现公司市值大幅提升。同时,陈磊与林建武以《劲拓股份投资咨询合作协议》约定,林建武负责协助君如资产与劲拓股份的市值管理合作谈判成功,协助完成信托产品的设立和账户使用,并在合作期间提供或协助君如资产获取劲拓股份相关信息,而君如资产向其支付相应比例收益。且陈磊在林建武促成合作后向其出具《居间服务费支付承诺书》,称“鉴于林建武先生在本公司与劲拓股份市值管理项目合作的谈判中起到关键性作用,且协助我方完成若干信托计划及私募、资管产品的设立”,君如资产承诺将提取部分市值管理项目的业绩报酬及产品管理费,作为居间服务费支付给林建武。由此可见,2017年8月,在林建武的积极撮合下,陈磊与吴限就共同出资设立产品对劲拓股份进行市值管理达成合作。根据当事人微信交流内容、相关协议及相关人员陈述等,陈磊、吴限、林建武等当事人对其合作的本质为上市公司大股东与私募基金共同出资交易本公司股票,利用持股、资金及信息优势操纵股价,均有较明确认知。针对吴限提出其受他人蒙蔽、不知悉林建武与陈磊私下签订居间协议等申辩,我会认为,吴限作为上市公司董事长、实际控制人,在他人游说下同意与私募集基金合作,筹集资金、账户用于交易本公司股票,并配合提供股东名册等,其行为足以证明其操纵股价之意图。吴限对另两位当事人签订居间协议是否知情,并不影响对其操纵股价行为的认定。其次,当事人实施了操纵股价的相关行为。一是陈磊、吴限、林建武等人密切合作,为市值管理积极筹集资金、账户用于交易“劲拓股份”。根据吴限同学徐某、华林证券李某、黄某等人询问笔录及相关账户交易资料、银行流水等证据,陈磊控制的“辉煌184号”“金元宝31号”产品的B类份额资金实际来源于吴限,“罗某1”账户资金实际来源于吴限,由林建武提供给陈磊方操作。根据林建武询问笔录及相关人员陈述、相关账户交易资料、银行流水等证据,因吴限出资未达合作约定的2亿元,林建武本人提供几千万资金,通过借款给其下属李某中、徐某雄认购“君如创智1号”“君如赢丰1号”,借用老乡刘某婷、同学黄某合、亲戚林某芬等人账户等方式,增加交易“劲拓股份”资金规模。根据相关微信聊天记录、相关账户交易资料、银行流水及相关人员陈述等证据,陈磊不仅通过君如资产、前海小龙、玖盈资本等平台,发起设立数只私募基金产品用于交易“劲拓股份”,还通过证券投资合作方式向姚某刚借用“姚某刚”“孙某梅”等个人账户交易“劲拓股份”。关于账户控制关系,本案系根据相关人员指认、自认,涉案账户资金流转,交易终端关联,微信聊天记录中有关账户信息交流、投资合作协议文件等多项主客观证据综合作出认定,此外相关账户存在交易趋同、对倒等情形亦可印证当事人对涉案账户实际控制。我会对涉案账户控制关系的认定并无不当,对当事人的申辩不予采纳。二是陈磊、吴限、林建武通过集中资金优势、持股优势连续买卖,在实际控制的账户之间交易,以及利用信息优势影响股价等方式,操纵“劲拓股份”交易价格。关于集中资金、持股优势连续买卖。操纵期间的361个交易日中,当事人控制的账户组持有“劲拓股份”流通股占公司流通股比例的日均值为23.41%,占比最高为2018年10月18日,达37.35%。账户组竞价买入成交量(扣除对倒成交量)占市场竞价买成交量比例在10%以上的有160天,占比在20%以上的有93天,占比最高为2018年6月19日,达67.25%。关于在实际控制的账户之间交易。操纵期间,账户组内存在大量对倒成交,如:2017年12月20日,“劲通电子”账户共计卖出127.3万股,与“辉煌184号”“金元宝31号”“君如赢丰1号”三账户共计对倒成交79.41万股。2018年10月18日至19日,“傅某斌”账户共计买入212.17万股,与“辉煌184号”对倒成交113.63万股。2019年1月14日至15日,“孙某聚”账户共计卖出77.94万股,与“玖盈一号”“玖盈三号”两账户共计对倒成交28.53万股。关于利用信息优势影响股价。劲拓股份公司公告、兴业证券等券商研究报告、相关人员询问笔录、微信聊天记录等证据显示,在操纵后期即2019年1月10日至4月29日,陈磊、吴限等人通过密集发布利好公告、联系证券分析师配合发布研究报告及组织人员在股吧发贴等方式拉抬股价。期间,“劲拓股份”股价从14.85元/股涨到19.92元/股,上涨34.14%,其中2019年4月4日收盘价达25.19元/股,相比期初上涨69.63%。与此同时,账户组大量卖出,持有流通股总数由5776.71万股减至2780.12万股,持仓占公司流通股本比例由34.71%降至16.57%。针对陈磊、吴限辩称其未利用信息优势影响股价,我会认为其申辩不能成立。其一,陈磊作为君如资产的实际控制人,对君如资产增持“劲拓股份”及其信息披露有完全的主导权。君如资产于2019年2月14日披露其增持1%,并承诺六个月内不减持。当天股价上涨7%。结合陈磊指示员工在“股吧”发帖诱导投资者,同时涉案相关账户大量卖出等事实,足以认定其利用增持公告影响股价。其二,吴限作为劲拓股份董事长、实际控制人,足以左右上市公司的重大决策并对公司信息发布具有明显优势。相关信息披露形式上是否合规并非操纵与否的判定标准。其三,根据相关人员询问笔录及微信聊天记录等证据,以回购股份提振股价系陈磊提议,且君如资产员工还参与了劲拓股份回购账户开立事宜。以上事实表明陈磊、吴限等人共同谋划了回购事项。吴限提出的有关回购决策理由等申辩缺乏相应证据,其主张难以成立。综合以上事实,并结合吴限授意公司人员联系券商配合发布相关研报等行为,我会认定其利用信息优势影响股价并无不当。再次,本案对操纵违法所得认定并无不当。其一,本案中,陈磊、吴限、林建武基于共同的故意实施了操纵违法行为,我会在统计操纵指标与计算交易获利时,将其三人控制账户视为一个整体统一计算,符合共同操纵违法行为的认定逻辑与处理原则。当事人要求按各自控制使用账户分别计算违法所得的主张不能成立。其二,本案操纵盈利计算方法符合我会执法惯例,不存在当事人所称重复计算盈利问题。其三,关于当事人提出违法所得应剔除“林某芬”“邓某”“孙某聚”等账户大宗交易获利,我会认为,大宗交易虽不直接影响股价,但其作为当事人建仓手段之一,属于操纵行为的组成部分,不应将其同连续买卖、对倒交易等直接影响股价的操纵行为割裂开来。其四,关于当事人主张其于2018年10月决裂,其后的相关行为及获利均应分别认定与计算,我会认为,根据相关人员询问笔录及微信聊天记录等证据,上述主张与事实不符,不应采纳。最后,本案对当事人的量罚及责任比例分担并无不当。综合全案事实、证据,本案是私募基金实际控制人、上市公司实际控制人及居间人以市值管理合作为名,共同操纵上市公司股价的违法案件。其中,陈磊主动联络上市公司实际控制人,组织并具体实施操纵行为,包括控制多个产品与自然人账户通过连续买卖、对倒交易及发布增持公告等方式操纵股价;吴限作为上市公司董事长、实际控制人,与他人合谋操纵本公司股票,不仅提供部分账户和大量交易资金,还存在利用信息优势影响股价情形。陈磊、吴限在本案操纵违法行为中起主要作用,应承担主要责任。林建武明知陈磊存在操纵股价意图,为获取居间收益积极促成其与吴限的合作,并为市值管理筹集资金、账户,及帮助陈磊获取股东名册等,在本案操纵违法行为中起次要作用,应承担次要责任。我会在量罚时已综合考量本案违法行为性质、主客观情节等,并根据三位当事人在共同违法中的地位、作用确定责任比例,处理适当。综上,我会对当事人的申辩意见不予采纳。根据当事人违法行为的事实、性质、情节和社会危害程度,依据2005年《证券法》第二百零三条的规定,我会决定:对陈磊、吴限、林建武等人合谋操纵“劲拓股份”价格的行为没收违法所得共计165,262,585.59元,并处以495,787,756.76元的罚款,违法所得及罚款合计661,050,342.35元,由陈磊承担40%即264,420,136.94元,吴限承担40%即264,420,136.94元,林建武承担20%即132,210,068.47元。上述当事人应自收到本处罚决定之日起15日内,将罚款汇交中国证券监督管理委员会,开户银行:中信银行北京分行营业部,账号:7111010189800000162,由该行直接上缴国库,并将注有当事人名称的付款凭证复印件送中国证券监督管理委员会行政处罚委员会办公室备案。当事人如果对本处罚决定不服,可在收到本处罚决定书之日起60日内向中国证券监督管理委员会申请行政复议,也可在收到本处罚决定书之日起6个月内直接向有管辖权的人民法院提起行政诉讼。复议和诉讼期间,上述决定不停止执行。中国证监会2023年11月30日 | D2: 45260
A3: 是 | B3: 是 | C3: 〔2023〕40号当事人:俞国生,男,1957年10月出生,住址:浙江省杭州市下城区。张一苗,男,1982年11月出生,住址:浙江省杭州市下城区。依据2005年修订的《中华人民共和国证券法》(以下简称2005年《证券法》)的有关规定,我会对俞国生、张一苗操纵市场、超比例持股未披露及限制期交易行为进行了立案调查、审理,并依法向当事人告知了作出行政处罚的事实、理由、依据及当事人依法享有的权利,应当事人俞国生、张一苗的要求,2023年2月15日举行了听证会,听取了俞国生、张一苗及其代理人的陈述和申辩。本案现已调查、审理终结。经查明,俞国生、张一苗存在以下违法事实:一、俞国生、张一苗实际控制使用账户及交易情况俞国生系野风集团有限公司(以下简称野风集团)决策咨询委员会主任,浙江野风资产管理有限公司(以下简称野风资管)实际控制人,张一苗时任野风资管董事长,其为俞国生女婿。涉案期间,俞国生、张一苗以个人名义借入配资账户,并实际控制143个证券账户,交易“浙数文化”、“浙江交科”、“浙大网新”等。其中,俞国生、张一苗控制使用“童某青”等67个证券账户于2016年10月31日至2017年7月28日交易“浙数文化”,控制使用“童某青”等36个证券账户于2017年8月25日至2018年5月18日交易“浙江交科”,控制使用“童某青”等33个证券账户于2018年5月21日至2019年1月11日交易“浙江交科”,控制使用“童某青”等78个证券账户于2016年3月21日至2017年3月6日交易“浙大网新”。二、俞国生、张一苗操纵“浙数文化”情况(一)俞国生、张一苗控制使用“童某青”等67个证券账户情况2016年10月31日至2017年7月28日期间(以下简称操纵期间1),俞国生、张一苗以个人名义借入证券账户,并控制使用“童某青”“李某灵”“韩某挺”等67个证券账户(以下简称账户组1)交易“浙数文化”。(二)俞国生、张一苗控制账户组1实施操纵的总体情况和三个阶段操纵期间1共计145个交易日,俞国生、张一苗控制的账户组1期初无持股,其通过利用资金优势、持股优势连续买卖、在自己实际控制的账户之间进行交易等方式影响“浙数文化”交易价格和交易量,同时存在日内反向交易、盘中拉抬等手段,直至操纵期间1期末全部卖出“浙数文化”。操纵期间1内,俞国生、张一苗控制账户组1累计买入“浙数文化”201,502,203股,累计买入金额3,662,748,396元,累计卖出201,502,203股,累计卖出成交3,935,985,843元,盈利274,313,073.19元。根据交易行为、持仓变动及停牌等情况,俞国生、张一苗于操纵期间1内控制账户组1的操纵行为可分为建仓拉抬、震仓拉抬、减仓三个阶段:第一阶段为建仓拉抬阶段。自2016年10月31日起,账户组1集中买入“浙数文化”,并在2017年1月10日停牌前持续买入建仓。2016年10月31日至2017年1月9日,账户组1竞价买入“浙数文化”77,141,691股,竞价卖出“浙数文化”9,360,548股,净买入67,781,143股,由期初持股为0增加至期末持股67,781,143股,占总股本5.21%,占流通股5.70%。期间,“浙数文化”交易价格由每股14.31元上涨至最高19.21元,涨幅34.24%。第二阶段为震仓拉抬阶段。浙报数字文化集团股份有限公司(原浙报传媒集团股份有限公司,以下简称浙数文化)因筹划资产重组事项,于2017年1月10日至3月9日停牌。2017年3月10日复牌后,2017年3月10日至3月14日期间,“浙数文化”交易价格累计上涨5.91%,资产重组事项未显著影响“浙数文化”交易价格。2017年3月10日至6月16日,账户组1竞价买入成交“浙数文化”87,772,901股,竞价卖出成交80,233,639股,净买入7,539,262股,截至6月16日,账户组1持有“浙数文化”75,320,405股,占总股本比例为5.79%,占流通股的比例为6.34%。2017年3月10日至6月16日,账户组1连续交易“浙数文化”,维持“浙数文化”交易价格,同时继续增加买入,以在自己实际控制的账户之间进行交易、连续交易拉抬股价、日内反向交易等方式实施操纵。该期间内,“浙数文化”股票交易价格震荡明显,最高振幅21.31%,“浙数文化”股票交易价格从每股17.44元上涨至每股18.52元,涨幅6.19%。第三阶段为减仓阶段。2017年6月19日至7月28日,账户组1竞价买入成交“浙数文化”36,587,611股,竞价卖出成交“浙数文化”111,908,016股,净卖出“浙数文化”75,320,405股,期末无持股。减仓阶段,账户组1主要为卖出“浙数文化”,稳步减持“浙数文化”后大量卖出,直至全部卖出。该期间内,“浙数文化”交易价格从每股18.52元上涨至每股20.68元,涨幅11.66%。(三)俞国生、张一苗控制账户组1利用资金优势、持股优势连续买卖“浙数文化”1.资金优势账户组1在操纵期间1内对“浙数文化”的交易中具有明显资金优势。操纵期间1内的145个交易日中,账户组1有140个交易日存在竞价买入交易,合计买入成交366,274.83万元。其中,账户组1竞价买入成交金额超过2,500万元的有54个交易日,占账户组1竞价买入交易天数的38.57%;账户组1竞价买入成交金额超过4,000万元的有26个交易日,占账户组1竞价买入交易天数的18.57%。账户组1日均竞价买入成交金额为2,616.25万元,占市场平均日成交额的10.84%。其中,2016年10月31日,账户组1竞价买入“浙数文化”10,032,220股,成交金额高达15,278.99万元。2.持股优势操纵期间1内,账户组1利用资金优势大量买入进而形成持股优势,持有“浙数文化”超过流通股本比例5%的交易日为96天,占操纵期间1内全部交易日的66.2%。其中,2017年4月27日,账户组1持有“浙数文化”占流通股本比例达到最高值7.94%。3.连续交易关于申买量排名指标。在操纵期间1内的145个交易日中,账户组有144个交易日交易了“浙数文化”,占比99.31%。其中有93个交易日,账户组1的申买量排名第一,占比为64.58%;有138个交易日,账户组1的申买量排名前十,占比为95.83%;有74个交易日,账户组1的申卖量排名第一,占比为51.39%;有111个交易日,账户组1的申卖量排名前十,占比为77.08%。关于竞价成交量指标。操纵期间1内,有79个交易日,账户组1的竞价成交量占比超过10%,占比为56.43%;有16个交易日,账户组1的竞价成交量占比超过20%,占比为11.11%。其中,2017年5月16日,账户组1的竞价成交量占比达到最高值,为27.08%。关于账户组1竞价买入及卖出成交量占市场竞价成交量指标。有86个交易日,账户组1竞价买入成交量占市场竞价成交量的比例超过10%,占比为59.72%;有23个交易日,该指标超过20%,占比为15.97%;有3个交易日,该指标超过30%,占比为2.08%。其中,2016年10月31日,账户组1竞价买入成交量占市场竞价成交量的比例达最高值,为43.07%。有70个交易日,账户组1竞价卖出成交量占市场竞价成交量的比例超过10%,占比为48.61%;有36个交易日,该指标超过20%,占比为25%。其中,2017年5月19日,账户组1竞价卖出成交量占市场竞价成交量的比例达最高值,为32.74%。关于申买价指标。操纵期间1内,账户组1申买价不低于市场卖一价的申买量为162,038,100股,占操纵期间1内账户组1连续竞价阶段总申买量230,839,700股的70.20%;账户组1申买价不低于卖一价且申报数量大于卖方一档数量的总申报量为141,835,500股,占操纵期间1内账户组1连续竞价阶段总申买量230,839,700股的61.44%;账户组1申买价不低于申买前最新市场成交价的申买量为175,858,200股,占操纵期间1内账户组1连续竞价阶段总申买量230,839,700股的76.18%;特别是2017年4月14日至7月19日期间内,账户组1申买价高于申买前最新市场成交价大于或等于1%的申买量为1,393,700股,占账户组期间连续竞价阶段总申买量23,436,800股的5.95%。上述指标说明账户组1在能以更低价格买到“浙数文化”的情形下,仍以高于市场价的价格申买,可见其影响“浙数文化”交易量和交易价格的意图明显。4.连续交易的典型拉抬区间操纵期间1内,在11个交易日中有12个时间段,账户组1多次盘中拉抬“浙数文化”交易价格,最高拉抬幅度达2.35%,并存在拉抬中及拉抬后反向卖出情形。典型拉抬区间如下:2017年3月13日,9:32:12至9:36:29期间,账户组1拉抬前一笔市场成交价为每股17.98元,该期间内,其最低申买价格为每股18.07元,最高申买价格为每股18.43元,申买均价为每股18.263元。该期间内,账户组1申报买入543,000股,申买占比29.35%,不低于卖一价申买量占账户组1总申买量的83.06%;主动买成交280,800股,占市场买成交量的比例为22.83%。账户组1在拉抬后反向卖出1,100,600股,卖出均价为每股18.57元。账户组1拉抬前一笔市场成交价为每股17.98元,该时段截止时市场成交价为18.43元,涨幅为2.35%。(四)俞国生、张一苗控制账户组1在自己实际控制的账户之间进行交易及日内反向交易在操纵期间1内的145个交易日中,有93个交易日存在账户组1的账户之间交易“浙数文化”的情况,占整个操纵期间1交易日天数的64.13%,占操纵期间1内账户组交易天数的64.58%。同时,有13个交易日存在账户组1的账户之间交易“浙数文化”成交量占当日市场竞价成交量的比例超过5%的情况,其中,2017年7月19日,账户组1的账户之间交易“浙数文化”成交量占当日市场竞价成交量的比例达到最高值7.76%。同时,操纵期间1内,账户组1有110个交易日存在日内反向交易,其中有70个交易日的反向交易成交量占账户组1成交量的比例超过50%。日均反向交易成交量占账户组1成交量比例为55.80%,最高达99.68%。(五)操纵期间1内,“浙数文化”股价走势偏离大盘指数及所在行业指数情况操纵期间1内,“浙数文化”股票交易价格出现较大波动。其中,2016年10月31日至2017年1月9日,“浙数文化”股票交易价格从14.31元/股上涨至17.44元/股,涨幅21.87%,与同期上证综指(上涨2.16%)相比偏离19.71个百分点,与出版指数(882463.WI,下跌2.75%)相比偏离24.62个百分点。2017年3月10日至6月16日,“浙数文化”股票交易价格从17.44元/股上涨至18.52元/股,涨幅6.19%,与同期上证综指(下跌1.52%)相比偏离7.71个百分点,与出版指数(882463.WI,下跌10.72%)相比偏离16.91个百分点。2017年6月19日至7月28日,“浙数文化”股票交易价格从18.52元/股上涨至20.68元/股,涨幅11.66%,与同期上证综指(上涨4.16%)相比偏离7.5个百分点,与出版指数(882463.WI,上涨2.17%)相比偏离9.49个百分点。综上,操纵期间1内,“浙数文化”股票交易价格走势与大盘面指数及所在行业指数出现较大背离。三、俞国生、张一苗于2017年8月25日至2018年5月18日操纵“浙江交科”情况(一)俞国生、张一苗控制使用“童某青”等36个证券账户情况2017年8月25日至2018年5月18日期间(以下简称操纵期间2),俞国生、张一苗以个人名义借入证券账户,并控制使用“童某青”“何某晨”“陈某夫”等36个证券账户(以下简称账户组2)交易“浙江交科”。(二)俞国生、张一苗控制账户组2实施操纵的总体情况和三个阶段操纵期间2共计170个交易日,俞国生、张一苗控制的账户组2期初无持股,其通过利用资金优势、持股优势连续买卖、在自己实际控制的账户之间进行交易等方式影响“浙江交科”交易价格和交易量,同时存在日内反向交易、盘中拉抬等手段,直至操纵期间2期末基本清空“浙江交科”。操纵期间2内,俞国生、张一苗控制账户组2累计买入“浙江交科”261,658,238股,累计买入金额3,663,333,011.57元,累计卖出253,337,359股,累计卖出成交3,678,886,536.46元,盈利102,545,916.82元。根据交易行为、持仓变动等情况,俞国生、张一苗于操纵期间2内控制账户组2的操纵行为可分为建仓拉抬、震仓拉抬、减仓三个阶段:第一阶段为建仓拉抬阶段。2017年8月25日至2017年11月3日,账户组2竞价买入“浙江交科”89,368,984股,竞价卖出17,446,217股,净买入71,922,767股,该期间期末持股71,922,767股,占总股本10.87%,占流通股15.87%。期间,“浙江交科”交易价格由每股10.75元上涨至每股14.00元,涨幅30.23%。第二阶段为震仓拉抬阶段。2017年11月6日至2018年1月10日,账户组2竞价买入“浙江交科”股票83,623,796股,竞价卖出102,856,015股,净卖出19,232,219股,该期间期末持股52,690,548股,占总股本4.04%,占流通股11.62%。期间,账户组2连续交易“浙江交科”,维持“浙江交科”交易价格,同时以在自己实际控制的账户之间进行交易、连续交易拉抬股价、日内反向交易等方式实施操纵。该期间内,“浙江交科”股票交易价格震荡明显,最高振幅18.79%。整个期间,“浙江交科”股票交易价格从每股14.00元上涨至每股16.00元,涨幅14.29%。第三阶段为减仓阶段。2018年1月11日至2018年5月18日,账户组竞价买入成交“浙江交科”股票88,665,458股,竞价卖出成交133,035,127股,净卖出44,369,669股,该期间期末持股8,320,879股。减仓阶段,账户组2主要为卖出“浙数文化”,交易活跃,同时以在自己实际控制的账户之间进行交易、连续交易拉抬股价、日内反向交易等方式实施操纵。账户组2在该期间内持有“浙数文化”股数逐渐下降,“浙江交科”交易价格从每股16.00元下跌至最低每股10.96元,跌幅31.50%。(三)俞国生、张一苗控制账户组2利用资金优势、持股优势连续买卖“浙江交科”1.资金优势账户组2在操纵期间2内对“浙江交科”的交易中具有明显资金优势。操纵期间2内的170个交易日中,账户组2有151个交易日存在竞价买入交易,合计买入成交366,333.3万元。其中,账户组2竞价买入金额超过1,500万元的有103个交易日,占账户组2竞价买入交易天数的68.21%;账户组2竞价买入成交金额超过3,000万元的有45个交易日,占账户组2竞价买入交易天数的29.80%;账户组2日均竞价买入成交金额为2,426.05万元,占市场平均日成交额的16.10%。其中,2017年8月31日,账户组2竞价买入“浙江交科”7,803,080股,成交金额9,440.80万元。2.持股优势操纵期间2内,账户组2利用资金优势大量买入进而形成持股优势,持有“浙江交科”超过流通股本比例5%的交易日为134天,占操纵期间2内全部交易日的78.82%;持有“浙江交科”超过流通股本比例10%的天数为75天,占操纵期间2内全部交易日的44.11%。其中,2017年11月3日,账户组2持有“浙江交科”占流通股本比例达到最高值15.87%。3.连续交易关于申买量排名指标。在操纵期间2内的170个交易日中,账户组2有162个交易日交易了“浙江交科”,占比95.29%。其中有106个交易日,账户组2的申买量排名第一,占比为65.43%;有150个交易日,账户组2的申买量排名前十,占比为92.59%;有135个交易日,账户组2的申卖量排名第一,占比为83.33%;有153个交易日,账户组2的申卖量排名前十,占比为94.44%。关于竞价成交量指标。操纵期间2内,有120个交易日,账户组2的竞价成交量占比超过10%,占比为74.07%;有56个交易日,账户组2的竞价成交量占比超过20%,占比为34.57%;有32个交易日,账户组2的竞价成交量占比超过30%,占比为19.75%。其中,2018年3月20日,账户组2的竞价成交量占比达到最高值,为48.58%。关于账户组2竞价买入及卖出成交量占市场竞价成交量指标。有108个交易日,账户组2竞价买入成交量占市场竞价成交量的比例超过10%,占比为66.67%;有59个交易日,该指标超过20%,占比为36.42%;有29个交易日,该指标超过30%,占比为17.9%。其中,2018年3月20日,账户组2竞价买入成交量占市场竞价成交量的比例达最高值,为48.13%。有106个交易日,账户组2竞价卖出成交量占市场竞价成交量的比例超过10%,占比为65.43%;有70个交易日,该指标超过20%,占比为43.21%;有37个交易日,该指标超过30%,占比为22.84%。其中,2018年3月28日,账户组2竞价卖出成交量占市场竞价成交量的比例达最高值,为50.93%。关于申买价指标。操纵期间2内,账户组2申买价不低于市场卖一价的申买量为230,051,900股,占操作期间2内账户组2连续竞价阶段总申买量296,834,900股的77.50%;账户组2申买价不低于卖一价且申报数量大于卖方一档数量的总申报量为207,325,200股,占操纵期间2内账户组2连续竞价阶段总申买量296,834,900股的69.85%;账户组2申买价不低于申买前最新市场成交价的申买量为244,545,700股,占操纵期间2内账户组2连续竞价阶段总申买量296,834,900股的82.38%;特别是2017年9月18日至2018年4月18日期间内,账户组2申买价高于申买前最新市场成交价大于或等于1%的申买量为2,714,000股,占账户组期间连续竞价阶段总申买量35,919,100股的7.56%。上述指标说明账户组2在能以更低价格买到“浙江交科”的情形下,仍以高于市场价的价格申买,可见其影响“浙江交科”交易量和交易价格的意图明显。4.连续交易的典型拉抬区间操纵期间2内,在77个交易日中有128个时间段,账户组2多次盘中拉抬“浙江交科”交易价格,最高拉抬幅度达3.37%,并存在拉抬中及拉抬后反向卖出情形。典型拉抬区间如下:2018年1月10日,9:34:30至10:04:36期间,账户组2拉抬前一笔市场成交价为每股16.21元,该期间内,其最低申买价格为每股16.23元,最高申买价格为每股16.83元,申买均价为每股16.56元。该期间内,账户组2申报买入3,698,400股,申买占比36.06%,不低于卖一价申买量占账户组2总申买量的61.62%;主动买成交1,281,064股,占市场买成交量的比例为33.02%。账户组2在拉抬后存在反向卖出,其中,拉抬中卖出1,369,400股,卖出均价为每股16.62元;拉抬后卖出2,199,300股,卖出均价为每股16.30元。账户组2拉抬前一笔市场成交价为每股16.21元,该时段截止时市场成交价为16.75元,涨幅为3.33%。(四)俞国生、张一苗控制账户组2在自己实际控制的账户之间进行交易及日内反向交易在操纵期间2内的170个交易日中,有121个交易日存在账户组2的账户之间交易“浙江交科”的情况,占整个操纵期间2交易日天数的71.17%。有49个交易日存在账户组2的账户之间交易“浙江交科”成交量占当日市场竞价成交量的比例超过5%的情况,有32个交易日存在账户组2的账户之间交易“浙江交科”成交量占当日市场竞价成交量的比例超过10%的情况,有4个交易日存在账户组2的账户之间交易“浙江交科”成交量占当日市场竞价成交量的比例超过20%的情况。其中,2018年3月20日,账户组2的账户之间交易“浙数文化”成交量占当日市场竞价成交量的比例达到最高值28.24%。同时,操纵期间2内,账户组2有137个交易日存在日内反向交易,其中有97个交易日的反向交易成交量占账户组2成交量的比例超过50%。日均反向交易成交量占账户组2成交量比例为66.99%,最高达99.34%。(五)操纵期间2内,“浙江交科”股价走势偏离大盘指数及所在行业指数情况操纵期间2内,“浙江交科”股票交易价格出现较大波动。其中,2017年8月25日至2017年11月3日,“浙江交科”股票交易价格从10.75元/股上涨至14.00元/股,涨幅30.23%,与同期中小板指(上涨8.85%)相比偏离21.38个百分点,与建筑指数(886016.WI,下跌1.68%)相比偏离31.91个百分点。2017年11月6日至2018年1月10日,“浙江交科”股票交易价格从14.00元/股上涨至16.00元/股,涨幅14.29%,与同期中小板指(下跌0.48%)相比偏离14.77个百分点,与建筑指数(886016.WI,下跌5.23%)相比偏离19.52个百分点。2018年1月11日至2018年5月18日,“浙江交科”股票交易价格从16.00元/股下跌至12.21元/股,跌幅23.69%,与同期中小板指(下跌6.83%)相比偏离16.86个百分点,与建筑指数(886016.WI,下跌12.85%)相比偏离10.84个百分点。综上,操纵期间2内,“浙江交科”股票交易价格走势与大盘指数及所在行业指数出现较大背离。四、俞国生、张一苗于2018年5月21日至2019年1月11日操纵“浙江交科”情况(一)俞国生、张一苗控制使用“童某青”等33个证券账户情况2018年5月21日至2019年1月11日期间(以下简称操纵期间3),俞国生、张一苗以个人名义借入证券账户,并控制使用“童某青”“张某”“邓某”等33个证券账户(以下简称账户组3)交易“浙江交科”。(二)俞国生、张一苗控制账户组3实施操纵的总体情况和三个阶段操纵期间3共计161个交易日,俞国生、张一苗控制的账户组3期初持有“浙江交科”8,320,879股,其通过利用资金优势、持股优势连续买卖、在自己实际控制的账户之间进行交易等方式影响“浙江交科”交易价格和交易量,同时存在日内反向交易、盘中拉抬等手段,直至操纵期间3期末全部卖出“浙江交科”。操纵期间3内,俞国生、张一苗控制账户组3累计买入“浙江交科”208,542,533股,累计买入金额2,171,351,363.81元,累计卖出216,863,412股,累计卖出成交2,303,834,342.46元,盈利36,451,611.14元。根据交易行为、持仓变动等情况,俞国生、张一苗于操纵期间3内控制账户组3的操纵行为可分为建仓、拉抬、减仓三个阶段:第一阶段为建仓阶段。2018年5月21日至10月16日,账户组3期初持股8,320,879股,该期间竞价买入“浙江交科”108,222,144股,竞价卖出64,893,359股,净买入43,328,785股,该期间期末持股51,649,664股,占总股本3.75%,占流通股9.23%。第二阶段为拉抬阶段。2018年10月17日至12月6日,账户组3竞价买入“浙江交科”股票63,979,952股,竞价卖出52,183,099股,净买入11,796,853股,该期间期末持股63,446,517股,占总股本4.61%,占流通股10.96%。期间,账户组3连续交易“浙江交科”,拉抬“浙江交科”交易价格,同时以在自己实际控制的账户之间进行交易、连续交易拉抬股价等方式实施操纵。该期间内,“浙江交科”股票交易价格大幅上涨。整个期间,“浙江交科”股票交易价格从每股7.25元上涨至每股11.26元,涨幅55.31%。第三阶段为减仓阶段。2018年12月7日至2019年1月11日,账户组竞价买入成交“浙江交科”股票36,340,437股,竞价卖出成交99,786,954股,净卖出63,446,517股,该期间期末无持股。减仓阶段,账户组3主要为卖出“浙数文化”,在该期间内持有“浙数文化”股数及比例大幅下降,“浙江交科”交易价格从每股11.26元下跌至每股8.78元,跌幅22.02%。(三)俞国生、张一苗控制账户组3利用资金优势、持股优势连续买卖“浙江交科”1.资金优势账户组3在操纵期间3内对“浙江交科”的交易中具有明显资金优势。操纵期间3内的161个交易日中,账户组3有153个交易日存在竞价买入交易,合计买入成交217,135.13万元。其中,账户组3竞价买入金额超过800万元的有101个交易日,占账户组3竞价买入交易天数的66.01%;账户组3竞价买入成交金额超过1,500万元的有59个交易日,占账户组3竞价买入交易天数的38.56%;账户组3日均竞价买入成交金额为1,419.18万元,占市场平均日成交额的17.88%。其中,2018年5月21日,账户组3竞价买入“浙江交科”4,130,805股,成交金额4,920.57万元。2.持股优势操纵期间3内,账户组3利用资金优势大量买入进而形成持股优势,持有“浙江交科”超过流通股本比例5%的交易日为106天,占操纵期间3内全部交易日的65.83%;持有“浙江交科”超过流通股本比例10%的天数为34天,占操纵期间3内全部交易日的21.11%。其中,2018年11月26日,账户组3持有“浙江交科”占流通股本比例达到最高值11.67%。3.连续交易关于申买量排名指标。在操纵期间3内的161个交易日中,账户组3有161个交易日交易了“浙江交科”,占比99.38%。其中有111个交易日,账户组3的申买量排名第一,占比为69.38%;有151个交易日,账户组3的申买量排名前十,占比为94.38%;有104个交易日,账户组3的申卖量排名第一,占比为65.00%;有140个交易日,账户组3的申卖量排名前十,占比为87.50%。关于竞价成交量指标。操纵期间3内,有113个交易日,账户组3的竞价成交量占比超过10%,占比为70.63%;有58个交易日,账户组3的竞价成交量占比超过20%,占比为36.25%;有22个交易日,账户组3的竞价成交量占比超过30%,占比为13.75%。其中,2018年12月19日,账户组3的竞价成交量占比达到最高值,为62.10%。关于账户组3竞价买入及卖出成交量占市场竞价成交量指标。有122个交易日,账户组3竞价买入成交量占市场竞价成交量的比例超过10%,占比为76.25%;有71个交易日,该指标超过20%,占比为44.38%;有29个交易日,该指标超过30%,占比为18.13%。其中,2018年11月15日,账户组3竞价买入成交量占市场竞价成交量的比例达最高值,为52.36%。有89个交易日,账户组3竞价卖出成交量占市场竞价成交量的比例超过10%,占比为55.63%;有52个交易日,该指标超过20%,占比为32.50%;有32个交易日,该指标超过30%,占比为20%。其中,2018年12月19日,账户组3竞价卖出成交量占市场竞价成交量的比例达最高值,为74.64%。关于申买价指标。操纵期间3内,账户组3申买价不低于市场卖一价的申买量为151,414,800股,占操作期间3内账户组3连续竞价阶段总申买量232,438,400股的65.14%;账户组3申买价不低于卖一价且申报数量大于卖方一档数量的总申报量为129,050,600股,占操纵期间3内账户组3连续竞价阶段总申买量232,438,400股的55.52%;账户组3申买价不低于申买前最新市场成交价的申买量为168,666,400股,占操纵期间3内账户组3连续竞价阶段总申买量232,438,400股的72.56%;特别是2018年6月7日至2019年1月7日期间内,账户组3申买价高于申买前最新市场成交价大于或等于1%的申买量为1,152,500股,占账户组期间连续竞价阶段总申买量34,301,000股的3.36%。上述指标说明账户组3在能以更低价格买到“浙江交科”的情形下,仍以高于市场价的价格申买,可见其影响“浙江交科”交易量和交易价格的意图明显。4.连续交易的典型拉抬区间操纵期间3内,在55个交易日中有94个时间段,账户组3多次盘中拉抬“浙江交科”交易价格,最高拉抬幅度达4.19%,并存在拉抬中及拉抬后反向卖出情形。典型拉抬区间如下:2018年11月26日,11:04:14至11:22:18期间,账户组3拉抬前一笔市场成交价为每股10.43元,该期间内,其最低申买价格为每股10.44元,最高申买价格为每股10.85元,申买均价为每股10.66元。该期间内,账户组3申报买入411,800股,申买占比45.59%,不低于卖一价申买量占账户组3总申买量的98.08%;账户组3买成交326,800股,占市场买成交量的比例为55.25%。账户组3在拉抬后存在反向卖出,其中,拉抬中卖出88,300股,卖出均价为每股10.72元;拉抬后卖出784,700股,卖出均价10.82元/股。账户组3拉抬前一笔市场成交价为每股10.43元,该时段截止时市场成交价为10.85元,涨幅为4.03%。(四)俞国生、张一苗控制账户组3在自己实际控制的账户之间进行交易及日内反向交易在操纵期间3内的161个交易日中,有121个交易日存在账户组3的账户之间交易“浙江交科”的情况,占整个操纵期间3交易日天数的75.15%。有52个交易日存在账户组3的账户之间交易“浙江交科”成交量占当日市场竞价成交量的比例超过5%的情况,有27个交易日存在账户组3的账户之间交易“浙江交科”成交量占当日市场竞价成交量的比例超过10%的情况,有7个交易日存在账户组3的账户之间交易“浙江交科”成交量占当日市场竞价成交量的比例超过20%的情况。其中,2018年12月19日,账户组3的账户之间交易“浙数文化”成交量占当日市场竞价成交量的比例达到最高值35.11%。同时,操纵期间3内,账户组3有136个交易日存在日内反向交易,其中有95个交易日的反向交易成交量占账户组3成交量的比例超过50%。日均反向交易成交量占账户组3成交量比例为65.28%,最高达99.10%。(五)操纵期间3内,“浙江交科”股价走势偏离大盘指数及所在行业指数情况操纵期间3内,“浙江交科”股票交易价格出现较大波动。其中,2018年5月21日至10月16日,“浙江交科”股票交易价格从每股12.21元下跌至每股7.25元,跌幅40.62%,与同期中小板指(下跌32.84%)相比偏离7.78个百分点,与建筑指数(886016.WI,下跌19.42%)相比偏离21.20个百分点。2018年10月17日至12月6日,股价从每股7.25元上涨至每股11.26元,涨幅55.31%,与同期中小板指(上涨4.10%)相比偏离51.21个百分点,与建筑指数(886016.WI,上涨5.24%)相比偏离50.07个百分点。2018年12月7日至2019年1月11日,股价从每股11.26元下跌至每股8.78元,跌幅22.02%,与同期中小板指(下跌5.24%)相比偏离16.78个百分点,与建筑指数(886016.WI,下跌1.56%)相比偏离20.46个百分点。综上,操纵期间3内,“浙江交科”股票交易价格走势与大盘指数及所在行业指数出现较大背离。五、俞国生、张一苗超比例持有“浙大网新”未披露及限制期内交易“浙大网新”(一)俞国生、张一苗控制使用“童某青”等78个账户情况2016年3月21日至2017年3月6日(以下简称交易期间),俞国生、张一苗控制使用“童某青”“姜某冬”“杨某”等78个证券账户(以下简称账户组4)交易“浙大网新”。(二)超比例持有“浙大网新”未披露的情况2016年3月21日至2017年3月6日期间,俞国生、张一苗控制“童某青”等78个证券账户连续交易“浙大网新”。2016年3月21日,账户组4在交易期间期初未持有“浙大网新”。截至2016年4月15日,账户组4持有“浙大网新”42,482,296股,占上市公司已发行股份的比例达到4.65%。截至2016年4月18日,账户组4持有“浙大网新”48,053,596股,占上市公司已发行股份的比例达到5.26%,首次达到上市公司已发行股份的5%。截至2016年7月12日,账户组4持有“浙大网新”92,459,435股,占上市公司已发行股份的比例达到10.12%。截至2016年7月13日,账户组4持有“浙大网新”98,312,735股,占上市公司已发行股份的比例达到10.76%。截至2016年8月11日,账户组4持有“浙大网新”118,809,976股,占上市公司已发行股份的比例达到13%,为涉案期间内的最高值。截至2016年10月26日,账户组4持有“浙大网新”43,767,216股,占上市公司已发行股份的比例达到4.79%。截至2017年3月6日,账户组4未持有“浙大网新”。俞国生、张一苗控制的账户组4持有“浙大网新”占上市公司已发行股份的比例达到5%后,未向国务院证券监督管理机构、证券交易所作书面报告,通知上市公司,并予公告。(三)限制期内交易情况2016年4月18日,俞国生、张一苗控制的账户组4持有“浙大网新”首次达到上市公司已发行股份的5%后未按规定履行报告及公告义务,并持续交易“浙大网新”,直至2017年3月6日全部卖出其持有的“浙大网新”。2016年4月19日至2017年3月6日期间内,账户组4累计买入“浙大网新”200,955,388股,买入金额为2,662,188,791.51元,累计卖出“浙大网新”249,008,984股,卖出金额为3,622,781,065元。上述违法事实,有相关人员询问笔录、银行流水、交易结算表、证券账户资料、交易所相关数据信息等证据证明,足以认定。俞国生、张一苗操纵“浙数文化”“浙江交科”的行为,违反2005年《证券法》第七十七条第一项、第三项的规定,构成2005年《证券法》第二百零三条所述的操纵证券市场行为。俞国生、张一苗在持股比例达到浙大网新科技股份有限公司(以下简称浙大网新)总股本的5%时,未按规定履行报告和信息披露义务,违反了2005年《证券法》第八十六条第一款规定,构成2005年《证券法》第一百九十三条第一款所述“发行人、上市公司或者其他信息披露义务人未按照规定披露信息”的信息披露违法行为。俞国生、张一苗限制期内交易“浙大网新”的行为,违反了2005年《证券法》第三十八条、第八十六条第一款规定,构成2005年《证券法》第二百零四条所述“违反法律规定,在限制转让期限内买卖证券”的违法行为。上述交易由俞国生负责总体决策,提供资金并承担交易产生的收益和亏损;张一苗负责具体决策并向交易员下达指令,安排相关人员通过其控制的银行账户向证券账户对应的存管银行账户进行转入保证金、支付利息、收取盈利等资金流转,同时向俞国生汇报,野风集团工作人员参与上述借入账户、划转资金和执行交易等过程。俞国生、张一苗及其代理人在听证及申辩材料中共同提出:其一,事先告知书认定张一苗与俞国生共同控制143个账户是错误的。两人之间仅存在借款关系,张一苗借入资金后的配资行为和借用配资账户交易股票行为均与俞国生无关,俞国生并未参与张一苗等人对资金的使用和决策,张一苗是自主交易决策,也未向俞国生汇报股票交易事项。其二,《结算表》《利息表》《备忘录》等文件(以下简称《结算表》等文件)与事实不符,不具备证据效力。联锦大厦23楼的办公室并非俞国生使用。俞国生称不知悉《结算表》等文件内容,且《结算表》等文件是假的。其三,部分证据不具有合法性,不符合证据标准。部分言辞证据存在相互矛盾的情形。关键性书证缺失,书证之间不能相互衔接,无法形成完整证据链条。其四,金某君、张某坤的交易与俞国生、张一苗无关。俞国生仅是将资金借给张一苗、金某君、张某坤等人,俞国生从未参与上述资金的具体使用和决策。金某君、张某坤相关交易系由其自行决策,金某君、张某坤的交易与俞国生、张一苗无关。此外,张一苗及其代理人在听证及申辩材料中还提出:其一,张一苗仅控制26个账户。张一苗与金某君、张某坤使用的证券账户无任何关系。张一苗控制的26个涉案账户交易“浙大网新”“浙数文化”“浙江交科”的情况并未达到事先告知书所述的数额和比例,不构成操纵市场、超比例持股未披露、限制期内交易等违法行为。其二,张一苗交易“浙数文化”“浙江交科”有充分合理的理由,没有操纵的主观故意,不构成操纵行为。张一苗通过调研、查阅公开信息等方式使用26个账户交易“浙大网新”“浙数文化”“浙江交科”,投资符合价值投资战略方向,与其以往偏向细分行业龙头的投资风格相符。张一苗委托章某铭操作时不涉及具体操作方式,由章某铭决定交易方式、价格、数量,故即使张一苗控制的账户存在违法情形,也不应由张一苗承担责任。综上,俞国生、张一苗请求免于处罚。经复核,我会认为:第一,关于账户控制关系。根据当事人自认、操盘方工作人员自认、配资方指认、第三方指认、《结算表》等文件、出资及配资协议、涉案账户组的资金来源及去向等在案证据,足以认定143个涉案账户由俞国生、张一苗共同控制,具体如下:1.根据在案证据,俞国生总体决策涉案账户组资金流转,获取盈利,涉案期间,相关账户累计向俞国生转出近3亿元,向野风集团转出近1亿元。涉案证券账户的资金来源和去向指向张一苗控制的账户,资金流转情况与张一苗、金某君关于以配资模式借用证券账户的陈述相符,张一苗控制账户的资金在违法行为发生前与俞国生、野风集团及其关联公司存在大额、频繁的资金往来。2.根据在案证据,张一苗在交易前后及中间阶段会向俞国生汇报,俞国生总体知悉所交易的股票情况,在资金划转、股票交易方面进行总体决策,起到核心作用。张一苗承认,交易“浙大网新”“浙数文化”“浙江交科”前,张一苗向俞国生汇报并征得俞国生同意。3.张一苗申辩称“我在调查中确实说过俞国生参与投资决策的话,但并非客观事实,是我在接受调查时临时编的”,同时张一苗申辩称金某君、张某坤系独立决策交易,该二人的交易与张一苗无关。我会认为,张一苗在调查阶段承认俞国生参与投资决策,并承认其通过金某君、张某坤借入配资账户,张一苗直接安排涉案银行账户的资金流转,具体决策证券交易,能够与本案其他证据相互印证。张一苗在陈述申辩材料和听证会上否认其在调查阶段的陈述,缺乏证据支持,我会依法不予采信。第二,关于《结算表》等文件的真实性。根据在案证据,杭州联锦大厦A幢23楼最大办公室是俞国生的办公室。调查人员在上述办公室取得《结算表》等文件,取证时俞国生秘书姚某晔在场,俞国生大女儿俞某签字确认“此文件取自俞国生位于联锦大厦A座23层办公室”。调查人员询问张一苗时,向张一苗出示《结算表》等文件,张一苗确认“此文件中涉及的证券账户是我借用的部分配资证券账户”。《结算表》等文件在制表、复核等过程经过数名野风集团员工签字审核,最终由张一苗签字并向俞国生汇报,且文件呈现的账户范围、统计期间、盈利情况与事先告知书认定事实基本相符。上述事实足以证明《结算表》等文件的真实性,当事人申辩称《结算表》等文件与事实不符没有相应证据支持,我会依法不予采信。第三,关于证据效力。调查程序符合法定程序要求,在案证据符合法定形式,主要违法事实有多方面证据相互印证,形成完整证据链,具备证据效力。我会对当事人相关申辩意见不予采纳。第四,关于金某君、张某坤是否独立交易决策的问题。在案证据足以证明金晓君、张建坤并非独立进行交易决策,而是由张一苗直接控制资金流转和交易决策。当事人所述部分账户由金某君、张某坤控制的说法与事实不符。具体如下:1.金某君承认其借入涉案配资账户,并交张一苗使用,金某君本人并未参与决策交易。张一苗承认其通过金某君、张某坤借入配资账户,并承认与张一苗所控制的银行账户相对应的证券账户都是其借用的。张一苗直接安排涉案银行账户的资金流转,具体决策证券交易。涉案账户组的相关交易呈现由同一主体控制的特征。同时,金某君、张某坤等人在野风集团任职并领取薪酬。2.《结算表》等文件涵盖与金某君、张某坤银行账户存在资金关联的证券账户。前已述及,《结算表》等文件由调查部门取自俞国生办公场所,由野风集团工作人员审核确认,最终由张一苗确认后向俞国生汇报,且张一苗承认《结算表》等文件涉及的证券账户是其借用的配资账户,该说法与金某君所述为张一苗借来配资账户的说法相互印证。故《结算表》等文件证明张一苗直接控制涉案账户组。第五,关于张一苗提出其控制26个涉案账户,基于价值投资原则从事交易的相关问题。如前所述,在案证据足以证明俞国生、张一苗共同控制涉案账户组,故张一苗所述其仅控制26个账户的申辩意见不予采纳。同时,根据在案证据,涉案账户组在涉案期间通过连续交易、在自己实际控制的账户内交易等手段,影响涉案股票价格和交易量,构成操纵市场违法行为。且张一苗询问笔录和交易痕迹显示,涉案账户组总体是每个账户匹配一台电脑,交易行为呈现相互配合、一致行动等特征,进一步说明当事人存在操纵的主观故意。对张一苗辩称相关交易不构成操纵行为等申辩意见,我会不予采纳。综上,我会对俞国生、张一苗及其代理人的申辩意见不予采纳。根据当事人违法行为的事实、性质、情节与社会危害程度,依据2005年《证券法》第一百九十三条第一款、第二百零三条、第二百零四条的规定,我会决定:一、对俞国生、张一苗操纵“浙数文化”行为,没收违法所得274,313,073.19元,并对俞国生、张一苗合计处以274,313,073.19元罚款,其中,对俞国生处以182,875,382.13元罚款,对张一苗处以91,437,691.06元罚款。二、对俞国生、张一苗于2017年8月25日至2018年5月18日操纵“浙江交科”行为,没收违法所得102,545,916.82元,并对俞国生、张一苗合计处以102,545,916.82元的罚款,其中,对俞国生处以68,363,944.55元罚款,对张一苗处以34,181,972.27元罚款。三、对俞国生、张一苗于2018年5月21日至2019年1月11日操纵“浙江交科”行为,没收违法所得36,451,611.14元,并对俞国生、张一苗合计处以36,451,611.14元的罚款,其中,对俞国生处以24,301,074.1元罚款,对张一苗处以12,150,537.04元罚款。四、对俞国生、张一苗超比例持有“浙大网新”未披露的行为,责令改正,给予警告,并处以30万元罚款,其中,对俞国生处以20万元罚款,对张一苗处以10万元罚款。五、对俞国生、张一苗限制期内交易“浙大网新”行为,责令改正,给予警告,并处以3,000万元罚款,其中,对俞国生处以2,000万元罚款,对张一苗处以1,000万元罚款。上述当事人应自收到本处罚决定书之日起15日内,将罚款汇交中国证券监督管理委员会开户银行:中信银行北京分行营业部,账号:7111010189800000162,由该行直接上缴国库,并将注有当事人名称的付款凭证复印件送中国证券监督管理委员会行政处罚委员会办公室备案。当事人如果对本处罚决定不服,可在收到本处罚决定书之日起60日内向中国证券监督管理委员会申请行政复议,也可在收到本处罚决定书之日起6个月内直接向有管辖权的人民法院提起行政诉讼。复议和诉讼期间,上述决定不停止执行。中国证监会2023年6月6日 | D3: 45083
A4: 是 | B4: 否 | C4: 〔2023〕36号当事人:任良成,男,1958年11月出生,住址:上海市嘉定区。依据2005年修订、2014年修正的《中华人民共和国证券法》(以下简称2005年《证券法》)的有关规定,我会对任良成操纵证券市场行为进行了立案调查、审理,并依法向当事人告知了作出行政处罚的事实、理由、依据及当事人依法享有的权利。应当事人要求,我会于2023年3月20日举行了听证会,听取了任良成及其代理人的陈述和申辩。本案现已调查、审理终结。经查明,任良成存在以下违法事实:一、任良成控制使用账户的情况2015年4月至2015年12月,任良成先后控制使用陈某华、陈某(甲)等31人名下的51个账户(以下简称第一组账户),包括:(1)华福证券有限责任公司上海遵义路证券营业部“陈某华”信用账户;(2)华泰证券股份有限公司深圳深南大道证券营业部“陈某(甲)”普通账户和信用账户;(3)华鑫证券有限责任公司深圳深南东路证券营业部“陈某辉”普通账户;(4)江海证券有限公司北京东三环南路证券营业部“陈某辉”普通账户;(5)兴业证券股份有限公司郑州商务外环路证券营业部“陈某明”普通账户;(6)广发证券股份有限公司深圳高新南一道证券营业部“陈某(乙)”普通账户;(7)国泰君安证券股份有限公司石家庄建华南大街证券营业部“褚某”普通账户;(8)华龙证券股份有限公司兰州安宁东路证券营业部“褚某”普通账户;(9)中信建投证券股份有限公司上海北京西路证券营业部“丁某漓”普通账户;(10)华泰证券股份有限公司武汉友谊大道证券营业部“郭某妹”普通账户和信用账户;(11)华泰证券股份有限公司武汉友谊大道证券营业部“何某彬”普通账户;(12)中国银河证券股份有限公司沈阳三经街证券营业部“何某彬”普通账户;(13)华泰证券股份有限公司常州和平北路证券营业部“金某亮”普通账户;(14)华泰证券股份有限公司盐城分公司“李某甘”普通账户;(15)广发证券股份有限公司上海东方路证券营业部“凌某”普通账户;(16)中信建投证券股份有限公司上海控江路证券营业部“凌某”普通账户;(17)安信证券股份有限公司青岛山东路证券营业部“刘某君”普通账户;(18)华泰证券股份有限公司岳阳五里牌证券营业部“卢某霞”普通账户;(19)中国银河证券股份有限公司上海肇嘉浜路证券营业部“卢某霞”普通账户;(20)首创证券有限责任公司南京高淳古檀大道证券营业部“卢某霞”普通账户;(21)华泰证券股份有限公司深圳分公司“马某里”普通账户和信用账户;(22)国泰君安证券股份有限公司上海江苏路证券营业部“孟某”普通账户;(23)银泰证券有限责任公司杭州体育场路证券营业部“孟某”普通账户;(24)渤海证券股份有限公司天津友谊南路证券营业部“任某恩”普通账户;(25)东兴证券股份有限公司上海肇嘉浜路证券营业部“任良成”普通账户和信用账户;(26)国泰君安证券股份有限公司上海江苏路证券营业部“邵某珍”普通账户;(27)西南证券股份有限公司上海黄陵路证券营业部“沈某(甲)”普通账户;(28)中信证券(浙江)有限责任公司海宁海昌南路证券营业部“沈某(甲)”普通账户;(29)华泰证券股份有限公司海门解放中路证券营业部“沈某(甲)”信用账户;(30)中原证券股份有限公司郑州经三路证券营业部“沈某(甲)”普通账户;(31)东兴证券股份有限公司上海肇嘉浜路证券营业部“谭某”普通账户;(32)国泰君安证券股份有限公司上海静安区南京西路证券营业部(原国泰君安证券股份有限公司上海延平路证券营业部)“唐某明”普通账户;(33)华福证券有限责任公司上海遵义路证券营业部“陶某雯”普通账户;(34)华泰证券股份有限公司上海浦东新区福山路证券营业部“陶某雯”普通账户;(35)东北证券股份有限公司福州东街证券营业部“陶某雯”普通账户;(36)华泰证券股份有限公司广州东风西路证券营业部“涂某约”普通账户;(37)浙商证券股份有限公司常州怀德中路证券营业部“涂某约”普通账户;(38)国泰君安证券股份有限公司上海江苏路证券营业部“王某(甲)”普通账户;(39)东兴证券股份有限公司上海肇嘉浜路证券营业部“吴某玲”信用账户;(40)湘财证券股份有限公司乌鲁木齐克拉玛伊东路证券营业部“严某华”普通账户;(41)宏源证券股份有限公司上海源深路证券营业部“张某(甲)”普通账户;(42)海通证券股份有限公司上海普陀区枣阳路证券营业部“赵某青”信用账户;(43)国泰君安证券股份有限公司上海江苏路证券营业部“钟某庆”普通账户;(44)华泰证券股份有限公司淮安分公司“钟某镇”普通账户;(45)东北证券股份有限公司福州五一中路证券营业部“钟某镇”普通账户和信用账户;(46)中国银河证券股份有限公司上海新郁路证券营业部“钟某镇”普通账户。2016年8月至2017年10月,任良成先后控制使用蔡某农、陈某华等98人(包括2家法人)名下的150个账户(以下简称第二组账户),包括:(1)华福证券有限责任公司浙江分公司“蔡某农”普通账户;(2)华泰证券股份有限公司盐城分公司“陈某华”普通账户和信用账户;(3)华福证券有限责任公司上海东方路证券营业部“陈某华”普通账户;(4)首创证券有限责任公司厦门厦禾路证券营业部“陈某(丙)”普通账户;(5)财通证券股份有限公司安吉体育场证券营业部“陈某(丁)”普通账户;(6)国泰君安证券股份有限公司上海江苏路证券营业部“陈某(戊)”普通账户;(7)兴业证券股份有限公司深圳海德三道证券营业部“陈某辉”普通账户和信用账户;(8)国泰君安证券股份有限公司福州华林路证券营业部“陈某芳”普通账户;(9)中国银河证券股份有限公司福州东水路证券营业部“陈某其”普通账户;(10)中国银河证券股份有限公司福清万达广场证券营业部“陈某荷”普通账户和信用账户;(11)广发证券股份有限公司深圳高新南一道证券营业部“陈某(乙)”普通账户;(12)华福证券有限责任公司上海遵义路证券营业部“程某梅”普通账户;(13)联储证券有限责任公司烟台科技大道证券营业部“程某梅”普通账户;(14)中泰证券股份有限公司安丘兴安路证券营业部“程某梅”普通账户;(15)华金证券有限责任公司上海宁夏路证券营业部“程某梅”普通账户;(16)华泰证券股份有限公司南通环城西路证券营业部“程某梅”普通账户和信用账户;(17)华泰证券股份有限公司上海武定路证券营业部“池某娟”普通账户;(18)国泰君安证券股份有限公司石家庄建华南大街证券营业部“褚某”普通账户;(19)华林证券股份有限公司深圳海秀路证券营业部“崔某辉”信用账户;(20)广发证券股份有限公司南通工农南路证券营业部“丁某漓”普通账户;(21)华泰证券股份有限公司溧阳南大街证券营业部“丁某漓”普通账户;(22)华泰证券股份有限公司南通环城西路证券营业部“高某”普通账户;(23)华福证券有限责任公司上海遵义路证券营业部“郭某妹”普通账户和信用账户;(24)华泰证券股份有限公司溧水珍珠南路证券营业部“郭某习”普通账户和信用账户;(25)招商证券股份有限公司镇江谷阳路证券营业部“郭某习”普通账户;(26)东海证券股份有限公司常州博爱路证券营业部“何某彬”普通账户;(27)东方证券股份有限公司江阴人民东路证券营业部“何某彬”普通账户;(28)渤海证券股份有限公司西安劳动南路证券营业部“何某中”普通账户;(29)中国银河证券股份有限公司长沙解放中路证券营业部“湖南同恒资产管理有限公司”普通账户;(30)华泰证券股份有限公司常州和平北路证券营业部“揭某道”普通账户;(31)兴业证券股份有限公司深圳侨香路证券营业部“匡某颖”普通账户;(32)华林证券股份有限公司深圳海秀路证券营业部“赖某珍”普通账户;(33)中信证券股份有限公司杭州凤起路证券营业部“李某甘”普通账户;(34)九州证券股份有限公司深圳分公司“李某甘”普通账户;(35)江海证券有限公司北京东三环南路证券营业部“李某侠”普通账户;(36)华福证券有限责任公司福州上三路证券营业部“李某”普通账户;(37)中国银河证券股份有限公司广州华夏路证券营业部“李某”普通账户;(38)华泰证券股份有限公司上海黄河路证券营业部“林某妹”普通账户;(39)中国银河证券股份有限公司福州证券营业部“林某”普通账户;(40)华泰证券股份有限公司淮安淮安区韩信南路证券营业部“凌某”普通账户;(41)招商证券股份有限公司厦门湖滨东路证券营业部“刘某锋”普通账户;(42)国金证券股份有限公司天津南马路证券营业部“刘某(甲)”普通账户;(43)中国银河证券股份有限公司深圳福华一路证券营业部“刘某(乙)”普通账户;(44)金元证券股份有限公司北京新外大街证券营业部“刘某媛”信用账户;(45)中航证券有限公司青岛江西路证券营业部“刘某媛”普通账户;(46)浙商证券股份有限公司上虞江扬路证券营业部“刘某媛”普通账户;(47)华福证券有限责任公司上海遵义路证券营业部“陆某”普通账户和信用账户;(48)五矿证券有限公司福州八一七中路证券营业部“陆某”普通账户;(49)华泰证券股份有限公司深圳分公司“马某里”信用账户;(50)广发证券股份有限公司无锡太湖东大道证券营业部(原广发证券股份有限公司无锡清扬路证券营业部)“孟某”普通账户;(51)华泰证券股份有限公司武汉友谊大道证券营业部“孟某”普通账户;(52)华泰证券股份有限公司海门解放中路证券营业部“潘某玉”普通账户和信用账户;(53)恒泰证券股份有限公司深圳香林路证券营业部“潘某玉”普通账户;(54)财通证券股份有限公司诸暨店口华佳路证券营业部“钱某”普通账户;(55)渤海证券股份有限公司天津友谊南路证券营业部“任某恩”普通账户;(56)东兴证券股份有限公司上海肇嘉浜路证券营业部“任良成”信用账户;(57)华泰证券股份有限公司南通环城西路证券营业部“任某帆”普通账户;(58)中泰证券股份有限公司上海西安路证券营业部“沈某(乙)”普通账户;(59)西南证券股份有限公司萧山市心北路证券营业部“沈某希”普通账户;(60)华泰证券股份有限公司郑州农业路证券营业部“沈某希”普通账户;(61)中国银河证券股份有限公司上海东宝兴路证券营业部“沈某希”信用账户;(62)渤海证券股份有限公司西安劳动南路证券营业部“沈某(甲)”普通账户;(63)华泰证券股份有限公司海门长江路证券营业部“沈某凤”信用账户;(64)联储证券有限责任公司烟台科技大道证券营业部“史某雯”普通账户;(65)金元证券股份有限公司北京新外大街证券营业部“宋某林”普通账户;(66)金元证券股份有限公司北京新外大街证券营业部“宋某国”普通账户;(67)东兴证券股份有限公司上海肇嘉浜路证券营业部“苏某”普通账户;(68)兴业证券股份有限公司河南分公司“苏某”普通账户;(69)中信建投证券股份有限公司深圳深南中路证券营业部“苏某丝”信用账户;(70)中国银河证券股份有限公司长沙解放中路证券营业部“孙某波”普通账户;(71)中信证券股份有限公司上海瑞金南路证券营业部“谭某”普通账户;(72)方正证券股份有限公司台州市府大道证券营业部“陶某雯”普通账户;(73)广发证券股份有限公司上海新松江路证券营业部“汪某琪”普通账户和信用账户;(74)华泰证券股份有限公司盐城分公司“汪某琪”普通账户;(75)首创证券有限责任公司上海宝山区殷高路证券营业部“汪某龙”普通账户;(76)招商证券股份有限公司镇江谷阳路证券营业部“王某曦”普通账户;(77)恒泰证券股份有限公司上海杜鹃路证券营业部“王某伟”普通账户;(78)东海证券股份有限公司泰兴济川路证券营业部“王某文”普通账户;(79)申万宏源证券有限公司盐城滨海海滨大道证券营业部“王某文”普通账户;(80)华融证券股份有限公司北京石景山路证券营业部“王某(乙)”普通账户;(81)中泰证券股份有限公司北京安立路证券营业部“王某(乙)”普通账户;(82)广发证券股份有限公司昆山前进东路证券营业部“王某(乙)”普通账户;(83)中泰证券股份有限公司上海东方路证券营业部“王某飞”普通账户;(84)东海证券股份有限公司泰兴济川路证券营业部“王某飞”普通账户;(85)渤海证券股份有限公司天津友谊路证券营业部“王某雅”普通账户;(86)东北证券股份有限公司上海虹口区吴淞路证券营业部“王某雅”普通账户;(87)国信证券股份有限公司上海淮海西路证券营业部“王某(丙)”普通账户;(88)中信证券股份有限公司杭州市心南路证券营业部“王某源”普通账户和信用账户;(89)方正证券股份有限公司杭州中河中路证券营业部“魏某萍”信用账户;(90)东北证券股份有限公司石家庄民生路证券营业部“魏某萍”普通账户;(91)华泰证券股份有限公司南通环城西路证券营业部“吴某玲”普通账户;(92)中信证券股份有限公司平湖建国北路证券营业部“吴某玲”普通账户;(93)首创证券有限责任公司上海宝山区殷高路证券营业部“吴某红”普通账户;(94)华泰证券股份有限公司张家港金港镇长江中路证券营业部“徐某”普通账户;(95)华安证券股份有限公司厦门吕岭路证券营业部“徐某中”普通账户;(96)国联证券股份有限公司北京建材城西路证券营业部“许某芳”信用账户;(97)华安证券股份有限公司厦门吕岭路证券营业部“许某枝”普通账户;(98)华泰证券股份有限公司武汉友谊大道证券营业部“鄢某飞”普通账户;(99)中国银河证券股份有限公司福州东水路证券营业部“颜某翠”普通账户;(100)华福证券有限责任公司福州湖东路证券营业部“杨某锋”普通账户和信用账户;(101)渤海证券股份有限公司上海彰武路证券营业部“杨某(甲)”普通账户;(102)华泰证券股份有限公司常州和平北路证券营业部“杨某(甲)”普通账户;(103)中国银河证券股份有限公司南通工农路证券营业部“杨某(乙)”普通账户;(104)华泰证券股份有限公司上海浦东新区乳山路证券营业部“杨某(乙)”普通账户;(105)东吴证券股份有限公司张家港杨舍镇沙洲中路证券营业部“杨某(乙)”普通账户;(106)国泰君安证券股份有限公司上海静安区南京西路证券营业部“杨某启”普通账户;(107)华泰证券股份有限公司深圳深南大道证券营业部“杨某(丙)”普通账户;(108)联讯证券股份有限公司清远人民二路证券营业部“俞某辰”普通账户;(109)中信证券股份有限公司上海瑞金南路证券营业部“云南国际信托有限公司-臻尹一号集合资金信托计划”“云南国际信托有限公司-臻尹二号集合资金信托计划”普通账户;(110)东海证券股份有限公司泰兴济川路证券营业部“张某昌”信用账户;(111)华西证券股份有限公司杭州学院路证券营业部“张某昌”普通账户;(112)华泰证券股份有限公司上海武定路证券营业部“张某岚”普通账户;(113)中信建投证券股份有限公司福州浦上大道证券营业部“张某奇”普通账户;(114)东兴证券股份有限公司上海肇嘉浜路证券营业部“张某(乙)”普通账户;(115)国泰君安证券股份有限公司上海江苏路证券营业部“张某(丙)”普通账户;(116)申万宏源证券有限公司上海黄浦区雁荡路证券营业部“张某(丙)”普通账户;(117)东吴证券股份有限公司常熟商城中路证券营业部“张某敏”普通账户;(118)华泰证券股份有限公司上海武定路证券营业部“张某(丁)”信用账户;(119)中信建投证券股份有限公司安吉天荒坪路证券营业部“张某(丁)”普通账户;(120)中泰证券股份有限公司安丘兴安路证券营业部“张某(丁)”普通账户;(121)方正证券股份有限公司上海杨高北路证券营业部“赵某博”普通账户;(122)长城证券股份有限公司前海分公司“赵某博”信用账户;(123)华林证券股份有限公司北京太平桥大街证券营业部“赵某楠”普通账户;(124)中国银河证券股份有限公司北京阜成路证券营业部“赵某楠”普通账户;(125)东兴证券股份有限公司上海肇嘉浜路证券营业部“赵某青”普通账户和信用账户;(126)东兴证券股份有限公司北京北四环中路证券营业部“赵某欣”普通账户;(127)开源证券股份有限公司上海分公司“郑某丹”普通账户;(128)华福证券有限责任公司福州上三路证券营业部“郑某珍”普通账户;(129)中泰证券股份有限公司安丘兴安路证券营业部“周某(甲)”普通账户;(130)中信证券股份有限公司上海长寿路证券营业部“周某(甲)”普通账户;(131)国泰君安证券股份有限公司南京溧水中大街证券营业部“周某浩”普通账户;(132)中国银河证券股份有限公司长沙解放中路证券营业部“周某浩”信用账户;(133)南京证券股份有限公司上海西藏南路证券营业部“周某浩”普通账户;(134)华林证券股份有限公司深圳海秀路证券营业部“周某浩”普通账户;(135)长城证券股份有限公司北京西直门外大街证券营业部“周某(乙)”普通账户;(136)东莞证券股份有限公司厦门枋湖东路证券营业部“朱某东”普通账户;(137)中信证券股份有限公司上海世纪大道证券营业部“朱某”普通账户。二、任良成操纵“酒钢宏兴”等股票的情况2015年4月13日至2017年10月24日期间,任良成先后操纵16只股票的交易价格和交易量,其中控制第一组账户操纵“酒钢宏兴”“贵人鸟”“美锦能源”“太化股份”“漳州发展”“国脉科技”“广宇发展”“曙光股份”“钱江生化”“广宇集团”“全柴动力”“天宝股份”等12只股票的交易价格和交易量,控制第二组账户操纵“远兴能源”“隆华节能”“冠农股份”“维维股份”等4只股票交易价格和交易量。具体情况如下:(一)操纵“酒钢宏兴”情况2015年4月13日至2015年5月14日,任良成控制第一组账户,集中资金优势连续买卖“酒钢宏兴”,操纵“酒钢宏兴”交易价格和交易量。期间竞价买入成交741,220,753股,竞价买入成交金额4,172,176,394.98元,大宗交易买入成交739,243,800股,大宗交易买入成交金额3,863,447,524.00元;竞价卖出成交1,480,464,553股,竞价卖出成交金额8,250,766,675.05元。第一组账户期初无持股,期末将持有的“酒钢宏兴”全部卖出。2015年4月13日至2015年5月14日期间,“酒钢宏兴”共有23个交易日,第一组账户在23个交易日均发生交易。第一组账户在21个交易日有买入交易(含大宗交易),日均买入成交股数70,498,312股,日均买入成交金额382,648,758.05元,有18个交易日的竞价买入成交量市场排名第一。第一组账户在22个交易日有卖出交易,日均卖出成交股数67,293,843股,日均卖出成交金额375,034,848.87元,有18个交易日的竞价卖出成交量市场排名第一。第一组账户当日竞价成交量占市场竞价成交量的比例(以下简称竞价成交占比)超过20%的有9个交易日,其中2015年4月16日竞价成交占比达到最高的29.99%。上述期间,第一组账户多次实施盘中拉抬行为,以“时段股价涨幅2%以上且时段买成交占比20%以上”为筛选条件,第一组账户在42个时段有盘中拉抬股价行为。经统计,任良成操纵“酒钢宏兴”盈利201,757,388.36元。(二)操纵“贵人鸟”情况2015年6月2日至2015年8月3日,任良成控制第一组账户,集中资金优势连续买卖“贵人鸟”,操纵“贵人鸟”交易价格和交易量。期间竞价买入成交84,339,941股,竞价买入成交金额3,944,200,030.38元,大宗交易买入成交2,800,000股,大宗交易买入成交金额169,484,000.00元;竞价卖出成交87,139,941股,竞价卖出成交金额4,039,515,506.61元。第一组账户期初无持股,期末将持有的“贵人鸟”全部卖出。2015年6月2日至2015年8月3日期间,“贵人鸟”共有39个交易日,第一组账户在37个交易日发生交易,其中在36个交易日有买入交易(含大宗交易),日均买入成交股数2,420,554股,日均买入成交金额114,269,000.84元,有32个交易日的竞价买入成交量市场排名第一。第一组账户在33个交易日有卖出交易,日均卖出成交股数2,640,604股,日均卖出成交金额122,409,560.81元,有26个交易日的竞价卖出成交量市场排名第一。第一组账户当日竞价成交占比超过20%的有18个交易日,其中2015年6月9日竞价成交占比达到最高的39.36%。上述期间,第一组账户多次实施盘中拉抬行为,以“时段股价涨幅2%以上且时段买成交占比20%以上”为筛选条件,第一组账户在156个时段有盘中拉抬行为。经统计,任良成操纵“贵人鸟”亏损79,099,708.70元。(三)操纵“美锦能源”情况1.2015年6月11日至2015年8月18日操纵情况。2015年6月11日至2015年8月18日,任良成控制第一组账户,集中资金优势连续买卖“美锦能源”,操纵“美锦能源”交易价格和交易量。期间竞价买入成交98,566,408股,竞价买入成交金额1,452,757,611.68元,大宗交易买入成交13,000,000股,大宗交易买入成交金额290,810,000.00元;竞价卖出成交111,566,408股,竞价卖出成交金额1,670,749,365.79元。第一组账户期初无持股,期末将持有的“美锦能源”全部卖出。2015年6月11日至2015年8月18日期间,“美锦能源”共有35个交易日,第一组账户在33个交易日发生交易,其中29个交易日有买入交易(含大宗交易),日均买入成交股数3,847,118股,日均买入成交金额60,123,021.09元,有26个交易日的竞价买入成交量市场排名第一。第一组账户在28个交易日有卖出交易,日均卖出成交股数3,984,515股,日均卖出成交金额59,669,620.21元,有25个交易日的竞价卖出成交量市场排名第一。第一组账户当日竞价成交占比超过10%的有17个交易日,其中2015年6月30日竞价成交占比达到最高的21.63%。上述期间,第一组账户多次实施盘中拉抬行为,以“时段股价涨幅2%以上且时段买成交占比20%以上”为筛选条件,第一组账户在46个时段有盘中拉抬行为。2.2015年8月31日至2015年9月10日操纵情况。2015年8月31日至2015年9月10日,任良成控制第一组账户,集中资金优势连续买卖“美锦能源”,操纵“美锦能源”交易价格和交易量。期间竞价买入成交11,162,768股,竞价买入成交金额97,386,535.80元;竞价卖出成交11,162,768股,竞价卖出成交金额98,165,369.52元。第一组账户期初无持股,期末将持有的“美锦能源”全部卖出。2015年8月31日至2015年9月10日期间,“美锦能源”共有7个交易日,第一组账户在7个交易日均发生交易,其中6个交易日有买入交易,日均买入成交股数1,860,461股,日均买入成交金额16,231,089.30元,有5个交易日的竞价买入成交量市场排名第一。第一组账户在4个交易日有卖出交易,日均卖出成交股数2,790,692股,日均卖出成交金额24,541,342.38元,有3个交易日的竞价卖出成交量市场排名第一。第一组账户当日竞价成交占比超过10%的有3个交易日,其中2015年9月2日竞价成交占比达到最高的21.51%。上述期间,第一组账户多次实施盘中拉抬行为,以“时段股价涨幅2%以上且时段买成交占比20%以上”为筛选条件,第一组账户在6个时段有盘中拉抬行为。经统计,任良成操纵“美锦能源”亏损74,717,609.29元。(四)操纵“太化股份”情况1.2015年6月25日至2015年7月22日操纵情况。2015年6月25日至2015年7月22日,任良成控制第一组账户,集中资金优势连续买卖“太化股份”,操纵“太化股份”交易价格和交易量。期间竞价买入成交76,047,289股,竞价买入成交金额630,361,048.70元,大宗交易买入成交12,200,000股,大宗交易买入成交金额155,428,000.00元;竞价卖出成交88,247,289股,竞价卖出成交金额741,591,560.77元。第一组账户期初无持股,期末将持有的“太化股份”全部卖出。2015年6月25日至2015年7月22日期间,“太化股份”共有19个交易日,第一组账户在16个交易日发生交易,其中13个交易日有买入交易(含大宗交易),日均买入成交股数6,788,253股,日均买入成交金额60,445,311.44元,有12个交易日的竞价买入成交量市场排名第一。第一组账户在15个交易日有卖出交易,日均卖出成交股数5,883,153股,日均卖出成交金额49,439,437.38元,有8个交易日的竞价卖出成交量市场排名第一。第一组账户当日竞价成交占比超过10%的有8个交易日,其中2015年7月16日竞价成交占比达到最高的36.63%。上述期间,第一组账户多次实施盘中拉抬行为,以“时段股价涨幅2%以上且时段买成交占比20%以上”为筛选条件,第一组账户在52个时段有盘中拉抬行为。2.2015年7月30日至2015年8月10日操纵情况。2015年7月30日至2015年8月10日,任良成控制第一组账户,集中资金优势连续买卖“太化股份”,操纵“太化股份”交易价格和交易量。期间竞价买入成交9,857,638股,竞价买入成交金额66,584,685.58元;竞价卖出成交9,857,638股,竞价卖出成交金额67,905,252.53元。第一组账户期初无持股,期末将持有的“太化股份”全部卖出。2015年7月30日至2015年8月10日期间,“太化股份”共有8个交易日,第一组账户在8个交易日均发生交易,其中在7个交易日有买入交易,日均买入成交股数1,408,234股,日均买入成交金额9,512,097.94元,有3个交易日的竞价买入成交量市场排名第一。第一组账户在4个交易日有卖出交易,日均卖出成交股数2,464,410股,日均卖出成交金额16,976,313.13元,且4个交易日的竞价卖出成交量均市场排名第一。第一组账户当日竞价成交占比超过10%的有3个交易日,其中2015年8月7日竞价成交占比达到最高的15.07%。上述期间,第一组账户多次实施盘中拉抬行为,以“时段股价涨幅2%以上且时段买成交占比20%以上”为筛选条件,第一组账户在上述期间的6个时段有盘中拉抬行为。经统计,任良成操纵“太化股份”亏损44,299,555.69元。(五)操纵“漳州发展”情况1.2015年7月20日至2015年9月17日操纵情况。2015年7月20日至2015年9月17日,任良成控制第一组账户,集中资金优势连续买卖“漳州发展”,操纵“漳州发展”交易价格和交易量。期间竞价买入成交36,640,599股,竞价买入成交金额230,367,672.35元;竞价卖出成交36,640,599股,竞价卖出成交金额228,299,206.98元。第一组账户期初无持股,期末将持有的“漳州发展”全部卖出。2015年7月20日至2015年9月17日期间,“漳州发展”共有17个交易日,第一组账户在16个交易日发生交易,其中13个交易日有买入交易,日均买入成交股数2,818,508股,日均买入成交金额17,720,590.18元,有6个交易日的竞价买入成交量市场排名第一。第一组账户在11个交易日有卖出交易,日均卖出成交股数3,330,964股,日均卖出成交金额20,754,473.36元,有6个交易日的竞价卖出成交量市场排名第一。第一组账户当日竞价成交占比超过10%的有2个交易日,其中2015年8月6日竞价成交占比达到最高的11.05%。上述期间,第一组账户多次实施盘中拉抬行为,以“时段股价涨幅2%以上且时段买成交占比20%以上”为筛选条件,第一组账户在12个时段有盘中拉抬行为。2.2015年10月15日至2015年10月19日操纵情况。2015年10月15日至2015年10月19日,任良成控制第一组账户,集中资金优势连续买卖“漳州发展”,操纵“漳州发展”交易价格和交易量。期间竞价买入成交9,702,184股,竞价买入成交金额56,255,892.58元;竞价卖出成交9,702,184股,竞价卖出成交金额59,295,270.04元。第一组账户期初无持股,期末将持有的“漳州发展”全部卖出。2015年10月15日至2015年10月19日期间,“漳州发展”共有3个交易日,第一组账户在3个交易日均发生交易,其中2个交易日有买入交易,日均买入成交股数4,851,092股,日均买入成交金额28,127,946.29元,且该2个交易日的竞价买入成交量均市场排名第一。第一组账户在2个交易日有卖出交易,日均卖出成交股数4,851,092股,日均卖出成交金额29,647,635.02元,且该2个交易日的竞价卖出成交量均市场排名第一。上述期间,第一组账户以不低于市场卖一价或市价合计申报买入7,688,800股,占同期第一组账户买入申报总量11,277,600股的68.18%。同时,以“时段股价涨幅2%以上且时段买成交占比20%以上”为筛选条件,第一组账户亦在2015年10月16日的1个时段存在盘中拉抬行为。经统计,任良成操纵“漳州发展”盈利509,059.91元。(六)操纵“国脉科技”情况1.2015年7月20日至2015年8月10日操纵情况。2015年7月20日至2015年8月10日,任良成控制第一组账户,集中资金优势连续买卖“国脉科技”,操纵“国脉科技”交易价格和交易量。期间竞价买入成交36,704,655股,竞价买入成交金额537,925,253.25元;竞价卖出成交36,704,655股,竞价卖出成交金额541,252,726.84元。第一组账户期初无持股,期末将持有的“国脉科技”全部卖出。2015年7月20日至2015年8月10日期间,“国脉科技”共有16个交易日,第一组账户在15个交易日发生交易,其中14个交易日有买入交易,日均买入成交股数2,621,761股,日均买入成交金额38,423,232.38元,有9个交易日的竞价买入成交量市场排名第一。第一组账户在11个交易日有卖出交易,日均卖出成交股数3,336,787股,日均卖出成交金额49,204,793.35元,有9个交易日的竞价卖出成交量市场排名第一。第一组账户2015年8月6日的竞价成交占比达到最高,为10.89%。上述期间,第一组账户多次实施盘中拉抬行为,以“时段股价涨幅2%以上且时段买成交占比20%以上”为筛选条件,第一组账户在12个时段有盘中拉抬行为。2.2015年8月28日至2015年9月7日操纵情况。2015年8月28日至2015年9月7日,任良成控制第一组账户,集中资金优势连续买卖“国脉科技”,操纵“国脉科技”交易价格和交易量。期间竞价买入成交15,980,255股,竞价买入成交金额180,184,639.62元;竞价卖出成交15,980,255股,竞价卖出成交金额164,740,328.02元。第一组账户期初无持股,期末将持有的“国脉科技”全部卖出。2015年8月28日至2015年9月7日期间,“国脉科技”共有5个交易日,第一组账户在5个交易日均发生交易,其中4个交易日有买入交易,日均买入成交股数3,995,064股,日均买入成交金额45,046,159.91元,且该4个交易日的竞价买入成交量均市场排名第一。第一组账户在3个交易日有卖出交易,日均卖出成交股数5,326,752股,日均卖出成交金额54,913,442.67元,且该3个交易日的竞价卖出成交量均市场排名第一。第一组账户当日竞价成交占比超过10%的有2个交易日,其中2015年9月2日竞价成交占比达到最高的12.79%。上述期间,第一组账户多次实施盘中拉抬行为,以“时段股价涨幅2%以上且时段买成交占比20%以上”为筛选条件,第一组账户在6个时段有盘中拉抬行为。经统计,任良成操纵“国脉科技”亏损13,194,820.53元。(七)操纵“广宇发展”情况1.2015年7月23日至2015年9月8日操纵情况。2015年7月23日至2015年9月8日,任良成控制第一组账户,集中资金优势连续买卖,操纵“广宇发展”交易价格和交易量。期间竞价买入成交88,150,569股,竞价买入成交金额822,359,615.35元;竞价卖出成交88,150,569股,竞价卖出成交金额818,809,542.32元。第一组账户期初无持股,期末将持有的“广宇发展”全部卖出。2015年7月23日至2015年9月8日期间,“广宇发展”共有32个交易日,第一组账户在30个交易日发生交易,其中28个交易日有买入交易,日均买入成交股数3,148,235股,日均买入成交金额29,369,986.26元,有21个交易日的竞价买入成交量市场排名第一。第一组账户在22个交易日有卖出交易,日均卖出成交股数4,006,844股,日均卖出成交金额37,218,615.56元,有15个交易日的竞价卖出成交量市场排名第一。第一组账户当日竞价成交占比超过10%的有9个交易日,其中2015年8月31日竞价成交占比达到最高的16.13%。上述期间,第一组账户多次实施盘中拉抬行为,以“时段股价涨幅2%以上且时段买成交占比20%以上”为筛选条件,第一组账户在30个时段有盘中拉抬行为。2.2015年9月25日至2015年11月13日操纵情况。2015年9月25日至2015年11月13日,任良成控制第一组账户,集中资金优势连续买卖,操纵“广宇发展”交易价格和交易量。期间竞价买入成交192,941,140股,竞价买入成交金额1,687,972,159.10元;竞价卖出成交192,941,140股,竞价卖出成交金额1,704,230,901.42元。第一组账户期初无持股,期末将持有的“广宇发展”全部卖出。2015年9月25日至2015年11月13日期间,“广宇发展”共有31个交易日,第一组账户在29个交易日发生交易,其中26个交易日有买入交易,日均买入成交股数7,420,813股,日均买入成交金额64,922,006.12元,有25个交易日的竞价买入成交量市场排名第一。第一组账户在25个交易日有卖出交易,日均卖出成交股数7,717,646股,日均卖出成交金额68,169,236.06元,有23个交易日的竞价卖出成交量市场排名第一。第一组账户当日竞价成交占比超过10%的有23个交易日,超过20%的有9个交易日,其中2015年10月12日竞价成交占比达到最高的26.31%。上述期间,第一组账户多次实施盘中拉抬行为,以“时段股价涨幅2%以上且时段买成交占比20%以上”为筛选条件,第一组账户在51个时段有盘中拉抬行为。3.2015年11月26日至2015年12月14日操纵情况。2015年11月26日至2015年12月14日,任良成控制第一组账户,集中资金优势连续买卖,操纵“广宇发展”交易价格和交易量。期间竞价买入成交31,516,524股,竞价买入成交金额307,032,500.42元;竞价卖出成交31,516,524股,竞价卖出成交金额311,515,487.56元。第一组账户期初无持股,期末将持有的“广宇发展”全部卖出。2015年11月26日至2015年12月14日期间,“广宇发展”共有13个交易日,第一组账户在13个交易日均发生交易,其中11个交易日有买入交易,日均买入成交股数2,865,139股,日均买入成交金额27,912,045.49元,有8个交易日的竞价买入成交量市场排名第一。第一组账户在10个交易日有卖出交易,日均卖出成交股数3,151,652股,日均卖出成交金额31,151,548.76元,有6个交易日的竞价卖出成交量市场排名第一。第一组账户当日竞价成交占比超过10%的有4个交易日,其中2015年12月7日竞价成交占比达到最高的17.66%。上述期间,第一组账户多次实施盘中拉抬行为,以“时段股价涨幅2%以上且时段买成交占比20%以上”为筛选条件,第一组账户在7个时段有盘中拉抬行为。经统计,任良成操纵“广宇发展”盈利13,078,936.83元。(八)操纵“曙光股份”情况2015年8月13日至2015年9月2日,任良成控制第一组账户,集中资金优势连续买卖“曙光股份”,操纵“曙光股份”交易价格和交易量。期间竞价买入成交26,796,599股,竞价买入成交金额207,451,588.34元;竞价卖出成交26,796,599股,竞价卖出成交金额208,041,670.81元。第一组账户期初无持股,期末将持有的“曙光股份”全部卖出。2015年8月13日至2015年9月2日期间,“曙光股份”共有15个交易日,第一组账户在13个交易日发生交易,其中12个交易日有买入交易,日均买入成交股数2,233,050股,日均买入成交金额17,287,632.36元,有6个交易日的竞价买入成交量市场排名第一。第一组账户在7个交易日有卖出交易,日均卖出成交股数3,828,086股,日均卖出成交金额29,720,238.69元,有5个交易日的竞价卖出成交量市场排名第一。第一组账户当日竞价成交占比超过10%的有2个交易日,其中2015年8月17日竞价成交占比达到最高的13.67%。上述期间,第一组账户多次实施盘中拉抬行为,以“时段股价涨幅2%以上且时段买成交占比20%以上”为筛选条件,第一组账户在16个时段有盘中拉抬行为。经统计,任良成操纵“曙光股份”盈利269,636.45元。(九)操纵“钱江生化”情况2015年8月13日至2015年9月8日,任良成控制第一组账户,集中资金优势连续买卖“钱江生化”,操纵“钱江生化”交易价格和交易量。期间竞价买入成交40,373,824股,竞价买入成交金额422,924,494.29元;竞价卖出成交40,373,824股,竞价卖出成交金额411,598,965.91元。第一组账户期初无持股,期末将持有的“钱江生化”全部卖出。2015年8月13日至2015年9月8日期间,“钱江生化”共有17个交易日,第一组账户在15个交易日发生交易,其中13个交易日有买入交易,日均买入成交股数3,105,679股,日均买入成交金额32,532,653.41元,有12个交易日的竞价买入成交量市场排名第一。第一组账户在12个交易日有卖出交易,日均卖出成交股数3,364,485股,日均卖出成交金额34,299,913.83元,有10个交易日的竞价卖出成交量市场排名第一。第一组账户当日竞价成交占比超过10%的有6个交易日,其中2015年8月17日竞价成交占比达到最高的18.10%。上述期间,第一组账户多次实施盘中拉抬行为,以“时段股价涨幅2%以上且时段买成交占比20%以上”为筛选条件,第一组账户在45个时段有盘中拉抬行为。经统计,任良成操纵“钱江生化”亏损11,954,832.52元。(十)操纵“广宇集团”情况2015年8月13日至2015年9月7日,任良成控制第一组账户,集中资金优势连续买卖“广宇集团”,操纵“广宇集团”交易价格和交易量。期间竞价买入成交80,917,223股,竞价买入成交金额616,724,401.69元;竞价卖出成交80,917,223股,竞价卖出成交金额594,960,835.56元。第一组账户期初无持股,期末将持有的“广宇集团”全部卖出。2015年8月13日至2015年9月7日期间,“广宇集团”共有16个交易日,第一组账户在15个交易日发生交易,其中14个交易日有买入交易,日均买入成交股数5,779,802股,日均买入成交金额44,051,742.98元,有12个交易日的竞价买入成交量市场排名第一。第一组账户在13个交易日有卖出交易,日均卖出成交股数6,224,402股,日均卖出成交金额45,766,218.12元,有11个交易日的竞价卖出成交量市场排名第一。第一组账户当日竞价成交占比超过10%的有5个交易日,其中2015年8月28日竞价成交占比达到最高的19.95%。上述期间,第一组账户多次实施盘中拉抬行为,以“时段股价涨幅2%以上且时段买成交占比20%以上”为筛选条件,第一组账户在20个时段有盘中拉抬行为。经统计,任良成操纵“广宇集团”亏损22,663,532.46元。(十一)操纵“全柴动力”情况1.2015年9月21日至2015年9月30日操纵情况。2015年9月21日至2015年9月30日,任良成控制第一组账户,集中资金优势连续买卖“全柴动力”,操纵“全柴动力”交易价格和交易量。期间竞价买入成交25,998,119股,竞价买入成交金额263,636,466.11元;竞价卖出成交25,998,119股,竞价卖出成交金额266,339,581.32元。第一组账户期初无持股,期末将持有的“全柴动力”全部卖出。2015年9月21日至2015年9月30日期间,“全柴动力”共有8个交易日,第一组账户在8个交易日均发生交易,其中7个交易日有买入交易,日均买入成交股数3,714,017股,日均买入成交金额37,662,352.30元,有5个交易日的竞价买入成交量市场排名第一。第一组账户在6个交易日有卖出交易,日均卖出成交股数4,333,020股,日均卖出成交金额44,389,930.22元,有5个交易日的竞价卖出成交量市场排名第一。第一组账户当日竞价成交占比超过10%的有4个交易日,其中2015年9月24日竞价成交占比达到最高的25.90%。上述期间,第一组账户多次实施盘中拉抬行为,以“时段股价涨幅2%以上且时段买成交占比20%以上”为筛选条件,第一组账户在11个时段有盘中拉抬行为。2.2015年11月25日至2015年12月17日操纵情况。2015年11月25日至2015年12月17日,任良成控制第一组账户,集中资金优势连续买卖“全柴动力”,操纵“全柴动力”交易价格和交易量。期间竞价买入成交20,699,918股,竞价买入成交金额275,624,328.98元;竞价卖出成交20,699,918股,竞价卖出成交金额277,234,466.04元。第一组账户期初无持股,期末将持有的“全柴动力”全部卖出。2015年11月25日至2015年12月17日期间,“全柴动力”共有17个交易日,第一组账户在16个交易日发生交易,其中14个交易日有买入交易,日均买入成交股数1,478,566股,日均买入成交金额19,687,452.07元,有11个交易日的竞价买入成交量市场排名第一。第一组账户在11个交易日有卖出交易,日均卖出成交股数1,881,811股,日均卖出成交金额25,203,133.28元,有8个交易日的竞价卖出成交量市场排名第一。第一组账户当日竞价成交占比超过10%的有6个交易日,其中2015年12月14日竞价成交占比达到最高的15.30%。上述期间,第一组账户多次实施盘中拉抬行为,以“时段股价涨幅2%以上且时段买成交占比20%以上”为筛选条件,第一组账户在13个时段有盘中拉抬行为。经统计,任良成操纵“全柴动力”盈利3,528,949.11元。(十二)操纵“天宝股份”情况2015年10月16日至2015年11月2日,任良成控制第一组账户,集中资金优势连续买卖“天宝股份”,操纵“天宝股份”交易价格和交易量。期间竞价买入成交30,630,419股,竞价买入成交金额310,771,661.72元;竞价卖出成交30,630,419股,竞价卖出成交金额313,930,402.71元。第一组账户期初无持股,期末将持有的“天宝股份”全部卖出。2015年10月16日至2015年11月2日期间,“天宝股份”共有12个交易日,第一组账户在12个交易日均发生交易,其中11个交易日有买入交易,日均买入成交股数2,784,584股,日均买入成交金额28,251,969.25元,有9个交易日的竞价买入成交量市场排名第一。第一组账户在9个交易日有卖出交易,日均卖出成交股数3,403,380股,日均卖出成交金额34,881,155.86元,有7个交易日的竞价卖出成交量市场排名第一。第一组账户当日竞价成交占比超过10%的有7个交易日,其中2015年10月22日竞价成交占比达到最高的21.04%。上述期间,第一组账户多次实施盘中拉抬行为,以“时段股价涨幅2%以上且时段买成交占比20%以上”为筛选条件,第一组账户在13个时段有盘中拉抬行为。经统计,任良成操纵“天宝股份”盈利2,703,506.01元。(十三)操纵“远兴能源”情况1.2016年8月19日至2016年11月7日操纵情况。2016年8月19日至2016年11月7日,任良成控制第二组账户,集中资金优势连续买卖“远兴能源”,操纵“远兴能源”交易价格和交易量。期间竞价买入成交747,499,250股,竞价买入成交金额2,356,660,991.19元,大宗交易买入成交397,993,971股,大宗交易买入成交金额1,225,137,610.36元;竞价卖出成交1,145,493,221股,竞价卖出成交金额3,621,167,079.03元。第二组账户期初无持股,期末将持有的“远兴能源”全部卖出。2016年8月19日至2016年11月7日期间,“远兴能源”共有50个交易日,第二组账户在46个交易日发生交易,其中38个交易日有买入交易(含大宗交易),日均买入成交股数30,144,558股,日均买入成交金额94,257,857.94元,有28个交易日的竞价买入成交量市场排名第一。第二组账户在40个交易日有卖出交易,日均卖出成交股数28,637,331股,日均卖出成交金额90,529,176.98元,有34个交易日的竞价卖出成交量市场排名第一。第二组账户当日竞价成交占比超过10%的有37个交易日,超过20%的有16个交易日,其中2016年8月23日竞价成交占比达到最高的30.64%。上述期间,第二组账户多次实施盘中拉抬行为,以“时段股价涨幅2%以上且时段买成交占比20%以上”为筛选条件,第二组账户在27个时段有盘中拉抬行为。2.2017年7月4日至2017年9月21日操纵情况。2017年7月4日至2017年9月21日,任良成控制第二组账户,集中资金优势连续买卖“远兴能源”,操纵“远兴能源”交易价格和交易量。期间竞价买入成交1,643,587,950股,竞价买入成交金额5,589,587,224.68元;竞价卖出成交1,643,587,950股,竞价卖出成交金额5,605,696,437.03元。第二组账户期初无持股,期末将持有的“远兴能源”全部卖出。2017年7月4日至2017年9月21日期间,“远兴能源”共有58个交易日,第二组账户在42个交易日发生交易,其中35个交易日有买入交易,日均买入成交股数46,959,656股,日均买入成交金额159,702,492.13元,有28个交易日的竞价买入成交量市场排名第一。第二组账户在32个交易日有卖出交易,日均卖出成交股数51,362,123股,日均卖出成交金额175,178,013.66元,有25个交易日的竞价卖出成交量市场排名第一。第二组账户当日竞价成交占比超过10%的有25个交易日,超过20%的有18个交易日,其中2017年9月18日竞价成交占比达到最高的40.78%。上述期间,第二组账户多次实施盘中拉抬行为,以“时段股价涨幅2%以上且时段买成交占比20%以上”为筛选条件,第二组账户在42个时段有盘中拉抬行为。经统计,任良成操纵“远兴能源”盈利42,451,175.18元。(十四)操纵“隆华节能”情况2017年5月17日至2017年9月25日,任良成控制第二组账户,集中资金优势连续买卖“隆华节能”,操纵“隆华节能”交易价格和交易量。期间竞价买入成交1,019,828,865股,竞价买入成交金额8,297,084,632.87元;竞价卖出成交1,019,828,865股,竞价卖出成交金额8,273,742,071.92元。第二组账户期初无持股,期末将持有的“隆华节能”全部卖出。2017年5月17日至2017年9月25日期间,“隆华节能”共有92个交易日,第二组账户在84个交易日发生交易,其中76个交易日有买入交易,日均买入成交股数13,418,801股,日均买入成交金额109,172,166.22元,有67个交易日的竞价买入成交量市场排名第一。第二组账户在75个交易日有卖出交易,日均卖出成交股数13,597,718股,日均卖出成交金额110,316,560.96元,有64个交易日的竞价卖出成交量市场排名第一。第二组账户当日竞价成交占比超过10%的有60个交易日,超过20%的有48个交易日,其中2017年8月3日竞价成交占比达到最高的42.43%。上述期间,第二组账户多次实施盘中拉抬行为,以“时段股价涨幅2%以上且时段买成交占比20%以上”为筛选条件,第二组账户在121个时段有盘中拉抬行为。经统计,任良成操纵“隆华节能”亏损34,373,920.86元。(十五)操纵“冠农股份”情况2017年6月9日至2017年7月18日,任良成控制第二组账户,集中资金优势连续买卖“冠农股份”,操纵“冠农股份”交易价格和交易量。期间竞价买入成交126,404,574股,竞价买入成交金额1,010,889,627.10元;竞价卖出成交126,404,574股,竞价卖出成交金额993,579,687.98元。第二组账户期初无持股,期末将持有的“冠农股份”全部卖出。2017年6月9日至2017年7月18日期间,“冠农股份”共有28个交易日,第二组账户在28个交易日均发生交易,其中27个交易日有买入交易,日均买入成交股数4,681,651股,日均买入成交金额37,440,356.56元,有25个交易日的竞价买入成交量市场排名第一。第二组账户在23个交易日有卖出交易,日均卖出成交股数5,495,851股,日均卖出成交金额43,199,116.87元,有21个交易日的竞价卖出成交量市场排名第一。第二组账户当日竞价成交占比超过10%的有23个交易日,超过20%的有15个交易日,其中2017年6月27日竞价成交占比达到最高的38.52%。上述期间,第二组账户多次实施盘中拉抬行为,以“时段股价涨幅2%以上且时段买成交占比20%以上”为筛选条件,第二组账户在24个时段有盘中拉抬行为。经统计,任良成操纵“冠农股份”亏损18,451,944.68元。(十六)操纵“维维股份”情况1.2017年6月6日至2017年6月16日操纵情况。2017年6月6日至2017年6月16日,任良成控制第二组账户,集中资金优势连续买卖“维维股份”,操纵“维维股份”交易价格和交易量。期间竞价买入成交146,312,943股,竞价买入成交金额817,027,133.07元;竞价卖出成交146,312,943股,竞价卖出成交金额819,701,856.07元。第二组账户期初无持股,期末将持有的“维维股份”全部卖出。2017年6月6日至2017年6月16日期间,“维维股份”共有9个交易日,第二组账户在9个交易日均发生交易,其中8个交易日有买入交易,日均买入成交股数18,289,118股,日均买入成交金额102,128,391.63元,且该8个交易日的竞价买入成交量均市场排名第一。第二组账户在8个交易日有卖出交易,日均卖出成交股数18,289,118股,日均卖出成交金额102,462,732.01元,且该8个交易日的竞价卖出成交量均市场排名第一。第二组账户当日竞价成交占比超过10%的有9个交易日,超过20%的有7个交易日,其中2017年6月13日竞价成交占比达到最高的40.45%。上述期间,第二组账户多次实施盘中拉抬行为,以“时段股价涨幅2%以上且时段买成交占比20%以上”为筛选条件,第二组账户在27个时段有盘中拉抬行为。2.2017年7月13日至2017年7月27日操纵情况。2017年7月13日至2017年7月27日,任良成控制第二组账户,集中资金优势连续买卖“维维股份”,操纵“维维股份”交易价格和交易量。期间竞价买入成交177,423,327股,竞价买入成交金额1,035,683,668.41元;竞价卖出成交177,423,327股,竞价卖出成交金额1,038,353,211.79元。第二组账户期初无持股,期末将持有的“维维股份”全部卖出。2017年7月13日至2017年7月27日期间,“维维股份”共有11个交易日,第二组账户在11个交易日均发生交易,其中10个交易日有买入交易,日均买入成交股数17,742,333股,日均买入成交金额103,568,366.84元,且该10个交易日的竞价买入成交量均市场排名第一。第二组账户在10个交易日有卖出交易,日均卖出成交股数17,742,333股,日均卖出成交金额103,835,321.18元,有9个交易日的竞价卖出成交量市场排名第一。第二组账户当日竞价成交占比超过10%的有10个交易日,超过20%的有8个交易日,其中2017年7月24日竞价成交占比达到最高的36.19%。上述期间,第二组账户多次实施盘中拉抬行为,以“时段股价涨幅2%以上且时段买成交占比20%以上”为筛选条件,第二组账户在20个时段有盘中拉抬行为。3.2017年10月11日至2017年10月24日操纵情况。2017年10月11日至2017年10月24日,任良成控制第二组账户,集中资金优势连续买卖“维维股份”,操纵“维维股份”交易价格和交易量。期间竞价买入成交87,286,528股,竞价买入成交金额481,164,583.03元,大宗交易买入成交33,440,000股,大宗交易买入成交金额158,194,585.00元;竞价卖出成交119,988,128股,竞价卖出成交金额646,293,982.37元。2017年10月11日至2017年10月24日期间,“维维股份”共有10个交易日,第二组账户在10个交易日均发生交易,其中8个交易日有买入交易(含大宗交易),日均买入成交股数15,090,816股,日均买入成交金额79,919,896.00元,有6个交易日的竞价买入成交量市场排名第一。第二组账户在8个交易日有卖出交易,日均卖出成交股数14,998,516股,日均卖出成交金额80,786,747.80元,有7个交易日的竞价卖出成交量市场排名第一。第二组账户当日竞价成交占比超过10%的有7个交易日,超过20%的有5个交易日,其中2017年10月16日竞价成交占比达到最高的29.11%。上述期间,第二组账户多次实施盘中拉抬行为,以“时段股价涨幅2%以上且时段买成交占比20%以上”为筛选条件,第二组账户在3个时段有盘中拉抬行为。经统计,任良成操纵“维维股份”盈利11,598,156.65元。综上,2015年4月13日至2017年10月24日期间,任良成控制涉案账户操纵“酒钢宏兴”等16只股票交易价格和交易量,其中操纵“酒钢宏兴”“漳州发展”“广宇发展”“曙光股份”“全柴动力”“天宝股份”“远兴能源”“维维股份”等8只股票合计盈利275,896,808.50元,操纵“贵人鸟”“美锦能源”“太化股份”“国脉科技”“钱江生化”“广宇集团”“隆华节能”“冠农股份”等8只股票合计亏损298,755,924.73元。上述违法事实,有相关资金账户资料、证券账户交易流水、银行账户资料、证券交易所提供数据、涉案人员提供的情况说明、询问笔录等证据证明,足以认定。我会认为,任良成的上述行为,违反了2005年《证券法》第七十七条第一款第一项的规定,构成2005年《证券法》第二百零三条所述操纵证券市场的行为。任良成及其代理人主要提出如下申辩意见,请求减轻行政处罚:其一,涉案行为不构成操纵证券市场。任良成对“酒钢宏兴”“贵人鸟”“美锦能源”“太化股份”“远兴能源”“维维股份”等6只股票的大宗交易系正常交易。任良成大宗交易买入“贵人鸟”“美锦能源”“太化股份”后,于次一交易日卖出时,因遇到他人猛烈“出货”,为顺利卖出,被迫买入部分股票以摊平成本,相关行为并非操纵证券市场。除大宗交易外,对“美锦能源”“太化股份”“远兴能源”“维维股份”等4只股票的其他二级市场交易,都属于主动建仓,交易时间较短,持股数量不多,流通股占比很低,不构成操纵证券市场行为。任良成在同一交易日内既买入又卖出同一股票,系利用此方式实现股票交易的“T+0”以赚取差价,而非为了操纵证券市场。本案中未发生大宗交易的10只股票,即“漳州发展”“国脉科技”“广宇发展”“曙光股份”“钱江生化”“广宇集团”“全柴动力”“天宝股份”“隆华节能”“冠农股份”,系任良成主动选股交易以赚取差价,属正常交易而非操纵证券市场。此外,证监会认定的个别数据可能有误,包括误将大宗交易买入股票数量计入竞价买入股票数量、使用错误的计算公式等。其二,本案违法所得认定错误。大宗交易“酒钢宏兴”“远兴能源”“维维股份”的获利,系源自于大宗交易折扣,不属于违法所得。同时,即使认定涉案行为构成操纵证券市场,因交易“酒钢宏兴”而向中间人支付的佣金、预留款等支出1亿余元,亦应从违法所得中扣除。其三,本案行政处罚过于严苛。任良成本人主观恶性低,采取的交易手法较为简单,未联合他方共同炒作股价。大部分股票是大宗交易,并未恶意“炒小、炒差、炒新”。交易个股时间短暂,未持续、长期、反复“炒作”一只股票,亦未利用股市“黑嘴”诱骗投资者跟风操作。任良成没有恶意逃避监管,主动配合证监会调查并说明情况。任良成自1991年开始投身证券市场,投资股票30余年,大宗交易股票近10年,每年交易2,000亿元至5,000亿元,年缴纳印花税和佣金2亿元以上。投资设立股票博物馆,为宣传股票文化作出重大贡献。目前,任良成因涉及操纵证券市场刑事犯罪,被一审法院判处刑罚,已受严惩,不宜再给予严厉的行政处罚。经复核,我会认为任良成及其代理人的申辩理由不能成立:其一,根据现有证据,足以认定任良成涉案行为构成操纵证券市场。任良成本人在接受我会调查时曾明确承认,其在卖出股票时,为能以高于成本价的价格顺利卖出,有时会指挥下属公司员工进行“护盘”操作,即以高于即时市场成交价申报买入。本案中,涉案账户交易“酒钢宏兴”等股票的手法,与任良成自述的操纵手法完全一致。任良成涉案交易系典型的操纵证券市场行为,而非其所谓的“正常交易”。此外,对任良成有关“个别数据可能有误”的疑问,经我会再次核实,相关交易数据准确无误。其二,本案违法所得金额认定准确。本案中,“酒钢宏兴”等6只股票的大宗交易获利和二级市场交易密切关联,即任良成之所以高于即时市场成交价申报买入,目的在于保障大宗交易买入股票的高价减持。换言之,涉案账户大宗交易的获利实际上源自任良成操纵证券市场行为,故应依法纳入违法所得。我会在认定本案违法所得时,已依法扣除买入股票成本和支付的印花税、交易佣金等与交易直接相关的税费。任良成所谓“应将大宗交易折扣获利、支付给中间人的佣金、预留款等金额从违法所得中扣除”的主张,既无法律依据,也无证据支持。即使任良成向大宗交易中间人支付了佣金、预付款,亦系任良成对违法所得的分配和流转,不影响违法所得的认定。其三,本案对任良成的量罚适当。任良成长期实施操纵证券市场行为,尤其是在被我会多次行政处罚后,仍继续实施操纵证券市场行为。任良成操纵股票数量众多,动用资金量巨大,操纵行为持续时间长,其所称“未联合上市公司实际控制人实施操纵”等情况虽然属实,但并不直接影响对其违法情节的认定。对任良成一定程度上配合我会调查以及任良成涉及刑事案件的情况,我会在量罚时已予以充分考虑,目前我会对任良成的量罚幅度适当。须说明的是,本案任良成操纵的16只股票中,除“酒钢宏兴”外,其余15只股票均不涉及现有刑事案件。对涉及刑事案件的“酒钢宏兴”,我会暂不予罚没处罚。若任良成交易“酒钢宏兴”行为最终被法院认定为构成操纵证券市场罪,我会将不再予以处理。根据前述复核意见,剔除涉及刑事案件中的“酒钢宏兴”后,任良成操纵“漳州发展”等7只股票合计盈利74,139,420.14元。根据当事人违法行为的事实、性质、情节与社会危害程度,依据2005年《证券法》第二百零三条的规定,我会决定:没收任良成违法所得74,139,420.14元,并处以222,418,260.42元的罚款。上述当事人应自收到本处罚决定书之日起15日内,将罚没款汇交中国证券监督管理委员会开户银行:中信银行北京分行营业部,账号:7111010189800000162,由该行直接上缴国库,并将注有当事人名称的付款凭证复印件送中国证券监督管理委员会行政处罚委员会办公室备案。当事人如果对本处罚决定不服,可在收到本处罚决定书之日起60日内向中国证券监督管理委员会申请行政复议,也可在收到本处罚决定书之日起6个月内直接向有管辖权的人民法院提起行政诉讼。复议和诉讼期间,上述决定不停止执行。中国证监会2023年5月19日 | D4: 45065
A5: 是 | B5: 否 | C5: 〔2022〕73号当事人:陈霄,男,1984年1月出生,住址:江苏省南京市江宁区。依据《中华人民共和国证券法》(以下简称《证券法》)的有关规定,我会对陈霄操纵牧高笛户外用品股份有限公司(以下简称牧高笛)等13只股票价格行为进行了立案调查、审理,并依法向当事人告知了作出行政处罚的事实、理由、依据及当事人依法享有的权利。应当事人陈霄的申请,我会于2022年10月11日举行了听证会,听取了当事人的陈述和申辩意见。本案现已调查、审理终结。经查明,当事人存在以下违法事实:一、陈霄控制利用证券账户以及交易决策情况2019年3月15日至2020年4月20日期间,陈霄实际控制“孙某”等142个证券账户交易“牧高笛”等13只股票。142个证券账户在交易涉案股票期间存在IP、MAC关联,并由陈霄自认、部分证券账户介绍人指认、部分证券账户与陈霄有签署协议。资金来源于账户配资资金及自有资金,交易由陈霄本人决策、由其负责的团队具体负责操作下单。二、陈霄操纵“牧高笛”等13只股票情况(一)“牧高笛”的交易情况1.账户情况2019年4月15日至4月25日,陈霄控制“顾某琴”等54个证券账户(以下简称“牧高笛”账户组)交易“牧高笛”。2.交易情况2019年4月15日至4月25日共9个交易日,“牧高笛”账户组均交易了“牧高笛”,累计买入3,173,439股,买入金额93,094,043.26元。其中7个交易日“牧高笛”账户组申买市场排名第一,8个交易日“牧高笛”账户组竞价买入成交市场排名第一。2019年4月15日至4月25日,“牧高笛”账户组累计卖出3,173,439股,卖出金额99,949,753.96元,获利6,172,768.69元。陈霄通过连续交易等方式操纵“牧高笛”,分为“建仓、拉抬、出货”三个阶段:建仓期为4月15日至4月19日,累计买入737,205股,买入金额20,354,037.3元,累计卖出90,500股,卖出金额2,514,038元。“牧高笛”账户组连续竞价阶段申买数量为822,000股,不低于卖一价申买数量538,400股,“牧高笛”账户组不低于卖一价申买数量占连续竞价账户申买数量占比65.69%,“牧高笛”账户组不低于卖一价申买对应成交数量537,200股,“牧高笛”账户组不低于卖一价申买对应成交数量占市场连续竞价总成交量比例13.74%。期间,“牧高笛”股价上涨3.87%。拉抬期为4月22日至4月24日,累计买入2,436,234股,买入金额72,740,005.96元,累计卖出374,305股,卖出金额11,015,408.3元。“牧高笛”账户组连续竞价阶段申买数量为2,413,500股,不低于卖一价申买数量1,921,300股,“牧高笛”账户组不低于卖一价申买数量占连续竞价账户申买数量占比79.21%,“牧高笛”账户组不低于卖一价申买对应成交数量1,903,734股,“牧高笛”账户组不低于卖一价申买对应成交数量占市场连续竞价总成交量比例33.96%。期间,“牧高笛”股价上涨14.03%。出货期为4月25日,期间无买入,累计卖出2,708,634股,卖出金额86,420,307.66元。期间,“牧高笛”股价上涨0.33%。(二)宁波圣龙汽车动力系统股份有限公司(以下简称圣龙股份)股票的交易情况1.账户情况2019年4月29日至5月13日,陈霄控制“顾某琴”等57个账户(以下简称“圣龙股份”账户组)交易“圣龙股份”。2.交易情况2019年4月29日至5月13日,“圣龙股份”账户组在8个交易日均交易了“圣龙股份”,累计买入9,463,553股,买入金额104,790,144.08元。其中6个交易日“圣龙股份”账户组申买市场排名第一,7个交易日“圣龙股份”账户组竞价买入成交市场排名第一。2019年4月29日至5月13日,“圣龙股份”账户组累计卖出9,463,553股,卖出金额112,455,620.85元,获利6,896,938.93元。陈霄通过连续交易等方式操纵“圣龙股份”,分为“建仓拉抬、出货”两个阶段:建仓拉抬期为4月29日至5月9日,累计买入9,108,453股,买入金额100,638,987.08元,累计卖出572,700股,卖出金额6,786,069元。“圣龙股份”账户组连续竞价阶段申买数量为9,459,400股,不低于卖一价申买数量6,913,800股,“圣龙股份”账户组不低于卖一价申买数量占连续竞价账户申买数量平均占比74.99%,“圣龙股份”账户组不低于卖一价申买对应成交数量6,899,253股,“圣龙股份”账户组不低于卖一价申买对应成交数量占市场连续竞价总成交量平均占比32.06%。期间,“圣龙股份”股价上涨13.22%。出货期为5月10日至5月13日,累计买入355,100股,买入金额4,151,157元,累计卖出8,890,853股,卖出金额105,669,551.85元。期间,“圣龙股份”股价下跌12.98%。(三)浙江仙通橡塑股份有限公司(以下简称浙江仙通)股票的交易情况1.账户情况2019年6月10日至6月13日,陈霄控制“王某”等28个账户(以下简称“浙江仙通”账户组)交易“浙江仙通”。2.交易情况2019年6月10日至6月13日,“浙江仙通”账户组在4个交易日均交易了“浙江仙通”,期初持股108,500股,期末无余股。累计买入3,307,400股,买入金额33,875,603.22元。其中1个交易日“浙江仙通”账户组申买市场排名第一,1个交易日“浙江仙通”账户组竞价买入成交市场排名第一。2019年6月10日至6月13日,“浙江仙通”账户组累计卖出3,415,900股,卖出金额36,066,430元,获利949,675.42元。陈霄通过连续交易等方式操纵“浙江仙通”,分为“建仓、拉抬、出货”三个阶段:建仓期为6月10日至6月11日,累计买入679,200股,买入金额6,543,270.78元,卖出108,500股,卖出金额1,006,380元。“浙江仙通”账户组连续竞价阶段申买数量为770,900股,不低于卖一价申买数量622,100股,“浙江仙通”账户组不低于卖一价申买数量占连续竞价账户申买数量占比76.43%,“浙江仙通”账户组不低于卖一价申买对应成交数量594,200股,“浙江仙通”账户组不低于卖一价申买对应成交数量占市场连续竞价总成交量比例4.82%。期间,“浙江仙通”股价上涨8.4%。拉抬期为6月12日,累计买入2,628,200股,买入金额27,332,332.44元,累计卖出433,400股,卖出金额4,523,416元。“浙江仙通”账户组连续竞价阶段申买数量为2,288,000股,不低于卖一价申买数量2,071,800股,“浙江仙通”账户组不低于卖一价申买数量占连续竞价账户申买数量占比90.55%,“浙江仙通”账户组不低于卖一价申买对应成交数量1,930,800股,“浙江仙通”账户组不低于卖一价申买对应成交数量占市场连续竞价总成交量比例24.19%。期间,“浙江仙通”股价上涨6.49%。出货期为6月13日,期间无买入,累计卖出2,874,000股,卖出金额30,536,634元。期间,“浙江仙通”股价下跌3.64%。(四)奇精机械股份有限公司(以下简称奇精机械)股票的交易情况1.账户情况2019年7月22日至7月31日,陈霄控制“顾某琴”等44个账户(以下简称“奇精机械”账户组)交易“奇精机械”。2.交易情况2019年7月22日至7月31日,“奇精机械”账户组在8个交易日均交易了“奇精机械”,期初持股800股,期末无余股。累计买入5,010,038股,买入金额65,161,119.08元。其中6个交易日“奇精机械”账户组申买市场排名第一,6个交易日“奇精机械”账户组竞价买入成交市场排名第一。2019年7月22日至7月31日,“奇精机械”账户组累计卖出5,010,838股,卖出金额67,410,885.84元,盈利1,771,996.41元。陈霄通过连续交易等方式操纵“奇精机械”,分为“建仓、拉抬、减仓、二次拉抬、出货”五个阶段:建仓期为7月22日至7月23日,累计买入311,600股,买入金额3,681,569.2元,卖出800股,卖出金额9,896元。期间,“奇精机械”账户组连续竞价阶段申买数量为278,300股,不低于卖一价申买数量135,900股,“奇精机械”账户组不低于卖一价申买数量占连续竞价账户申买数量占比37.42%,“奇精机械”账户组不低于卖一价申买对应成交数量135,900股,“奇精机械”账户组不低于卖一价申买对应成交数量占市场连续竞价总成交量占比5.94%。期间,“奇精机械”股价下跌5.44%。拉抬期为7月24日至7月26日,期间累计买入2,466,000股,买入金额31,048,290.06元,累计卖出325,400股,卖出金额4,122,156.2元。“奇精机械”账户组连续竞价阶段申买数量为2,616,000股,不低于卖一价申买数量2,211,500股,“奇精机械”账户组不低于卖一价申买数量占连续竞价账户申买数量平均占比83.58%,“奇精机械”账户组不低于卖一价申买对应成交数量2,140,500股,“奇精机械”账户组不低于卖一价申买对应成交数量占市场连续竞价总成交量平均比例25.81%。期间,“奇精机械”股价上涨13.29%。减仓期为7月29日,期间累计买入455,400股,买入金额6,118,540.08元,累计卖出1,495,200股,卖出金额20,194,953.46。期间,“奇精机械”股价上涨0.47%。二次拉抬期为7月30日,累计买入1,777,038股,买入金额24,312,719.74元,累计卖出773,600股,卖出金额10,678,893元。“奇精机械”账户组连续竞价阶段申买数量为1,863,300股,不低于卖一价申买数量1,637,400股,“奇精机械”账户组不低于卖一价申买数量占连续竞价账户申买数量占比87.88%,“奇精机械”账户组不低于卖一价申买对应成交数量1,565,900股,“奇精机械”账户组不低于卖一价申买对应成交数量占市场连续竞价总成交量比例27.01%。期间,“奇精机械”股价上涨4.64%。出货期为7月31日,期间无买入,累计卖出2,415,838股,卖出金额32,404,987.18元。期间,“奇精机械”股价下跌7.40%。(五)无锡宏盛换热器制造股份有限公司(以下简称宏盛股份)股票的交易情况1.账户情况2019年7月31日至8月9日,陈霄控制“顾某琴”等38个账户(以下简称“宏盛股份”账户组)交易“宏盛股份”。2.交易情况2019年7月31日至8月9日,“宏盛股份”账户组在8个交易日均交易了“宏盛股份”。累计买入3,305,759股,买入金额49,992,955.73元。其中4个交易日“宏盛股份”账户组申买市场排名第一,4个交易日“宏盛股份”账户组竞价买入成交市场排名第一。2019年7月31日至8月9日,“宏盛股份”账户组累计卖出3,305,759股,卖出金额52,801,643.35元,盈利2,445,446.29元。陈霄通过连续交易等方式操纵“宏盛股份”,分为“建仓、拉抬、减仓、二次拉抬、出货”五个阶段:建仓期为7月31日至8月5日,累计买入186,100股,买入金额2,830,144.8元,累计卖出22,000股,卖出金额338,775元。“宏盛股份”账户组连续竞价阶段申买数量为197,100股,不低于卖一价申买数量158,700股,“宏盛股份”账户组不低于卖一价申买数量占连续竞价账户申买数量平均占比94.11%,“宏盛股份”账户组不低于卖一价申买对应成交数量158,700股,“宏盛股份”账户组不低于卖一价申买对应成交数量占市场连续竞价总成交量平均占比3.68%。期间,“宏盛股份”股价上涨0.26%。拉抬期为8月6日,累计买入1,356,900股,买入金额20,238,695.19元,无卖出。“宏盛股份”账户组连续竞价阶段申买数量为1,422,100股,不低于卖一价申买数量1,109,700股,“宏盛股份”账户组不低于卖一价申买数量占连续竞价账户申买数量占比78.03%,“宏盛股份”账户组不低于卖一价申买对应成交数量1,107,300股,“宏盛股份”账户组不低于卖一价申买对应成交数量占市场连续竞价总成交量比例33.91%。期间,“宏盛股份”股价下跌0.12%。减仓期为8月7日,累计买入129,600股,买入金额1,924,840.34元,卖出201,600股,卖出金额2,996,352元。“宏盛股份”账户组连续竞价阶段申买数量为102,700股,不低于卖一价申买数量92,700股,“宏盛股份”账户组不低于卖一价申买数量占连续竞价账户申买数量占比90.26%,“宏盛股份”账户组不低于卖一价申买对应成交数量92,700股,“宏盛股份”账户组不低于卖一价申买对应成交数量占市场连续竞价总成交量比例5.11%。期间,“宏盛股份”股价下跌2.70%。二次拉抬期为8月8日,累计买入1,633,159股,买入金额24,999,275.4元,卖出735,826股,卖出金额11,336,157.63元。“宏盛股份”账户组连续竞价阶段申买数量为1,707,200股,不低于卖一价申买数量1,369,000股,“宏盛股份”账户组不低于卖一价申买数量占连续竞价账户申买数量占比80.19%,“宏盛股份”账户组不低于卖一价申买对应成交数量1,369,000股,“宏盛股份”账户组不低于卖一价申买对应成交数量占市场连续竞价总成交量比例31.91%。期间,“宏盛股份”股价上涨8.18%。出货期为8月9日,期间无买入,累计卖出2,346,333股,卖出金额38,130,358.72元。期间,“宏盛股份”股价下跌1.25%。(六)江苏天目湖旅游股份有限公司(以下简称天目湖)股票的交易情况1.账户情况2019年8月2日至8月19日,陈霄控制“顾某琴”等39个账户(以下简称“天目湖”账户组)交易“天目湖”。2.交易情况2019年8月2日至8月19日,“天目湖”账户组在12个交易日均交易了“天目湖”,累计买入2,509,505股,买入金额50,595,502.04元。其中5个交易日“天目湖”账户组申买市场排名第一,7个交易日“天目湖”账户组竞价买入成交市场排名第一。2019年8月2日至8月19日,“天目湖”账户组累计卖出2,509,505股,卖出金额52,464,311.11元,盈利1,505,104.18元。陈霄通过连续交易等方式操纵“天目湖”,分为“建仓、拉抬、震荡、二次拉抬、出货”五个阶段:建仓期为8月2日至8月8日,累计买入223,800股,买入金额4,451,914.55元,累计卖出23,100股,卖出金额437,148元。“天目湖”账户组连续竞价阶段申买数量为240,400股,不低于卖一价申买数量164,100股,“天目湖”账户组不低于卖一价申买数量占连续竞价账户申买数量平均占比71.37%,账户组不低于卖一价申买对应成交数量153,600股,“天目湖”账户组不低于卖一价申买对应成交数量占市场连续竞价总成交量平均占比7.68%。期间,“天目湖”股价下跌5.98%。拉抬期为8月9日至8月12日,累计买入586,630股,买入金额11,448,644.2元,累计卖出176,700股,卖出金额3,473,204.3元。“天目湖”账户组连续竞价阶段申买数量为615,700股,不低于卖一价申买数量442,300股,“天目湖”账户组不低于卖一价申买数量占连续竞价账户申买数量占比80.43%,“天目湖”账户组不低于卖一价申买对应成交数量434,030股,“天目湖”账户组不低于卖一价申买对应成交数量占市场连续竞价总成交量比例24.55%。期间,“天目湖”股价上涨5.34%。震荡期为8月13日至14日,累计买入907,705股,买入金额18,233,778.55元,累计卖出1,086,645股,卖出金额21,904,955.73元。“天目湖”账户组连续竞价阶段申买数量为1,075,200股,不低于卖一价申买数量707,300股,“天目湖”账户组不低于卖一价申买数量占连续竞价账户申买数量占比67.46%,“天目湖”账户组不低于卖一价申买对应成交数量665,425股,“天目湖”账户组不低于卖一价申买对应成交数量占市场连续竞价总成交量比例17.84%。期间,“天目湖”股价上涨1.48%。二次拉抬期为8月15日,累计买入768,270股,买入金额15,945,893.69元,累计卖出130,090股,卖出金额2,688,972.08元。“天目湖”账户组连续竞价阶段申买数量为812,600股,不低于卖一价申买数量602,900股,“天目湖”账户组不低于卖一价申买数量占连续竞价账户申买数量占比74.19%,“天目湖”账户组不低于卖一价申买对应成交数量601,145股,“天目湖”账户组不低于卖一价申买对应成交数量占市场连续竞价总成交量比例32.37%。期间,“天目湖”股价上涨5.40%。出货期为8月16日至8月19日,累计买入23,100股,买入金额515,271.05元,累计卖出1,092,970股,卖出金额23,960,031元。期间,“天目湖”股价上涨4.74%。(七)江苏如通石油机械股份有限公司(以下简称如通股份)股票的交易情况1.账户情况2019年8月23日至9月5日,陈霄控制“顾某琴”等42个账户(以下简称“如通股份”账户组)交易“如通股份”。2.交易情况2019年8月23日至9月5日,“如通股份”账户组在10个交易日均交易了“如通股份”。累计买入7,650,310股,买入金额91,802,389.49元。其中8个交易日“如通股份”账户组申买市场排名第一,8个交易日“如通股份”账户组竞价买入成交市场排名第一。2019年8月23日至9月5日,“如通股份”账户组累计卖出7,650,310股,卖出金额94,835,532.7元,盈利2,374,661.12元。陈霄通过连续交易等方式操纵“如通股份”,分为“建仓拉抬、减仓、二次拉抬、出货”四个阶段:建仓拉抬期为8月23日至8月27日,累计买入3,231,710股,买入金额37,805,299.73元,累计卖出794,400股,卖出金额9,264,126元。“如通股份”账户组连续竞价阶段申买数量为3,490,700股,不低于卖一价申买数量2,418,300股,“如通股份”账户组不低于卖一价申买数量占连续竞价账户申买数量平均占比68.44%,“如通股份”账户组不低于卖一价申买对应成交数量2,408,200股,“如通股份”账户组不低于卖一价申买对应成交数量占市场连续竞价总成交量平均占比26.63%。期间,“如通股份”股价上涨8.38%。减仓期为8月28日至8月30日,累计买入1,250,000股,买入金额14,868,942元,累计卖出1,682,300股,卖出金额19,997,369.14元。“如通股份”账户组连续竞价阶段申买数量为1,418,600股,不低于卖一价申买数量975,700股,“如通股份”账户组不低于卖一价申买数量占连续竞价账户申买数量平均占比65.29%,“如通股份”账户组不低于卖一价申买对应成交数量961,500股,“如通股份”账户组不低于卖一价申买对应成交数量占市场连续竞价总成交量平均占比15.71%。期间,“如通股份”股价下降2.07%。二次拉抬期为9月2日至9月3日,累计买入3,158,600股,买入金额38,997,649.76元,累计卖出1,276,400股,卖出金额15,579,043.5元。“如通股份”账户组连续竞价阶段申买数量为3,252,900股,不低于卖一价申买数量2,996,400股,“如通股份”账户组不低于卖一价申买数量占连续竞价账户申买数量平均占比92.10%,“如通股份”账户组不低于卖一价申买对应成交数量2,994,100股,“如通股份”账户组不低于卖一价申买对应成交数量占市场连续竞价总成交量平均占比49.02%。期间,“如通股份”股价上涨6.62%。出货期为9月4日至9月5日,累计买入10,000股,买入金额130,500元,累计卖出3,897,210股,卖出金额49,994,994.06元。期间,“如通股份”股价上涨0.99%。(八)成都豪能科技股份有限公司(以下简称豪能股份)股票的交易情况1.账户情况2019年9月12日至9月19日,陈霄控制“顾某琴”等44个账户(以下简称“豪能股份”账户组)交易“豪能股份”。2.交易情况2019年9月12日至9月19日,“豪能股份”账户组在5个交易日均交易了“豪能股份”,累计买入7,502,120股,买入金额78,476,786.59元。其中4个交易日“豪能股份”账户组申买市场排名第一,4个交易日“豪能股份”账户组竞价买入成交市场排名第一。2019年9月12日至9月19日,“豪能股份”账户组累计卖出7,502,120股,卖出金额83,476,238.48元,盈利4,426,877.55元。陈霄通过连续交易等方式操纵“豪能股份”,分为“建仓拉抬、出货”两个阶段:建仓拉抬期为9月12日至9月18日,累计买入7,502,120股,买入金额78,476,786.59元,累计卖出2,291,620股,卖出金额23,924,958.08元。“豪能股份”账户组连续竞价阶段申买数量为7,888,300股,不低于卖一价申买数量5,387,800股,“豪能股份”账户组不低于卖一价申买数量占连续竞价账户申买数量平均占比68.88%,“豪能股份”账户组不低于卖一价申买对应成交数量5,377,600股,“豪能股份”账户组不低于卖一价申买对应成交数量占市场连续竞价总成交量平均占比23.19%。期间,“豪能股份”股价上涨11.80%。出货期为9月19日,期间无买入,累计卖出5,210,500股,卖出金额59,551,280.4元。期间,“豪能股份”股价上涨3.83%。(九)浙江台华新材料股份有限公司(以下简称台华新材)股票的交易情况1.账户情况2019年9月20日至10月14日,陈霄控制“顾某琴”等47个账户(以下简称“台华新材”账户组)交易“台华新材”。2.交易情况2019年9月20日至10月14日,“台华新材”账户组在12个交易日均交易了“台华新材”。累计买入14,717,173股,买入金额110,356,792.93元。其中9个交易日“台华新材”账户组申买市场排名第一,10个交易日“台华新材”账户组竞价买入成交市场排名第一。2019年9月20日至10月14日,“台华新材”账户组累计卖出14,717,173股,卖出金额112,444,639.5元,盈利1,302,541.59元。陈霄通过连续交易等方式操纵“台华新材”,分为“建仓、拉抬、出货”三个阶段:建仓期为9月20日至9月30日,累计买入7,079,313股,买入金额51,153,027.13元,累计卖出4,752,113股,卖出金额34,490,152.65元。“台华新材”账户组连续竞价阶段申买数量为10,158,700股,不低于卖一价申买数量4,437,800股,“台华新材”账户组不低于卖一价申买数量占连续竞价账户申买数量平均占比46.56%,“台华新材”账户组不低于卖一价申买对应成交数量4,361,320股,“台华新材”账户组不低于卖一价申买对应成交数量占市场连续竞价总成交量平均占比11.90%。期间,“台华新材”股价上涨4.48%。拉抬期为10月8日至10月10日,累计买入7,369,560股,买入金额57,058,368.6元,累计卖出2,031,366股,卖出金额15,450,751.08元。“台华新材”账户组连续竞价阶段申买数量为7,738,200股,不低于卖一价申买数量5,236,100股,“台华新材”账户组不低于卖一价申买数量占连续竞价账户申买数量占比65.98%,“台华新材”账户组不低于卖一价申买对应成交数量5,178,500股,“台华新材”账户组不低于卖一价申买对应成交数量占市场连续竞价总成交量占比24.19%。期间,“台华新材”股价上涨11.22%。出货期为10月11日至10月14日,累计买入268,300股,买入金额2,145,397.2元,累计卖出7,933,694股,卖出金额62,503,735.77元。期间,“台华新材”股价下跌8.89%。(十)青海华鼎实业股份有限公司(以下简称青海华鼎)股票的交易情况1.账户情况2019年3月15日至3月21日,陈霄控制“顾某琴”等12个账户(以下简称“青海华鼎”账户组)交易“青海华鼎”。2.交易情况2019年3月15日至3月21日,“青海华鼎”账户组在5个交易日均交易了“青海华鼎”,累计买入2,989,400股,买入金额16,273,847.36元。其中3个交易日存在买入行为,2个交易日“青海华鼎”账户组申买市场排名第一,2个交易日“青海华鼎”账户组竞价买入成交市场排名第一。2019年3月15日至3月21日,“青海华鼎”账户组累计卖出2,989,400股,卖出金额16,407,820.72元,盈利18,866.9元。陈霄通过连续交易等方式操纵“青海华鼎”,分为“建仓、拉抬、出货”三个阶段:建仓期为3月15日至3月18日,累计买入606,100股,买入金额3,176,817元,无卖出。“青海华鼎”账户组连续竞价阶段申买数量为764,900股,不低于卖一价申买数量329,200股,“青海华鼎”账户组不低于卖一价申买数量占连续竞价账户申买数量平均占比32.33%,“青海华鼎”账户组不低于卖一价申买对应成交数量327,700股,“青海华鼎”账户组不低于卖一价申买对应成交数量占市场连续竞价总成交量平均占比5.54%。期间,“青海华鼎”股价上涨5.13%。拉抬期为3月19日,累计买入2,383,300股,买入金额13,097,030.36元,无卖出。“青海华鼎”账户组连续竞价阶段申买数量为1,434,100股,不低于卖一价申买数量1,029,800股,“青海华鼎”账户组不低于卖一价申买数量占连续竞价账户申买数量占比71.81%,“青海华鼎”账户组不低于卖一价申买对应成交数量1,029,800股,“青海华鼎”账户组不低于卖一价申买对应成交数量占市场连续竞价总成交量占比27.80%。期间,“青海华鼎”股价上涨6.94%。出货期为3月20日至3月21日,期间无买入,累计卖出2,989,400股,卖出金额16,407,820.72元。期间,“青海华鼎”股价下跌4.91%。(十一)江西长运股份有限公司(以下简称江西长运)股票的交易情况1.账户情况2019年11月25日至12月5日,陈霄控制“顾某琴”等31个账户(以下简称“江西长运”账户组)交易“江西长运”。2.交易情况2019年11月25日至12月5日,“江西长运”账户组在9个交易日均交易了“江西长运”,累计买入5,737,965股,买入金额34,677,231.24元。其中6个交易日“江西长运”账户组申买市场排名第一,5个交易日“江西长运”账户组竞价买入成交市场排名第一。2019年11月25日至12月5日,“江西长运”账户组累计卖出5,737,965股,卖出金额35,032,342.33元,盈利109,555.84元。陈霄通过连续交易等方式操纵“江西长运”,分为“建仓拉抬、出货”两个阶段:建仓拉抬期为11月25日至12月3日,累计买入5,221,365股,买入金额31,374,232.85元,累计卖出268,100股,卖出金额1,567,260.99元。“江西长运”账户组连续竞价阶段申买数量为4,924,300股,不低于卖一价申买数量3,835,600股,“江西长运”账户组不低于卖一价申买数量占连续竞价账户申买数量平均占比66.09%,“江西长运”账户组不低于卖一价申买对应成交数量3,795,875股,“江西长运”账户组不低于卖一价申买对应成交数量占市场连续竞价总成交量平均占比30.66%。期间,“江西长运”股价上涨14.77%。出货期为12月4日至12月5日,累计买入516,600股,买入金额3,302,998.39元,累计卖出5,469,865股,卖出金额33,465,081.34元。期间,“江西长运”股价下跌9.97%。(十二)沈阳商业城股份有限公司(以下简称商业城)股票的交易情况1.账户情况2020年3月5日至3月12日,陈霄控制“顾某琴”等24个账户(以下简称“商业城”账户组)交易“商业城”。2.交易情况2020年3月5日至3月12日,“商业城”账户组在6个交易日均交易了“商业城”,累计买入6,644,001股,买入金额35,433,056.08元。其中5个交易日“商业城”账户组申买市场排名第一,5个交易日“商业城”账户组竞价买入成交市场排名第一。2020年3月5日至3月12日,“商业城”账户组累计卖出6,644,001股,卖出金额37,448,011.18元,盈利1,757,406.26元。陈霄通过连续交易等方式操纵“商业城”,分为“建仓、拉抬、出货”三个阶段:建仓期为3月5日至3月9日,累计买入3,106,801股,买入金额15,604,003.16元,累计卖出487,100股,卖出金额2,469,829元。“商业城”账户组连续竞价阶段申买数量为3,955,000股,不低于卖一价申买数量2,484,100股,“商业城”账户组不低于卖一价申买数量占连续竞价账户申买数量平均占比64.04%,“商业城”账户组不低于卖一价申买对应成交数量2,456,900股,“商业城”账户组不低于卖一价申买对应成交数量占市场连续竞价总成交量平均占比11.52%。期间,“商业城”股价上涨11.39%。拉抬期为3月10日,累计买入2,850,700股,买入金额15,852,300.92元,累计卖出773,212股,卖出金额4,285,793.52元。“商业城”账户组连续竞价阶段申买数量为2,520,500股,不低于卖一价申买数量2,256,900股,“商业城”账户组不低于卖一价申买数量占连续竞价账户申买数量占比89.54%,“商业城”账户组不低于卖一价申买对应成交数量2,238,000股,“商业城”账户组不低于卖一价申买对应成交数量占市场连续竞价总成交量平均占比31.86%。期间,“商业城”股价上涨6.82%。出货期为3月11日至3月12日,累计买入686,500股,买入金额3,976,752元,累计卖出5,383,689股,卖出金额30,692,388.66元。期间,“商业城”股价下跌8.5%。(十三)贵州永吉印务股份有限公司(以下简称永吉股份)股票的交易情况1.账户情况在2020年4月14日至4月20日,陈霄控制“顾某琴”等24个账户(以下简称“永吉股份”账户组)交易“永吉股份”。2.交易情况2020年4月14日至4月20日,“永吉股份”账户组在5个交易日均交易了“永吉股份”。累计买入3,751,010股,买入金额26,928,234.4元。其中3个交易日“永吉股份”账户组申买市场排名第一,3个交易日“永吉股份”账户组竞价买入成交市场排名第一。2020年4月14日至4月20日,“永吉股份”账户组累计卖出3,751,010股,卖出金额28,227,184.13元,盈利1,104,153.17元。陈霄通过连续交易等方式操纵“永吉股份”,分为“建仓、拉抬、出货”三个阶段:建仓期为4月14日至4月15日,累计买入1,036,900股,买入金额7,131,619元,累计卖出263,100股,卖出金额1,843,407元。“永吉股份”账户组连续竞价阶段申买数量为1,150,600股,不低于卖一价申买数量739,900股,“永吉股份”账户组不低于卖一价申买数量占连续竞价账户申买数量平均占比65.51%,“永吉股份”账户组不低于卖一价申买对应成交数量739,900股,“永吉股份”账户组不低于卖一价申买对应成交数量占市场连续竞价总成交量平均占比16.93%。期间,“永吉股份”股价上涨4.39%。拉抬期为4月16日,累计买入2,449,410股,买入金额17,794,154.4元,累计卖出155,100股,卖出金额1,143,471元。“永吉股份”账户组连续竞价阶段申买数量为2,124,800股,不低于卖一价申买数量1,661,200股,“永吉股份”账户组不低于卖一价申买数量占连续竞价账户申买数量占比78.18%,“永吉股份”账户组不低于卖一价申买对应成交数量1,634,700股,“永吉股份”账户组不低于卖一价申买对应成交数量占市场连续竞价总成交量占比20.90%。期间,“永吉股份”股价上涨8.13%。出货期为4月17日至4月20日,累计买入264,700股,买入金额2,002,461元,累计卖出3,332,810股,卖出金额25,240,306.13元。“永吉股份”股价下跌4.81%。经测算,陈霄操纵上述13只股票期间共计获利30,835,992.35元。上述违法事实,有当事人的询问笔录、协议文件、相关证券账户的开户资料、委托成交流水、银行流水、交易所提供的账户组连续交易相关指标统计表等证据证明,足以认定。在听证会上,陈霄提出如下申辩意见:其一,陈霄认为自己实际控制的证券账户数量不足事先告知书认定的142个。其二,陈霄认为自己实际盈利不足事先告知书认定3000余万元,资金成本、团队人员支出和红包打赏等应在计算盈利时予以扣除。其三,陈霄认为自己积极配合调查工作,同时近两年因为各种原因经济情况不佳,压力较大,希望予以考虑。综上,陈霄请求减轻处罚。经复核,我会认为:其一,针对陈霄所称证券账户控制数量问题,本案的账户控制关系认定主要考虑了以下几个方面的因素:一是陈霄本人承认自己实际控制本案142个证券账户并交易过涉案股票;二是涉案的142个证券账户,都在陈霄电脑里有所记录;三是有其他人的指认,部分账户介绍人承认将证券账户出借给陈霄使用;四是部分账户所有人与陈霄签署有借用协议;五是涉案证券账户在交易涉案股票期间存在IP、MAC关联;六是陈霄使用的银行账户与大量涉案证券账户三方存管银行账户存在资金往来。综上,所认定的142个证券账户在交易涉案股票期间存在IP、MAC关联,并有陈霄自认、部分证券账户介绍人指认、部分证券账户与陈霄有签署协议等多方面证据证明,证据充分,足以认定相关账户实际由陈霄控制。其二,针对陈霄所称盈利金额计算问题,违法所得由证券交易所进行计算得出,陈霄所主张的资金成本、团队人员支出和红包打赏等不在应予扣减的范围,违法所得金额计算无误。第三,处罚金额系综合违法行为的事实、性质、情节及社会危害性等方面综合确定,审理过程中已经充分考虑了陈霄对于调查工作积极配合情况,已对陈霄的违法违规行为从轻处理。综上,我会对陈霄的陈述申辩意见不予采纳。我会认为,陈霄控制使用142个证券账户采用连续交易手法操纵“牧高笛”等13只股票,获利30,835,992.35元。上述行为涉嫌违反《证券法》第五十五条第一款第(一)项的规定,构成第一百九十二条所述“操纵证券市场”的行为。根据当事人违法行为的事实、性质、情节与社会危害程度,依据《证券法》第一百九十二条的规定,我会决定:对陈霄操纵证券市场的行为,没收违法所得30,835,992.35元,并处以30,835,992.35元的罚款。当事人应自收到本处罚决定书之日起15日内,将罚没款汇交中国证券监督管理委员会开户银行:中信银行北京分行营业部,账号:7111010189800000162,由该行直接上缴国库,并将注有当事人名称的付款凭证复印件送中国证券监督管理委员会行政处罚委员会办公室备案。当事人如果对本处罚决定不服,可在收到本处罚决定书之日起60日内向中国证券监督管理委员会申请行政复议,也可在收到本处罚决定书之日起6个月内直接向有管辖权的人民法院提起行政诉讼。复议和诉讼期间,上述决定不停止执行。中国证监会2022年12月28日 | D5: 44923
A6: 是 | B6: 否 | C6: 〔2020〕110号 当事人：福建旭诚资产管理有限公司（以下简称福建旭诚），住所：福建省福州市软件大道89号软件园F区3号楼24F。陈贇，男，1982年2月出生，时为福建旭诚持股40%股东，时任福建旭诚总经理、投资经理，住址：福建省福州市台江区。杜闽峰，男，1980年11月出生，时为福建旭诚法定代表人、持股55%股东，时任福建旭诚董事长，住址：福建省福州市鼓楼区。陈晗，男，1978年12月出生，时为福建旭诚持股5%股东，时任福建旭诚副总经理，住址：福建省福州市台江区。蔡兆艺，男，1991年1月出生，时任福建旭诚研究员、交易员。林通，男，1988年8月出生，时任福建旭诚研究员、交易员，住址：福建省厦门市集美区。依据2005年修订的《中华人民共和国证券法》（以下简称2005年《证券法》）的有关规定，我会对福建旭诚操纵“亚星客车”等十只股票行为进行了立案调查、审理，并依法向当事人告知了作出行政处罚的事实、理由、依据及当事人依法享有的权利。当事人福建旭诚申请听证但未提交陈述申辩意见，陈贇、杜闽峰、陈晗提交了陈述申辩意见并申请听证，应上述当事人的要求，我会于2020年11月5日举行了听证会。蔡兆艺、林通提交了书面陈述申辩意见但未要求听证。本案现已调查、审理终结。经查明，福建旭诚存在以下违法事实：一、控制账户情况根据证券公司提供的账户开户资料、情况说明及证券交易委托流水、资金流水，福建旭诚提供的《旭诚资产产品明细》、投资顾问合同、合作协议，在福建旭诚查获的陈贇、蔡兆艺、林通等人的电脑信息，福建旭诚相关人员的聊天记录，相关人员询问笔录等证据，可以认定在案涉期间，福建旭诚实际控制“长安国际信托股份有限公司-旭诚二期证券投资（长安投资283号）集合资金信托”“长城证券－旭诚五期证券投资基金”“长城证券－旭诚十期证券投资基金”“福建旭诚资产管理有限公司-旭诚兴达证券投资基金”“东方证券－旭诚十二期私募投资基金”“福建旭诚资产管理有限公司旭诚辉煌证券投资基金”“华泰证券－旭诚十一期私募证券投资基金”“东方证券－旭诚丰盛证券投资基金”“长城证券－旭诚十五期证券投资基金”“东方证券－旭诚七期私募投资基金”“中信证券－旭诚国贸一号资产管理计划”等11个产品证券账户及“兴业证券福州五一北路蔡某东”“长城证券武汉关山大道蔡某东”“东方证券福州鳌江路陈某仙”“东兴证券福州学军路陈某1”“长城证券武汉关山大道陈某琴”“东兴证券北京北四环中路陈某2”“长城证券武汉关山大道邓某康”“长城证券武汉关山大道方某清”“长城证券武汉关山大道何某英”“国金证券成都龙泉驿区龙都南路何某”“长城证券武汉关山大道何某”“恒泰证券总部黄某红”“上海证券福州五四路黄某红”“东兴证券福州江厝路林某1”“东兴证券福州江厝路林某2”“东兴证券福州学军路林某2”“东兴证券福州学军路林某3”“东兴证券福州学军路林某4”“长城证券武汉关山大道刘某明”“兴业证券福州五一北路刘某霞”“长城证券武汉关山大道刘某1”“长城证券武汉关山大道芦某兵”“东兴证券福州学军路施某云”“长城证券武汉关山大道苏某兮”“长城证券武汉关山大道谭某容”“长城证券武汉关山大道王某道”“长城证券武汉关山大道谢某颖”“长城证券武汉关山大道徐某”“东兴证券福州学军路许某英（资金账号0001****3080）”“东兴证券福州学军路许某英（资金账号0001****6090）”“长城证券武汉关山大道杨某健”“上海证券福州五四路叶某”“长城证券武汉关山大道叶某辉”“长城证券武汉关山大道尹某星”“国泰君安证券福州杨桥东路原某”“长城证券武汉关山大道占某泽”“长城证券武汉关山大道张某敏”“长江证券福州五一北路赵某颖”“长城证券武汉关山大道赵某仁”“长城证券武汉关山大道郑某琳”“东兴证券北京北四环中路周某官”“长城证券武汉关山大道周某娟”“长城证券武汉关山大道陈某3”“长城证券上海延安西路陈某3”“长城证券武汉关山大道魏某红”“长城证券武汉关山大道吴某”“长城证券武汉关山大道刘某2”“长城证券武汉关山大道方某坚”“长城证券武汉关山大道陈某影”“长城证券武汉关山大道曾某容”“东兴证券福州学军路刘某莲”“东兴证券福州江厝路刘某莲”“东兴证券福州学军路陈某丹”“东兴证券福州学军路林某清”“东兴证券福州江厝路邱某强”“东兴证券福州江厝路林某超”“东兴证券福州学军路林某超”“东兴证券福州江厝路林某5”“上海证券福州五四路陈某豪”“上海证券福州五四路郑某俤”“华福证券仙游鲤城街吴某青”“长城证券武汉关山大道苏某坡”“长城证券武汉关山大道陈某4”等63个个人证券账户（以下简称账户组）。二、福建旭诚操纵“博信股份”等十只股票情况（一）“博信股份”的交易情况 1.2016年5月18日至5月19日“博信股份”的交易情况2016年5月18日13:19:03账户组开始交易至5月19日，福建旭诚控制使用的账户组期初持有0股，期间买入成交1,144,914股，成交金额22,754,002.89元，卖出成交758,514股，成交金额15,757,342.8元，期末余386,400股，扣除相关交易税费后获利996,026.45元。在2个交易日中，账户组买入成交量占当日市场成交量的比例（以下简称买入成交占比）均超过10%，且均排名第1，其中在2016年5月18日买入成交占比最高，为24.32%，当日持股占流通股比为0.33%；账户组2016年5月19日集中卖出，卖出成交量占当日市场成交量比例（以下简称卖出成交占比）为20.97%。在2个交易日中，账户组共申报买入104笔，多次申买价格高于卖方价格或申买价格高于卖方价格且申买量高于卖方申卖量，如：占其总申买股数78.85%的委托的申买价格高于或同于其申报前1刻卖委托第1档价格。占其总申买股数36.54%的委托的申买价格高于或同于其申报前1刻卖委托第5档价格。占其总申买股数18.27%的委托申买价格高于或同于其申报前1刻卖委托第1档价格，且委托申买量高于或同于其申报前1刻市场前5档卖出申报总量。占其总申买股数11.54%的委托申买价格高于或同于其申报前1刻卖委托第5档价格，且委托申买量高于或同于其申报前1刻市场前5档卖出申报总量。 2016年5月18日，“博信股份”股价涨幅-0.10%，上证综指涨幅-1.27%，行业指数当日涨幅-2.41%，涨跌幅较行业指数偏离2.05%。2016年5月18日开盘至13:19:03，股价涨幅-6.52%，13:19:03至收盘，期间股价涨幅6.42%。 2.2016年5月30日至6月1日“博信股份”的交易情况该期间共计3个交易日，福建旭诚控制使用的账户组期初持有986,382股，期间买入成交869,454股，成交金额17,940,261.22元，卖出成交1,855,836股，成交金额38,907,625元，期末无余股，扣除相关交易税费后获利554,795.68元。在3个交易日中，2016年5月30日账户组集中买入，买入成交占比31.28%，买入成交量排名第1，当日持股占流通股比为0.8%；2016年5月31日账户组有买有卖，买入成交32,200股，卖出1,823,636股。2016年6月1日账户组清仓卖出余股。 在3个交易日中，账户组共申报买入92笔，多次申买价格高于卖方价格或申买价格高于卖方价格且申买量高于卖方申卖量，如：占其总申买股数71.74%的委托的申买价格高于或同于其申报前1刻卖委托第1档价格。占其总申买股数20.65%的委托的申买价格高于或同于其申报前1刻卖委托第5档价格。占其总申买股数15.22%的委托申买价格高于或同于其申报前1刻卖委托第1档价格，且委托申买量高于或同于其申报前1刻市场前5档卖出申报总量。占其总申买股数4.35%的委托申买价格高于或同于其申报前1刻卖委托第5档价格，且委托申买量高于或同于其申报前1刻市场前5档卖出申报总量。 2016年5月30日，“博信股份”股价涨幅1.21%，上证综指涨幅0.05%，行业指数当日涨幅-0.38%，涨跌幅较行业指数偏离1.59%。3.2016年6月14日至6月28日“博信股份”的交易情况该期间共计11个交易日，福建旭诚控制使用的账户组期初持有0股，期间买入成交7,274,773股，成交金额148,611,543.29元，全部卖出，卖出金额146,865,852元，亏损1,975,773.12元，没有违法所得。 （1）连续买卖在11个交易日中，账户组在10个交易日有交易，账户组买入成交占比超过10%的有4个交易日，超过20%的有3个交易日，其中在2016年6月21日买入成交占比达到最高，为37.25%，有7个交易日买入排名第1；账户组卖出成交占比超过10%的有2个交易日，超过20%的有1个交易日，其中在2016年6月23日卖出成交占比达到最高，为59.62%，卖出排名第1的有2个交易日。账户组持股占流通股比最高达到2.68%（6月22日）。在11个交易日中，账户组共申报买入582笔，多次申买价格高于卖方价格或申买价格高于卖方价格且申买量高于卖方申卖量，如：占其总申买股数55.50%的委托的申买价格高于或同于其申报前1刻卖委托第1档价格。占其总申买股数29.73%的委托的申买价格高于或同于其申报前1刻卖委托第5档价格。占其总申买股数16.15%的委托申买价格高于或同于其申报前1刻卖委托第1档价格，且委托申买量高于或同于其申报前1刻市场前5档卖出申报总量。占其总申买股数11.68%的委托申买价格高于或同于其申报前1刻卖委托第5档价格，且委托申买量高于或同于其申报前1刻市场前5档卖出申报总量。 （2）虚假申报2016年6月22日11:02:35，账户组以第4档的价位申报6笔共30,200股，在档位上升至第1或第2档时，全部撤单。11:03:02账户组以第6档的价位申报3笔共22,300股，在档位上升至第2档时，全部撤单。11:06:04以第6档的价位申报3笔共16,900股，在档位上升至第2档时，全部撤单。 2016年6月14日至6月28日，“博信股份”股价涨幅9.14%，上证综指涨幅2.81%，行业指数涨幅6.93%，涨幅较行业指数偏离2.21%。 （二）“亚星客车”的交易情况 2016年5月12日至5月25日,该期间共计10个交易日，福建旭诚控制使用的账户组期初持有0股，期间买入成交8,795,916股，成交金额98,665,500.69元，卖出成交8,743,816股，成交金额102,161,576.73元，期末余52,100股，扣除相关交易税费后获利3,930,481.34元。 1.连续买卖在10个交易日中，帐户组在7个交易日有交易，账户组买入成交占比超过10%的有3个交易日，超过20%的有2个交易日，其中在2016年5月20日买入成交占比达到最高，为31.6%，有5个交易日买入排名第1；账户组卖出成交占比超过10%的有3个交易日，超过20%的有1个交易日，其中在2016年5月23日卖出成交占比达到最高，为40.48%，卖出排名第1的有4个交易日。账户组持股占流通股比最高达到2.71%（5月20日）。在7个交易日中，账户组共申报买入782笔，多次申买价格高于卖方价格或申买价格高于卖方价格且申买量高于卖方申卖量，如：占其总申买股数35.68%的委托的申买价格高于或同于其申报前1刻卖委托第1档价格。占其总申买股数9.37%的委托的申买价格高于或同于其申报前1刻卖委托第5档价格。占其总申买股数9.08%的委托申买价格高于或同于其申报前1刻卖委托第1档价格，且委托申买量高于或同于其申报前1刻市场前5档卖出申报总量。占其总申买股数2.05%的委托申买价格高于或同于其申报前1刻卖委托第5档价格，且委托申买量高于或同于其申报前1刻市场前5档卖出申报总量。 2.虚假申报2016年5月20日，当日申买17,074,000股，占市场申买量54.48%，撤买11,957,266股，撤买量占申买量比例达70.03%。其中10:14:11账户组以第6档的价位申报6笔共300,000股，其中两笔部分成交后，将剩余仍在第2档买单撤单，4笔在档位上升至第2档时，全部撤单；随后10:14:23以第5档的价位申报5笔共62,500股，在档位上升至第2档时，全部撤单；11:08:21以第1档的价格申报4笔2,194,600股，部分成交后，立即将仍在第1档位申买撤单。2016年5月23日，账户组频繁双向连续交易29个来回，一面以低价申买“垫单”，制造买盘汹涌假象，待申卖成交后撤单。当日账户组申买7,642,200股，占市场申买量30.25%，撤买6,396,422股，撤买量占申买量比例达83.70%。其中10:33:11-10:33:33在低档位申报3笔上升至高档位部分成交后撤单，13:23:08-13:23:24在第1档位22笔全部撤单，13:24:56-13:25:09在低档位申报3笔上升至高档位部分成交后撤单。2016年5月24日，当日账户组申买664,500股，撤买612,400股，撤买量占申买量比例达92.16%。其中9:46:30-9:46:55在低档位申报4笔上升至高档位后全部撤单，9:55:22-9:56:53在低档位申报5笔上升至高档位后全部撤单。账户组存在多次申买价格临近成交价格即撤单的情形。 2016年5月12日至5月25日，“亚星客车”股价涨幅5.61%，上证综指涨幅-0.77%，行业指数涨幅0.8%，涨幅较行业指数偏离4.81%。（三）“龙建股份”的交易情况2016年5月16日至5月17日,该期间共计2个交易日，福建旭诚控制使用的账户组期初持有4,343,287股，期间买入成交3,470,420股，成交金额18,174,802.94元，卖出成交4,824,016股，成交金额25,243,959.86元，期末余2,989,691股，扣除相关交易税费后获利643,715.23元。 1.连续买卖在2个交易日中，2016年5月16日账户组连续交易拉抬股价持续至尾市，买入成交占比26.23%，买入成交量排名第1；5月17日以频繁虚假申买制造买盘汹涌假象掩护卖出，占市场卖出量31.95%，卖出排名第1。账户组持股占流通股比最高达到1.46%（5月16日）。在2个交易日中，账户组共申报买入87笔，多次申买价格高于卖方价格或申买价格高于卖方价格且申买量高于卖方申卖量，如：占其总申买股数50.57%的委托的申买价格高于或同于其申报前1刻卖委托第1档价格。占其总申买股数3.45%的委托的申买价格高于或同于其申报前1刻卖委托第5档价格。占其总申买股数8.05%的委托申买价格高于或同于其申报前1刻卖委托第1档价格，且委托申买量高于或同于其申报前1刻市场前5档卖出申报总量。 2.虚假申报2016年5月17日，账户组在申报卖出的同时，反向申报买入，并对申报买入全部撤单。当日申买7,431,000股，占市场申买量26.27%，撤买7,431,000股，撤买量占申买量比例达100%。9:51:04至10:08:33以5.25元至5.30元申卖400,000股，全部成交。10:09:34至10:09:40以5.24元（买2价）、5.25元（买2价）申买380,500股，占10:09:40买前5申报总量的78.62%，没有成交。10:09:48至10:09:57以5.26元申卖100,000股，全部成交。10:10:06至10:10:17以5.23元（买4价）、5.26元（买1价）申买510,000股，占10:10:17买前5申报总量的54.28%，没有成交。10:10:23至10:29:25以5.20至5.27元价格申卖1,674,500股，部分成交。10:14:37，账户组将前述申买全部撤单。10:29:48以5.20元（买1价）申买3,000,000股，占当时买1总量的99.31%，10:32:39在第1档位全部撤单。13:06:49至13:53:42以5.23元大量申卖，部分成交，期间13:41:02至13:54:33以5.22元（买1价）申买3,540,500股，占13:54:33买1总量98.95%，14:02:32在第1档位全部撤单。13:54:58至14:53:55以5.18元至5.25元价格申卖1,497,800股，成交1,353,596股。 2016年5月16日，“龙建股份”股价涨幅6.56%，上证综指涨幅0.84%，行业指数当日涨幅0.86%，涨幅较行业指数偏离5.70%。（四）“赛福天”的交易情况 2016年6月23日至6月28日,期间共计4个交易日，福建旭诚控制使用的账户组期初持有0股，期间买入成交4,012,196股，成交金额120,752,242.84元，全部卖出，成交金额122,169,485.14元，扣除相关交易税费后获利1,234,576.71元。 1.连续买卖在4个交易日中，2016年6月23日买入成交占比3.97%，成交量排名第1；6月24日买入成交占比8.38%，成交量排名第1，卖出成交占比4.01%、卖出成交量排名第1；6月27日买入成交占比2.37%，买入成交量排名第1，卖出成交占比10.57%，卖出成交量排名第1；6月28日卖出成交占比3.16%，卖出成交量排名第1。账户组持股占流通股比最高达到4.27%（6月24日）。在4个交易日中，账户组共申报买入307笔，多次申买价格高于卖方价格或申买价格高于卖方价格且申买量高于卖方申卖量，如：占其总申买股数28.34%的委托的申买价格高于或同于其申报前1刻卖委托第1档价格。占其总申买股数13.68%的委托的申买价格高于或同于其申报前1刻卖委托第5档价格。占其总申买股数16.61%的委托申买价格高于或同于其申报前1刻卖委托第1档价格，且委托申买量高于或同于其申报前1刻市场前5档卖出申报总量。占其总申买股数10.42%的委托申买价格高于或同于其申报前1刻卖委托第5档价格，且委托申买量高于或同于其申报前1刻市场前5档卖出申报总量。 2.虚假申报2016年6月23日13:08:55,账户组在申报前一刻市场买前5总量为559,025股，且无卖单的情况下，以第1档30.46元的价位申报24笔共2,348,200股，部分成交后，立即将仍在第1档位的2,320,739股买单撤单，撤买量占申买量比例达98.83%。 2016年6月23日至6月28日，“赛福天”股价涨幅10.47%，上证综指涨幅0.24%，行业指数涨幅2.04%，涨幅较行业指数偏离8.43%。（五）“杭电股份”的交易情况2016年2月24日至3月1日,期间共计5个交易日，福建旭诚控制使用的账户组期初持有0股，期间买入成交2,834,616股，成交金额76,498,697.97元，全部卖出，成交金额79,687,767元，扣除相关交易税费后获利3,065,606.27元。在5个交易日中，账户组买入成交占比超过10%的有3个交易日，其中在2016年2月24日买入成交占比达到最高，为16.18%，前4个交易日买入成交均排名第1；账户组有2个交易日存在卖出，最后一个交易日集中卖出，成交占比为22.06%，卖出成交排名第1。账户组持股占流通股比最高达到3.21%（2月29日）。在5个交易日中，账户组共申报买入350笔，多次申买价格高于卖方价格或申买价格高于卖方价格且申买量高于卖方申卖量，如：占其总申买股数53.14%的委托的申买价格高于或同于其申报前1刻卖委托第1档价格。占其总申买股数14.29%的委托的申买价格高于或同于其申报前1刻卖委托第5档价格。占其总申买股数17.14%的委托申买价格高于或同于其申报前1刻卖委托第1档价格，且委托申买量高于或同于其申报前1刻市场前5档卖出申报总量。占其总申买股数5.71%的委托申买价格高于或同于其申报前1刻卖委托第5档价格，且委托申买量高于或同于其申报前1刻市场前5档卖出申报总量。 2016年2月24日至3月1日，“杭电股份”股价涨幅12.92%，上证综指涨幅-5.86%，行业指数涨幅-11.57%，涨跌幅较行业指数偏离24.49%。（六）“正虹科技”的交易情况2016年5月26日至5月31日，期间共计4个交易日，福建旭诚控制使用的账户组期初持有0股，期间买入成交“正虹科技”3,077,164股，成交金额37,376,397.13元，全部卖出，成交金额38,890,711.95元，扣除相关交易税费后获利1,458,518.09元。在4个交易日中，账户组买入成交占比超过10%的有2个交易日，超过20%的有1个交易日，其中在2016年5月26日买入成交占比达到最高，为20.62%，前2个交易日买入均排名第1；账户组卖出成交占比超过20%的有1个交易日，在2016年5月30日卖出成交占比为33.99%，卖出排名第1。账户组持股占流通股比最高达到1.04%（5月27日）。在4个交易日中，账户组共申报买入342笔，多次申买价格高于卖方价格或申买价格高于卖方价格且申买量高于卖方申卖量，如：占其总申买股数30.41%的委托的申买价格高于或同于其申报前1刻卖委托第1档价格。占其总申买股数3.22%的委托的申买价格高于或同于其申报前1刻卖委托第5档价格。占其总申买股数9.06%的委托申买价格高于或同于其申报前1刻卖委托第1档价格，且委托申买量高于或同于其申报前1刻市场前5档卖出申报总量。占其总申买股数2.34%的委托申买价格高于或同于其申报前1刻卖委托第5档价格，且委托申买量高于或同于其申报前1刻市场前5档卖出申报总量。 2016年5月26日至5月31日，“正虹科技”股价涨幅11.89%，中小板综指涨幅4.01%，行业指数涨幅3.83%，涨幅较行业指数偏离8.06%。（七）“山东威达”的交易情况2016年9月5日至9月12日，期间共计6个交易日，福建旭诚控制使用的账户组期初持有1,124,000股，期间买入成交4,636,697股，成交金额55,619,002.86元，卖出5,760,697股，成交金额69,743,930.93元，期末无余股，扣除相关交易税费后获利1,128,624.89元。 1.连续买卖在6个交易日中，账户组买入成交占比超过10%的有2个交易日，超过20%的有1个交易日，其中在2016年9月6日买入成交占比达到最高，为42.16%，有2个交易日买入排名第1；账户组卖出成交占比超过20%的有1个交易日，在2016年6月23日卖出成交占比为44.41%，卖出排名第1的有2个交易日。账户组持股占流通股比最高达到1.45%（9月6日）。在6个交易日中，账户组共申报买入180笔，多次申买价格高于卖方价格或申买价格高于卖方价格且申买量高于卖方申卖量，如：占其总申买股数52.78%的委托的申买价格高于或同于其申报前1刻卖委托第1档价格。占其总申买股数27.22%的委托的申买价格高于或同于其申报前1刻卖委托第5档价格。占其总申买股数7.78%的委托申买价格高于或同于其申报前1刻卖委托第1档价格，且委托申买量高于或同于其申报前1刻市场前5档卖出申报总量。占其总申买股数6.11%的委托申买价格高于或同于其申报前1刻卖委托第5档价格，且委托申买量高于或同于其申报前1刻市场前5档卖出申报总量。 2.虚假申报2016年9月7日，账户组当日申买6,091,400股，占市场申买量30.39%，撤买5,723,600股，撤买量占申买量比例达93.96%。其中，9:48:49至9:49:11以12.11元（买5价）至12.14元（买2价）申买370,000股，后期在档位持平或上升的情况下大部分撤单，撤单比达91.89%。9:49:23至9:50:44账户组以12.05元（买9价）至12.09元（买6价）申买150,000股，部分成交后，将挡位上升买单全部撤单。10:12:21以12.14元（买3价）申买50,000股，后期在档位上升至第1档时全部撤单。10:12:30以12.15元（买1价）申买60,000股，10:26:37全部撤单；10:26:49再次以12.15元（买2价）申买30,000股，10:30:01在上升到第1档位全部撤单。2016年9月5日至9月12日，“山东威达”股价涨幅1.57%，中小板综指涨幅-1.48%，行业指数涨幅-1.11%，涨跌幅较行业指数偏离2.68%。（八）“棒杰股份”的交易情况1.2016年1月20日至1月27日“棒杰股份”的交易情况该期间共计6个交易日，福建旭诚控制使用账户组期初持有4,016,879股，买入5,013,786股，成交金额182,263,235.62元，卖出9,030,165股，成交金额341,046,848元，期末余500股，扣除相关交易税费后获利29,467,541.45元。在6个交易日中，账户组买入成交占比超过10%的有3个交易日，超过20%的有3个交易日，其中在2016年1月25日买入成交占比达到最高，为42.34%，有4个交易日买入排名第1；账户组卖出成交占比超过20%的有1个交易日，在2016年1月27日卖出成交占比达到最高，为44.04%，卖出排名第1。账户组持股占流通股比最高达到12.62%（1月26日）。在6个交易日中，账户组共申报买入541笔，多次申买价格高于卖方价格或申买价格高于卖方价格且申买量高于卖方申卖量，如：占其总申买股数58.23%的委托的申买价格高于或同于其申报前1刻卖委托第1档价格。占其总申买股数14.6%的委托的申买价格高于或同于其申报前1刻卖委托第5档价格。占其总申买股数13.12%的委托申买价格高于或同于其申报前1刻卖委托第1档价格，且委托申买量高于或同于其申报前1刻市场前5档卖出申报总量。占其总申买股数4.99%的委托申买价格高于或同于其申报前1刻卖委托第5档价格，且委托申买量高于或同于其申报前1刻市场前5档卖出申报总量。 2016年1月19日至1月26日，“棒杰股份”期间股价涨幅17.83%，中小板综指涨幅-9.62%，行业指数涨幅-9.34%，涨跌幅较行业指数偏离27.17%。2.2016年7月13日至7月18日“棒杰股份”的交易情况该期间共计4个交易日，福建旭诚控制使用的账户组期初持有0股，期间买入成交5,956,654股，成交金额65,082,556.01元，全部卖出，成交金额65,653,050.46元，扣除相关交易税费后获利478,134.72元。在4个交易日中，账户组买入成交占比有2个交易日买入排名第1；账户组卖出成交占比超过10%的有1个交易日，在2016年7月15日卖出成交占比为17.58%，卖出排名第1。账户组持股占流通股比最高达到1.26%（7月13日）。在4个交易日中，账户组共申报买入137笔，多次申买价格高于卖方价格或申买价格高于卖方价格且申买量高于卖方申卖量，如：占其总申买股数45.99%的委托的申买价格高于或同于其申报前1刻卖委托第1档价格。占其总申买股数22.63%的委托的申买价格高于或同于其申报前1刻卖委托第5档价格。占其总申买股数15.33%的委托申买价格高于或同于其申报前1刻卖委托第1档价格，且委托申买量高于或同于其申报前1刻市场前5档卖出申报总量。占其总申买股数10.22%的委托申买价格高于或同于其申报前1刻卖委托第5档价格，且委托申买量高于或同于其申报前1刻市场前5档卖出申报总量。 2016年7月13日至7月18日，“棒杰股份”股价涨幅4.16%，中小板综指涨幅0.27%，行业指数涨幅0.01%，涨幅较行业指数偏离4.15%。（九）“博实股份”的交易情况 2016年1月27日至1月28日，期间共计2个交易日，福建旭诚控制使用的账户组期初持有0股，买入893,704股，成交金额16,909,228.01元，全部卖出，成交金额17,162,520.81元，扣除相关交易税费后获利227,203.96元。2016年1月27日，账户组成交893,704股，占市场成交量的14.23%，买入排名1，当日持股占流通股比0.17%。2016年1月28日，申卖成交893,704股，占市场成交量20.36%，卖出排名第1，无余股。在2个交易日中，账户组共申报买入33笔，多次申买价格高于卖方价格或申买价格高于卖方价格且申买量高于卖方申卖量，如：占其总申买股数84.85%的委托的申买价格高于或同于其申报前1刻卖委托第1档价格。占其总申买股数33.33%的委托的申买价格高于或同于其申报前1刻卖委托第5档价格。占其总申买股数69.70%的委托申买价格高于或同于其申报前1刻卖委托第1档价格，且委托申买量高于或同于其申报前1刻市场前5档卖出申报总量。占其总申买股数33.33%的委托申买价格高于或同于其申报前1刻卖委托第5档价格，且委托申买量高于或同于其申报前1刻市场前5档卖出申报总量。2016年1月27日，“博实股份”股价当日涨幅3.87%，中小板综指涨幅-1.05%，行业指数当日涨幅-0.89%，涨跌幅较行业指数偏离4.76%。（十）“金利华电”的交易情况2016年2月16日至2月17日,期间共计2个交易日，福建旭诚控制使用的账户组期初持有0股，期间买入成交6,823,492股，成交金额185,349,183.42元，全部卖出，成交金额195,140,427.15元，扣除相关交易税费后获利9,498,872.18元。2016年2月16日，“金利华电”公告发行股份及支付现金购买资产并募集资金暨关联交易预案并于当日开市起复牌，开盘即跌停并持续至帐户组开始交易。2016年2月16日，账户组申买成交6,823,492股，占市场成交量28.07%，排名第1。账户组持股占流通股比为8.10%。2016年2月17日，申卖12,547,048股，占市场申卖量35.88%，成交6,823,492股，占市场成交量36.44%，卖出排名第1，无余股。在2个交易日中，账户组共申报买入93笔，多次申买价格高于卖方价格或申买价格高于卖方价格且申买量高于卖方申卖量，如：占其总申买股数81.72%的委托的申买价格高于或同于其申报前1刻卖委托第1档价格。占其总申买股数30.11%的委托的申买价格高于或同于其申报前1刻卖委托第5档价格。占其总申买股数13.98%的委托申买价格高于或同于其申报前1刻卖委托第1档价格，且委托申买量高于或同于其申报前1刻市场前5档卖出申报总量。占其总申买股数11.83%的委托申买价格高于或同于其申报前1刻卖委托第5档价格，且委托申买量高于或同于其申报前1刻市场前5档卖出申报总量。2016年2月16日，“金利华电”股价当日涨幅6.20%，创业板综指涨幅4.49%，行业指数当日涨幅4.07%，涨幅较行业指数偏离2.13%。上述违法事实，有相关人员电脑信息，相关人员聊天截屏，福建旭诚加盖公章的《旭诚资产产品明细》、投资顾问合同、合作协议，证券账户开户资料、资金流水、委托成交记录，银行账户资金流水，相关人员询问笔录，交易所提供的交易数据等证据证明，足以认定。我会认为，福建旭诚的上述行为违反了2005年《证券法》第七十七条第一款第一项、第四项的规定，构成2005年《证券法》第二百零三条所述的操纵证券市场行为。对福建旭诚的违法行为，陈贇为福建旭诚持股40%股东，任福建旭诚总经理、投资经理，负责交易决策并亲自操作部分账户，为直接负责的主管人员；杜闽峰系福建旭诚法定代表人、持股55%股东、董事长，负责介绍证券账户供福建旭诚使用，为直接负责的主管人员；陈晗为福建旭诚持股5%股东、副总经理，负责联系维护证券账户，为直接负责的主管人员；蔡兆艺、林通为福建旭诚交易员，根据陈贇指令下单操作，陈贇指令包括“尾盘拉上去”“垫单要大一些”“底下撤单”等，故为其他直接责任人员。福建旭诚代理人在听证过程中提出，福建旭诚自成立没有大额收入，对于《行政处罚及市场禁入事先告知书》认定的违法所得金额不认可。请求免于或减轻处罚。陈贇代理人在听证过程中宣读了陈贇的书面陈述意见。陈贇在陈述意见中承认福建旭诚利用实际控制的基金帐户及个人帐户在2016年操纵了十只股票，其对《行政处罚及市场禁入事先告知书》认定的操纵事实没有任何意见，尊重服从证监会的处罚决定。杜闽峰代理人在听证过程中提出：一是对涉案操纵事项未参与、不知悉。其时任福建旭诚董事长期间，工作职责为公司外围人脉维护、大客户的开发，未参与具体投资账户管理及其他投资。公司实际控制人为总经理，投资相关工作由总经理负责，其对于操纵股票的内容和事实完全不知晓。二是对于违法所得不认可。福建旭诚从未有过大额收入，因此对《行政处罚及市场禁入事先告知书》中没收福建旭诚的违法所得不能理解。三是对《行政处罚及市场禁入事先告知书》给予其警告并处以30万元罚款，难以认同和接受。请求免于或减轻处罚。陈晗在听证过程中提出：一是对涉案操纵事项未参与、不知悉。其时任福建旭诚副总经理期间，工作职责是公司相关内勤管理和渠道拓展，主要工作内容属于接待和拜访，未参与投资部分，投资相关工作由总经理负责，其对于操纵股票的内容和事实完全不知晓。二是对于违法所得不认可。福建旭诚从未有过大额收入，因此对《行政处罚及市场禁入事先告知书》中没收福建旭诚的违法所得不能理解。三是对《行政处罚及市场禁入事先告知书》给予其警告并处以20万元罚款，难以认同和接受。请求免于或减轻处罚。蔡兆艺在其申辩材料中提出，其知错认错改错并认罚，其担任福建旭诚交易员期间，不存在自主决策交易权，只执行公司上级领导的交易指令，不存在操纵股价的意愿，请求减轻处罚。林通在其申辩材料中提出，其认错认罚，其作为交易员服从公司董事会集体决策后发出的指令进行操作，请求减轻或免于处罚。经复核，我会认为：一是对于福建旭诚的申辩意见，我会认定的违法所得并非公司的收入，而是涉案账户违法行为产生的获利，符合我会一贯认定。福建旭诚操纵行为成立，不存在《中华人民共和国行政处罚法》（以下简称《行政处罚法》）第二十七条规定的应予从轻或减轻的情形，故对福建旭诚的意见不予采纳。二是对于杜闽峰的申辩意见，其系福建旭诚大股东、法定代表人、董事长，对公司具有管理职责。此外，其负责介绍证券账户供福建旭诚使用，且为涉案基金产品寻找投资资金。我会认定其为直接负责的主管人员并无不当，其不存在《行政处罚法》第二十七条规定的应予从轻或减轻的情形，故对杜闽峰的意见不予采纳。三是对于陈晗的申辩意见，其为福建旭诚股东、副总经理，对公司具有管理职责。此外，其负责联系维护证券账户。我会认定其为直接负责的主管人员并无不当，其不存在《行政处罚法》第二十七条规定的应予从轻或减轻的情形，故对陈晗的意见不予采纳。四是对于蔡兆艺、林通的申辩意见，该二人虽系执行陈贇交易指令下单，但陈贇“尾盘拉上去”“垫单要大一些”“底下撤单”等指令带有操纵意图，在此情况下，其二人依旧执行了陈贇的交易指令，故我会认定其二人为其他直接责任人员。但念其主观恶性较低，考虑其二人在违法行为中的作用等情况，我会对其二人的罚款金额进行了调减。根据当事人违法行为的事实、性质、情节与社会危害程度，依据2005年《证券法》第二百零三条的规定，我会决定：一、没收福建旭诚资产管理有限公司违法所得52,684,096.98元，并处以158,052,290.94元罚款；二、对陈贇给予警告，并处以60万元罚款；三、对杜闽峰给予警告，并处以30万元罚款；四、对陈晗给予警告，并处以20万元罚款；五、对蔡兆艺、林通分别给予警告，并分别处以5万元罚款。上述当事人应自收到本处罚决定书之日起15日内，将罚没款汇交中国证券监督管理委员会（财政汇缴专户）开户银行：中信银行北京分行营业部，账号：7111010189800000162，由该行直接上缴国库，并将注有当事人名称的付款凭证复印件送中国证券监督管理委员会行政处罚委员会备案。当事人如果对本处罚决定不服，可在收到本处罚决定书之日起60日内向中国证券监督管理委员会申请行政复议，也可在收到本处罚决定书之日起6个月内直接向有管辖权的人民法院提起行政诉讼。复议和诉讼期间，上述决定不停止执行。 中国证监会 2020年12月28日 | D6: 44193
A7: 是 | B7: 是 | C7: 〔2019〕149号 当事人：林军，男，1967年8月出生，广西明利创新实业股份有限公司（以下简称明利股份）实际控制人，广西明利集团有限公司（以下简称明利集团）董事长，住址：广西壮族自治区南宁市江南区壮锦大道。何忠华，男，1975年9月出生，时任明利股份董事，明利集团副总裁，住址：广西壮族自治区南宁市江南区。陈志强，男，1981年5月出生，时任明利股份监事，住址：广西壮族自治区南宁市。依据《中华人民共和国证券法》（以下简称《证券法》）的有关规定，我会对林军等操纵明利股份的行为进行了立案调查、审理，并依法向当事人告知了作出行政处罚的事实、理由、依据及当事人依法享有的权利。应当事人林军、何忠华、陈志强的要求，我会于2019年3月25日举行了听证会，听取了林军、何忠华、陈志强及其代理人的陈述和申辩。本案现已调查、审理终结。经查明，林军、何忠华、陈志强存在以下违法事实：一、林军、何忠华、陈志强控制使用32个证券账户（以下简称账户组）情况（一）账户组的控制情况涉案账户组包括：一是法人明利集团、广西天勋物流服务有限公司（以下简称天勋物流）、广西防城港恒鑫化工有限公司（以下简称恒鑫化工）、广西桂东磷业投资有限公司（以下简称桂东磷业）、钦州市申达通实业有限公司（以下简称申达通）、广西工创信息咨询有限公司（以下简称工创信息）、南宁市强顺农资有限公司（以下简称强顺农资）7个账户（上述账户以下简称法人证券账户）；二是自然人卢某坚、李某明（2015年7月31日前控制）、陈某喜（2015年6月19日前控制）等21个账户（上述账户以下简称自然人证券账户）；三是资管计划华茂资本华通1号证券投资基金、西域稳健新三板2号证券投资基金、中科沃土优选1号资产管理计划、国海明利股份1号集合资产管理计划4个账户（上述账户以下简称资管计划证券账户）。林军、何忠华、陈志强控制使用上述证券账户组：第一，“明利集团”等7个法人证券账户对应的7家涉案公司实际由林军、何忠华等人先后设立并实际控制、管理，相应的证券账户及密码根据林军或何忠华的指示、安排开立后交由陈志强使用。第二，卢某坚等账户名义持有人承认将其证券账户及密码经林军交由陈志强使用。第三，4个资管计划证券账户系由林军指使成立，限定以明利股份为单一的投资方向并全额建仓，且由林军提供补仓资金。第四，林军承认控制部分证券账户，陈志强承认受林军指使，控制全部证券账户。第五，账户组下单所使用的电脑、交易地址相互重合，且与调查组现场查获的操纵下单电脑相重合。第六，林军指使公司员工控制账户组资金流转的银行账户。（二）账户组资金来源情况账户组交易“明利股份”的资金往来与林军存在密切关联，其中法人证券账户的资金流转由林军指使何忠华安排明利集团工作人员进行操作，自然人证券账户资金来源为林军的自有资金、借款和配资三种情况，资管计划证券账户均是由林军提供建仓全额资金、补仓资金。（三）账户组决策交易情况林军指使何忠华、陈志强及公司员工操作法人证券账户与自然人证券账户交易“明利股份”，陈志强等人通过各自的办公电脑进行交易。林军通过追加劣后资金的方式保证资管计划证券账户持续买入“明利股份”股票。二、通过多种手段操纵“明利股份”股价和交易量林军组织、指使何忠华、陈志强控制账户组，集中资金优势、持股优势，采用多种手段操纵“明利股份”。“明利股份”第一笔交易出现在2015年4月24日，至2016年12月23日停牌，共有255个交易日。（一）集中资金优势和持股优势连续买卖操纵“明利股份”股价和交易量账户组通过参与两次股票定向增发加强持股优势。明利集团持有明利股份原始股票4,950万股。明利股份于2015年3月23日第一次定向增发股票7,500万股，其中恒鑫化工认购3,500万股，桂东磷业认购3,307.5万股。明利股份于2015年5月24日第二次定向增发股票24,000万股，其中明利集团认购1亿股，恒鑫化工认购2,144万股，桂东磷业认购2,500万股，工创信息认购1,800万股，天勋物流认购1,760万股，强顺农资认购1,720万股。账户组集中资金优势和持股优势连续交易操纵“明利股份”股价和交易量。在2015年4月24日至2016年12月23日，账户组每个交易日均交易“明利股份”，交易股票数量为114,291.40万股，成交金额56.67亿元，同期“明利股份”总成交量为146,621.50万股,成交金额70.39亿元，账户组交易“明利股份”成交量在市场总成交量中占比为77.9%、账户组成交金额在市场总成交金额中占比为80.5%。上述期间，账户组当日成交量占当日市场总成交量达80%以上的有146个交易日，占全部交易日的57.25%；最高占比为100%的有20个交易日，占全部交易日的7.84%；其中在2015年5月19日至2016年1月27日的142个交易日内，账户组成交量占当日市场总成交量的比例均在30%以上。同时，在账户组操纵期间，账户组当日成交金额占当日市场总成交金额达80%以上的亦有146个交易日，占全部交易日的57.25%；最高占比为100%的有20个交易日，占全部交易日的7.84%；其中在2015年5月19日至2016年6月8日的230个交易日内，账户组成交金额占当日市场总成交金额的比例均在20%以上。账户组持续大量交易“明利股份”，导致市场成交均价受账户组交易“明利股份”成交价格的影响巨大。在操纵期间，当日账户组交易“明利股份”成交均价与市场成交均价无偏差的达59个交易日，占全部交易日的23.14%；当日账户组成交均价与市场成交均价偏差在0.2%以下的达211个交易日，占全部交易日的82.75%；偏差在0.5%以下的达226个交易日，占全部交易日的88.63%。（二）通过在自己控制的账户之间进行交易操纵“明利股份”股价和交易量协议转让期间（2015年4月24日至2015年6月18日，共39个交易日），账户组有36个交易日在自己实际控制的账户之间交易，账户组内成交金额为12,669.08万元，占“明利股份”总成交金额35,208.949万元的35.98%。账户组每日成交金额占“明利股份”当日成交金额中，有3个交易日达到最高占比100%;有22个交易日占比在20%以上的，占协议转让交易日的56.41%；有16个交易日占比在50%以上的，占协议转让交易日的41.03%。做市转让期间（2015年6月19日至2016年12月26日，共216个交易日），林军控制的账户组虽通过做市商进行交易，但实际上达到了将股票在其控制的不同账户间进行交易、做大成交量的目的，虚假交易意图明显。1.持股变化比例低。做市转让期间账户组持股变动数量（前复权）为4,592.95万股，同期账户组股票成交数量（前复权）为107,111.85万股，账户组所持股票发生变动的比例仅为4.29%。2.账户组频繁进行买卖方向相反、数量相同或大致相同、时间连续、价格相近的申报。第一，账户组买卖数量大致相同。一是按账户组进行匹配，账户组当日买入与卖出数量偏差小于10%的有113个交易日，占做市转让交易日的52.31%；买卖数量偏差小于5%的有74个交易日，占做市转让交易日的34.26%；买卖数量偏差小于2%的有37个交易日，占做市转让交易日的17.13%。二是按单个账户进行匹配，单个账户之间当日买入与卖出数量偏差在5%以下的有147个交易日，占做市转让交易日的68.06%；买卖数量偏差在2%以下的有113个交易日，占做市转让交易日的52.31%；买卖数量完全一致的有24个交易日，共28次，其中同一主体的账户买卖数量一致的情况出现20次。第二，账户组申报成交时间相近。一是从相邻两笔成交平均间隔时间来看，在60秒以内的有127个交易日，占做市转让交易日的58.8%；二是从相邻两笔成交间隔时间的中位数来看，在60秒以内的有194个交易日，占做市转让交易日的89.81%，其中在1秒以内的有76个交易日，最短间隔时间的中位数是0秒，有32个交易日；三是从每个交易日里间隔小于1分钟的相邻两笔成交“配对”数在当日所有相邻两笔成交“配对”数中的占比来看，占比达50%以上的有194个交易日，占做市转让交易日的89.81%，其中占比达80%以上的有47个交易日。第三，账户组申报买卖价格趋同。在做市转让交易期间，每个交易日的买入申报均价与卖出申报均价之差占当日卖出申报均价的绝对值在1%以内的有202个交易日，占做市转让交易日的93.52%；在0.1%以内的有93个交易日，占做市转让交易日的43.06%；当日买入申报均价不低于卖出申报均价的有150个交易日，占做市转让交易日的69.44%。 最为典型的交易期间有：2015年8月5日9:30:29至14:59:36期间，账户组累计买入股票85.3万股，买入成交均价为3.95元，累计卖出股票85.3万股，卖出成交均价为3.94元，成交总笔数为267笔，每笔成交平均间隔时间为53.90秒；2015年9月18日9:30:00至14:58:00期间，账户组累计买入股票299.9万股，买入成交均价为4.67元，累计卖出股票300万股，卖出成交均价为4.67元，成交总笔数为366笔，每笔成交平均间隔时间为39.13秒；2015年12月11日9:30:22至14:59:20期间，账户组累计买入股票808.4万股，买入成交均价为5.59元，累计卖出股票807.5万股，卖出成交均价为5.59元，成交总笔数为428笔，每笔成交平均间隔时间为33.58秒。3.账户组大部分交易直接以做市商报价申报成交。在做市交易期间，账户组以做市商报价申报成交笔数共57,788笔，占总成交笔数61,054笔的比例为94.65%；账户组以做市商报价申报成交数量为99,676.4万股，占总成交数量108,133万股的比例为92.18%。林军控制账户组直接以做市商报价申报，实际上是利用做市商连续双边报价、并在该价位上接受投资者的买卖要求的交易制度特点，在自己控制的账户之间进行频繁交易，制造“明利股份”交易活跃的假象，实现操纵“明利股份”股价和交易量的目的。综上，2015年4月24日至2016年12月24日期间，林军、何忠华、陈志强通过采用集中资金优势、持股优势连续交易、在自己实际控制的证券账户之间交易的方式，影响了“明利股份”股票交易量，造成“明利股份”交易活跃的假象，成交量、成交额在全国中小企业股份转让系统（以下简称新三板）中均排名全国第四，吸引大量投资者、做市商踊跃跟进购买“明利股份”股票，维持了股票价格，以实现减持股票获利的目的。账户组净减持股数7,329.05万股，剔除账户组买入股票金额及净减持股票成本，账户组共获利29,342.48万元。以上事实有相关人员询问笔录、证券账户资料、交易流水、银行账户资料、电脑交易地址、相关公告、相关材料及交易数据、股转公司计算数据等证据证明，足以认定。林军以减持股票获利为目的，组织、指使何忠华、陈志强控制账户组，通过采用集中资金优势、持股优势连续交易，在自己实际控制的证券账户之间交易的方式操纵“明利股份”，影响了股票股价和交易量，违反了《证券法》第七十七条第一款第一项、第三项的规定，构成《证券法》第二百零三条所述的操纵证券市场的违法行为。林军作为明利股份的实际控制人，是上述违法行为的组织者、决策者和主要实施者；何忠华、陈志强具体负责控制账户组的相关交易，是上述违法行为的主要执行者。林军系主要责任人员，何忠华、陈志强系其他直接责任人员。林军、何忠华、陈志强及其代理人提出如下陈述、申辩意见：第一，违法所得的认定存在事实不清、计算错误的问题。一是将成本认定为零没有事实依据，任何证券交易均有客观的买卖成本，即使是拆借资金认购定增股，明利股份与认购人之间仍然存在法律上的债权债务关系，这种债权债务关系就是认购定增股的成本，二是未考虑余股属于事实认定错误，事先告知书认定定向增发是操纵的手段之一，理应将通过定增持有的股份认定为操纵的手段和工具，在计算获利时予以合并计算，而本案采用净减持股获利法与以往案例的计算方式不一致。第二，本案责任认定与事实不符，量罚不当。一是林军没有操纵证券市场的主观故意；二是新三板市场的特殊性决定本案社会危害性较轻；三是何忠华、陈志强没有操纵市场谋利的动机和意图，没有因操纵市场行为获取不当利益；四是本案量罚幅度过重。综上，请求从轻、减轻或免除处罚。经复核，我会认为：第一，本案操纵行为的特殊性在于林军等人通过在一级市场认购定增股票进行建仓，故应将其定增行为与操纵行为予以整体考量。当事人辩称本案将成本认定为零与我会事先告知认定不符。经查，我会根据案件实际情况，对明利集团实际出资部分（1.5亿元）已计算其定增股票成本，其他未实际出资部分认定无定增成本，并无不妥。同时，净减持股票获利法可简化买卖交易过程中的动态变化，反映股份数量变动的最终状态，进而完整反映客观盈亏情况，因此以净减持股票获利法计算违法所得更为合理；第二，林军为获取资金优势和持股优势，直接决策拆借资金用于6个法人账户购买定增股票并为其他个人及资管账户提供资金、账户组通过一级市场认购股票进行建仓等事项，且直接指挥陈志强、何忠华及公司员工操作账户组交易“明利股份”股票，林军在操纵市场行为中起组织、策划作用，其客观行为充分体现林军具有操纵市场的主观故意。同时，本案违法性质恶劣，当事人存在转移资金出境、操纵金额巨大、对新三板市场价格和成交量扰乱波动大等恶劣情形，因此当事人所称本案社会危害较轻与事实不符；第三，何忠华、陈志强在操纵行为中起次要作用，我会已充分考虑两人参与程度作出责任认定并处罚，量罚适当。综上，我会对上述申辩意见不予采纳。根据当事人违法行为的事实、性质、情节与社会危害程度，依据《证券法》第二百零三条的规定，我会决定：没收林军、何忠华、陈志强违法所得29,342.48万元，并处以146,712.4万元罚款，其中对林军处以146,412.4万元罚款，对何忠华、陈志强分别处以150万元罚款。上述当事人应自收到本处罚决定书之日起15日内，将罚没款汇交中国证券监督管理委员会，开户银行：中信银行北京分行营业部，账号：7111010189800000162，由该行直接上缴国库，并将注有当事人名称的付款凭证复印件送中国证券监督管理委员会稽查局备案。当事人如果对本处罚决定不服，可在收到本处罚决定书之日起60日内向中国证券监督管理委员会申请行政复议，也可在收到本处罚决定书之日起6个月内直接向有管辖权的人民法院提起行政诉讼。复议和诉讼期间，上述决定不停止执行。 中国证监会 2019年12月12日 | D7: 43811 | E7: 〔2019〕149
A8: 是 | B8: 否 | C8: 〔2019〕148号 当事人：广西明利创新实业股份有限公司（以下简称明利股份），住所：广西壮族自治区防城港市东部吹填区。林军，男，1967年8月出生，明利股份实际控制人，广西明利集团有限公司（以下简称明利集团）董事长，住址：广西壮族自治区南宁市江南区。唐映，女，1976年10月出生，时任明利股份董事长，住址：广西壮族自治区南宁市江南区。何忠华，男，1975年9月出生，时任明利股份董事，明利集团副总裁，住址：广西壮族自治区南宁市江南区。卢敏坚，男，1968年10月出生，时任明利股份董事，住址：广西壮族自治区南宁市江南区。李超雄，男，1960年5月出生，时任明利股份董事，住址：广西壮族自治区南宁市青秀区。姜红，女，1975年3月出生，时任明利股份董事，住址：广西壮族自治区南宁市江南区。冯京，男，1982年8月出生，时任明利股份董事、总经理，住址：广西壮族自治区钦州市钦南区。徐赞枢，男，1945年9月出生，时任明利股份董事，住址：广西壮族自治区南宁市青秀区。陈志强，男，1981年5月出生，时任明利股份监事，住址：广西壮族自治区南宁市。张翠芳，女，1954年7月出生，时任明利股份监事，住址：广西壮族自治区南宁市青秀区。郑佰超，男，1987年2月出生，时任明利股份监事，住址：广西壮族自治区钦州市钦南区。蒙芳铭，女，1980年6月出生，时任明利股份董事会秘书（2015年7月后），住址：广西壮族自治区。邓红梅，女，1980年11月出生，时任明利股份董事会秘书（2015年7月前），时任明利股份财务总监，住址：广西壮族自治区南宁市江南区。黄志刚，男，1974年2月出生，时任明利股份副总经理，住址：广西壮族自治区崇左市江州区。依据《中华人民共和国证券法》（以下简称《证券法》）的有关规定，我会对明利股份违法违规行为进行了立案调查、审理，并依法向当事人告知了作出行政处罚的事实、理由、依据及当事人依法享有的权利。应当事人明利股份、林军、唐映、何忠华、卢敏坚、李超雄、姜红、冯京、徐赞枢、陈志强、张翠芳、郑佰超、蒙芳铭、黄志刚的要求，我会于2019年3月25日举行了听证会，听取了上述当事人的陈述和申辩。当事人邓红梅提交书面陈述申辩意见，但未要求听证。本案现已调查、审理终结。经查明，明利股份存在以下违法事实：一、明利股份《股票发行情况报告书》和《2015年第二次股票发行情况报告书》存在虚假记载明利集团是广西天勋物流服务有限公司（以下简称天勋物流）、广西防城港恒鑫化工有限公司（以下简称恒鑫化工）、广西桂东磷业投资有限公司（以下简称桂东磷业）、广西工创信息咨询有限公司（以下简称工创信息）、南宁市强顺农资有限公司（以下简称强顺农资）、防城港申达通实业有限公司（以下简称防城港申达通）六家公司的实际控制人，明利集团与恒鑫化工、桂东磷业、天勋物流、工创信息、强顺农资、防城港申达通等六家公司之间的控制关系具体表现如下：第一，恒鑫化工等六家公司均是为了明利集团及下属公司的业务发展需要而设立，或直接从明利集团分立；第二，恒鑫化工等六家公司的股东均为自然人股东，其股东和法定代表人均由明利集团副总裁何忠华安排和指定明利集团关联公司员工担任，注册资金来源于明利集团自有资金或何忠华借贷所得资金；第三，恒鑫化工等六家公司由明利集团董事长林军负责经营管理，由何忠华等明利集团现员工、原员工负责日常管理，明利集团直接决策恒鑫化工等六家公司的财务与经营事项及其他重大事项；第四，明利集团财务部直接处理恒鑫化工等六家公司的会计和出纳工作，并直接保管上述公司的银行支票和会计账册。综上，综合考虑设立目的、股东和法定代表人的决定权、注册资金来源、财务与经营事项的决策权、会计和出纳工作的管理权等因素，明利集团与恒鑫化工等六家公司之间存在《企业会计准则第36号-关联方披露》第三条第二款所述的控制关系。明利集团为明利股份的控股股东，明利集团同时控制恒鑫化工等六家公司，根据《中华人民共和国公司法》（以下简称《公司法》）第二百一十六条第四项和《企业会计准则第36号-关联方披露》第三条规定，明利股份与恒鑫化工等六家公司存在关联关系，构成关联方。2015年4月，明利股份进行了2015年第一次非公开发行股票，并公告《广西明利仓储股份有限公司股票发行情况报告书》，该公告称本次非公开发行股票的发行对象包括恒鑫化工和桂东磷业，并披露“公司新增股东与公司无关联关系”。《广西明利仓储股份有限公司股票发行情况报告书》存在虚假记载。2015年6月，明利股份进行了2015年第二次非公开发行股票，并公告《广西明利仓储股份有限公司2015年第二次股票发行情况报告书》，该公告称本次非公开发行股票的发行对象包括工创信息、天勋物流、强顺农资，并披露“本次发行新增投资者之间，新增投资者与公司及主要股东之间无关联关系”。《广西明利仓储股份有限公司2015年第二次股票发行情况报告书》存在虚假记载。明利股份应当按照《非上市公众公司监督管理办法》（证监会令第96号,以下简称《监督管理办法》）第二十一条、第四十六条第一款的规定披露发行情况报告书。明利股份在《广西明利仓储股份有限公司股票发行情况报告书》和《广西明利仓储股份有限公司2015年第二次股票发行情况报告书》中披露的信息有虚假记载的行为，违反《证券法》第六十三条、《监督管理办法》第二十条第一款规定，构成《证券法》第一百九十三条第一款所述披露的信息有虚假记载的违法行为。二、明利股份《2015年半年度报告》和《2015年年度报告》中未披露关联交易，存在重大遗漏2015年3月27日，明利股份向明利集团转款2.993亿元。2015年6月3日，明利股份向防城港申达通转款8.462亿元。明利集团和明利股份之间、防城港申达通和明利股份之间构成关联方，上述资金交易属于《企业会计准则第36号-关联方披露》第七条、第八条第五项规定的关联方交易。根据《企业会计准则第36条-关联方披露》第二条、第八条、第十条和第十一条，明利股份应当在财务报表及其附注中披露上述关联交易，包括该关联方关系的性质、交易类型及交易要素，明利股份在《2015年半年度报告》和《2015年年度报告》中均未披露上述关联方及关联交易，该行为违反《证券法》第六十三条、《监督管理办法》第六十条规定，构成《证券法》第一百九十三条第一款所述披露的信息有重大遗漏的违法行为。三、明利股份年报披露的实际控制人林军的持股比例存在虚假记载，且《股票发行情况报告书》未披露股份代持情况，2015年年报披露的股份代持情况存在虚假记载2015年4月至2016年12月，林军实际控制使用明利集团、恒鑫化工、桂东磷业、天勋物流、工创信息、强顺农资、钦州市申达通实业有限公司、中科沃土新三板优选1号资产管理计划、华茂资本华通1号证券投资基金、西域稳健新三板2号证券投资基金、国海明利股份1号集合资产管理计划、“卢敏坚”等32个证券账户（以下简称账户组）持有明利股份股票。2015年4月8日至4月10日，明利股份时任董事卢敏坚、姜红、时任董事会秘书蒙芳铭以及李某玲、张某、彭某、刘某琳、杨某滢、何某忠等9人分别与桂东磷业签订《广西明利仓储股票代持协议》，约定上述9人委托桂东磷业以每股4元的价格购买并持有明利股份股票，在桂东磷业代持股票满6个月至24个月期间内，上述9人有权要求桂东磷业以不低于实际投资额加年化12%的收益计算的价格收购该明利股份股票，明利集团为桂东磷业履行合同义务提供担保。李某明、陈某喜、王某祥分别与林军签订《明利仓储股票投资补充协议》，该协议中提及上述3人在与桂东磷业签订的股票转让合同中约定以每股4元的价格认购明利股份股票，在桂东磷业代持股票满6个月至24个月期间内，李某明、陈某喜、王某祥有权要求林军以不低于实际投资额加年化12%的收益计算的价格收购该股票。上述账户组持有的明利股份股票应合并计算为林军的持股数量和持股比例。明利股份在《2015年半年度报告》《2015年年度报告》和《2016年半年度报告》披露的实际控制人林军的持股比例分别为33.17%、33.40%和28.96%，上述定期报告所披露的林军持股比例并未包含账户组持有的明利股份股票，明利股份在《2015年半年度报告》《2015年年度报告》和《2016年半年度报告》披露的实际控制人林军持股比例存在虚假记载。明利股份在2015年4月22日公告的《股票发行情况报告书》中未披露桂东磷业存在上述股票代持情况，该行为违反《证券法》第六十三条、《监督管理办法》第三条、第六十条规定，构成《证券法》第一百九十三条第一款所述披露的信息有重大遗漏的违法行为。明利股份《2015年半年度报告》《2015年年度报告》均披露桂东磷业为当期普通股前十名股东之一，披露的股份代持情况均为“无”，明利股份《2015年半年度报告》《2015年年度报告》披露的股份代持情况存在虚假记载。明利股份在《2015年半年度报告》《2015年年度报告》披露的信息有虚假记载的行为，违反《证券法》第六十三条、《监督管理办法》第六十条规定，构成《证券法》第一百九十三条第一款所述披露的信息有虚假记载的违法行为。时任董事长唐映、时任董事何忠华、李超雄在涉案定期报告、临时报告上签字，卢敏坚在两次发行情况报告书和《2015年半年度报告》上签字，时任董事姜红在《2015年年度报告》《2016年半年度报告》上签字，时任董事、总经理冯京在涉案期间任职并在相关定期报告、临时报告上签字，时任董事徐赞枢在两次发行情况报告书和《2015年半年度报告》上签字，时任监事张翠芳、陈志强、郑佰超在涉案临时报告、定期报告上签字，时任副总经理黄志刚在涉案期间任职并在相关定期报告、临时报告上签字，时任董事会秘书、财务总监邓红梅在涉案期间任职并在两次发行情况报告书和《2015年年度报告》上签字，时任董事会秘书蒙芳铭在《2015年年度报告》《2016年半年度报告》上签字。上述违法事实，有相关人员询问笔录、银行账户流水、明利股份《股票发行情况报告书》《2015年第二次股票发行情况报告书》、明利股份《2015年半年度报告》《2015年年度报告》《2016年半年度报告》等证据证明，足以认定。明利股份在《广西明利仓储股份有限公司股票发行情况报告书》和《广西明利仓储股份有限公司2015年第二次股票发行情况报告书》中披露的信息有虚假记载的行为，违反《证券法》第六十三条、《监督管理办法》第二十条第一款规定，构成《证券法》第一百九十三条第一款所述披露的信息有虚假记载的违法行为。明利股份在《2015年半年度报告》和《2015年年度报告》中均未披露关联关系及关联交易，违反《证券法》第六十三条、《监督管理办法》第六十条规定，构成《证券法》第一百九十三条第一款所述披露的信息有重大遗漏的违法行为。明利股份在《2015年半年度报告》《2015年年度报告》和《2016年半年度报告》披露的信息有虚假记载的行为，违反《证券法》第六十三条、《监督管理办法》第六十条规定，构成《证券法》第一百九十三条第一款所述披露的信息有虚假记载的违法行为。唐映作为时任董事长，何忠华作为时任董事，上述人员未勤勉尽责，是直接负责的主管人员。卢敏坚、徐赞枢、李超雄、姜红作为时任董事，张翠芳、陈志强、郑佰超作为时任监事，蒙芳铭作为时任董事会秘书（2015年7月后），冯京作为时任董事、总经理，黄志刚作为时任副总经理、邓红梅作为时任董事会秘书（2015年7月前）、时任财务总监，上述人员未勤勉尽责，是其他直接责任人员。林军作为明利股份实际控制人，知悉明利股份存在关联交易行为，隐瞒、不告知应当披露的信息，构成《证券法》第一百九十三条第三款所述指使明利股份从事信息披露违法行为的情形。明利股份、林军、唐映等当事人及其代理人提出如下陈述、申辩意见：第一，本案的相关行为是林军操纵明利股份案的手段行为，两案存在牵连关系，故本案应被林军操纵明利股份案吸收，不应在认定林军操纵明利股份构成违法后再对本案涉案人员作出处罚。第二，林军并未在明利股份担任董事、监事、高级管理人员等职务，不应将其认定为直接负责的主管人员。第三，对明利股份及唐映、何忠华等董事、监事、高级管理人员处罚过重。唐映、何忠华等董事、监事、高级管理人员大部分不知悉涉案事实，未参与涉案行为或仅起到次要作用，本案情节轻微，对明利股份及涉案董事、监事、高级管理人员处罚过重。第四，蒙芳铭、姜红提出，根据两人任职时间，不应认定两人对两次发行情况报告书和2015年半年报承担责任；徐赞枢提出，其并未担任明利股份董事职务，未在相关文件上签字，不应认定其构成未勤勉尽责，请求免于处罚；李超雄提出，其不知悉、未参与涉案违法事实，不应承担未勤勉尽责的责任，且其曾向广西证监局举报明利股份存货有虚假记载，本案应对其从轻或减轻处罚；邓红梅提出，其不知悉、未参与涉案违法事实，也缺乏必要的调查能力和手段，在履职过程中已通过国家企业信用信息公示系统查证相关情况，不应认定其未勤勉尽责，请求免于处罚。经复核，我会认为，对林军、姜红、蒙芳铭及其代理人申辩意见中的部分内容予以采纳，对其他申辩意见不予采纳。具体如下：第一，本案与林军等人操纵明利股份案的违法行为侵犯的是不同的法益，依法不应被林军操纵明利股份案吸收；第二，我会依据涉案行为的违法事实性质、情节和社会危害性认定本案各当事人的处罚幅度，并无不当；第三，关于徐赞枢任职和签字事项的问题。根据在案证据，涉案会议文件上有徐赞枢签名，经听证会现场对质，徐赞枢亦承认上述文件上的签字系其本人在空白页上所签，同时，明利股份公开披露的涉案定期报告、临时报告载明其为公司董事，其从未提出过异议。上述事项更进一步表明其未勤勉尽责；第四，关于李超雄是否勤勉尽责及是否有从轻或减轻处罚情节的问题。经核实，李超雄未对涉案事实作充分核查即在相关文件上签字，应认定其未勤勉尽责，同时，其举报的相关事实与本案无关，不构成法定从轻或减轻处罚的情形；第五，关于邓红梅是否勤勉尽责的问题。邓红梅作为时任董事会秘书和时任财务总监，有责任充分核查公司关联交易等财务事项并监督公司依法披露，其未充分核查涉案事实即在相关会议文件上签字确认，应认定其未勤勉尽责，其所述不知悉、不参与等申辩意见均不构成免责理由。综上，我会认定涉案当事人构成未勤勉尽责，同时对当事人及其代理人提出部分内容予以采纳，并作相应调整。根据当事人违法行为的事实、性质、情节与社会危害程度，依据《证券法》第一百九十三条第一款、第三款的规定，我会决定：一、对广西明利创新实业股份有限公司责令改正，给予警告，并处以60万元的罚款；二、对林军给予警告，并处以60万元罚款；三、对唐映、何忠华分别给予警告，并分别处以30万元罚款；四、对陈志强、卢敏坚、李超雄分别给予警告，并分别处以10万元的罚款；五、对姜红、蒙芳铭、邓红梅分别给予警告，并分别处以7万元罚款；六、对徐赞枢、张翠芳、郑佰超、冯京、黄志刚分别给予警告，并分别处以5万元的罚款。上述当事人应自收到本处罚决定书之日起15日内，将罚款汇交中国证券监督管理委员会，开户银行：中信银行北京分行营业部，账号：7111010189800000162，由该行直接上缴国库，并将注有当事人名称的付款凭证复印件送中国证券监督管理委员会稽查局备案。当事人如果对本处罚决定不服，可在收到本处罚决定书之日起60日内向中国证券监督管理委员会申请行政复议，也可在收到本处罚决定书之日起6个月内直接向有管辖权的人民法院提起行政诉讼。复议和诉讼期间，上述决定不停止执行。 中国证监会 2019年12月5日 | D8: 43804 | E8: 〔2019〕148
A9: 是 | B9: 是 | C9: 〔2019〕143 号 当事人：陈亚发，男，1968年9月出生，住址：福建省厦门市湖里区。依据《中华人民共和国证券法》（以下简称《证券法》）的有关规定，我会对陈亚发违法违规行为进行了立案调查、审理，并依法向当事人告知了作出行政处罚的事实、理由、依据及当事人依法享有的权利。应当事人的要求举行了听证，听取了当事人及其代理人的陈述和申辩。本案现已调查、审理终结。经查明，陈亚发存在以下违法事实：一、陈亚发控制使用“海富通-陈亚发”账户认购云南罗平锌电股份有限公司非公开发行股票2017年1月11日，陈亚发作为委托人，与管理人海富通基金管理有限公司（以下简称海富通基金）、托管人宁波银行股份有限公司签订《海富通欣祥二号资产管理计划资产管理合同》（以下简称欣祥二号），合同显示，欣祥二号即“海富通-陈亚发”，二者系同一产品。依照合同约定，管理人海富通基金按照委托人陈亚发的投资指令从事投资活动。2017年1月，云南罗平锌电股份有限公司（以下简称罗平锌电）与海富通基金签订《非公开发行股票认购协议书》，约定由“海富通-陈亚发”参与罗平锌电2017年非公开发行。2017年1月13日，“海富通-陈亚发”参与认购罗平锌电非公开发行股票10,173,547股，认购价格16.71元/股，认购价款共计169,999,970.37元。1月16日，陈亚发向“海富通-陈亚发”账户转入1.7亿元，作为认购非公开发行股票资金。该笔资金源于陈亚发向华融（福建自贸试验区）投资股份有限公司（以下简称华融投资）借款，华融投资通过国民信托设立产品，由国民信托银行账户将1.7亿元转入陈亚发工商银行账户。1月19日，陈亚发向“海富通-陈亚发”账户转入6.8万元和40.8万元分别用于支付产品托管费和管理费。罗平锌电2017年2月17日公告显示，“海富通-陈亚发”持股数量10,173,547股，持股比例3.15%。罗平锌电2017年年度报告及2018年第一季度报告、中期报告、第三季度报告显示，该产品持股数量与比例均未发生变化。二、陈亚发控制使用“聚宝盆80号”账户交易“罗平锌电”陈亚发与吴某波系同乡，关系很好。2017年5月17日，吴某波与陕西省国际信托股份有限公司签订《陕国投·聚宝盆80号证券投资集合资金信托计划信托合同》（以下简称聚宝盆80号），优先级资金1亿元，劣后资金5,000万元，劣后方吴某波，紧急联系人陈某平。劣后级资金5,000万元中的3,700万元系陈亚发向吴某波的借款，1,300万元系陈亚发向孙某珍的借款。产品设立后，吴某波将账号密码告诉陈亚发。陈亚发认为“罗平锌电”价格较低、可以买入，故作出交易“罗平锌电”的决策，主要由陈亚发下单操作，偶尔由陈某平根据陈亚发指令下单操作。“聚宝盆80号”产品主要由两台电脑进行下单操作，两台电脑MAC地址与陈亚发控制使用的“傅某城”等证券账户交易“罗平锌电”主要MAC地址相同。“聚宝盆80号”买入“罗平锌电”后，交易处于亏损状态，陈亚发借款用于补仓。“聚宝盆80号”自2017年5月19日起至2018年7月19日，主要交易“罗平锌电”，同时少量交易“建发股份”等。罗平锌电2017年第三季度报告显示该产品首次成为罗平锌电前十大股东，持股5,834,420股，持股比例1.80%。罗平锌电2017年年度报告及2018年第一季度报告显示该产品持股6,085,420股，持股比例1.88%；2018年度中期报告显示该产品持股5,234,220股，持股比例1.62%；2018年度第三季度报告显示，该产品未入前十大流通股东。三、陈亚发另控制20个自然人证券账户交易“罗平锌电”陈亚发本人拥有6个证券账户，同时，陈亚发直接联系借用“傅某城”等5个证券账户，并通过吴某波借用“顾某东”等9个证券账户，陈亚发合计控制使用20个自然人证券账户。上述20个证券账户由陈亚发作出账户交易决策，由陈亚发下单操作，有时由陈某平根据陈亚发指令下单操作。下单操作设备为陈亚发的笔记本电脑及厦门盛世汇金投资管理有限公司（以下简称盛世汇金）办公电脑，下单地点在盛世汇金，陈亚发控制使用的20个证券账户交易“罗平锌电”的MAC地址高度重合。四、陈亚发控制使用“海富通-陈亚发”“聚宝盆80号”以及20个自然人证券账户（以下简称账户组）违法增持“罗平锌电”2017年5月25日，账户组持有“罗平锌电”首次达到5%，陈亚发未按规定及时履行报告和公告义务，且于限制交易期内继续交易，2018年6月19日，账户组持有“罗平锌电”达到8.08%。在限制交易期内，账户组违法增持的股数约为9,960,967股，违法增持金额约为119,232,782.77元。上述违法事实，有当事人询问笔录、证券账户资料、银行账户资料、证券账户交易信息、相关公告等证据证明，足以认定。我会认为，陈亚发控制账户组交易“罗平锌电”，持股比例达到5%后，陈亚发未报告和公告且未在限制交易期内停止交易，存在违法增持，其行为违反《证券法》第八十六条第一款、第三十八条的规定，构成《证券法》第一百九十三条第一款和第二百零四条所述违法情形。陈亚发代理人在听证和申辩材料中提出：第一，涉案账户组交易严重亏损。第二，陈亚发看好罗平锌电股票，系长期投资，超比例持股和限制期交易是由于其建仓、加仓和补仓行为导致，不具有明显恶劣性。第三，陈亚发没有举牌行为，没有侵害《证券法》第八十六条所保护的法益。第四，陈亚发超比例持股和限制期交易行为未对市场交易产生实质影响。第五，与同期同类案件相比，本案处罚偏重。第六，亏损型操纵市场案可能同时合并限制期交易问题，相较该类案件，本案处罚有失公平。综上，请求减轻处罚。经复核，我会认为：第一，《证券法》第一百九十三条和第二百零四条均不以违法行为是否获利作为处罚依据，陈亚发是否存在亏损以及主观故意与认定其违法行为无直接关系。第二，根据《证券法》第八十六条第一款的规定，陈亚发在持有罗平锌电已发行股份5%时，应在三日内报告并公告，在上述期限内不得买卖该股票。陈亚发未履行信息披露义务，且在限制转让期内继续交易，其行为损害了上市公司以及其他投资者对市场变化的知情权。第三，我会的处罚已综合考虑了陈亚发违法行为的事实、性质、情节和社会危害程度，量罚适当。根据当事人违法行为的事实、性质、情节与社会危害程度，我会决定：依据《证券法》第一百九十三条第一款的规定，对陈亚发未及时报告和公告的行为责令改正，给予警告，并处以30万元罚款；依据《证券法》第二百零四条的规定，对陈亚发限制交易期内买卖证券的行为责令改正，给予警告，并处以300万元罚款。上述当事人应自收到本处罚决定书之日起15日内，将罚款汇交中国证券监督管理委员会（财政汇缴专户），开户银行：中信银行北京分行营业部，账号：7111010189800000162，由该行直接上缴国库，并将注有当事人名称的付款凭证复印件送中国证券监督管理委员会稽查局备案。当事人如果对本处罚决定不服，可在收到本处罚决定书之日起60日内向中国证券监督管理委员会申请行政复议，也可在收到本处罚决定书之日起6个月内直接向有管辖权的人民法院提起行政诉讼。复议和诉讼期间，上述决定不停止执行。 中国证监会 2019年12月5日 | D9: 43804 | E9: 〔2019〕143
A10: 是 | B10: 否 | C10: 〔2019〕141号 当事人：江苏保千里视像科技集团股份有限公司（以下简称保千里），住所：江苏省南京经济技术开发区。庄敏，男，1968年7月出生，时为保千里实际控制人，时任保千里董事长，住址：广东省广州市越秀区。鹿鹏，男，1976年12月出生，时任保千里董事、总裁，住址：广东省深圳市南山区。何年丰，男，1983年12月出生，时任保千里董事、财务总监，住址：广东省深圳市福田区。 周皓琳，男，1970年3月出生，时任保千里董事、副总裁、董事会秘书，住址：广东省深圳市福田区。 陈杨辉，男，1977年7出生，时任保千里董事、副总裁，住址：湖北省松滋市新江口镇。丁立红，男，1971年11月出生，时任保千里董事，住址：广东省普宁市流沙北街道。张乾峰，男，1977年7月出生，时任保千里董事，住址：江苏省江阴市申港镇。黄焱，女，1970年11月出生，时任保千里独立董事，住址：广东省深圳市南山区。周少强，男，1966年11月出生，时任保千里独立董事，住址：广东省深圳市罗湖区。曹亦为，男，1963年6月出生，时任保千里独立董事，住址：广东省深圳市南山区。周含军，男，1969年10月出生，时任保千里独立董事，住址：广东省深圳市罗湖区。蒋建平，男，1979年6月出生，时任保千里常务副总裁，住址：广东省深圳市宝安区。陈献文，男，1974年11月出生，时任保千里常务副总裁，住址：广东省深圳市罗湖区。 陈德银，男，1971年12出生，时任保千里总裁助理，住址：广东省深圳市龙岗区。龙刚，男，1972年10月出生，时任保千里副总裁、总工程师，住址：广东省深圳市南山区。林宋伟，男，1979年4月出生，时任保千里副总裁，住址：广东省深圳市宝安区。李小虎，男，1974年8月出生，时任保千里副总裁，住址：河北省霸州市霸州镇。 李翊，男，1972年3月出生，时任保千里副总裁，住址：湖南省长沙市开福区。童爱平，男，1956年12月出生，时任保千里副总裁，住址：江苏省江阴市滨江中路。王务云，男，1961年5月出生，时任保千里副总裁，住址：江苏省南京市秦淮区。梁国华，男，1964年10月出生，时任保千里监事会主席，住址：广东省深圳市福田区。颜佳德，男，1987年4月出生，时任保千里职工监事，住址：广东省深圳市龙华新区。林新阳，男，1989年8月出生，时任保千里监事，住址：广东省深圳市南山区。依据《中华人民共和国证券法》（以下简称《证券法》）的有关规定，我会对保千里信息披露违法案进行了立案调查、审理，并依法向当事人告知了作出行政处罚的事实、理由、依据及当事人依法享有的权利。当事人周皓琳、陈杨辉、丁立红、周含军、童爱平、王务云等6名责任人提出书面陈述、申辩意见，未要求召开听证会。保千里公司、庄敏等责任人员未提出陈述、申辩意见，也未要求召开听证会。本案现已调查、审理终结。经查明，保千里存在以下违法事实：一、未按规定披露关联方及关联交易 2015年至2017年9月，保千里实际控制人、时任保千里董事长庄敏以扶持小微企业为名，与深圳市车米云图科技有限公司、深圳市心悦云端技术有限公司、广州优果蔬网络科技有限公司、深圳市九鹿鸣文化传媒有限公司、上海宜生源文化传播有限公司、深圳市中鹏云谷文化传媒发展有限公司、深圳市尚流移动互联网有限公司、广州澳视互动传媒有限公司、深圳市中星宝电商平台有限公司、深圳市云邦信息技术有限责任公司、深圳市益佰年文化传播有限公司、深圳市思瑞网络信息有限公司、南京鹈鹕电子商务有限公司、南京正和文化传媒有限公司、长沙松致文化传播有限公司、北京生活半小时科技有限公司、武汉夏荷冬雪食品有限公司、深圳双安智农科技发展有限公司、深圳市唯美会智能信息有限公司、厦门阳扬广告有限公司共20家小微企业合作，实际控制了上述企业的经营和财务。庄敏指挥其下属以投资名义为这些小微企业注入资金，用于购买保千里的产品，并使用上述企业银行账户进行具体的采购付款操作。根据《企业会计准则第36号-关联方披露》第三条的规定，这20家小微企业属于庄敏控制的企业，与保千里构成关联方，其与保千里之间的购销业务属于关联交易。 庄敏策划、实施上述行为的方式如下： 1.寻找下游合作对象。庄敏通过朋友、员工介绍或者邀请小微企业在保千里现场进行路演等方式，联系小微企业进行洽谈合作。这些企业绝大多数之前与保千里没有业务往来，有的公司则属于没有经营业务的空壳公司。庄敏承诺扶持这些企业发展，帮助这些企业提高估值，前提是这些企业必须要采购保千里及其子公司生产的显示屏、乐摇宝、小宝机器人等新产品。采购资金由庄敏负责组织提供，参与合作小微企业只需要按照庄敏的要求采购并铺货。 2.为下游合作对象注入资金。庄敏安排下属肖某、许某忠等人负责和参与合作的小微企业进行对接，通过大量实际控制账户以投资名义向这些小微企业注入资金。具体方式是肖某、许某忠等人要求小微企业提供银行账户用来进行注入资金和划款采购，经肖某、许某忠等人带回的银行卡和U盾交给庄敏下属詹某冬等人，由詹某冬等人进行具体划款操作。肖某、许某忠为保千里上市前的员工，分别于2015年、2014年离职，两人根据庄敏指示负责上述工作，工资由庄敏发放。 3.控制下游合作对象的银行账户实施采购。詹某冬于2007年进入保千里上市前主体工作，于2015年离职。2016年年初开始带领陈某娜等人为庄敏工作，专门负责资金划转，詹某冬团队人员工资均由庄敏发放。詹某冬等人收到肖某、许某忠等人带回的小微企业银行卡及U盾后，按照庄敏的指令向这些卡中划入资金，并按照庄敏的指令向保千里划款采购显示屏、乐摇宝和小宝机器人等产品。具体采购由庄敏组织保千里时任财务总监何年丰等人和詹某冬等人开会确定，詹某冬负责按照庄敏的指令划款。詹某冬按照庄敏提供的转账路线图把资金划入肖某、许某忠等人提供的小微企业银行账户，然后按照何年丰提供的转账路线图，把资金转到保千里及其子公司账户。 4.20家小微企业按照庄敏确定的经营模式运营，庄敏为20家小微企业提供资金。按照庄敏要求，20家小微企业每月向肖某、许某忠等人申请运营费用，经审核后由肖某、许某忠等人拨付经营费用。保千里向上述小微企业销售产品，2015年度销售收入4.07亿元，相应利润1.57亿元，占当年净利润比重41.95%；2016年度销售收入16.16亿元，相应利润7.10亿元，占当年净利润比重88.79%；2017年1至9月销售收入为13.86亿元，相应利润6.07亿元，占当期净利润比重150.39%。保千里未对上述关联交易予以披露，且未在2015年年度报告；2016年半年度报告、年度报告；2017年半年度报告中对上述关联方和关联交易予以披露。二、未按规定披露对外担保情况2016年至2017年，保千里下属子公司深圳市保千里电子有限公司（以下简称保千里电子）、深圳市图雅丽特种技术有限公司在深圳南山宝生村镇银行股份有限公司和洛银金融租赁公司为深圳志豪供应链有限公司、深圳市同威盛世科技有限公司、深圳市晶锐显科技有限公司、深圳市睿盟贸易有限公司、深圳市中海鑫运实业发展有限公司、深圳市天绮泰实业发展有限公司、深圳市中海鑫通实业发展有限公司、深圳市中海鑫品实业发展有限公司、深圳云邦信息技术有限责任公司、深圳市心悦云端技术有限公司、深圳市九鹿鸣文化传媒有限公司、广州澳视互动传媒有限公司12家企业共计12笔借款提供担保，金额总计7.05亿。保千里未就上述担保进行临时信息披露，也未在当期年度报告和半年度报告中予以披露。三、未按规定披露大股东股份被司法冻结事项2017年9月12日，庄敏所持有保千里1亿股股份被江苏省南京市中级人民法院执行司法冻结；2017年9月25日，庄敏所持公司股份0.68亿股被湖南省高级人民法院执行司法冻结。保千里未及时进行信息披露。我会认为，保千里的上述行为违反了《证券法》第六十三条“发行人、上市公司依法披露的信息，必须真实、准确、完整，不得有虚假记载、误导性陈述或重大遗漏”的规定；违反了《证券法》第六十八条第三款“上市公司董事、监事、高级管理人员应当保证上市公司所披露的信息真实、准确、完整”的规定，构成《证券法》第一百九十三条第一款“发行人、上市公司或者其他信息披露义务人未按照规定披露信息，或者所披露的信息有虚假记载、误导性陈述或者重大遗漏的”所述情形。时为实际控制人、董事长庄敏组织、策划、领导实施了上述关联交易行为，作为共同保证人在上述对外担保合同上签字，未向上市公司及时报告有关股权被冻结事项，并在有关定期报告的董事会决议、确认意见上签字，构成《证券法》第一百九十三条第三款所述实际控制人指使从事信息披露违法行为的情形，且系保千里上述违法行为直接负责的主管人员。时任总裁鹿鹏、时任财务总监、董事何年丰参与或知悉关联交易事项并在涉案定期报告的董事会决议、确认意见上签字，鹿鹏还担任保千里全资子公司保千里电子等公司法定代表人。上述二人为关联交易和对外担保未披露行为直接负责的主管人员。时任董事、监事、高级管理人员周皓琳、陈杨辉、丁立红、张乾峰、黄焱、周少强、曹亦为、周含军、蒋建平、陈献文、陈德银、龙刚、林宋伟、李小虎、李翊、童爱平、王务云、梁国华、颜佳德、林新阳在其任期内的涉及有关定期报告的董事会决议、监事会决议、确认意见上签字，为定期报告未如实披露的其他直接责任人员。以上事实，有上市公司定期报告、上市公司会议文件、相关人员询问笔录、涉案银行账户转账记录、有关财务凭证、保证合同等证据证明，足以认定。时任保千里董事、副总裁、董事会秘书周皓琳在陈述、申辩意见中提出：其一，涉案违法行为系保千里原控股股东、实际控制人庄敏策划、实施。申辩人作为公司第二大股东推荐派往公司的董事会秘书，在公司日常经营管理活动中受到排挤、防范，在重大经营活动关键环节上均被绕开，无法获知涉案的违法事项，不应承担责任。其二，因庄敏等人刻意隐瞒违法行为，申辩人不具有履行信息披露义务的客观条件，虽已尽到审慎注意义务，仍然无法发现违法行为。事先告知书所认定的其他直接责任人均知悉或参与违法行为，而申辩人对违法行为既未参与也不知情，不应当被认定为直接负责的主管人员。其三，仅凭申辩人在年度报告确认意见上签字就处罚，不符合《信息披露违法行为行政责任认定规则》（以下简称《责任认定规则》），也违反法律公平性和一致性原则。时任董事丁立红提出：其一，保千里信息披露违法行为涉及事项均未经董事会、股东大会决策，且完全背离公司的宗旨和目的，也违反公司内部规定，不能代表公司意志，申辩人及公司均无违法故意。其二，申辩人不分管保千里公司具体业务，不参与公司日常管理，对违法行为既不知情，也未参与，不能仅凭在相关定期报告的确认意见上签字就对申辩人作出处罚。其三，申辩人在任职期间勤勉尽责，多次通过邮件、会议等多种方式要求董监高人员规范运作。其四，申辩人在得知违法事项后，主动积极履职，及时采取必要补救措施，进行整改、纠正，开展公司自救。在就任董事长后，积极组织公司自救，拟通过破产重组程序尽最大程度保障投资者利益。时任董事、副总裁陈杨辉提出：对于关联交易和关联方，公司未披露的信息或披露的文件信息不是其管理范围，与其没有直接或间接关系，不应对其处罚；对于对外担保、大股东股权冻结事项，均不知情，也没有签字。时任副总裁童爱平提出：其一，作为保千里重组上市前的工作人员，在重组后处理遗留事项，主要负责保千里的南京业务，涉案事项并不属于申辩人职责范围。相关违法行为系庄敏策划、实施，申辩人既不知情，也未参与，即便尽到审慎注意义务也无法发现违法行为，不应当被认定为其他直接责任人员。其二，仅凭申辩人在年报确认意见签字就处罚，不符合《责任认定规则》，违反法律公平性和一致性原则。其三，始终对自己职责范围内的业务恪尽职守，勤勉尽责，不能对高管苛以过严的勤勉尽责义务。其四，积极配合调查，今后将更加谨慎履职。时任副总裁王务云提出申辩意见：其一，申辩人作为保千里重组上市前主体工作人员，在重组后处理遗留事项，主要负责保千里的南京业务，涉案事项并不属于申辩人职责范围。相关违法行为系庄敏策划、实施，其本人不知情未参与，即便尽到审慎注意义务也无法发现，不应当被认定为其他直接责任人员。其二，仅凭申辩人在年度报告确认意见签字就处罚，不符合《责任认定规则》，违反法律公平性和一致性原则。其三，作为保千里下属公司南京威尔卡软件公司董事长，申辩人始终对自己职责范围内的业务恪尽职守，勤勉尽责，不应对高管苛以过严勤勉尽责义务。其四，本人积极配合调查，今后将更加谨慎履职。时任独立董事周含军提出：其一，告知涉及三项事实均为庄敏一手操纵，个别关键岗位人员协助，其本人勤勉尽责但仍不可能发现，属于应当免责的情形。其二，告知书所列事项系事后知悉，但其本人未接受过告知书相关内容的调查，对相关事实的认定过程无从知晓，对调查程序合法性质疑。其三，于2016年12月出任独立董事，18年5月辞职。任职期间已勤勉尽责，并在2016年年度报告审计工作中与会计师、财务负责人保持了密切沟通，未发现异常。在2017年半年度报告公布时，发现公司大额现金净流出后，对公司提出了核查要求。证监会应当出示其未勤勉尽责的证据。针对上述申辩意见，我会认为：第一，根据《证券法》第六十八条第三款、第一百九十三条；《上市公司信息披露管理办法》第五十八条等规定，上市公司信息披露存在虚假记载、误导性陈述或者重大遗漏，上市公司董事、监事、高级管理人员应当承担相应责任，除非其能够证明已经履行勤勉尽责义务。相关申辩意见不能反映申辩人对涉案违法事实进行过特别关注，或采取过积极的履职行为，不能证明其已尽到勤勉尽责义务。其提出的不直接参与经营管理、履职存在客观困难、对违法行为不知情、未参与等申辩理由亦不属于不予处罚的情形。因此，不能免除上述申辩人违法行政责任。第二，信息披露违法责任人员的责任大小，一般从当事人在信息披露违法行为发生过程中所起的作用、知情程度和态度、职务、具体职责及履职情况、专业背景等方面综合认定。针对申辩人周皓琳的申辩意见，鉴于现有证据并未显示周皓琳存在直接参与或知悉违法行为的情形，综合考虑本案其他直接责任人员的认定理由和申辩人的违法情节、性质和社会危害程度，我会认定周皓琳为相应信息披露违法行为的其他责任人员，并对其处以15万元罚款；针对其他5名申辩人的意见，我会认为，本案对相关人员的责任认定和处罚幅度，已充分考虑了各自在违法行为中所起的作用和违法情节，将其认定为相应信息披露违法行为的其他直接责任人员并处以5万元较低档次处罚，并无不当。第三，部分申辩人提出其未接受调查的说法，与事实不符。在案证据证明，我会已依法对案件进行了全面客观调查，对申辩人依法进行了询问，并依法调取了签字的文件、相关定期报告等证据。第四，部分申辩人关于相关事项未经公司法定决策程序，不能代表公司意志的说法，我会认为，本案对上市公司违法行为的认定和处罚符合《证券法》第一百九十三条之规定。部分涉案事实，与大股东隐瞒有关事实相关，我会在对实际控制人、责任人的处罚中已体现责任承担上的区别。综上所述，对相关申辩意见不予采纳。根据当事人违法行为的事实、性质、情节与社会危害程度，依据《证券法》第一百九十三条第一款、第三款的规定，我会决定：一、对保千里责令改正，给予警告，并处以60万元罚款。二、对庄敏给予警告，并处以90万元罚款。其中作为直接负责的主管人员罚款30万元，作为指使从事违法行为的实际控制人罚款60万元。三、对鹿鹏、何年丰给予警告，并分别处以30万元罚款。四、对周皓琳给予警告，并处以15万元罚款；对陈杨辉、丁立红、张乾峰、黄焱、周少强、曹亦为、周含军、蒋建平、陈献文、陈德银、龙刚、林宋伟、李小虎、李翊、童爱平、王务云、梁国华、颜佳德、林新阳给予警告，并分别处以5万元罚款。上述当事人应自收到本处罚决定书之日起15日内，将罚款汇交中国证券监督管理委员会，开户银行：中信银行北京分行营业部，账号：7111010189800000162，由该行直接上缴国库，并将注有当事人名称的付款凭证复印件送中国证券监督管理委员会稽查局备案。当事人如果对本处罚决定不服，可在收到本处罚决定书之日起60日内向中国证券监督管理委员会申请行政复议，也可在收到本处罚决定书之日起6个月内直接向有管辖权的人民法院提起行政诉讼。复议和诉讼期间，上述决定不停止执行。 中国证监会 2019年12月3日 | D10: 43802 | E10: 〔2019〕141
A11: 是 | B11: 是 | C11: 〔2019〕140号 当事人：朱康军，男，1968年11月出生，住址：浙江省仙居县。依据《中华人民共和国证券法》（以下简称《证券法》）的有关规定，我会对朱康军操纵“神开股份”行为进行了立案调查、审理，并依法向当事人告知了作出行政处罚的事实、理由、依据及当事人依法享有的权利，朱康军未提出陈述、申辩意见，也未要求听证。本案现已调查、审理终结。经查明，朱康军存在以下违法事实：一、朱康军控制使用“蔡某领”等74个证券账户朱康军控制使用“鲁证期货股份有限公司—鲁证汇泉万泰利群资产管理计划”“上海爱建信托有限责任公司－爱建民生天雷1号证券投资集合资金信托计划”“上海爱建信托有限责任公司－爱建民生天雷2号证券投资集合资金信托计划”“上海爱建信托有限责任公司－爱建信托晨辉3号证券投资集合资金信托计划”“中信盈时资产管理有限公司－中信盈时君隆1号资产管理计划”及“蔡某领”等共计74个证券账户（以下简称账户组）进行股票交易。在案证据显示，账户组交易决策由朱康军完成，其他人根据朱康军指示进行资金划转。二、朱康军利用账户组操纵市场的情况2016年10月14日至2017年4月19日期间，朱康军控制使用账户组集中资金优势、持股优势连续买卖“神开股份”，并在自己实际控制的账户之间进行交易，影响“神开股份”交易价格、交易量。具体情况如下：（一）集中资金优势和持股优势2016年10月14日至2017年4月19日，朱康军控制账户组，以大宗交易和集中竞价交易方式买入“神开股份”196,313,282股，买入金额3,378,421,037.08元。其中，以大宗交易方式买入“神开股份”14,168,795股，买入金额264,673,090.60元；以集中竞价交易方式买入“神开股份”182,144,487股，买入金额3,113,747,946.48元。以集中竞价交易方式卖出“神开股份”177,439,524股，卖出金额2,751,430,165.77元。2016年10月14日至2017年4月19日期间，“神开股份”共有126个交易日。在该126个交易日内，朱康军控制的账户组持股数量占“神开股份”流通股本比例（以下简称持股比例）在10%以上的有96个交易日，占总交易日的76.19%；持股比例在20%以上的有60个交易日，占总交易日的47.62%。2017年4月6日，账户组持股比例达到最高的24.45%。 （二）连续买卖“神开股份” 在上述126个交易日中，朱康军控制的账户组有120个交易日交易“神开股份”，其中，1个交易日存在大宗交易，全部120个交易日均存在集中竞价交易。在集中竞价交易中，账户组买入成交量占当日该股市场竞价成交量的比例（以下简称买入成交占比）超过10%的有81个交易日，占总交易日的64.29%；买入成交占比超过20%的有61个交易日，占总交易日的48.41%；买入成交占比超过30%的有35个交易日，占总交易日的27.78%；买入成交占比超过40%的有17个交易日，占总交易日的13.49%；买入成交占比超过50%的有5个交易日，占总交易日的3.97%。2017年1月26日，账户组买入成交占比达到最高的71.07%。在集中竞价交易中，账户组卖出成交量占当日该股市场竞价成交量的比例（以下简称卖出成交占比）超过10%的有57个交易日，占总交易日的45.24%；卖出成交占比超过20%的有36个交易日，占总交易日的28.57%；卖出成交占比超过30%的有19个交易日，占总交易日的15.08%；卖出成交占比超过40%的有13个交易日，占总交易日的10.32%；卖出成交占比超过50%的有6个交易日，占总交易日的4.76%。2017年4月13日，账户组卖出成交占比达到最高的70.37%。朱康军控制账户组集中资金优势连续买卖拉抬“神开股份”较为典型的交易日有2016年10月14日、2016年11月10日、2016年11月16日、2016年12月9日、2016年12月16日、2017年1月20日、2017年1月26日、2017年3月9日等，主要手法为：账户组在盘中某一时段，分多笔以高价连续申报买入“神开股份”，拉抬“神开股份”股价，且申报量明显放大，交易异常性突出。以账户组2016年10月14日的交易为例，当日账户组申报买入“神开股份”5,075,400股，成交4,202,499股，买入申报量和买入成交量均市场排名第一。账户组大部分买入发生在当日下午，即13:07:34至13:18:47，账户组分20笔申报买入3,913,300股，申报买入金额64,369,398元，其中以涨停价16.52元申报买入10笔共计3,173,300股。20笔买入申报中13笔买入申报价格高于申报前卖方第一档价格，7笔买入申报价格高于申报前市场最新成交价。上述20笔买入申报成交3,040,349股，成交金额50,087,595.19元。期间“神开股份”股价由16.03元升至16.52元，涨幅3.06%。（三）在自己实际控制的账户之间进行交易在上述126个交易日中，朱康军控制的账户组买入“神开股份”申报与卖出“神开股份”申报之间存在成交情况的有82个交易日，占总交易日的65.08%。账户组买入申报与卖出申报之间累计成交36,979,204股，分别占账户组竞价买入成交量（182,144,487股）、竞价卖出成交量（177,439,524股）的20.30%、20.84%。账户组买入申报与卖出申报之间成交量占当日该股市场竞价成交量的比例（以下简称自成交占比）超过10%的有24个交易日，占总交易日的19.05%；自成交占比超过20%的有4个交易日，占总交易日的3.17%。2017年1月26日，账户组自成交占比达到最高的31.66%。上述期间，朱康军控制的账户组交易“神开股份”累计亏损433,938,043.54元。上述违法事实，有证券开户资料、账户统计情况表、银行流水、委托交易流水、证券交易所统计数据、交易终端信息、相关人员询问笔录或情况说明、相关协议等证据证明，足以认定。朱康军的上述行为违反了《证券法》第七十七条第一款第一项、第三项的规定，构成《证券法》第二百零三条所述操纵证券市场行为。根据当事人违法行为的事实、性质、情节与社会危害程度，依据《证券法》第二百零三条的规定，我会决定：对朱康军处以300万元的罚款。上述当事人应自收到本处罚决定书之日起15日内，将罚款汇交中国证券监督管理委员会（财政汇缴专户），开户银行：中信银行北京分行营业部，账号：7111010189800000162，由该行直接上缴国库，并将注有当事人名称的付款凭证复印件送中国证券监督管理委员会稽查局备案。当事人如果对本处罚决定不服，可在收到本处罚决定书之日起60日内向中国证券监督管理委员会申请行政复议，也可在收到本处罚决定书之日起6个月内直接向有管辖权的人民法院提起行政诉讼。复议和诉讼期间，上述决定不停止执行。 中国证监会 2019年12月2日 | D11: 43801 | E11: 〔2019〕140
A12: 是 | B12: 是 | C12: 〔2019〕128号 当事人：赵坚，男，1964年2月出生，时任浙江金利华电气股份有限公司（以下简称金利华电）董事长，住址：浙江省东阳市巍山镇巍山社区巍一新成里27号。楼金萍，女，1974年12月出生，住址：浙江省金华市婺城区三江街道宾虹路599号12幢4单元501室。朱攀峰，男，1986年10月出生，住址：浙江省金华市金东区岭下镇诗翁东路28-1号。依据《中华人民共和国证券法》（以下简称《证券法》）的有关规定，我会对赵坚、楼金萍、朱攀峰操纵“金利华电”价格行为进行立案调查、审理，并依法向当事人告知作出行政处罚的事实、理由、依据及当事人依法享有的权利。应当事人赵坚、楼金萍、朱攀峰的申请，我会于2019年9月10日举行听证会，听取当事人及其代理人的陈述和申辩。本案现已调查、审理终结。经查明，当事人存在以下违法事实：一、当事人控制利用证券账户以及交易决策情况2015年10月至2018年4月，金利华电实际控制人、董事长赵坚与前董事会秘书、财务总监楼金萍控制涉案109个证券账户，配资中介朱攀峰控制3个证券账户，共计112个证券账户（以下简称账户组）交易“金利华电”，其中99个证券账户通过配资关系（股票借款融资）由朱攀峰提供，13个证券账户由其他配资中介或亲属朋友提供。账户组的保证金、利息和部分交易资金实际来源于赵坚，结算资金和大部分盈利流向赵坚及其指定的银行账户，少部分流向楼金萍控制的银行账户。账户组的交易由赵坚、楼金萍决策并承担账户盈亏，由楼金萍亲自或者指令他人下单交易，朱攀峰使用其控制的3个证券账户决策下单，参与交易，维持股价。 二、当事人操纵“金利华电”价格的过程2015年10月8日至2018年4月27日，赵坚、楼金萍合谋、朱攀峰参与以拉抬“金利华电”股价获利或者维持“金利华电”价格为目的，控制利用112个证券账户，采用多种手段操纵、影响“金利华电”交易价格和交易量。（一）集中资金优势、持股优势连续买卖，操纵“金利华电”交易价格和交易量2015年10月8日至2018年4月27日共有534个交易日，账户组共交易423天，累计买入成交84,462,254股，买入金额2,697,006,331.30元，累计卖出成交63,359,088股，卖出金额2,106,177,320.29元；持股占总股本比例超过5%的交易日共325天，最高持股占比为22.67%。账户组交易量占该股市场交易总量（以下简称账户组成交占比）的平均比例为14.25%，账户组成交占比最高为87.21%。其中，账户组成交占比大于10%的交易日有176天，成交占比大于20%的交易日有109天，成交占比大于30%的交易日有67天，成交占比大于40%的交易日有38天，成交占比大于50%的交易日有23天。2018年3月26日至4月24日期间共计连续20个交易日，账户组成交占比为33.51%。（二）在控制的证券账户之间进行交易，影响“金利华电”交易价格和交易量2015年10月8日至2018年4月27日，账户组在控制的证券账户之间进行交易的交易日有184天，累计成交数量为26,530,548股。在控制的证券账户之间进行交易占市场成交量比例（简称账户组对倒占比）平均为14.87%，账户组对倒占比最高为84.75%。账户组对倒占比超过10%的交易日有87天，对倒占比超过20%的交易日有51天，对倒占比超过30%的交易日有31天。2018年1月2日至1月29日共计连续20个交易日，账户组在控制的证券账户之间进行交易成交2,863,572股，账户组对倒占比为20.25%。（三）盘中拉抬，影响“金利华电”交易价格和交易量2015年10月8日至2018年4月27日，账户组存在34次盘中拉抬股价行为，平均拉抬股价幅度为3.21%，盘中拉抬股价期间，平均买入成交量占市场总买入成交量的比例为84.86%，且存在反向卖出行为。（四）利用信息优势交易,操纵“金利华电”交易价格和交易量赵坚作为金利华电董事长、实际控制人，筹划、决策金利华电向文化产业转型过程中实施重大资产重组、股权转让等重大事项；并且为维持股价，在2018年2月存在人为控制“金利华电”停牌时点的行为。赵坚、楼金萍利用上述信息优势连续买卖“金利华电”股票，操纵“金利华电”交易价格和交易量。三、当事人操纵“金利华电”价格的结果2015年10月8日至2018年4月27日，“金利华电”价格上涨幅度为44.65%，股价振幅为170.30%。同期创业板指数下跌幅度为13.30%，振幅为64.56%；电气设备行业指数下跌幅度为8.31%，振幅为67.95%。“金利华电”价格涨幅偏离创业板指数走势57.95个百分点，偏离电气设备行业指数走势52.96个百分点；“金利华电”价格振幅偏离创业板指数振幅105.74个百分点，偏离电气设备行业指数振幅102.35个百分点。经测算，截至2018年8月29日，账户组持有“金利华电”7,100股，累计亏损157,433,903.71元。上述违法事实，有证券账户资料、银行账户资料、询问笔录、上市公司公告、交易所相关数据信息等证据证明，足以认定。我会认为，2015年10月8日至2018年4月27日期间，当事人控制账户组交易“金利华电”，集中资金优势、持股优势连续买卖，在控制的证券账户之间进行交易，使用盘中拉抬、利用信息优势等手段操纵、影响“金利华电”交易价格和交易量，账户组共计亏损157,433,903.71元。上述行为违反《证券法》第七十七条第一款第一项、第三项、第四项规定，构成《证券法》第二百零三条所述操纵证券市场的行为。赵坚是账户组的出资、控制、交易决策者，金利华电重大信息的筹划、决策者，是操纵证券市场行为的决策者，在本案中起主要作用，行为恶劣，情节较为严重。楼金萍对账户组交易具有控制决策权，是操纵证券市场行为的组织、决策和实施者，在本案中起主要作用，行为恶劣，情节较为严重。朱攀峰为赵坚、楼金萍提供交易资金、交易场所及设备，在控制的证券账户之间进行交易，维持“金利华电”价格，是操纵证券市场行为的参与者和协助者，在本案中起次要作用，情节严重。在听证过程中，赵坚提出如下申辩意见：第一，赵坚的行为本质系大股东增持，并无操纵证券市场的主观故意，申请不予处罚。其一，账户组持续买入时间长，呈现净买入特征，存在盘中拉抬且反向交易的交易日极少，且申辩人不知晓具体交易细节，操作人员陈某杭存在擅自买卖行为，申辩人行为系大股东增持；其二，没有利用短线交易获利的企图，也没有利用资金、信息优势操纵股价的主观故意。第二，申辩人没有利用信息优势影响“金利华电”交易价格和交易量，没有控制上市公司信息披露。第三，2018年2月5日停牌时点由总经理朱某文决定，申辩人事先并不知情，并且股票停牌及相关信息披露均无违法情形。第四，账户组中大量账户存在不再出借而被迫卖出的情形，应当扣除此类账户的交易，重新计算交易量及交易占比。第五，不应采纳陈某杭询问笔录部分内容。经复核，我会认为：第一，当事人行为系操纵证券市场而非大股东增持，大股东增持有其独特的方法、途径和信息披露方式。其一，账户组在上述期间买入和卖出的天数均超过300天，其交易行为是以集中资金优势、持股优势进行连续买卖为主要特征，最终清仓出货，完成操纵的整个过程，是典型的操纵证券市场行为。其二，当事人利用资金优势、持股优势和信息优势连续买卖“金利华电”，成交占比高、在控制的证券账户之间进行交易持续时间长、交易量大，其操纵“金利华电”的行为混合了多种操纵手法，具有盘中拉抬股价或反向交易，利用资金、信息优势操纵股价的主观故意。第二，赵坚作为金利华电董事长、实际控制人，早已开始筹划金利华电转型，2015年10月至2018年4月，金利华电陆续发布与产业转型相关的重大事项公告，具体包括：2015年，收购杭州信立传媒广告有限公司100%股权；2016年，以43元/股的价格转让赵某及本人合计持有公司14.97%股权给珠海安赐成长股权投资基金企业（有限合伙）；2017年，以40元/股的价格将赵某所持8.55%股权转让给杭州金龙佳沃投资管理合伙企业（有限合伙）；2018年，金利华电收购北京中和德娱文化传媒有限公司（以下简称中和德娱）股权重大资产重组事项。赵坚是上述重大事项的筹划者、参与者或决策者，其在上述重大事项公告前后，存在控制账户组利用信息优势进行连续买卖的行为，操纵“金利华电”交易价格和交易量。第三，2018年1月31至2月2日，“金利华电”股价大幅下跌，为防止账户组爆仓，急需维持股价。2月4日，金利华电总经理朱某文参加中和德娱年会，向中和德娱总裁赵某芳表达了金利华电有收购中和德娱股权的意向，双方仅就交易价格做了简单口头交流，且朱某文未与中和德娱实际控制人赵某俊商谈相关事项，更未与中和德娱达成相关协议，在不具备正当停牌事由的情况下，赵坚决定金利华电停牌。2月5日，金利华电停牌并发布《关于筹划重大事项停牌的公告》，2月26日，“金利华电”复牌，当日股价涨幅为3.39%，账户组交易量占市场交易总量比例为58.86%。赵坚是此重大事项的决策者，控制信息披露的时点。第四，赵坚所谓的“账户被迫卖出”主要通过在控制的证券账户之间进行交易的方式完成，股票所有权并未转移。经测算，交易量及交易占比数据无误。第五，询问笔录作为调查证据之一，需要客观证据予以佐证，陈某杭的询问笔录所述内容与其他证据吻合度高且有相关事实依据，我会充分综合全案证据对本案予以认定，事实清楚、证据充分。楼金萍提出如下申辩意见：对账户组没有控制决策权，未实施操纵证券市场行为，申请不予处罚。其一，仅听从赵坚安排进行资金划转；其二，不决策账户交易，不出资，不承担账户组盈亏，不参与盈利分成。经复核，我会认为：赵坚和楼金萍对账户组具有共同控制和决策权，楼金萍的行为构成操纵市场。其一，根据银行流水、询问笔录等证据，赵坚和楼金萍是账户组的实际控制人。赵坚主要负责提供账户资金、安排部分银行账户隐匿资金线索，负责账户组交易决策；楼金萍主要负责出面对接配资业务和具体事项，安排大部分银行账户隐匿资金线索，并发出买卖指令或者亲自操作部分账户的买卖。其二，账户组部分盈利流向楼金萍个人银行账户并由楼金萍用于个人消费和理财。同时，楼金萍承认利用赵坚提供的资金，通过其亲戚朋友和其他配资中介提供的13个账户买入金利华电，且13个账户的交易决策均由楼金萍本人作出。另外，朱攀峰提供的“张某诚”“陈某”“杨某岗”“任某寿”等4个账户，也由楼金萍实际控制交易。朱攀峰提出如下申辩意见：第一，本人没有与赵坚、楼金萍操纵“金利华电”股价的共同故意。其一，未获证券账户盈利分成，与赵坚、楼金萍也无有关约定；其二，杭州犇马投资管理有限公司（简称犇马公司）业务为配资，不会主动进行配资账户交易，本人按照赵坚指令买卖金利华电股票，没有账户决策权。第二，本人行为系职务行为，应由犇马公司承担责任，本人作为犇马公司负责人承担相应责任。其一，赵坚与犇马公司开展配资业务；其二，业务转账虽使用公司员工个人银行卡，但均纳入公司财务记账；其三，交易资金、交易电脑、交易场所均为犇马公司统一提供。第三，陈某杭负责接收指令，操作配资账户交易，本人作用及责任远小于陈某杭。第四，积极配合调查，应予从轻处罚。经复核，我会认为：第一，2018年1月31至2月2日，“金利华电”股价出现大幅下跌，赵坚、楼金萍急需维持股价，朱攀峰因不能及时配足证券账户，先后于2018年2月1日、2月26日等期间使用本人控制的“诸某富”“谢某中”“徐某良”3个证券账户下单交易，合计买入金额约1,600万元。朱攀峰使用自己控制的证券账户，按照赵坚的指令买入“金利华电”，并为二人提供交易场所、交易设备等帮助，与赵坚、楼金萍共同构成操纵“金利华电”。是否获利不是操纵市场违法行为的构成要件，不影响行为违法性的认定。第二，当事人行为系个人行为，应自负后果。其一，根据犇马公司的工商登记资料和社会保险证明，朱攀峰与犇马公司无任何法律关系，其行为与犇马公司无关。即使朱攀峰与犇马公司有间接联系，配资业务也不属于犇马公司法定经营业务范围，由此产生的系列行为不能归属为单位行为。其二，朱攀峰、张某军等以个人名义与出资方签订相关《借款协议》《融资服务居间协议》，业务转账通过朱攀峰控制的个人银行账户进行，与犇马公司无关。朱攀峰长期从事股票配资业务，知晓赵坚、楼金萍在实施操纵“金利华电”股价的行为，依然为二人提供交易场所和交易设备等帮助，允许陈某杭在其交易场所长期交易，并且为维持股价，参与了交易“金利华电”，与赵坚、楼金萍共同构成操纵“金利华电”。第三，陈某杭仅负责账户交易，没有交易决策权，其积极配合调查并主动提供相关证据和线索，对查清案件事实提供了重大帮助，行为性质及社会危害程度显然低于朱攀峰。第四，我会已经充分考虑朱攀峰在整个操纵市场行为中的作用以及配合调查的相关情况，量罚合理。综上，我会对赵坚、楼金萍、朱攀峰的陈述申辩意见不予采纳。根据当事人违法行为的事实、性质、情节与社会危害程度，依据《证券法》第二百零三条的规定，我会决定：对赵坚、楼金萍、朱攀峰共同操纵证券市场的行为，责令依法处理非法持有的证券，处以300万元的罚款，其中对赵坚处以150万元的罚款，对楼金萍处以120万元的罚款，对朱攀峰处以30万元的罚款。上述当事人应自收到本处罚决定书之日起15日内，将罚款汇交中国证券监督管理委员会（财政汇缴专户），开户银行：中信银行北京分行营业部，账号：7111010189800000162，由该行直接上缴国库，并将注有当事人名称的付款凭证复印件送中国证券监督管理委员会稽查局备案。当事人如果对本处罚决定不服，可在收到本处罚决定书之日起60日内向中国证券监督管理委员会申请行政复议，也可在收到本处罚决定书之日起6个月内直接向有管辖权的人民法院提起行政诉讼。复议和诉讼期间，上述决定不停止执行。 中国证监会 2019年11月18日 | D12: 43787 | E12: 〔2019〕128
A13: 是 | B13: 否 | C13: 〔2019〕125号 当事人：吕乐，男，1981年8月出生，时任深圳嘉谟资本管理有限公司（以下简称深圳嘉谟）执行董事、总经理，住址：江苏省南京市建邺区。陈志龙，男，1976年6月出生，住址：北京市海淀区复兴路。依据《中华人民共和国证券法》（以下简称《证券法》）的有关规定，我会对吕乐、陈志龙操纵证券市场行为进行了立案调查、审理，并依法向当事人告知了作出行政处罚的事实、理由、依据及当事人依法享有的权利。当事人陈志龙进行了陈述和申辩，但未要求听证。应当事人吕乐的要求，我会于2019年2月25日举行了听证会，听取了吕乐及其代理人的陈述和申辩。本案现已调查、审理终结。经查明，吕乐、陈志龙存在以下违法事实：一、 吕乐、陈志龙控制使用有关证券账户情况吕乐为深圳嘉谟实际控制人、执行董事、总经理，“吕乐”中信证券账户、“吕乐”南京证券账户、“吕乐”华泰证券账户、“吕乐”海通证券账户、“吕乐”海通国际证券沪港通账户、“吕乐”中泰国际证券沪港通账户、“陶某琴”华泰证券账户、“陶某琴”南京证券账户、“嘉谟动量证券投资基金”中信证券账户、“嘉谟进取1期证券投资基金”招商证券账户、“嘉谟进取3期证券投资基金”招商证券账户、“嘉谟?堂宋证券投资基金”招商证券账户、“嘉谟4号证券投资基金”招商证券账户、“嘉谟7号证券投资基金”中信证券账户等14个账户（以下简称“吕乐”相关证券账户）由吕乐控制，上述账户资金主要来源于吕乐家庭资金，各账户之间存在频繁资金互转，账户交易IP、MAC地址存在大量重合。陈志龙控制“叶某昌”华泰证券账户。叶某昌和瞿某经陈志龙介绍合作理财，叶某昌出资3500万元、瞿某提供525万元的保证金存入“叶某昌”证券账户，由瞿某全权管理理财资金。双方资金划入后，瞿某将“叶某昌”证券账户交由陈志龙决策交易。二、吕乐、陈志龙具有合谋操纵证券价格的主观故意吕乐控制“吕乐”相关证券账户以及陈志龙控制“叶某昌”华泰证券账户，吕乐单独或者与陈志龙合谋利用资金优势，大量买入、连续交易“菲达环保”“人民网”“东风科技”3只股票，操纵股价并反向卖出获利，具有明显的操纵证券价格的主观故意。吕乐与陈志龙是好友，平时见面较多，经常在一起沟通股票买卖、交易手法和策略以及近期买卖股票的情况，吕乐向陈志龙教授了“大单买入，批量卖出”的操作手法。操纵期间，吕乐向陈志龙推荐了“菲达环保”，两人频繁联系、相互交流交易和持仓情况，吕乐、陈志龙具有合谋操纵证券价格的主观故意。三、吕乐、陈志龙操纵证券价格情况2015年12月至2016年至7月，吕乐单独或者与陈志龙合谋利用资金优势，通过连续买卖操纵“菲达环保”等3只股票价格，此外，吕乐还通过在自己实际控制的账户之间交易“菲达环保”操纵股价。具体操纵情况如下：2015年12月17日至22日，吕乐通过分多笔连续买卖和在自己实际控制的账户之间交易股票的方式，操纵“菲达环保”股价，获利5,937,356.93元。2016年4月27日、28日，吕乐通过分多笔连续买卖方式操纵“菲达环保”股价，获利1,648,655.34元。2016年6月2日、3日、6月7日、8日，吕乐通过分多笔连续买卖方式操纵“东风科技”股价，获利810,035.98元。2016年6月6日至15日，吕乐通过分多笔连续买卖方式操纵“菲达环保”股价，获利894,580.42元。2016年6月17日至23日，吕乐通过分多笔连续买卖方式操纵“人民网”股价，获利1,957,580.10元。2016年6月27、28日，吕乐、陈志龙通过分多笔连续买卖方式操纵“菲达环保”，获利594,628.17元。其中，吕乐获利568,618.89元，陈志龙获利26,009.28元。2016年7月11日、12日、7月14日至19日，吕乐、陈志龙通过分多笔连续买卖方式操纵“菲达环保”股价，获利3,258,082.19元。其中吕乐获利3,258,082.19元，陈志龙获利0元。上述操纵行为，吕乐获利合计15,074,909.85元，陈志龙获利合计26,009.28元。上述违法事实，有“吕乐”“陶某琴”“叶某昌”等证券账户开户资料、账户委托记录及交易记录，吕乐、陶某琴、叶某昌等人询问笔录，上海证券交易所相关证券账户交易资料等证据证明，足以认定。吕乐的上述行为违反了《证券法》第七十七条第一款第一项、第三项的规定，陈志龙的上述行为违反了《证券法》第七十七条第一款第一项的规定，构成《证券法》第二百零三条所述的操纵证券市场行为。在听证过程中，吕乐及其代理人提出如下申辩意见：其一，吕乐不具有资金优势、持股优势或者信息优势；其二，吕乐部分交易造成影响证券交易价格或者证券交易量的结果很小，属于股票价格自然波动，不符合操纵行为的“结果要件”；其三，操纵影响消除后申辩人以市场价卖出余券的盈利不应计算在违法所得范围内，证券交易手续费的计算不准确；其四，吕乐系初犯并配合调查，且已摒弃可能触犯法律法规的投资策略，量罚幅度上应从轻或者减轻处罚。陈志龙在其申辩材料中提出如下申辩意见：其一，陈志龙不具有操纵股价的主观意愿和需要；其二，陈志龙不具有资金优势；其三，将陈志龙的交易数据与吕乐的交易数据混在一起属于认定事实不清；其四，相关交易并未严重影响股票价格、交易量，交易与操纵股价之间缺乏必然的逻辑关系。综上，吕乐请求不予或从轻、减轻行政处罚，陈志龙请求不予行政处罚。经复核，我会认为：第一，吕乐与陈志龙二人交易“菲达环保”属合谋操纵，有关资金优势、相关交易行为应合并分析。从二人的陈述来看，吕乐承认其在交易涉案3只股票时，股票卖出过程中发现价格下跌，会大量买入以拉升股价，在收盘时发现价格低于持仓成本时买入，目的是拉升价格。二人均承认陈志龙向吕乐学习如何操作买卖股票，吕乐向陈志龙推荐了“菲达环保”及交易策略、二人均交易了案涉股票且在交易过程中有沟通。从二人的交易行为来看，二人交易涉案股票时间上大体一致，手法基本相同，总体呈现买入时单笔大单买入、卖出时分多笔批量卖出的特点，交易过程中有配合，尾市阶段交替拉抬股价，对方卖出过程中有拉抬或维持股价的配合行为。综上，吕乐与陈志龙二人交易“菲达环保”属合谋操纵，有关资金优势、相关交易行为应合并分析。第二，吕乐及陈志龙具有资金优势。经对依法调取的交易数据分析，日成交占比等指标可以证明吕乐单独或与陈志龙共同具有资金优势。2016年6月2日至6月3日、6月7日至6月8日吕乐交易“东风科技”期间，6月2日、3日、7日，吕乐单日买入成交占比分别为31.66%、20.75%、15.24%。2016年6月27日至6月28日、2016年7月11日至7月12日、7月14日至7月19日吕乐、陈志龙交易“菲达环保”期间，7月11日、12日、14日、18日，吕乐、陈志龙单日买入成交占比分别为17.19%、10.45%、16.46%、26.13%。吕乐、陈志龙在各操纵期间内，均存在单日买入成交占比10%以上的情形。从单日买入成交占比数据可知，吕乐单独或与陈志龙共同在交易上述股票期间具有资金优势。第三，相关交易行为已对股价造成影响，构成操纵证券市场。当事人认为其交易行为对股价影响较小，部分交易所造成的影响系正常市场波动。证据显示，本案当事人通过分多笔连续大量买入的方式拉升股价，而后反向卖出获利，此种交易方式带有明显的操纵股价的主观意图，吕乐也承认存在大量买入以拉升股价的行为，相关行为客观上对股价造成了影响，扰乱了正常交易秩序。同时，吕乐还通过在自己实际控制的账户之间交易“菲达环保”操纵股价。此外，本案属于短线操纵，股价涨幅多数未超过3%，甚至不到2%，但因短线操纵所需资金量小，资金周转率高等特点，虽然股价上涨有限，但获利可观，不能因其涨幅较小而无视其危害性。此外，对当事人提到的个别涨幅不足1%的情形，应纳入其整个操纵行为来看待，不应单独割裂分析。2016年6月17日14:05:28至14:59:59，吕乐分98笔以16.10元至16.43元买入3,658,793股“人民网”，金额59,546,956.07元。买成交量占市场买成交量的50.63%。“人民网”从16.09元上涨至16.40元，上涨0.31元，涨幅1.94%。在6月17日已将股价拉抬上涨1.94%的情况下，6月20日9:31:46至9:35:43的多笔买入具有拉抬股价的性质，但主要是其卖出过程中的为避免股价下跌而采取的维持股价的行为，是其操纵的一部分，不应因涨幅小而排除在操纵之外。第四，关于违法所得计算问题，我会已采纳当事人的申辩意见，在盈利计算中将操纵行为影响消除后卖出余券的所得予以扣除，根据当事人提供的证据对交易费金额进行调整，并对违法所得重新计算。第五，关于当事人从轻、减轻或免于处罚的请求，我会已综合考虑当事人的违法情节、配合调查等表现情况予以量罚。综上，我会对吕乐、陈志龙的申辩意见予以部分采纳。根据当事人违法行为的事实、性质、情节与社会危害程度，依据《证券法》第二百零三条，我会决定：一、没收吕乐违法所得15,074,909.85元，并处以30,149,819.70元罚款；二、没收陈志龙违法所得26,009.28元，并处以52,018.56元罚款。上述当事人应自收到本处罚决定书之日起15日内，将罚没款汇交中国证券监督管理委员会（财政汇缴专户），开户银行：中信银行北京分行营业部，账号：7111010189800000162，由该行直接上缴国库，并将注有当事人名称的付款凭证复印件送中国证券监督管理委员会稽查局备案。当事人如果对本处罚决定不服，可在收到本处罚决定书之日起60日内向中国证券监督管理委员会申请行政复议，也可在收到本处罚决定书之日起6个月内直接向有管辖权的人民法院提起行政诉讼。复议和诉讼期间，上述决定不停止执行。 中国证监会 2019年11月14日 | D13: 43783 | E13: 〔2019〕125
A14: 是 | B14: 否 | C14: 〔2019〕113号 当事人：刘晓闽，男，1981年1月出生，住址：福建省福州市晋安区。依据《中华人民共和国证券法》（以下简称《证券法》）的有关规定，我会对刘晓闽操纵“日月股份”的行为进行了立案调查、审理，并依法向当事人告知了作出行政处罚的事实、理由、依据及当事人依法享有的权利。当事人未提出陈述、申辩意见，也未要求听证。本案现已调查、审理终结。经查明，当事人存在以下违法事实：一、当事人控制账户情况根据梁某超指认、配资中介指认、出借方指认、资金来源或去向、交易地址、合同资料、交易趋同等证据，可以认定在2017年2月14日至3月10日期间，当事人控制陈某1、宋某梅、魏某雪、修某梅、邹某文、王某1、徐某芳、史某仙、冯某林、吕某扬、孙某霞、俞某、严某美、于某花、邹某、许某皓、吴某强、周某清、吴某晴、徐某娟、朱某霞、孙某辉、吴某杰、綦某凯、张某、朱某锋、李某、王某2、王某艳、徐某壮、瞿某波、瞿某玲、赵某世、宫某、罗某、沈某花、孟某珍、庄某、何某勇、王某杰、戴某萍、金某刚、王某明、闫某华、俞某英、徐某素、陈某2、刘某、黄某等49人名义下的53个证券账户（以下简称账户组）进行证券交易。二、当事人通过多种手段操纵“日月股份”2017年2月14日至3月10日期间，当事人控制账户组采用集中资金优势、持股优势连续买卖，在自己实际控制的账户间交易等手段操纵“日月股份”，累计买入36,996,410股，成交金额1,966,472,475元；累计卖出36,996,410股，成交金额2,027,016,764元，获利57,255,924.06元。 （一）集中资金优势、持股优势连续买卖在2017年2月14日至3月10日期间，账户组集中资金优势、持股优势连续买卖“日月股份”。在19个交易日中，账户组在17个交易日有交易“日月股份”的行为，其中：账户组买成交量占市场买成交量排名第一的有14个交易日、排名第二的有1个交易日。账户组买入成交量占市场买入成交量的比重超过10%的有10个交易日，超过20%的有9个交易日，超过30%的有4个交易日，于2017年3月2日达到最高，为52.82%。账户组卖成交量占市场卖成交量排名第一的有12个交易日、排名第二的有1个交易日。账户组卖出成交量占市场卖出成交量的比重超过10%的有8个交易日，超过20%的有3个交易日，超过30%的有2个交易日，于2017年3月3日达到最高，为55.10%。账户组买卖成交量占市场买卖成交量超过60%的有1天，50%至60%的有1天，40%至50%的有2天，30%至40%的有6天，10%至20%的有2天，于2017年3月3日达到最高，为61.25%。账户组实际控制的流通股份数占“日月股份”当日实际流通股份总数比（以下简称持仓占比）超过30%的有3天，20%到30%的有3天，10%到20%的有3天，5%到10%的有1天，在2017年3月2日持仓量达到峰值，持仓占比为37.86%。 账户组申买价格高于其申报前一笔市场成交价格，且高于其申报前一刻卖委托第一档价格的委托的申买股数占其总申买股数的57.19%，高出幅度最大为11.72元；申买价格高于其申报前一刻卖委托第五档价格的委托的申买股数占其总申买股数的26.83%，高出幅度最大为11.65元；申买数量高于其申报前一刻市场第一档卖出申报总量的委托的申买股数占其总申买股数的79.87%；申买数量高于其申报前一刻市场前五档卖出申报总量的委托申买股数占其总申买股数的63%，高出幅度最大为前一档卖出申报总量的3500倍，前五档卖出申报总量的285.72倍；申买价格高于其申报前一刻卖委托第五档价格，且委托申买量高于其申报前一刻市场前五档卖出申报总量的委托申买股数占其总申买股数的24.20%。 （二）在自己实际控制的账户间交易账户组在交易“日月股份”的17个交易日中有11个交易日存在在自己实际控制的账户间交易（以下简称对倒交易）的情况，对倒交易数量8,686,211股，对倒交易金额494,916,301.3元，其中对倒交易数量占当日账户组成交总量的比例超过5%的有4个交易日，超过10%的有3个交易日，超过20%的有2个交易日，于2017年3月3日达到最高，为34.04%。2017年2月14日至3月10日期间，日月股份股价由2月14日前一日收盘价39.36元最高上涨至3月2日收盘价65.07元，累计上涨65.32%，同期上证指数由3216.84下跌至3212.76，累计下跌0.13%，偏离度高达65.2%。其后账户组清仓卖出，日月股份股价由3月2日收盘价65.07元最低下跌至3月9日收盘价49.36元，累计下跌24.14%，同期上证指数由3230.03下跌至3216.75，累计下跌0.41%，偏离度高达23.73%。以上事实有相关证券账户开户资料、资金流水、委托交易流水、相关人员询问笔录、相关合同资料、交易所提供的交易数据等证据证明，足以认定。我会认为，当事人的上述行为违反了《证券法》第七十七条“禁止任何人以下列手段操纵证券市场：（一）单独或者通过合谋，集中资金优势、持股优势或者利用信息优势联合或者连续买卖，操纵证券交易价格或者证券交易量；……（三）在自己实际控制的账户之间进行证券交易，影响证券交易价格或者证券交易量”的规定，构成了《证券法》第二百零三条所述操纵证券市场的行为。根据当事人违法行为的事实、性质、情节与社会危害程度，依据《证券法》第二百零三条的规定，我会决定：没收当事人违法所得57,255,924.06元，并处以57,255,924.06元的罚款。上述当事人应自收到本处罚决定书之日起15日内，将罚没款汇交中国证券监督管理委员会（财政汇缴专户），开户银行：中信银行北京分行营业部，账号：7111010189800000162，由该行直接上缴国库，并将注有当事人名称的付款凭证复印件送中国证券监督管理委员会稽查局备案。当事人如果对本处罚决定不服，可在收到本处罚决定书之日起60日内向中国证券监督管理委员会申请行政复议，也可在收到本处罚决定书之日起6个月内直接向有管辖权的人民法院提起行政诉讼。复议和诉讼期间，上述决定不停止执行。 中国证监会 2019年10月31日 | D14: 43769 | E14: 〔2019〕113
A15: 是 | B15: 否 | C15: 〔2019〕120号 当事人：天马轴承集团股份有限公司（以下简称天马股份），住所：北京市海淀区。徐茂栋，男，1967年12月出生，天马股份实际控制人、董事，时任天马股份董事长、财务总监、董事会秘书，住址：山东省日照市东港区。傅淼，男，1970年9月出生，时任天马股份董事长、董事，住址：山东省日照市东港区。陶振武，男，1979年7月出生，时任天马股份总经理、董事、财务总监，住址：北京市西城区。韦京汉，女，1968年4月出生，时任天马股份董事，住址：广东省深圳市南山区。杨利军，男，1977年8月出生，时任天马股份董事，住址：河南省郑州市中原区。张志成，男，1982年1月出生，时任天马股份董事，住址：北京市海淀区。马兴法，男，1962年11月出生，时任天马股份法定代表人、董事长、董事会秘书，住址：浙江省杭州市拱墅区。刘艳秋，女，1972年10月出生，时任天马股份财务部总经理，住址：吉林省长春市南关区。岳基伟，男，1987年1月出生，时任天马股份监事，住址：山东省日照市岚山区。胡亮，男，1980年4月出生，时任天马股份监事会主席，住址：山东省日照市东港区。郭松波，男，1972年12月出生，时任天马股份监事，住址：北京市崇文区。赵华，男，1968年5月出生，时任天马股份独立董事，住址：山东省日照市东港区。丁海胜，男，1967年7月出生，时任天马股份独立董事，住址：山东省济南市历下区。依据《中华人民共和国证券法》（以下简称《证券法》）的有关规定，我会对天马股份信息披露违法违规行为进行了立案调查、审理，并依法向当事人告知了作出行政处罚的事实、理由、依据及当事人依法享有的权利。当事人天马股份、傅淼、陶振武、郭松波提出陈述、申辩意见并要求听证。当事人韦京汉进行了陈述和申辩，但未要求听证。其余当事人未提出陈述、申辩意见，也未要求听证。据此，我会2019年8月2日举行了听证会，听取了当事人及其代理人的陈述和申辩。本案现已调查、审理终结。经查明，天马股份存在以下违法事实：一、徐茂栋及其控制的企业与天马股份存在关联关系徐茂栋持有霍尔果斯食乐淘创业投资有限公司（以下简称食乐淘）99%股份，徐某持股1%。食乐淘持有北京星河世界集团有限公司（以下简称星河世界）100%股份，徐茂栋为星河世界法定代表人、执行董事、经理。星河世界持有喀什星河创业投资有限公司（以下简称喀什星河）100%股份。喀什星河为星河互联集团有限公司（以下简称星河互联）第二大股东，徐茂栋控制的亿德宝（北京）科技发展有限责任公司（以下简称亿德宝）为星河互联第一大股东。徐茂栋是天马股份实际控制人，喀什耀灼创业投资有限公司（以下简称喀什耀灼）是天马股份全资子公司。根据《中华人民共和国公司法》第二百一十六条第四项和《上市公司信息披露管理办法》第七十一条第三项的规定，徐茂栋及其控制的企业是天马股份的关联人和关联法人，天马股份及其控制的企业与徐茂栋控制的企业之间的交易构成关联交易。 二、天马股份未真实披露喀什星河收购天马股份的资金来源2016年12月3日，天马股份发布对深圳证券交易所的回复公告，称喀什星河收购天马股份的资金中有15亿元来自兄弟企业星河互联的往来款，资金主要来源于星河互联的股东投入及经营所获资金，无约定的资金成本，无固定期限和担保措施。但据调查，该15亿元实际来自星河互联向信托公司的借款，星河互联获得15亿元借款后，即支付给霍尔果斯天马创业投资集团有限公司（原名天马控股集团有限公司，以下简称天马创业，为天马股份原第一大股东），同时天马创业将该笔款项质押，作为对星河互联借款的担保。借款到期后，星河互联未还款，天马创业质押的15亿元被用于归还了星河互联的借款。天马股份对深圳证券交易所的回复公告存在虚假记载，违反《证券法》第六十三条的规定，构成《证券法》第一百九十三条第一款所述行为。三、天马股份未按规定披露徐茂栋及其控制的企业非经营性占用资金及关联交易情况等2017年9月1日，天马股份董事会决议通过两项议题，一是同意天马股份以存货质押向安徽金丰典当有限公司申请的贷款提供担保，二是本次借款相关事项的确认。天马股份董事傅淼、陶振武、韦京汉、杨利军、张志成出席并签字确认。同日，天马股份与该典当公司签订5000万元借款合同，天马股份于当日出具放款委托函，该典当公司将5000万元转入食乐淘账户。2017年9月27日，天马股份与北京祥云小额贷款有限责任公司签订7000万元借款合同，约定收款账户为星河世界，徐茂栋和星河世界提供担保。同日，该贷款公司委托北京雪云投资管理有限公司将7000万元转入星河世界账户。2017年10月27日，天马股份与德清县中小企业金融服务中心有限公司（以下简称德清中小企业服务中心）签订1亿元借款合同，合同约定收款账户为食乐淘，同时喀什星河、浙江步森服饰股份有限公司、星河世界、星河互联、食乐淘、徐茂栋提供担保。2017年10月30日和11月2日，德清中小企业服务中心将1亿元转入食乐淘账户。2017年12月19日，喀什耀灼将1.1亿元通过北京朔赢科技有限公司（以下简称北京朔赢）和北京卓久信息技术有限公司（以下简称北京卓久）转入徐茂栋控制的食乐淘账户。2017年12月27日和28日，负责天马股份融资工作的陈某波、天马股份财务部总经理刘艳秋、北京星河智能科技有限公司（以下简称星河智能）出纳张某、星河互联高级财务经理张某峰、星河互联出纳付某雪、天马创业会计管某超、深圳市东方博裕贸易有限公司（以下简称东方博裕）江某俊等人按照徐茂栋指示，通过东方博裕、北京朔赢、北京卓久、中易金经实业发展有限公司（以下简称中易金经）、亿德宝等公司多道划转，将天马股份5.66亿元转入星河互联、喀什耀灼等公司账户，用于归还徐茂栋及其控制企业的借款。2018年1月2日，喀什耀灼将1亿元转入东方博裕账户，其中7000万元用于归还徐茂栋控制的企业向江某俊的借款，3000万元用于支付徐茂栋给罗某新的款项。东方博裕为资金拆借平台，没有实际贸易业务。2018年2、3月份，为应对会计师事务所审计，天马股份与东方博裕签订钢材采购合同，并伪造了部分东方博裕对外采购钢材合同。2018年2月5日，天马股份与胡某签订借款合同，约定天马股份向胡某借款2500万元，收款账户为食乐淘，同时喀什星河、星河世界、星河互联、徐茂栋、陈某波提供担保。胡某委托他人于2018年2月6日将2500万转入食乐淘账户。天马股份未按照《证券法》第六十六条第六项、《公开发行证券的公司信息披露内容与格式准则第2号——年度报告的内容与格式（2017年修订）》（以下简称年报准则）第三十一条、第四十条第四项的规定，在2017年年度报告中披露徐茂栋及其控制的企业非经营性占用天马股份8.96亿元和关联交易的情况，构成《证券法》第一百九十三条第一款所述行为。此外，调查期间查明的10.21亿元被占用的资金中，有2.45亿元是通过天马股份对外签订借款合同，实际由徐茂栋控制的企业收款的方式形成占用，天马股份未按照《证券法》第六十七条第二款第三项、第四项的规定履行临时报告披露义务，构成《证券法》第一百九十三条第一款所述行为。并且，天马股份未将上述2.45亿元借款中的2.2亿元计入2017年年度报告，未将1.2亿元计入2017年第三季度报告，违反了《证券法》第六十三条的规定，构成《证券法》第一百九十三条第一款所述行为。四、天马股份为徐茂栋控制的企业借款担保2亿元，天马股份未按规定披露2018年1月22日，天马股份董事会决议同意天马股份为星河世界向北京佳隆房地产开发集团有限公司的借款提供连带责任担保，表决同意董事签名为：傅淼、陶振武、杨利军、韦京汉、张志成。同日，天马股份与该地产公司签订保证合同，为星河世界的2亿元借款提供担保。天马股份未按照《证券法》第六十七条第二款第十二项、《上市公司信息披露管理办法》第三十条第二款第十七项的规定履行临时报告披露义务。五、天马股份成立基金以收购徐茂栋控制的资产，天马股份未按规定披露2017年1月26日，天马股份公告与浙江诚合资产管理有限公司合作设立并购基金，本次对外投资的资金来源为天马股份自有资金。3月18日，天马股份公告杭州天马诚合投资合伙企业（有限合伙）（以下简称诚合基金）完成工商注册登记。2018年4月28日，天马股份公告2017年5月22日诚合基金与徐茂栋控制的企业霍尔果斯市微创之星创业投资有限公司（以下简称微创之星）签署了股权转让协议，微创之星以16.61亿元转让喀什诚合基石创业投资有限公司（以下简称喀什基石）99.99%股权给诚合基金，追认此交易为关联交易，并认定天马股份对诚合基金形成控制，诚合基金纳入天马股份合并范围。据调查，诚合基金的优先级资金来源为浙商银行，浙商银行通过浙商证券资产管理有限公司设立资管计划，资管计划作为诚合基金优先级LP实缴资金11.63亿元，并明确资金用途为收购徐茂栋控制的持股平台喀什星河互联创业投资有限公司（后改名为喀什基石），底层资产为57家互联网公司，优先级份额以年化7.2%收取利息。天马股份对浙商银行优先级份额承担远期收购义务和差额补足义务，星河世界、徐茂栋及其配偶承担连带责任保证。天马股份认购诚合基金劣后级出资5.01亿元，其中2.23亿元来自中信资本（深圳）资产管理有限公司通过招商银行的委托贷款，并非天马股份自有资金。根据《企业会计准则第33号——合并财务报表（2014年修订）》第七条、第八条规定，天马股份作为诚合基金的唯一劣后级有限合伙人，实际控制诚合基金，应将诚合基金纳入合并范围，诚合基金是天马股份控股子公司，收购喀什基石构成天马股份的关联交易。天马股份2017年半年度报告、第三季度报告未将诚合基金纳入合并，存在虚假记载。对2017年半年度报告的主要影响为虚减资产总额、虚减负债总额均为11.63亿元，虚减金额占期末实际资产总额、负债总额的比例分别为14.84%、37.46%。对2017年第三季度报告的主要影响为虚减资产总额、虚减负债总额均为11.63亿元，虚减金额占期末实际资产总额、负债总额的比例分别为12.77%、32.02%，同时导致2017年第三季度虚减财务费用21,392,576元，虚增净利润16,044,432元，调整后净利润为-13,854,048.6元。并且，天马股份关于诚合基金资金来源的临时公告存在虚假记载。前述行为违反《证券法》第六十三条的规定，构成《证券法》第一百九十三条第一款所述行为。此外，天马股份未按照《证券法》第六十七条第二款第二项的规定，及时披露诚合基金收购喀什基石事项，构成《证券法》第一百九十三条第一款所述行为。上述违法事实，有相关合同、财务账套、银行流水、相关公告、定期报告、询问笔录、情况说明等证据证明，足以认定。徐茂栋是天马股份实际控制人，其知悉喀什星河收购天马股份的真实资金来源，并且指使他人实施非经营性占用天马股份资金、利用天马股份为其控制的企业担保、利用天马股份成立合伙企业收购其控制的资产等事项。徐茂栋是天马股份信息披露违法违规行为直接负责的主管人员。傅淼时任天马股份董事长、董事，陶振武时任天马股份总经理、董事、财务总监，两人知悉天马股份部分借款事项并在借款文件上签字，两人知悉天马股份为徐茂栋控制的企业担保事项并在相关董事会决议上签字同意，两人知悉天马股份成立并购基金收购徐茂栋资产的事项，两人多次在审议相关定期报告的决议上签字确认，是天马股份信息披露违法违规行为直接负责的主管人员。无证据表明当事人中，其他董事、监事、高级管理人员和相关部门负责人在上述事项中尽到勤勉尽责的法定义务。根据本案相关合同、审议涉案定期报告的会议决议、当事人职务、任职年限、涉案程度和勤勉尽责情况等，对天马股份上述违法行为，徐茂栋、傅淼、陶振武是直接负责的主管人员，韦京汉、杨利军、张志成、马兴法、刘艳秋、胡亮、岳基伟、郭松波、赵华、丁海胜是其他直接责任人员。天马股份董事、监事、高级管理人员违反《证券法》第六十八条的规定，构成《证券法》第一百九十三条第一款所述行为。同时，徐茂栋作为天马股份实际控制人，其行为构成《证券法》第一百九十三条第三款所述行为。天马股份及其代理人在申辩材料中提出：第一，喀什星河是收购天马股份的资金来源的信息披露义务主体，天马股份不应对喀什星河的信息披露违规行为承担责任。第二，天马股份未按规定披露关联交易、未按规定披露诚合基金收购喀什基石、违规担保、违规借款等行为均系控股股东和实际控制人操纵导致，天马股份非刻意隐瞒，没有主观恶意。第三，天马股份已全面核查并纠正，确认违规行为造成损失的金额为对控股股东及实际控制人的债权，由控股股东、实际控制人及相关方履行偿还义务，积极主动消除和减轻危害后果。第四，天马股份现任管理层积极挽回损失，尽力消除影响。第五，天马股份具备从轻、减轻或免予处罚的情形。傅淼及其代理人在申辩材料中提出：第一，傅淼实为天马股份挂名董事，其工作重心实为在天马股份体系外为其筛选优质投资标的，天马股份董事会是徐茂栋个人经营决策活动的工具，傅淼在徐茂栋指使下签署相关文件。第二，天马股份发布对深圳证券交易所的回复公告时傅淼未担任董事。第三，傅淼仅知悉天马股份的部分对外借款和担保事项并签字，对星河世界收款行为以及徐茂栋的其他安排不知情。第四，傅淼作为挂名董事未参与有关诚合基金合并问题及关联交易的讨论，未合并是相关人员对会计准则的理解偏差。第五，傅淼与徐茂栋合作多年，对其充分信任，同时傅淼认可陶振武的专业能力和职业素养，对其也十分信任。第六，天马股份被调查后，傅淼积极协调各方资源，消除信息披露违法违规对天马股份的不利影响，符合从轻减轻或免予处罚的规定。陶振武在申辩材料中提出：第一，陶振武不知悉天马股份向安徽金丰典当有限公司借款5000万元的事项，未参与董事会决策，未在董事会决议上签字。第二，陶振武在天马股份为星河世界2亿元借款提供担保的董事会决议签字系受徐茂栋胁迫，并非其本人真实意愿。第三，诚合基金成立以及收购行为发生时陶振武未入职天马股份。第四，天马股份被立案调查前，陶振武曾主动前往监管机构反映徐茂栋和天马股份的潜在信息披露违法违规行为，天马股份被调查后其积极配合调查，维护天马股份稳定，直至新任管理层到岗，并且其及时制止徐茂栋要求天马股份为其关联方付款的行为，使天马股份未遭受进一步损失。韦京汉在申辩材料中提出：第一，韦京汉只负责天马股份的宣传推广工作，在其职责范围内，未出现违法违规情况。第二，其没有接受过天马股份董事的专业培训，但曾多次提醒、建议天马股份应遵守法律法规。第三，董事会决议签署以及相关信息披露时，经办人不提供完整真实信息，其曾多次索要资料并询问详情，但被经办人欺骗，且由于相关事项不在其职责范围内其无权过问。第四，其未在天马股份领取报酬。申请免予处罚。郭松波在申辩材料中提出：第一，《行政处罚及市场禁入事先告知书》（以下简称《告知书》）认定事实均发生在郭松波担任监事之前。第二，其担任监事后，努力促成天马股份及时发布相关公告，并积极参与年报审计讨论，在监事会上对审计意见投赞成票。第三，其担任监事至审计报告发布仅19个工作日，其他大部分责任人任职时间可覆盖违法事项发生时段，对其处罚有失公允。对于天马股份的申辩意见，经复核，我会认为：第一，上市公司依法披露的信息，必须真实、准确、完整，不得有虚假记载、误导性陈述或者重大遗漏。天马股份在信息披露过程中存在虚假记载和重大遗漏，天马股份是信息披露违法违规的责任主体。第二，天马股份已公告撤销星河智能对广州星河正泽股权投资管理合伙企业（有限合伙）（以下简称星河正泽）的出资，撤销星河正泽收购北京星河空间科技集团有限公司的交易，将星河智能出资享有的收益权转让与喀什星河，尚未收回的投资资金由喀什星河、徐茂栋及徐州睦德信息科技有限公司承诺共同履行足额补偿之义务，基于此，我会不再认定天马股份未按规定披露星河正泽的收购事项以及《告知书》认定的重大资产重组事项。第三，我会已关注到天马股份董事会新任成员及管理层实施的核查和部分代偿资金等行为，但徐茂栋及其控制的企业非经营性占用天马股份资金金额巨大，2017年年度报告被出具无法表示意见后连续多日跌停，严重损害投资者利益，且《告知书》认定了多项信息披露违法违规事项，对其量罚是综合考虑了其违法情节、社会危害程度、代偿行为后做出的，量罚适当、公平合理。对于上述责任人的申辩意见，我会认为：第一，上市公司董事、监事、高级管理人员对上市公司信息披露的真实性、准确性、完整性等负有法定责任，上市公司董事、监事、高级管理人员应具备公司管理所需的专业知识，主动了解公司的经营和财务等状况，基于自己的判断独立履行职责，负有合理、审慎的注意义务和质询义务。不知情、未参与、未领取报酬、任职时间短、未实际履职等均不能成为免责理由。第二，天马股份2017年年度报告被审计机构出具无法表示意见的审计报告，天马股份的相关董事、监事和高级管理人员没有勤勉尽责地进行核查，在年度报告的书面确认意见和书面审核意见上签字确认，并保证前述报告内容的真实、准确、完整。我会已查明天马股份2017年年度报告存在未披露非经营性占用资金及关联交易，未计入2.2亿元借款等事项，同时查明天马股份2017年半年度报告、第三季度报告、以及临时报告存在虚假记载、未及时披露相关信息等行为，天马股份相关董事、监事和高级管理人员没有相应勤勉尽责的表现。第三，有责任人提出本案部分违法事实发生时其尚未入职、曾向监管机构反映天马股份信息披露违法违规行为、以及积极消除不利影响或阻止天马股份的进一步损失等，我会已关注到相关责任人的上述情况。本案涉及多项违法事实且严重损害投资者利益，我会已综合考虑相关责任人的任职年限、岗位职责、涉案程度、勤勉尽责情况、后续采取的措施等，对各责任人量罚适当。根据当事人违法行为的事实、性质、情节与社会危害程度，依据《证券法》第一百九十三条第一款、第三款的规定，我会决定：一、对天马轴承集团股份有限公司责令改正、给予警告，并处以60万元罚款；二、对徐茂栋给予警告，并处以90万元罚款，其中作为直接负责的主管人员罚款30万元，作为实际控制人罚款60万元；三、对傅淼、陶振武给予警告，并分别处以30万元罚款；四、对韦京汉、杨利军、张志成给予警告，并分别处以20万元罚款；五、对马兴法、刘艳秋给予警告，并分别处以5万元罚款；六、对丁海胜、赵华、胡亮、岳基伟、郭松波给予警告，并分别处以3万元罚款。上述当事人应自收到本处罚决定书之日起15日内，将罚款汇交中国证券监督管理委员会（财政汇缴专户），开户银行：中信银行北京分行营业部，账号：7111010189800000162，由该行直接上缴国库，并将注有当事人名称的付款凭证复印件送中国证券监督管理委员会稽查局备案。当事人如果对本处罚决定不服，可在收到本处罚决定书之日起60日内向中国证券监督管理委员会申请行政复议，也可在收到本处罚决定书之日起6个月内直接向有管辖权的人民法院提起行政诉讼。复议和诉讼期间，上述决定不停止执行。 中国证监会 2019年10月31日 | D15: 43769 | E15: 〔2019〕120
A16: 是 | B16: 是 | C16: 〔2019〕108号 当事人：叶熙正，男，1966年3月出生，住址：天津市红桥区芥园道明华里。依据《中华人民共和国证券法》（以下简称《证券法》）的有关规定，我会对叶熙正操纵吉林化纤股份有限公司（以下简称吉林化纤）股票一案进行了立案调查、审理，并依法向当事人告知了作出行政处罚的事实、理由、依据及当事人依法享有的权利。当事人提出陈述、申辩意见，并要求听证。我会两次召开听证会，听取了当事人的陈述和申辩意见。本案现已调查、审理终结。经查明，叶熙正存在以下违法事实：一、叶熙正实际控制账户的情况2015年10月27日至2016年8月1日，叶熙正实际控制28个证券账户（以下简称账户组），具体为：叶熙正3个证券账户、叶某榕1个证券账户、王某强1个证券账户、张某通1个证券账户、周某铧1个证券账户、穆某2个证券账户、尹某雨1个证券账户、高某2个证券账户、韩某珊1个证券账户、熊某3个证券账户、杨某3个证券账户、狄某1个证券账户、刘某彤1个证券账户、刘某婷1个证券账户、王某3个证券账户、刘某1个证券账户、尹某红1个证券账户和谷某倩1个证券账户。叶熙正承认其使用了叶熙正、叶某榕、王某、张某通、王某强、刘某、尹某红、杨某、熊某、刘某彤、谷某倩、韩某珊、尹某雨、周某铧、高某15人名下的证券账户。叶某榕为叶熙正之子，王某与叶熙正共同生活，王某强为王某的父亲，张某通为王某的母亲。周某铧、穆某、尹某雨、高某、韩某珊、熊某、杨某、狄某、刘某彤、刘某婷为叶熙正实际控制的天津国脉电信设备销售有限公司（以下简称天津国脉）曾经或现在的员工。刘某为刘某婷的丈夫，尹某红为穆某的母亲。上述账户的资金主要来源于天津国脉工商银行账户、天津沁雅达商贸有限公司（叶熙正实际控制的另外一家公司）工商银行账户，以及狄某、刘某、谷某倩、熊某、杨某、周某铧、韩某珊的银行账户。账户组使用多台电脑下单，叶熙正本人笔记本电脑涉及多个账户，不同账户的交易地址存在重合。综上，2015年10月27日至2016年8月1日，叶熙正实际控制涉案账户组。二、叶熙正实际控制账户组操纵“吉林化纤”2015年10月27日至2016年8月1日，叶熙正实际控制涉案账户组，利用资金优势、持股优势连续买卖，盘中拉抬，反向交易等手段，影响“吉林化纤”交易价格和交易量。具体情况如下：账户组集中资金优势、持股优势连续买卖“吉林化纤”，有122个交易日的买卖成交量位列当日成交量排名前五名，其中105个交易日的买卖成交量位居第一。账户组交易该股的数量占该股市场成交量的占比超过15%且账户组成交量超过450万股的有30个交易日，超过30%的有4个交易日。2016年2月1日成交占比最高，达到33.49%。账户组频繁大量以高出申报前一刻市场成交价的价格买入“吉林化纤”，97个交易日的申买量位列当日申买量排名前五名，其中75个交易日的申买量位居第一，46个交易日的申买量占前10名股东申买总量的比例超过50%。账户组有102个交易日的买入成交量位列当日买入成交量排名前五名，其中85个交易日的买入成交量位居第一，52个交易日的买入成交量占前10名股东买入成交总量的比例超过50%。2016年1月14日的买入占比最高，申买量占市场申买总量比例达49.33%，买入成交量占市场买入成交总量比例达62.23%。账户组有84个交易日存在日内反向交易，反向交易量达15,027万股。账户组反向交易量超过150万股且反向交易量占账户组成交量比例超过50%的有37个交易日。账户组拉抬股价导致“吉林化纤”价格上涨，在买入占比超过30%、价格涨幅超过2%的88次买入行为中，涨幅为2%-3%的有31次，涨幅为3%-4%的有29次，涨幅为4%-5%的有11次，涨幅超过5%的为17次。2016年1月20日10点19分46秒至11点4分14秒拉抬涨幅最高，为10.05%，“吉林化纤”成交均价由7.36元拉升至8.10元。以2016年1月14日为例，13点14分22秒至13点31分45秒，账户组申报买入“吉林化纤”33笔，委托买入量234.72万股，占同期市场申买量的72.27%，买入成交合计175.10万股，成交金额1,053.90万元，占同期市场买入成交量的85.18%，推动股价由5.76元上涨至6.25元，期间涨幅8.51%。当天账户组又对“吉林化纤”进行两次拉抬，将股价推至涨停，一次是13点43分13秒至14点9分22秒，账户组申报买入“吉林化纤”47笔，委托买入量345.95万股，占同期市场申买量的73.94%，买入成交合计250.52万股，成交金额1,576.68万元，占同期市场买入成交量的85.94%，推动股价由6.14元上涨至6.46元，期间涨幅5.21%；一次是14点22分40秒至14点39分58秒，账户组申报买入“吉林化纤”32笔，委托买入量324.46万股，占同期市场申买量的64.26%，买入成交合计228.89万股，成交金额1,473.80万元，占同期市场买入成交量的78.78%，推动股价由6.28元上涨至6.47元，期间涨幅3.03%。2015年10月27日至2016年8月1日，叶熙正利用其实际控制的账户组，累计买入“吉林化纤”278,659,888股，截至2016年10月28日，累计卖出273,960,933股，分红派股38,061,460股，期末持有42,760,415股。扣除交易费用后，获利共计6,019,834.94元。上述违法事实，有相关工商登记资料、相关银行账户资料、证券账户资料、证券账户交易流水、资金账户资料、电脑信息资料、交易地址及相关人员询问笔录等证据证明，足以认定。我会认为，2015年10月27日至2016年8月1日期间，叶熙正控制账户组，采取利用资金优势、持股优势连续买卖，盘中拉抬，反向交易等手段，影响“吉林化纤”交易价格和交易量，违反了《证券法》第七十七条第一款第一项和第四项的规定，构成《证券法》第二百零三条所述操纵市场行为。叶熙正在听证及陈述申辩材料中承认其操纵的违法事实，提出减轻处罚的请求，理由如下：第一，配合调查组调查，如实提交相关材料；第二，主动纠正违法违规行为，在立案调查之前已逐步清销账户，且在事后妥善、逐步出售其持有的“吉林化纤”；第三，未造成严重后果；第四，已认识到错误，行政处罚的部分目的已实现。经复核，根据当事人违法行为的事实、性质、情节与社会危害程度，依据《证券法》第二百零三条的规定，我会决定：责令叶熙正依法处理非法持有的证券，没收违法所得6,019,834.94元，并处以12,039,669.88元罚款。上述当事人应自收到本处罚决定书之日起15日内，将罚没款汇交中国证券监督管理委员会（财政汇缴专户），开户银行：中信银行北京分行营业部，账号：7111010189800000162，由该行直接上缴国库，并将注有当事人名称的付款凭证复印件送中国证券监督管理委员会稽查局备案。当事人如果对本处罚决定不服，可在收到本处罚决定书之日起60日内向中国证券监督管理委员会申请行政复议，也可在收到本处罚决定书之日起6个月内直接向有管辖权的人民法院提起行政诉讼。复议和诉讼期间，上述决定不停止执行。 中国证监会 2019年10月12日 | D16: 43750 | E16: 〔2019〕108
A17: 是 | B17: 是 | C17: 〔2019〕97号 当事人：张郁达，男，1977年7月出生，时任奔腾科技实业集团股份有限公司（以下简称奔腾集团）董事长，住址：内蒙古自治区赤峰市红山区。张晓敏，女，1970年3月出生，时任奔腾集团副董事长，张郁达配偶，住址：内蒙古自治区赤峰市红山区。依据《中华人民共和国证券法》（以下简称《证券法》）的规定，我会对张郁达、张晓敏操纵“奔腾集团”价格行为进行立案调查、审理，并依法向当事人告知作出行政处罚的事实、理由、依据及当事人依法享有的权利。应当事人张郁达、张晓敏的申请，我会举行听证会，听取当事人及其代理人的陈述、申辩意见。本案现已调查、审理终结。经查明，张郁达、张晓敏存在以下违法事实：一、张郁达、张晓敏控制使用证券账户情况根据证券账户交易终端硬件信息、资金往来记录、证人证言等证据，“张郁达”“王某蕾”“邹某燕”“周某言”“臧某强”“张某婷”“西藏奔腾中投股权投资管理合伙企业（有限合伙）（以下简称西藏奔腾）”“西藏万盛中投股权投资管理合伙企业（有限合伙）（以下简称西藏万盛）”“北京万盛国投股权投资管理合伙企业（有限合伙）（以下简称北京万盛）”9个证券账户（以下简称账户组）存在紧密关联性，由张郁达、张晓敏实际控制使用。张郁达、张晓敏利用账户组，使用自有资金和奔腾集团资金，操纵“奔腾集团”价格。二、张郁达、张晓敏操纵“奔腾集团”价格情况2016年12月30日至2017年1月6日（以下简称操纵期间），张郁达、张晓敏控制使用账户组，集中资金优势、持股优势、信息优势，连续交易“奔腾集团”，操纵交易价格和交易量，致使“奔腾集团”价格连续大幅上涨。（一）操纵过程账户组在操纵期间买入“奔腾集团”股票344.3万股，卖出66.7万股。2017年1月6日，“奔腾集团”股票停牌，账户组剩余持仓277.6万股，持股市值16,794,800元。（二）操纵手段1. 资金优势操纵期间共有5个交易日，账户组申报次数占比均超过30%，成交量占比在50%以上、买入成交量占比在40%以上的有4个交易日，有3个交易日存在反向交易；账户组总成交量占同期交易量的比率为56.74%。2017年1月6日，账户组成交量占当日总成交量的比率高达70.13%。2. 持股优势操纵期间，账户组持有奔腾集团非限售流通股占非限售流通股总量的比例不断增加，最高达到71.84%。而12家做市商所持奔腾集团非限售流通股占非限售流通股总量的比例不断降低，最低仅占非限售流通股总量的1.41%。3. 信息优势作为奔腾集团的董事长，张郁达知悉包括做市券商在内股东的持股情况。奔腾集团在2015年9月至2017年1月曾14次查询股东名册，中国证券登记结算有限公司在2016年3月至2017年1月自动向奔腾集团发送股东名册20次。2017年1月3日，奔腾集团在决定不参与竞购英力特化工股权的情况下，仍通过《内蒙古赤峰奔腾实业（集团）股份有限公司第二届董事会第十七次会议决议》并对外公告，公告内容足以对投资者产生误导。4. 连续买卖操纵期间的5个交易日内，账户组都发生了连续（3笔及3笔以上）主动买入“奔腾集团”股票的行为，股价在短时间内迅速被推高，最高幅度发生于2017年1月6日，“奔腾集团”股价在76分钟内提高了24.49%；同时，账户组都发生了以高于做市商卖出报价和明显高于其他市场投资者的申报价格进行买入申报的行为，做市商报价及股价在短时间内大幅提高。（三）操纵结果账户组在操纵期间买入“奔腾集团”344.3万股，买入金额15,372,400元，卖出“奔腾集团”66.7万股，卖出金额3,694,540元，实际盈利703,691.74元（扣除税费）；持仓“奔腾集团”277.6万股。操纵期间，“奔腾集团”股票价格从3.05元上涨至6.05元，涨幅为98.36%。同期全国中小企业股份转让系统（以下简称股份转让系统）成份指数下跌0.55%，偏离98.91%；做市成份指数上涨1.4%，偏离96.96%。以上事实，有相关证券账户交易终端硬件信息（IP、MAC、硬盘序列号、下单手机号），证券账户资料，银行账户资料，证券账户交易资料，相关人员询问笔录，股份转让系统相关数据信息等证据证明，足以认定。我会认为，张郁达和张晓敏利用资金优势、持股优势和信息优势，控制使用9个证券账户连续交易“奔腾集团”股价的行为，违反《证券法》第七十七条第一款第一项规定，构成《证券法》第二百零三条所述操纵证券市场行为。当事人及其代理人提出以下陈述申辩意见：第一，在“比照”《证券法》进行行政处罚时，应考虑股份转让系统挂牌公司的特殊性及挂牌规则同监管规则的一致性。《国务院关于全国中小企业股份转让系统有关问题的决定》（以下简称《决定》）法律责任部分未对市场操纵行为进行规定，应由股份转让系统实施自律监管；过高的监管规则会限制股份转让系统的创新性和包容性。第二，本案行政处罚金额巨大，应采用接近排除合理怀疑的证明标准。处罚结果过重，应考虑过罚相当及罚教结合。第三，认定张郁达、张晓敏控制涉案账户组事实不清、证据不足，没有证据证明以下事实：一是涉案账户由张郁达、张晓敏控制；二是涉案证券账户密码及对应的三方存管银行卡受张郁达、张晓敏控制；三是初始资金来源于张郁达、张晓敏（奔腾集团）；四是涉案证券账户所有人与张郁达、张晓敏、奔腾集团的资金往来用于操纵奔腾集团股票；五是涉案账户股份收益由张郁达、张晓敏所有。此外，未严格区分奔腾集团的资金、账户所有人自有资金与张郁达、张晓敏的资金。第四，认定张郁达、张晓敏操纵奔腾集团股票价格事实不清、证据不足。一是《行政处罚事先告知书》认定张郁达、张晓敏操纵市场的方式为“连续交易”，但认定的程度仅为“影响”而不是“操纵”。二是张郁达、张晓敏没有操纵市场的客观行为。理由包括：1.没有证据证明涉案账户买入行为来自张郁达、张晓敏的指令。2.操纵期间，张晓敏名下证券账户没有交易“奔腾集团”，“张郁达”证券账户仅卖出部分股票，涉案九个账户只有四个存在卖出行为。3.涉案账户与张郁达、张晓敏、张某之间的资金往来在操纵期之前就大量存在。三是涉案证券账户相关交易是长期持有的真实投资行为，“高位套现”特征不明显。四是股份转让系统挂牌公司流动性较差，少量资金就可以把股价“拉高”，认定市场操纵应结合客观行为和主观意图。五是张郁达、张晓敏没有操纵市场的主观目的与动机，拉高股价会增加为臧某强实现“定增”的成本。第五，认定张郁达、张晓敏操纵“奔腾集团”价格获利为5,081,319.63元缺乏事实及法律依据。一是涉案账户组中，除张郁达名下的账户外，其余账户内股票及获利均属于账户登记主体所有。二是“臧某强”账户股票是臧某强所有的财产。三是以2017年1月6日的收盘价计算浮动盈利，没有事实和法律依据。在发现股价出现增长后，奔腾集团主动于2017年1月6日申请停牌，且停牌当日，“臧某强”账户一直在进行买入交易。第六，对本案调查程序是否合法存疑。一是缺少调取涉案账户银行流水的出处及过程性材料。二是大量取证发生在立案之前，且未提供调取证据的具体依据以及过程信息。三是账户信息作为电子证据，应当符合证监会的相关规定，缺少证明材料。经复核，我会认为：第一，根据《决定》，“证监会应当比照证券法关于市场主体法律责任的相关规定，严格执法，对虚假披露、内幕交易、操纵市场等违法违规行为采取监管措施，实施行政处罚”。我会对操纵股份转让系统挂牌公司股价等违法违规行为实施行政处罚，于法有据。股份转让系统市场是证券市场的重要组成部分，依据《证券法》对于该市场交易过程中发生的市场操纵违法行为进行行政处罚，符合我会一贯执法实践。股份转让系统市场并非法外之地，股份转让系统市场的包容性并不包容违法行为，对股份转让系统市场放宽准入限制不等于放松监管。第二，本案事实清楚，证据确实充分，量罚幅度合理。当事人以特别恶劣的手段阻碍、抗拒我会工作人员行使调查职权，严重扰乱证券市场秩序。具体表现为：态度蛮横，多次威胁恐吓调查人员；在调查组开展调查工作的场所内安装录音设备进行窃听；藐视执法权威，对询问过程的严肃性毫不在意，信口雌黄，频频编造谎言以求自圆其说，并向调查组提供虚假证据材料，行为特别恶劣，情节特别严重，应当予以严惩。我会依法对张郁达、张晓敏采取“顶格”处罚。第三，本案证据足以认定张郁达、张晓敏对账户组的控制关系。一是从涉案账户名义所有人的询问笔录来看，其控制或操作涉案账户的陈述与客观事实不符，对其陈述均不予采信；并且账户名义所有人均与张郁达、张晓敏存在亲属或上下级关系，其证言证明力受到影响。二是涉案账户在操纵期间买入“奔腾集团”股票所用资金全部来源于张郁达、张晓敏和奔腾集团，卖出资金流向张晓敏、奔腾集团。三是涉案账户组操作具有同一性，下单IP地址与MAC地址高度一致，其中，IP地址均为奔腾集团办公场所，MAC地址分别为4437E****9CA、0025A****3ED、00000****AAD、4437E****093。在MAC地址4437E****9CA下交易的账户有六个，分别为张郁达、王某蕾、周某言、张某婷、西藏奔腾、西藏万盛账户；在MAC地址0025A****3ED下交易的账户有两个，分别为邹某燕和臧某强账户；在MAC地址00000****AAD下交易的账户有两个，分别为王某蕾和北京万盛账户；在MAC地址4437E****093下交易的账户有三个，分别为王某蕾、张某婷和西藏奔腾账户；上述账户存在同一时间段先后在同一台电脑进行交易的情况，应为同一控制关系。四是西藏奔腾、西藏万盛、北京万盛三个公司账户均由奔腾集团员工邢某华代为开户，其中西藏奔腾、西藏万盛账户预留联系方式为张晓敏手机号码，张晓敏也承认自己是西藏奔腾账户的实际控制人；西藏奔腾等三公司账户交易行为均发生在奔腾集团办公场所，下单MAC地址分别与其余个人账户重合，更为异常；且操纵期前几日，西藏万盛账户在张郁达北京住所发生交易，买入143,000股“奔腾集团”。五是张郁达、张晓敏在调查期间虚构账户下单交易场所、唆使相关人员出具虚假证言等拒不配合调查行为，更加印证其行为的违法性。六是奔腾集团内部治理、财务账目混乱，张郁达、张晓敏、张某银行账户与奔腾集团银行账户之间频繁往来，张郁达、张晓敏和奔腾集团的资金无法进行严格划分，张郁达、张晓敏能够以个人名义调动奔腾集团的资金。结合账户组各账户资金来往情况、交易情况、交易所用IP地址与MAC地址高度重合的情况、当事人询问笔录等一系列在案证据，形成完整的证据链，足以证明“张郁达”等9个证券账户，在操纵期间均为张郁达、张晓敏所控制。第四，认定张郁达、张晓敏操纵“奔腾集团”股价事实清楚、证据充分。一是《行政处罚事先告知书》中提及张郁达、张晓敏连续交易“奔腾集团”，影响了该股票的交易价格和交易量，此处“影响”一词属用词不当，应更正为“操纵”。二是客观上，2016年12月30日至2017年1月6日，张郁达、张晓敏控制账户组，集中资金优势、持股优势、信息优势，连续交易“奔腾集团”，操纵该股票的交易价格和交易量，导致股票价格连续大幅上涨。1.根据账户组于操纵期间交易“奔腾集团”的记录分析，账户组交易量占比、买比重、持股比等数值明显较高，具有明显的资金优势、持股优势；作为奔腾集团的董事长，张郁达知悉包括做市券商在内股东的持股情况，并发布不实公告误导投资者，具有明显的信息优势；同时，账户组在短时间内以高于做市商报价和明显高于其他市场投资者的价格，多次连续申报买入“奔腾集团”，该股票价格从3.05元上涨至6.05元，涨幅高达98.36%，账户组的连续交易行为致使“奔腾集团”价格大幅上涨。2.操纵期间，“奔腾集团”股价上涨98.36%，同期股份转让系统成份指数下跌0.55%，偏离98.91%，做市成份指数上涨1.4%，偏离96.96%。三是主观上，张郁达称其知晓持续买入“奔腾集团”就会使“奔腾集团”价格上涨，具有操纵的主观故意。第五，违法所得计算无误，涉案账户组所得均是违法所得，账户组在操纵期间买入“奔腾集团”344.3万股，卖出“奔腾集团”66.7万股，实际盈利703,691.74元（扣除税费）；持仓“奔腾集团”277.6万股。一是账户组是张郁达、张晓敏操纵“奔腾集团”价格的工具，无论账户名义所有人是谁，操纵期间由张郁达、张晓敏控制使用，操纵行为产生的所得，皆属违法所得。关于涉案账户组违法所得计算方法科学合理，符合我会一贯执法惯例。二是虽然臧某强买入的股票数量与双方签订的定增协议数量一致，但在操纵期间该账户为张郁达实际控制和使用，且该账户在12月30日之前只买入25.1万股，每股价格不足3元，12月30日之后奔腾集团股价不断上涨，臧某强账户在5个交易日内买入164.9万股，且部分股票的申报价格高于做市商报价，明显存在拉抬股价的意图。该账户和账户组中其他账户共同完成操纵市场行为，客观上影响股票价格正常形成机制，应共同视为张郁达、张晓敏操纵市场的工具。三是2017年1月6日，奔腾集团因股价异动和信息披露问题被股份转让系统要求停牌，而非奔腾集团“主动停牌”。第六，关于调查程序。一是调取涉案账户银行流水的材料，调查人员已于听证会当场出示；二是我会查询并取得公民个人银行账户信息的依据为《证券法》第一百八十条的规定，具体为：“国务院证券监督管理机构依法履行职责，有权采取下列措施：……（六）查询当事人和与被调查事件有关的单位和个人的资金账户、证券账户和银行账户……”；三是我会依法对违反证券市场监督管理法律、行政法规的行为进行查处，进入涉嫌违法行为发生场所调查取证，询问当事人，查阅、复制相关资料和文件等，调查过程中调查人员不少于二人，并出示了合法证件和调查通知书，程序合法，执法过程中取得的证据真实合法有效，符合《证券法》及有关法律法规的规定；四是案卷中的账户信息，既有纸质记录，又有电子数据记录，且均在信息载体上加盖了提供单位公章，符合证据要求。综上，对当事人及代理人的陈述申辩意见均不予采纳。根据当事人违法行为的事实、性质、情节与社会危害程度，依据《证券法》第二百零三条的规定，我会决定：责令张郁达、张晓敏依法处理非法持有的“奔腾集团”股票，没收张郁达、张晓敏违法所得703,691.74元，并处以3,518,458.70元的罚款。上述当事人应自收到本处罚决定书之日起15日内，将罚没款汇交中国证券监督管理委员会（财政汇缴专户）开户银行：中信银行北京分行营业部，账号：7111010189800000162，由该行直接上缴国库，并将注有当事人名称的付款凭证复印件送中国证券监督管理委员会稽查局备案。当事人如果对本处罚决定不服，可在收到本处罚决定书之日起60日内向中国证券监督管理委员会申请行政复议，也可在收到本处罚决定书之日起6个月内直接向有管辖权的人民法院提起行政诉讼。复议和诉讼期间，上述决定不停止执行。 中国证监会 2019年9月4日 | D17: 43712 | E17: 〔2019〕97
A18: 是 | B18: 是 | C18: 〔2019〕96号 当事人：奔腾科技实业集团股份有限公司（以下简称奔腾集团），住所：内蒙古自治区赤峰市红山区。张郁达，男，1977年7月出生，时任奔腾集团董事长，住址：内蒙古自治区赤峰市红山区。田永林，男，1968年8月出生，时任奔腾集团董事会秘书、副总经理，住址：内蒙古自治区赤峰市红山区。依据《中华人民共和国证券法》（以下简称《证券法》）的规定，我会对奔腾集团信息披露违法行为进行立案调查、审理，并依法向当事人告知作出行政处罚的事实、理由、依据及当事人依法享有的权利。应当事人奔腾集团、张郁达、田永林的申请，我会举行听证会，听取当事人及其代理人的陈述、申辩意见。本案现已调查、审理终结。经查明，当事人存在以下违法事实：一、奔腾集团未按规定履行信息披露义务2016年12月6日，国电英力特能源化工集团股份有限公司（以下简称英力特集团）通过宁夏英力特化工股份有限公司（以下简称英力特化工）信息披露平台发布了《关于国有控股股东拟协议转让公司股份公开征集受让方的公告》。公告要求受让方需在2016年12月19日17点之前携带“资格预审材料（包括意向受让方关于同意受让本次转让股份的内部决策文件）”到英力特集团现场报名。2016年12月7日，奔腾集团董事会形成《内蒙古赤峰奔腾实业（集团）股份有限公司第二届董事会第十五次会议决议》（以下简称《第十五次董事会决议》），内容是：“同意公司参与认购国电英力特能源化工集团股份有限公司联合转让其持有的宁夏英力特化工股份有限公司155,322,687股股份（占上市公司总股本的51.25%）及所持宁夏英力特煤业有限公司100%股权和相关债权”。2016年12月16日，奔腾集团股东大会形成《内蒙古赤峰奔腾实业（集团）股份有限公司第2016届股东大会第十四次会议决议》（以下简称《股东大会决议》），同意《第十五次董事会决议》相关事项。2016年12月19日，奔腾集团法定代表人张郁达委托行业专业人士雷某华携带“资格预审资料”到英力特集团申请报名参加调研。递交的“资格预审材料”包括《第十五次董事会决议》和《股东大会决议》。根据《非上市公众公司监督管理办法》（证监会令第96号）第二十五条的规定，奔腾集团《第十五次董事会决议》和《股东大会决议》包含可能对股票价格产生较大影响的重大事件，奔腾集团对上述决议未履行信息披露义务。二、奔腾集团披露的相关信息存在误导性陈述2016年12月30日，奔腾集团召开第二届董事会第十七次会议，审议并通过三项议案，其中第二项议案为：《拟在A股市场收购上市公司的议案》，议案内容包括：“公司拟在A股市场收购上市公司，公司管理层正积极推进，寻找与公司战略契合的标的。”2017年1月3日，奔腾集团公告《内蒙古赤峰奔腾实业（集团）股份有限公司第二届董事会第十七次会议决议》（以下简称《第十七次董事会决议》）。奔腾集团提供的《关于奔腾集团参与收购英力特化工股权的情况说明》（以下简称《奔腾集团情况说明》）称：“2016年12月22日，雷某华经考察后向我公司董事长张郁达建议放弃参与英力特集团的股权公开转让，听其建议后，我公司决定不再参加英力特集团的股权公开转让，之后未再与英力特集团有过任何联系”。英力特集团2017年5月15日出具的《国电英力特能源化工集团股份有限公司关于就内蒙古赤峰奔腾实业（集团）股份有限公司参与英力特化工股权转让事项有关情况的说明》（以下简称《英力特集团情况说明》）称：2016年12月22日，奔腾集团未参加尽调，且后续就本次股权转让事项再没与英力特集团有任何联系。《奔腾集团情况说明》与《英力特集团情况说明》互为印证，证明2016年12月22日后，奔腾集团已决定不参与竞购英力特化工股权。在这种情况下，奔腾集团仍通过有关决议并对外公告《第十七次董事会决议》，存在误导性陈述。三、奔腾集团披露的相关信息存在虚假记载2017年1月6日，奔腾集团收到全国中小企业股份转让系统（以下简称股份转让系统）的问询函，问询奔腾集团2017年1月3日披露的《第十七次董事会决议》内容及“奔腾集团”股票异常波动情况。奔腾集团于当日申请停牌。2017年2月21日，奔腾集团披露《关于〈内蒙古赤峰奔腾实业（集团）股份有限公司关于股转公司问询函〉的回复》（以下简称《关于股转公司问询函的回复》）称：“奔腾集团于2017年1月6日向英力特集团发送邮件申请成为意向受让方，当日奔腾集团收到英力特集团回复邮件，通过资格预审。公司并于当天收到英力特集团邮件发送的《资格预审合格通知书》后，及时告知主办券商，并申请停牌”，上述内容与《奔腾集团情况说明》和《英力特集团情况说明》描述的事实不符。以上事实，有当事人询问笔录、当事人提供的情况说明、相关资料、年度报告、董事会审议年报表决记录、英力特集团提供的说明及材料等证据证明，足以认定。奔腾集团上述行为违反《非上市公众公司监督管理办法》第二十条规定，构成《非上市公众公司监督管理办法》第六十条所述信息披露违法行为。奔腾集团董事长张郁达，组织、策划信息披露违法行为，是直接负责的主管人员；董事会秘书、副总经理田永林，参与、实施信息披露违法行为，是其他直接责任人员。当事人及其代理人提出以下陈述申辩意见：第一，应考虑股份转让系统挂牌公司的特殊性。首先，奔腾集团是股份转让系统挂牌公司，和上市公司在法律上存在主体差异，应考虑股份转让系统的创新性和包容性。其次，应由股份转让系统采取自律监管措施及纪律处分。再次，股份转让系统挂牌公司承担的信息披露责任与上市公司不同，否则可能抑制其发展。第二，如果证监会认定信息披露违规同时又对操纵市场进行处罚，应当慎重考虑两个行为是否有联系，是否有违法责任吸收的可能。第三，证监会未证明奔腾集团参加收购英力特资格预审的决定属于“重大事件”，应减轻公司信息披露责任。第四，认定奔腾集团相关议案存在误导性陈述，值得商榷。一是公告经主办券商审查后只在股份转让系统平台进行发布，且主办券商通过风险提示公告已经对奔腾集团公告中的风险做了明确和充分的提示。二是公告对投资者的误导缺乏事实和证据。第五，恳请酌情减轻对奔腾集团、张郁达、田永林的处罚幅度。经复核，我会认为：第一，《国务院关于全国中小企业股份转让系统有关问题的决定》第五部分规定，“证监会应当比照证券法关于市场主体法律责任的相关规定，严格执法，对虚假披露、内幕交易、操纵市场等违法违规行为采取监管措施，实施行政处罚”。我会对股份转让系统挂牌公司信息披露违法违规行为实施行政处罚，于法有据。股份转让系统市场是证券市场的重要组成部分，依据《证券法》对于该市场中发生的信息披露违法违规行为进行行政处罚，符合我会一贯执法实践。股份转让系统市场并非法外之地，股份转让系统市场的包容性并不包容违法行为，对股份转让系统市场放宽准入限制不等于放松监管。我会作出行政处罚决定和股份转让系统给予纪律处分，在作出主体、适用依据、行为的事实、性质、情节与社会危害程度方面有本质的区别，股份转让系统给予纪律处分不是我会作出行政处罚决定的前置性程序。即使股份转让系统给予纪律处分，我会也可以作出行政处罚决定。第二，奔腾集团的信息披露违法行为和张郁达等人的证券市场操纵行为（另案处理）构成要件不同，相互独立，属于不同性质的两类违法行为，对股份转让系统市场秩序造成不同的危害，不存在违法责任吸收问题。第三，关于“重大事件”的认定标准。一是《非上市公众公司监督管理办法》第二十五条规定：“发生可能对股票价格产生较大影响的重大事件，投资者尚未得知时，公众公司应当立即将有关该重大事件的情况报送临时报告，并予以公告，说明事件的起因、目前的状态和可能产生的后果。”二是《非上市公众公司监管指引第1号——信息披露》（证监会公告〔2013〕1号）第四部分规定，依法设立的证券交易场所可以在本指引的基础上，对股票公开转让的非上市公众公司制定更详尽、更严格的信息披露标准；公司应当按照从高从严的标准遵守证券交易场所的相关规定。奔腾集团作为股份转让系统挂牌公司，应当按照从高从严的标准遵守证券交易场所的相关规定。三是《全国中小企业股份转让系统挂牌公司信息披露细则（试行）》（股转系统公告〔2013〕3号，以下简称《信息披露细则》）第三章第四节规定了“其他重大事件”，其中，第四十六条规定，挂牌公司出现董事会就并购重组、股利分派、回购股份、定向发行股票或者其他证券融资方案、股权激励方案形成决议的，应当自事实发生之日起两个转让日内披露；同时第二十二条规定，挂牌公司应当在临时报告所涉及的重大事件最先触及董事会或者监事会作出决议时及时履行首次披露义务。奔腾集团参与认购英力特股权的行为，属于《信息披露细则》规定的并购重组事项，也属于《非上市公众公司监督管理办法》第二十五条规定的可能对股票价格产生较大影响的重大事件。奔腾集团应当及时履行信息披露义务。第四，奔腾集团的公告存在误导性陈述。首先，《奔腾集团情况说明》与《英力特集团情况说明》足以证明奔腾集团已决定不参与竞购英力特化工股权，在此情形下，奔腾集团公告的《第十七次董事会决议》存在误导性陈述。其次，券商发布风险提示公告，不能免除奔腾集团真实、准确、完整、及时地进行信息披露的义务，不构成奔腾集团规避法律责任的免责理由。奔腾集团违反信息披露义务，对投资者造成了误导。第五，本案事实清楚，证据确实充分，处罚幅度与当事人对股份转让系统市场的危害程度相适应。当事人以特别恶劣的手段，阻碍、抗拒我会调查人员行使调查职权，严重扰乱证券市场秩序。具体表现为：态度蛮横，多次威胁恐吓调查人员；在调查人员开展调查工作的场所内安装录音设备进行窃听；藐视执法权威，对询问过程的严肃性毫不在意，信口雌黄，频频编造谎言以求自圆其说，并向调查人员提供虚假证据材料，情节特别恶劣，应予以严惩。综上，对当事人及代理人的陈述申辩意见均不予采纳。根据当事人违法行为的事实、性质、情节与社会危害程度，依据《非上市公众公司监督管理办法》第六十条、《证券法》第一百九十三条第一款的规定，我会决定：一、责令奔腾科技实业集团股份有限公司改正，给予警告，并处以60万元的罚款；二、对张郁达给予警告，并处以30万元的罚款；三、对田永林给予警告，并处以10万元的罚款。上述当事人应自收到本处罚决定书之日起15日内，将罚款汇交中国证券监督管理委员会（财政汇缴专户），开户银行：中信银行北京分行营业部，账号：7111010189800000162，由该行直接上缴国库，并将注有当事人名称的付款凭证复印件送中国证券监督管理委员会稽查局备案。当事人如果对本处罚决定不服，可在收到本处罚决定书之日起60日内向中国证券监督管理委员会申请行政复议，也可在收到本处罚决定书之日起6个月内直接向有管辖权的人民法院提起行政诉讼。复议和诉讼期间，上述决定不停止执行。 中国证监会 2019年9月4日 | D18: 43712 | E18: 〔2019〕96
... A25: 是 | B25: 是 | C25: 〔2019〕2号 当事人：福建道冲投资管理有限公司（以下简称福建道冲），住所：福建省福州市仓山区。李盛开，男，1973年6月出生，时为福建道冲实际控制人、董事长，住址：福建省福州市鼓楼区。张秋丽，女，1984年5月出生，时任福建道冲总经理、执行董事，住址：福建省福州市鼓楼区。依据《中华人民共和国证券法》（以下简称《证券法》）的有关规定，我会对福建道冲操纵深证100交易型开放式指数基金（以下简称深100ETF）、中小企业板交易型开放式指数基金（以下简称中小板ETF）、中小板300交易型开放式指数证券投资基金（以下简称中小300ETF）一案进行了立案调查、审理，并依法向当事人告知了作出行政处罚的事实、理由、依据及当事人依法享有的权利，当事人福建道冲、李盛开、张秋丽进行了陈述和申辩，未要求听证。本案现已调查、审理终结。经查明，当事人存在以下违法事实：一、2015年6月15日至8月12日（以下简称操纵期间），福建道冲控制使用“千石资本——道冲套利1号资产管理计划”等9个账户（以下简称账户组）账户组所涉9个账户具体为千石资本——道冲套利1号、2号、3号、5号、8号、9号、10号、11号、12号资产管理计划，均为福建道冲通过北京千石资本管理有限公司发行的专户产品，福建道冲是投资顾问，由福建道冲决策下单。福建道冲设有投资决策委员会，李盛开、张秋丽均为投资决策委员会成员，并认购了部分产品劣后级出资份额。投资决策委员会定期召开会议，提出近期交易策略。上述9只产品由交易员在福建道冲专用的交易室利用套利软件，按照公司制订的既定交易策略下单交易。二、操纵期间，福建道冲在自己实际控制的单一账户或账户间进行深100ETF、中小板ETF、中小300ETF等3只ETF产品交易，影响上述ETF交易量，变相进行相应ETF与相应成分股日内回转交易，获取非法利益操纵期间共42个交易日内，账户组交易深100ETF、中小板ETF、中小300ETF等3只ETF，累计成交54.57亿元，占账户ETF总成交金额的25.93%。具体如下：账户组申购深100ETF3.934亿份，赎回4.148亿份；在二级市场累计成交深100ETF7.71亿份，成交金额38.73亿元。其中，买入成交3.97亿份，买入金额约19.66亿元；卖出成交3.74亿份，卖出金额约19.07亿元；单一账户或账户间交易1.81亿份，交易金额8.97亿元。其中，有3个交易日在单一账户或账户间进行深100ETF产品交易的成交量占同期该品种市场成交量的比例超过5%，最高占比达33.71%。账户组申购中小板ETF1.195亿份，赎回1.02亿份；在二级市场累计成交中小板ETF2.01亿份，成交金额8.47亿元。其中，买入成交0.92亿份，买入金额约3.76亿元；卖出成交1.09亿份，卖出金额约4.71亿元；单一账户或账户间交易0.22亿份，交易金额0.94亿元。其中，1个交易日在单一账户或账户间进行中小板ETF产品交易的成交量占同期该品种市场成交量的比例为6.33%。账户组申购中小300ETF1.905亿份，赎回1.845亿份；在二级市场累计成交中小300ETF3.70亿份，成交金额7.37亿元。其中，买入成交1.82亿份，买入金额约3.63亿元；卖出成交1.88亿份，卖出金额约3.74亿元；单一账户或账户间交易1.79亿份，交易金额3.58亿元。其中，有6个交易日在单一账户或账户间进行中小300ETF产品交易的成交量占同期该品种市场成交量的比例超过5%，最高占比达96.36%。福建道冲的上述交易亏损。以上违法事实，有相关的询问笔录、交易数据、交易流水、福建道冲的情况说明等证据证明，足以认定。福建道冲的上述行为违反了《证券法》第七十七条第一款第三项的相关规定，构成《证券法》第二百零三条所述操纵证券市场的行为。李盛开时为福建道冲实际控制人、董事长，张秋丽时任福建道冲总经理、执行董事，二人又是福建道冲投资委员会成员，为福建道冲违法行为直接负责的主管人员。福建道冲、李盛开、张秋丽提出：第一，福建道冲主观上没有操纵市场的主观目的，客观行为亦未达到操纵市场的程度，福建道冲操作的9个账户相互独立，互不干涉，不存在串通合谋操纵证券市场的行为。第二，账户组的交易行为合法合规，且在交易过程中均未收到投资管理人及证券公司风险控制部门异常交易提醒。经复核，我会认为：第一，操纵期间共42个交易日内，账户组交易深100ETF、中小板ETF、中小300ETF等3只ETF，累计成交54.57亿元，占账户ETF总成交金额的25.93%。其中，有3个交易日账户组在单一账户或账户间进行深100ETF产品交易的成交量占同期该品种市场成交量的比例超过5%，最高占比达33.71%；1个交易日账户组在单一账户或账户间进行中小板ETF产品交易的成交量占同期该品种市场成交量的比例为6.33%；6个交易日账户组在单一账户或账户间进行中小300ETF产品交易的成交量占同期该品种市场成交量的比例超过5%，最高占比达96.36%，充分印证福建道冲具有利用此种交易方式获利的主观故意。李盛开、张秋丽等人的询问笔录与上述事实充分印证。第二，福建道冲在自己实际控制的账户之间进行深100ETF、中小板ETF、中小300ETF交易的行为，对相应ETF产品交易量造成了影响，放大了同期成交量，干扰了市场正常交易秩序，同时，账户组相互交易的行为掩盖了市场真实供求关系，扭曲了正常的价格形成机制。上述行为被《证券法》第七十七条第一款第三项所明确禁止，符合操纵行为的特征。第三，ETF交易为投资者提供了一种交易产品和交易机制的选择，投资人可以进行正常的申赎套利机制，但相关交易不能违反法律和相关交易规则的规定。《深圳证券交易所交易型开放式指数基金业务实施细则》（以下简称《实施细则》）第二十一条规定，当日申购的基金份额，同日可以卖出，但不得赎回。福建道冲通过在自己实际控制的账户之间进行深100ETF、中小板ETF、中小300ETF交易，实现了当日申购的基金份额当日赎回，并通过卖出赎回的股票，变相实现股票T+0交易。上述交易行为违反了《实施细则》的明确规定，亦构成与在股票市场按照T+1交易规则进行交易的其他投资者的不对等交易，形成了不公平的交易机会。根据当事人违法行为的事实、性质、情节和社会危害程度，依据《证券法》第二百零三条的规定，我会决定：一、对福建道冲处以100万元罚款。二、对李盛开给予警告，并处以30万元罚款。三、对张秋丽给予警告，并处以30万元罚款。上述当事人应自收到本处罚决定书之日起15日内，将罚款汇交中国证券监督管理委员会（财政汇缴专户），开户银行：中信银行总行营业部，账号7111010189800000162，由该行直接上缴国库。当事人还应将注有其名称的付款凭证复印件送中国证券监督管理委员会稽查局备案。当事人如果对本处罚决定不服，可在收到本处罚决定书之日起60日内向中国证券监督管理委员会申请行政复议，也可以在收到本处罚决定书之日起6个月内直接向有管辖权的人民法院提起行政诉讼。复议和诉讼期间，上述决定不停止执行。中国证监会 2019年1月18日 | D25: 43483 | E25: 〔2019〕2

Sheet 补充空白与2019的股票代码
A1: 维格娜丝 | B1: 603518.SH
A2: 康隆达 | B2: =VLOOKUP(A2,部分空白与2019的股票代码!A:B,2,0) -> 603665.SH
A3: 金麒麟 | B3: =VLOOKUP(A3,部分空白与2019的股票代码!A:B,2,0) -> 603586.SH
A4: 铁流股份 | B4: =VLOOKUP(A4,部分空白与2019的股票代码!A:B,2,0) -> 603926.SH
A5: 红蜻蜓 | B5: =VLOOKUP(A5,部分空白与2019的股票代码!A:B,2,0) -> 603116.SH
A6: 日月股份 | B6: =VLOOKUP(A6,部分空白与2019的股票代码!A:B,2,0) -> 603218.SH
A7: 太平鸟 | B7: =VLOOKUP(A7,部分空白与2019的股票代码!A:B,2,0) -> 603877.SH
A8: 秦安股份 | B8: =VLOOKUP(A8,部分空白与2019的股票代码!A:B,2,0) -> 603758.SH
A9: 上海亚虹 | B9: =VLOOKUP(A9,部分空白与2019的股票代码!A:B,2,0) -> 603159.SH
A10: 恒润股份 | B10: =VLOOKUP(A10,部分空白与2019的股票代码!A:B,2,0) -> 603985.SH
A11: 中马传动 | B11: =VLOOKUP(A11,部分空白与2019的股票代码!A:B,2,0) -> 603767.SH
A12: 劲拓股份 | B12: =VLOOKUP(A12,部分空白与2019的股票代码!A:B,2,0) -> 300400.SZ
A13: 浙数文化 | B13: =VLOOKUP(A13,部分空白与2019的股票代码!A:B,2,0) -> 600633.SH
... A16: 酒钢宏兴 | B16: =VLOOKUP(A16,部分空白与2019的股票代码!A:B,2,0) -> 600307.SH
A17: 贵人鸟 | B17: F1006086.00
A18: 美锦能源 | B18: =VLOOKUP(A18,部分空白与2019的股票代码!A:B,2,0) -> 000723.SZ
A19: 太化股份 | B19: 600281.SH
A20: 漳州发展 | B20: =VLOOKUP(A20,部分空白与2019的股票代码!A:B,2,0) -> 000753.SZ
A21: 国脉科技 | B21: =VLOOKUP(A21,部分空白与2019的股票代码!A:B,2,0) -> 002093.SZ
A22: 广宇发展 | B22: 000537.SZ
A23: 曙光股份 | B23: 600303.SH
A24: 钱江生化 | B24: 600796.SH
A25: 广宇集团 | B25: =VLOOKUP(A25,部分空白与2019的股票代码!A:B,2,0) -> 002133.SZ
A26: 全柴动力 | B26: =VLOOKUP(A26,部分空白与2019的股票代码!A:B,2,0) -> 600218.SH
A27: 天宝股份 | B27: 002220.SZ
A28: 远兴能源 | B28: =VLOOKUP(A28,部分空白与2019的股票代码!A:B,2,0) -> 000683.SZ
A29: 隆华节能 | B29: 300263.SZ
A30: 冠农股份 | B30: =VLOOKUP(A30,部分空白与2019的股票代码!A:B,2,0) -> 600251.SH
A31: 维维股份 | B31: =VLOOKUP(A31,部分空白与2019的股票代码!A:B,2,0) -> 600300.SH
A32: 牧高笛 | B32: =VLOOKUP(A32,部分空白与2019的股票代码!A:B,2,0) -> 603908.SH
A33: 圣龙股份 | B33: =VLOOKUP(A33,部分空白与2019的股票代码!A:B,2,0) -> 603178.SH
A34: 浙江仙通 | B34: =VLOOKUP(A34,部分空白与2019的股票代码!A:B,2,0) -> 603239.SH
A35: 奇精机械 | B35: =VLOOKUP(A35,部分空白与2019的股票代码!A:B,2,0) -> 603677.SH
A36: 宏盛股份 | B36: =VLOOKUP(A36,部分空白与2019的股票代码!A:B,2,0) -> 603090.SH
A37: 天目湖 | B37: =VLOOKUP(A37,部分空白与2019的股票代码!A:B,2,0) -> 603136.SH
A38: 如通股份 | B38: =VLOOKUP(A38,部分空白与2019的股票代码!A:B,2,0) -> 603036.SH
A39: 豪能股份 | B39: =VLOOKUP(A39,部分空白与2019的股票代码!A:B,2,0) -> 603809.SH
A40: 台华新材 | B40: =VLOOKUP(A40,部分空白与2019的股票代码!A:B,2,0) -> 603055.SH
A41: 青海华鼎 | B41: =VLOOKUP(A41,部分空白与2019的股票代码!A:B,2,0) -> 600243.SH
A42: 江西长运 | B42: =VLOOKUP(A42,部分空白与2019的股票代码!A:B,2,0) -> 600561.SH
A43: 商业城 | B43: 600306.SH
A44: 永吉股份 | B44: =VLOOKUP(A44,部分空白与2019的股票代码!A:B,2,0) -> 603058.SH
A45: 博信股份 | B45: =VLOOKUP(A45,部分空白与2019的股票代码!A:B,2,0) -> 600083.SH
A46: 亚星客车 | B46: =VLOOKUP(A46,部分空白与2019的股票代码!A:B,2,0) -> 600213.SH
A47: 龙建股份 | B47: =VLOOKUP(A47,部分空白与2019的股票代码!A:B,2,0) -> 600853.SH
A48: 赛福天 | B48: =VLOOKUP(A48,部分空白与2019的股票代码!A:B,2,0) -> 603028.SH
A49: 杭电股份 | B49: =VLOOKUP(A49,部分空白与2019的股票代码!A:B,2,0) -> 603618.SH
A50: 正虹科技 | B50: =VLOOKUP(A50,部分空白与2019的股票代码!A:B,2,0) -> 000702.SZ
A51: 山东威达 | B51: =VLOOKUP(A51,部分空白与2019的股票代码!A:B,2,0) -> 002026.SZ
A52: 棒杰股份 | B52: =VLOOKUP(A52,部分空白与2019的股票代码!A:B,2,0) -> 002634.SZ
A53: 博实股份 | B53: =VLOOKUP(A53,部分空白与2019的股票代码!A:B,2,0) -> 002698.SZ
A54: 金利华电 | B54: =VLOOKUP(A54,部分空白与2019的股票代码!A:B,2,0) -> 300069.SZ
A55: 明利股份 | B55: 831963.NQ
A56: 罗平锌电 | B56: =VLOOKUP(A56,部分空白与2019的股票代码!A:B,2,0) -> 002114.SZ
A57: 保千里 | B57: 600074.SH
A58: 神开股份 | B58: =VLOOKUP(A58,部分空白与2019的股票代码!A:B,2,0) -> 002278.SZ
A59: 金利华电 | B59: =VLOOKUP(A59,部分空白与2019的股票代码!A:B,2,0) -> 300069.SZ
A60: 菲达环保 | B60: =VLOOKUP(A60,部分空白与2019的股票代码!A:B,2,0) -> 600526.SH
A61: 东风科技 | B61: =VLOOKUP(A61,部分空白与2019的股票代码!A:B,2,0) -> 600081.SH
A62: 人民网 | B62: =VLOOKUP(A62,部分空白与2019的股票代码!A:B,2,0) -> 603000.SH
A63: 日月股份 | B63: =VLOOKUP(A63,部分空白与2019的股票代码!A:B,2,0) -> 603218.SH
A64: 天马股份 | B64: 002122.SZ
A65: 吉林化纤 | B65: =VLOOKUP(A65,部分空白与2019的股票代码!A:B,2,0) -> 000420.SZ
A66: 奔腾集团 | B66: 832650.NQ
A67: 丰华股份 | B67: =VLOOKUP(A67,部分空白与2019的股票代码!A:B,2,0) -> 600615.SH
A68: 拓日新能 | B68: =VLOOKUP(A68,部分空白与2019的股票代码!A:B,2,0) -> 002218.SZ
A69: 粤水电 | B69: 002060.SZ
A70: 澳柯玛 | B70: =VLOOKUP(A70,部分空白与2019的股票代码!A:B,2,0) -> 600336.SH
A71: 海信科龙 | B71: 000921.SZ
A72: 柘中股份 | B72: =VLOOKUP(A72,部分空白与2019的股票代码!A:B,2,0) -> 002346.SZ
A73: 浩丰科技 | B73: =VLOOKUP(A73,部分空白与2019的股票代码!A:B,2,0) -> 300419.SZ
A74: 南华仪器 | B74: =VLOOKUP(A74,部分空白与2019的股票代码!A:B,2,0) -> 300417.SZ
A75: 山河药辅 | B75: =VLOOKUP(A75,部分空白与2019的股票代码!A:B,2,0) -> 300452.SZ
A76: 中飞股份 | B76: 300489.SZ

Sheet 部分空白与2019的股票代码
A1: 证券简称 | B1: 证券代码
A2: 康隆达 | B2: 603665.SH
A3: 金麒麟 | B3: 603586.SH
A4: 铁流股份 | B4: 603926.SH
A5: 红蜻蜓 | B5: 603116.SH
A6: 日月股份 | B6: 603218.SH
A7: 太平鸟 | B7: 603877.SH
A8: 秦安股份 | B8: 603758.SH
A9: 上海亚虹 | B9: 603159.SH
A10: 恒润股份 | B10: 603985.SH
A11: 中马传动 | B11: 603767.SH
A12: 劲拓股份 | B12: 300400.SZ
... A62: 山河药辅 | B62: 300452.SZ

Sheet 2012至2018处罚文本
A1: 是 | B1: 否 | C1: 〔2018〕111号 当事人：王炎贤，男，1969年2月出生，住址：广东省深圳市南山区。依据《中华人民共和国证券法》（以下简称《证券法》）有关规定，我会对王炎贤信息披露违法及限制期限内交易“兴化股份”、操纵浙江栋梁新材股份有限公司（现更名为万邦德新材股份有限公司，以下简称栋梁新材）股票价格的行为进行了立案调查、审理，并依法向当事人告知了作出行政处罚的事实、理由、依据及当事人依法享有的权利。当事人未提出陈述、申辩意见，也未要求听证。本案现已调查、审理终结。经查明，王炎贤存在如下违法事实：一、王炎贤控制并使用王炎贤、王某锐、黄某英账户“王炎贤”“王某锐”“黄某英”账户（以下简称账户组）主要资金来源于王炎贤、王炎贤的借款及其控制的银行账户。根据当事人询问笔录、证券账户交易情况，交易股票使用的IP、MAC地址及资金划转情况，账户组的实际控制人为王炎贤。二、王炎贤未按规定报告、公告其持股信息2014年11月5日，账户组合计持有“兴化股份”比例达5.89%，账户组持股比例达到上市公司已发行股份5%时，王炎贤未按规定向中国证券监督管理委员会、证券交易所作出书面报告，通知该上市公司，并予公告。三、在未履行报告、公告义务的情形下，王炎贤控制使用账户组持续交易账户组在合计持有“兴化股份”达到5%且未履行报告、公告义务的情形下，仍在11月5日当日以及11月6日-17日持续买卖“兴化股份”，合计持股比例最高达到6.33%，累计买卖“兴化股份”的金额为188,151,854.69元。四、王炎贤控制使用账户组尾市操纵“栋梁新材”2014年10月30日，账户组持有“栋梁新材”8,626,465股。2014年10月31日尾市阶段，王炎贤控制使用账户组操纵“栋梁新材”股价，在下一个交易日（11月3日）卖出7,822,326股，获利183,992.79元。2014年10月31日14：45-14：57，账户组申买“栋梁新材”16笔共计8,248,400股，申买量占期间市场申买量的62.24%，买入成交1,902,654股，占期间市场成交量的43.17%。该时段内市场成交价由10.83元上涨至11.36元，涨幅为4.89%，“栋梁新材”全天涨幅为5.77%。上述时段内，账户组逐步提高申买价格，占其总申买股数69.03%的委托申买价格高于其申报前一刻市场成交价格，且高于申报前一刻买委托第1档价格，同时高于其申报前一刻卖委托第一档价格，高出幅度最大为0.09元。上述时段内，占其总申买股数16.81%的委托申买价格甚至高于其申报前一刻卖委托第5档价格，高出幅度最大为0.03元。此外，占其总申买股数94.28%的委托申买数量高于其申报前一刻市场前5档卖出申报总量，占其总申买股数87.53%的委托申买数量甚至高于其申报前一刻市场前10档卖出申报总量，高出幅度最大为前5档卖出申报总量的21.11倍，前10档卖出申报总量的13.52倍。2014年10月31日集合竞价阶段14:59:23至14:59:35，账户组分2笔申报买入共计1,306,400股,委托价格均为11.35元。账户组申买量占期间市场申买量的89.73%。账户组申报时间逼近收市时点，且申报价格低于前一刻的市场成交价11.36元，上述申报均未成交。以上事实有相关人员询问笔录、证券账户资料、交易流水、银行账户资料、交易所计算的数据等证据证明。王炎贤的上述行为违反了《证券法》第八十六条第一款、第三十八条、第七十七条第一款第（四）项规定，构成《证券法》第一百九十三条所述“未按照规定披露信息”的行为，第二百零四条所述“违反法律规定，在限制转让期限内买卖证券”的行为，第二百零三条所述“操纵证券市场”的行为。根据当事人违法行为的事实、性质、情节与社会危害程度，依据《证券法》第一百九十三条第一款、第二百零四条及第二百零三条的规定，我会决定：一、对王炎贤持有“兴化股份”达到5%未报告、公告行为给予警告，并处以30万元罚款；二、对王炎贤在限制期内持续交易“兴化股份”的行为，给予警告，并处以300万元罚款；三、对王炎贤操纵“栋梁新材”行为给予警告，没收违法所得183,992.79元，并处以30万元罚款。以上合计对王炎贤没收违法所得183,992.79元，罚款360万元。上述当事人应自收到本处罚决定书之日起15日内，将罚没款汇交中国证券监督管理委员会（财政汇缴专户），开户银行：中信银行总行营业部，账号：7111010189800000162，由该行直接上缴国库，并将注有当事人名称的付款凭证复印件送中国证券监督管理委员会稽查局备案。当事人如果对本处罚决定不服，可在收到本处罚决定书之日起60日内向中国证券监督管理委员会申请行政复议，也可在收到本处罚决定书之日起6个月内直接向有管辖权的人民法院提起行政诉讼。复议和诉讼期间，上述决定不停止执行。中国证监会 2018年12月29日 | D1: 2018111 | E1: 43463
A2: 是 | B2: 是 | C2: 〔2018〕125号 当事人：宁波天一世纪投资有限责任公司（以下简称天一世纪），住所：浙江省宁波保税区曹娥江路。周方洁，男，1964年10月出生，时任天一世纪董事长、法定代表人，住址：北京市海淀区。依据《中华人民共和国证券法》（以下简称《证券法》）的有关规定，我会对天一世纪利用他人账户买卖证券行为进行了立案调查、审理，并依法向当事人告知了作出行政处罚的事实、理由、依据及当事人依法享有的权利。应当事人要求，我会举行听证会听取了当事人陈述申辩意见。本案现已调查、审理终结。经查明，当事人存在以下违法事实：“范某”普通账户于2012年7月开立于中信证券上海东方路营业部，资金账号203×××××448，下挂一个上海股东账户A40××××845和一个深圳股东账户015××××962。2014年12月，该账户在中信证券上海东方路营业部开立融资融券账户，资金账号800××××135，下挂一个上海信用账户E02××××144和一个深圳信用账户060××××466。从2014年开始至调查日，天一世纪法定代表人周方洁操作使用“范某”账户，从天一世纪转入交易资金1.67亿元买卖股票，损益由天一世纪承担。以上事实，有“范某”账户资料、资金转账记录、交易数据、相关当事人询问笔录等证据证明，足以认定。天一世纪的上述行为，违反了《证券法》第八十条的规定，构成《证券法》第二百零八条第一款所述法人利用他人账户买卖证券的行为，周方洁是直接负责的主管人员。听证过程中，当事人及其代理人提出申辩并辅以相关证据、证人证言，主张涉案证券交易行为属周方洁个人行为而非天一世纪法人行为，请求免于处罚。具体申辩如下：第一，天一世纪公司章程规定对外投资需经董事会审议批准，而公司从未批准或者同意周方洁或其他主体利用“范某”账户买卖证券，周方洁非控股股东，不能一人控制天一世纪，资金划转经办人也非天一世纪工作人员，涉案行为系周方洁个人行为而非天一世纪法人行为。第二，天一世纪与周方洁之间存在借款关系，借款中的部分资金被周方洁转入“范某”账户。“范某”账户中另有资金自周方洁个人账户直接转入。“范某”账户资金去向均用于周方洁个人用途。该账户自周方洁开始买卖证券至清仓时交易结果为亏损状态，亏损由周方洁而非天一世纪承担。第三，周方洁对社会做出过有益贡献，证监会在调查中未发现其存在内幕交易或操纵市场等违法行为，其已及时纠正了从公司借款炒股的不规范行为，归还了借款且未有获利。经复核，我会认为：第一，周方洁在调查环节对天一世纪利用“范某”账户买卖证券的行为进行了自认，详细阐述了行为动机和交易过程，事实清晰完整，已经其本人签字确认。周方洁虽不具备控股股东地位，但结合天一世纪股权结构、功能定位、相关人员询问笔录、职务关系等情况可以认定其对该公司的控制地位，结合资金划转情况等足以证明天一世纪利用他人账户买卖证券行为的成立。周方洁虽在听证环节对上述内容予以否认，改称资金划转实为借款关系，但前者是在正常调查询问状态下所作陈述，后者是在事先告知后所作陈述，后者的真实性和证明力明显弱于前者。第二，当事人所主张的周方洁与天一世纪之借款关系，其证人为周方洁利益相关人，所作证言均为事先告知后提供，且并无书面借款协议等客观证据佐证。如此巨额资金往来若为借款，却未签订书面借款协议，于商业常理不合。当事人所主张的周方洁向天一世纪还款的资金往来多发生在事先告知之后，有的亦不能明确其资金关系。当事人所提证据既不足以证明自天一世纪转入“范某”账户的资金为借款，也不足以推翻周方洁在调查环节所作陈述。第三，天一世纪利用他人账户买卖证券行为事实清楚，证据充分，当事人所提出的该行为未经天一世纪董事会批准、“范某”账户资金来源亦有周方洁个人账户、周方洁对于部分资金的使用情况等，只能说明天一世纪存在公司治理及资金管理不规范等问题，并不影响涉案违法行为的成立。综上，天一世纪利用他人账户买卖证券的行为足以认定。经上海证券交易所和深圳证券交易所统计，“范某”账户涉案期间的交易结果为亏损状态，未取得违法所得。根据当事人违法行为的事实、性质、情节与社会危害程度，依据《证券法》第二百零八条第一款的规定，我会决定：一、责令天一世纪改正，处以30万元罚款；二、对周方洁给予警告，并处以10万元罚款。上述当事人应自收到本处罚决定书之日起15日内，将罚款汇交中国证券监督管理委员会（财政汇缴专户），开户银行：中信银行总行营业部，账号：7111010189800000162，由该行直接上缴国库，并将注有当事人名称的付款凭证复印件送中国证券监督管理委员会稽查局备案。当事人如果对本处罚决定不服，可在收到本处罚决定书之日起60日内向中国证券监督管理委员会申请行政复议，也可在收到本处罚决定书之日起6个月内直接向有管辖权的人民法院提起行政诉讼。复议和诉讼期间，上述决定不停止执行。中国证监会 2018年12月29日 | D2: 2018125 | E2: 43463
A3: 是 | B3: 是 | C3: 〔2018〕129号 当事人：雅利（上海）资产管理有限公司（以下简称雅利资产），注册地址：上海市浦东新区。吕沈强，男，1977年9月出生，住址：上海市长宁区。依据《中华人民共和国证券法》（以下简称《证券法》）的有关规定，我会对雅利资产操纵股价行为进行了立案调查、审理，并依法向当事人告知了作出行政处罚的事实、理由、依据及当事人依法享有的权利。当事人雅利资产、吕沈强要求陈述申辩和听证。应当事人要求，我会举行了听证会，听取了当事人的陈述申辩意见。本案现已调查、审理终结。经查明，你们存在以下违法事实：一、涉案账户基本情况兴业国际信托有限公司-耀汇金1号资产集合资金信托计划（2）期（以下简称“耀汇金2期”）账户于2015年6月8日开立于中国国际金融股份有限公司广州天河路证券营业部，账户的资金来源于募集资金。耀汇金2期的所有股票交易决策人为雅利资产的吕沈强，下单人为公司交易员，下单电脑为公司电脑。二、耀汇金2期交易“中发科技”情况2015年9月10日14:57:32-14:59:55，耀汇金2期以远高于市价的价格分5笔申买“中发科技”209万股，占市场申买量的86.36%，成交1,814,252股，占市场成交量的89.48%，成交金额26,780,265.29元，买入均价14.76元/股，期间股票最大涨幅为7.9%，当天收盘价为14.83元/股，全天股价涨幅为4.29%，当天上证指数涨幅为-1.39%。拉抬后一个交易日9月11日，“中发科技”开盘价14.79元/股，开盘涨幅为-0.27%，14:18:18-14:32:46，耀汇金2期分35笔卖出“中发科技”754,771股，成交金额10,755,045.4元，成交均价14.25元/股，亏损54,157.37元。以上事实，有相关人员询问笔录、书面说明、相关协议、账户开户资料、交易流水、资金流水、证券交易所统计数据等证据证明。雅利资产利用资金优势，通过连续交易、尾盘拉抬等方式影响“中发科技”价格和交易量，其行为违反《证券法》第七十七条第一款第一项和第四项的规定，构成《证券法》第二百零三条所述的操纵市场行为。直接负责的主管人员为吕沈强。听证会上，当事人提出如下申辩意见：1.公司交易“中发科技”属正常股票交易行为，主观上没有通过交易行为欺诈其他投资者的主观故意，客观上没有造成股价或交易量的异常或形成虚拟水平的操纵行为，不应被认定为操纵证券市场违法行为。另外，盈亏计算存在错误。2.吕沈强提出其作为雅利资产的董事长，不应当基于其职务行为而受到行政处罚，在履职过程中没有操纵市场的意图和行为。请求不予处罚。经复核，我会认为，第一，在2015年9月10日尾盘阶段，当事人以远高于市价的价格申报买入“中发科技”，拉抬行为明显，导致期间股票最大涨幅为7.9%；成交1,814,252股，占市场成交量的89.48%。当事人的拉抬行为影响了股票价格和交易量。第二，结合本案操纵时点、操纵手法、卖出时点，本案盈亏计算并无不妥。第三，吕沈强负责耀汇金2期的交易决策，认定其为直接负责的主管人员，并无不当。第四，对其他意见部分予以采纳。根据当事人违法行为的事实、性质、情节与社会危害程度，依据《证券法》第二百零三条的规定，我会决定：对雅利资产操纵“中发科技”处以100万元罚款；对直接负责的主管人员吕沈强给予警告，并处以30万元罚款。上述当事人应自收到本处罚决定书之日起15日内，将罚款汇交中国证券监督管理委员会（财政汇缴专户），开户银行：中信银行总行营业部，账号：7111010189800000162，由该行直接上缴国库，并将注有当事人名称的付款凭证复印件送中国证券监督管理委员会稽查局备案。当事人如果对本处罚决定不服，可在收到本处罚决定书之日起60日内向中国证券监督管理委员会申请行政复议，也可在收到本处罚决定书之日起6个月内直接向有管辖权的人民法院提起行政诉讼。复议和诉讼期间，上述决定不停止执行。 中国证监会 2018年12月28日 | D3: 2018129 | E3: 43462
